Workbook

Sheet Cobranza
A1: ITEM | B1: NOMBRES | C1: MZ | D1: LT | E1: TIPO CONVENIO | F1: MAYOR 65 | G1: NO COBRO | H1: Costo x m3 | I1: MARCACION ACTUAL | K1: M3 | L1: Mes actual | M1: MES ANTERIOR | N1: Corte y reconexión | O1: Convenio | P1: Mant. | Q1: Reunión | R1: faena | S1: Ajuste | T1: Total | U1: Estado | V1: Fecha | W1: Medio | X1: Mes anterior | Y1: Comentario | Z1: Estado del servicio | AA1: corte | AB1: Efectivo | AC1: Yape | AD1: contador yape
A2: 1 | B2: MARCELINA OBREGON DE AVILA | C2: A | D2: 1 | H2: 1 | I2: 2599 | J2: 2607 | K2: =J2-I2 -> 8 | L2: 8 | M2: 11 | N2: 0 | O2: 0 | P2: 3 | Q2: 0 | R2: 0 | T2: =SUM(L2:S2) -> 22 | U2: c | W2: y | AA2: =IF(AND(L2>0, M2>=8, NOT(OR(U2="C", U2="c"))), "CORTE", "") | AB2: =IF(AND(LEN(U2)>0,LEN(W2)=0),T2,0) -> 0 | AC2: =IF(AND(LEN(U2)>0,TRIM(W2)="Y"),T2,0) -> 22 | AD2: =IF(ISBLANK(W2),0,1) -> 1
A3: 2 | B3: ROSA AURORA ROCA VIDAL | C3: A | D3: 2 | H3: 1 | I3: 2575 | J3: 2600 | K3: =J3-I3 -> 25 | L3: 25 | M3: 0 | N3: 0 | O3: 0 | P3: 3 | Q3: 0 | R3: 0 | T3: =SUM(L3:S3) -> 28 | AA3: =IF(AND(L3>0, M3>=8, NOT(OR(U3="C", U3="c"))), "CORTE", "") | AB3: =IF(AND(LEN(U3)>0,LEN(W3)=0),T3,0) -> 0 | AC3: =IF(AND(LEN(U3)>0,TRIM(W3)="Y"),T3,0) -> 0
A4: 3 | B4: LINDA PAJUELO COCHACHÍN | C4: A | D4: 3 | H4: 1 | I4: 22 | J4: 22 | K4: =J4-I4 -> 0 | L4: 5 | M4: 0 | N4: 0 | O4: 0 | P4: 3 | Q4: 0 | R4: 30 | T4: =SUM(L4:S4) -> 38 | U4: c | W4: y | AA4: =IF(AND(L4>0, M4>=8, NOT(OR(U4="C", U4="c"))), "CORTE", "") | AB4: =IF(AND(LEN(U4)>0,LEN(W4)=0),T4,0) -> 0 | AC4: =IF(AND(LEN(U4)>0,TRIM(W4)="Y"),T4,0) -> 38 | AD4: =IF(ISBLANK(W4),0,1) -> 1
A5: 4 | B5: YOLANDA ESPINOZA JAIMES | C5: A | D5: 4 | H5: 1 | I5: 1765 | J5: 1767 | K5: =J5-I5 -> 2 | L5: 5 | M5: 137 | N5: 40 | O5: 0 | P5: 3 | Q5: 40 | R5: 30 | T5: =SUM(L5:S5) -> 255 | Y5: No pago | AA5: =IF(AND(L5>0, M5>=8, NOT(OR(U5="C", U5="c"))), "CORTE", "") -> CORTE | AB5: =IF(AND(LEN(U5)>0,LEN(W5)=0),T5,0) -> 0 | AC5: =IF(AND(LEN(U5)>0,TRIM(W5)="Y"),T5,0) -> 0
A6: 5 | B6: JULIA AGAMA CUZCO | C6: A | D6: 5 | H6: 1 | I6: 3369 | J6: 3383 | K6: =J6-I6 -> 14 | L6: 14 | M6: 0 | N6: 0 | O6: 0 | P6: 3 | Q6: 0 | R6: 0 | T6: =SUM(L6:S6) -> 17 | U6: c | AA6: =IF(AND(L6>0, M6>=8, NOT(OR(U6="C", U6="c"))), "CORTE", "") | AB6: =IF(AND(LEN(U6)>0,LEN(W6)=0),T6,0) -> 17 | AC6: =IF(AND(LEN(U6)>0,TRIM(W6)="Y"),T6,0) -> 0 | AD6: =IF(ISBLANK(W6),0,1) -> 0
A7: 6 | B7: ESTEBAN REYES SANCHEZ | C7: A | D7: 6 | H7: 1 | I7: 1860 | J7: 1883 | K7: =J7-I7 -> 23 | L7: 23 | M7: 0 | N7: 0 | O7: 0 | P7: 3 | Q7: 0 | R7: 30 | T7: =SUM(L7:S7) -> 56 | U7: c | W7: y | AA7: =IF(AND(L7>0, M7>=8, NOT(OR(U7="C", U7="c"))), "CORTE", "") | AB7: =IF(AND(LEN(U7)>0,LEN(W7)=0),T7,0) -> 0 | AC7: =IF(AND(LEN(U7)>0,TRIM(W7)="Y"),T7,0) -> 56 | AD7: =IF(ISBLANK(W7),0,1) -> 1
A8: 7 | B8: JUAN CARLOS MELGAREJO BEDON | C8: A | D8: 7 | H8: 1 | I8: 1703 | J8: 1713 | K8: =J8-I8 -> 10 | L8: 10 | M8: 11 | N8: 0 | O8: 0 | P8: 3 | Q8: 0 | T8: =SUM(L8:S8) -> 24 | U8: c | W8: y | Y8: debe 30 faena | AA8: =IF(AND(L8>0, M8>=8, NOT(OR(U8="C", U8="c"))), "CORTE", "") | AB8: =IF(AND(LEN(U8)>0,LEN(W8)=0),T8,0) -> 0 | AC8: =IF(AND(LEN(U8)>0,TRIM(W8)="Y"),T8,0) -> 24 | AD8: =IF(ISBLANK(W8),0,1) -> 1
A9: 8 | B9: VICTOR MELGAREJO CORCINO | C9: A | D9: 8 | H9: 1 | I9: 6304 | J9: 6324 | K9: =J9-I9 -> 20 | L9: 20 | M9: 20 | N9: 0 | O9: 0 | P9: 3 | Q9: 0 | R9: 30 | T9: =SUM(L9:S9) -> 73 | U9: c | W9: y | AA9: =IF(AND(L9>0, M9>=8, NOT(OR(U9="C", U9="c"))), "CORTE", "") | AB9: =IF(AND(LEN(U9)>0,LEN(W9)=0),T9,0) -> 0 | AC9: =IF(AND(LEN(U9)>0,TRIM(W9)="Y"),T9,0) -> 73 | AD9: =IF(ISBLANK(W9),0,1) -> 1
A10: 9 | B10: JHONI MELGAREJO BEDON | C10: A | D10: 8-A | H10: 1 | I10: 148 | J10: 159 | K10: =J10-I10 -> 11 | L10: 11 | M10: 0 | N10: 0 | O10: 0 | P10: 3 | Q10: 0 | R10: 30 | T10: =SUM(L10:S10) -> 44 | AA10: =IF(AND(L10>0, M10>=8, NOT(OR(U10="C", U10="c"))), "CORTE", "") | AB10: =IF(AND(LEN(U10)>0,LEN(W10)=0),T10,0) -> 0 | AC10: =IF(AND(LEN(U10)>0,TRIM(W10)="Y"),T10,0) -> 0 | AD10: =IF(ISBLANK(W10),0,1) -> 0
A11: 10 | B11: ALEJANDRO MELGAREJO ESPINOZA | C11: A | D11: 9 | H11: 1 | I11: 2062 | J11: 2092 | K11: =J11-I11 -> 30 | L11: 30 | M11: 0 | N11: 0 | O11: 0 | P11: 3 | Q11: 0 | R11: 30 | T11: =SUM(L11:S11) -> 63 | U11: c | W11: y | AA11: =IF(AND(L11>0, M11>=8, NOT(OR(U11="C", U11="c"))), "CORTE", "") | AB11: =IF(AND(LEN(U11)>0,LEN(W11)=0),T11,0) -> 0 | AC11: =IF(AND(LEN(U11)>0,TRIM(W11)="Y"),T11,0) -> 63
A12: 11 | B12: ISABEL PUNTILLO VEGA | C12: A | D12: 10 | H12: 1 | I12: 581 | J12: 616 | K12: =J12-I12 -> 35 | M12: 22 | N12: 0 | O12: 0 | P12: 3 | Q12: 0 | R12: 0 | T12: =SUM(L12:S12) -> 25 | U12: c | W12: y | Y12: debe 30 faena, mes actual 35 | AA12: =IF(AND(L12>0, M12>=8, NOT(OR(U12="C", U12="c"))), "CORTE", "") | AB12: =IF(AND(LEN(U12)>0,LEN(W12)=0),T12,0) -> 0 | AC12: =IF(AND(LEN(U12)>0,TRIM(W12)="Y"),T12,0) -> 25
A13: 12 | B13: FELIX POZO CASTRO | C13: A | D13: 11 | H13: 1 | I13: 357 | J13: 358 | K13: =J13-I13 -> 1 | L13: 5 | M13: 0 | N13: 0 | O13: 0 | P13: 3 | Q13: 0 | R13: 30 | T13: =SUM(L13:S13) -> 38 | U13: c | W13: y | AA13: =IF(AND(L13>0, M13>=8, NOT(OR(U13="C", U13="c"))), "CORTE", "") | AB13: =IF(AND(LEN(U13)>0,LEN(W13)=0),T13,0) -> 0 | AC13: =IF(AND(LEN(U13)>0,TRIM(W13)="Y"),T13,0) -> 38 | AD13: =IF(ISBLANK(W13),0,1) -> 1
A14: 13 | B14: BACILIO UTRILLA FRANCISCO | C14: B | D14: 1 | H14: 1 | I14: 2255 | J14: 2263 | K14: =J14-I14 -> 8 | L14: 8 | M14: 2 | N14: 0 | O14: 0 | P14: 3 | Q14: 0 | R14: 30 | T14: =SUM(L14:S14) -> 43 | U14: c | AA14: =IF(AND(L14>0, M14>=8, NOT(OR(U14="C", U14="c"))), "CORTE", "") | AB14: =IF(AND(LEN(U14)>0,LEN(W14)=0),T14,0) -> 43 | AC14: =IF(AND(LEN(U14)>0,TRIM(W14)="Y"),T14,0) -> 0 | AD14: =IF(ISBLANK(W14),0,1) -> 0
A15: 14 | B15: ESTEBAN REYNALDO ROSALES | C15: B | D15: 2 | H15: 1 | I15: 2260 | J15: 2271 | K15: =J15-I15 -> 11 | L15: 11 | M15: 0 | N15: 0 | O15: 0 | P15: 3 | Q15: 0 | R15: 30 | T15: =SUM(L15:S15) -> 44 | U15: c | AA15: =IF(AND(L15>0, M15>=8, NOT(OR(U15="C", U15="c"))), "CORTE", "") | AB15: =IF(AND(LEN(U15)>0,LEN(W15)=0),T15,0) -> 44 | AC15: =IF(AND(LEN(U15)>0,TRIM(W15)="Y"),T15,0) -> 0 | AD15: =IF(ISBLANK(W15),0,1) -> 0
A16: 15 | B16: EDUARDO REYNALDO ROSALES | C16: B | D16: 3 | H16: 1 | I16: 779 | J16: 786 | K16: =J16-I16 -> 7 | L16: 7 | M16: 0 | N16: 0 | O16: 0 | P16: 3 | Q16: 0 | R16: 30 | T16: =SUM(L16:S16) -> 40 | U16: c | AA16: =IF(AND(L16>0, M16>=8, NOT(OR(U16="C", U16="c"))), "CORTE", "") | AB16: =IF(AND(LEN(U16)>0,LEN(W16)=0),T16,0) -> 40 | AC16: =IF(AND(LEN(U16)>0,TRIM(W16)="Y"),T16,0) -> 0 | AD16: =IF(ISBLANK(W16),0,1) -> 0
A17: 16 | B17: MELINA J. JUAREZ TOLEDO DE MORENO | C17: B | D17: 4 | H17: 1 | I17: 567 | J17: 578 | K17: =J17-I17 -> 11 | L17: 11 | M17: 0 | N17: 0 | O17: 0 | P17: 3 | Q17: 0 | R17: 30 | T17: =SUM(L17:S17) -> 44 | U17: c | W17: y | AA17: =IF(AND(L17>0, M17>=8, NOT(OR(U17="C", U17="c"))), "CORTE", "") | AB17: =IF(AND(LEN(U17)>0,LEN(W17)=0),T17,0) -> 0 | AC17: =IF(AND(LEN(U17)>0,TRIM(W17)="Y"),T17,0) -> 44 | AD17: =IF(ISBLANK(W17),0,1) -> 1
A18: 17 | B18: POMPEYO CELESTINO LLIUYA | C18: B | D18: 5 | H18: 1 | I18: 5222 | J18: 5252 | K18: =J18-I18 -> 30 | L18: 30 | M18: -3 | N18: 0 | O18: 0 | P18: 3 | Q18: 0 | R18: 30 | T18: =SUM(L18:S18) -> 60 | AA18: =IF(AND(L18>0, M18>=8, NOT(OR(U18="C", U18="c"))), "CORTE", "") | AB18: =IF(AND(LEN(U18)>0,LEN(W18)=0),T18,0) -> 0 | AC18: =IF(AND(LEN(U18)>0,TRIM(W18)="Y"),T18,0) -> 0
A19: 18 | B19: ROSA VICTORIA MILLA MORALES | C19: B | D19: 6 | H19: 1 | I19: 3879 | J19: 3899 | K19: =J19-I19 -> 20 | L19: 20 | M19: 0 | N19: 0 | O19: 0 | P19: 3 | Q19: 0 | R19: 0 | T19: =SUM(L19:S19) -> 23 | U19: c | AA19: =IF(AND(L19>0, M19>=8, NOT(OR(U19="C", U19="c"))), "CORTE", "") | AB19: =IF(AND(LEN(U19)>0,LEN(W19)=0),T19,0) -> 23 | AC19: =IF(AND(LEN(U19)>0,TRIM(W19)="Y"),T19,0) -> 0 | AD19: =IF(ISBLANK(W19),0,1) -> 0
A20: 19 | B20: LIRIA PARIAMACHI DE PAZ | C20: B | D20: 7 | H20: 1 | I20: 2650 | J20: 2671 | K20: =J20-I20 -> 21 | L20: 21 | M20: 0 | N20: 0 | O20: 0 | P20: 3 | Q20: 0 | R20: 30 | T20: =SUM(L20:S20) -> 54 | AA20: =IF(AND(L20>0, M20>=8, NOT(OR(U20="C", U20="c"))), "CORTE", "") | AB20: =IF(AND(LEN(U20)>0,LEN(W20)=0),T20,0) -> 0 | AC20: =IF(AND(LEN(U20)>0,TRIM(W20)="Y"),T20,0) -> 0 | AD20: =IF(ISBLANK(W20),0,1) -> 0
A21: 20 | B21: ROSALINA OLIMPIA CIRIACO SOTELO | C21: B | D21: 8 | H21: 1 | I21: 6665 | J21: 6683 | K21: =J21-I21 -> 18 | L21: 18 | M21: 0 | N21: 0 | O21: 0 | P21: 3 | Q21: 0 | R21: 0 | T21: =SUM(L21:S21) -> 21 | AA21: =IF(AND(L21>0, M21>=8, NOT(OR(U21="C", U21="c"))), "CORTE", "") | AB21: =IF(AND(LEN(U21)>0,LEN(W21)=0),T21,0) -> 0 | AC21: =IF(AND(LEN(U21)>0,TRIM(W21)="Y"),T21,0) -> 0
A22: 21 | B22: ALEJANDRO RAPRAY VELASQUEZ | C22: B | D22: 9 | F22: 1 | H22: 1 | I22: 40 | J22: 48 | K22: =J22-I22 -> 8 | L22: 8 | M22: 0 | N22: 0 | O22: 0 | P22: 3 | Q22: 0 | R22: 30 | T22: =SUM(L22:S22) -> 41 | AA22: =IF(AND(L22>0, M22>=8, NOT(OR(U22="C", U22="c"))), "CORTE", "") | AB22: =IF(AND(LEN(U22)>0,LEN(W22)=0),T22,0) -> 0 | AC22: =IF(AND(LEN(U22)>0,TRIM(W22)="Y"),T22,0) -> 0
A23: 22 | B23: ELVIRA PASCUALA MINAYA TAHUA | C23: B | D23: 11 | H23: 1 | I23: 3031 | J23: 3050 | K23: =J23-I23 -> 19 | L23: 19 | M23: 16 | N23: 0 | O23: 0 | P23: 3 | Q23: 0 | R23: 0 | T23: =SUM(L23:S23) -> 38 | U23: c | AA23: =IF(AND(L23>0, M23>=8, NOT(OR(U23="C", U23="c"))), "CORTE", "") | AB23: =IF(AND(LEN(U23)>0,LEN(W23)=0),T23,0) -> 38 | AC23: =IF(AND(LEN(U23)>0,TRIM(W23)="Y"),T23,0) -> 0
A24: 23 | B24: MARCELINO FELIX VILLAFANA PALLACA | C24: B | D24: 10 | H24: 1 | I24: 355 | J24: 360 | K24: =J24-I24 -> 5 | L24: 5 | M24: 19 | N24: 0 | O24: 0 | P24: 3 | Q24: 0 | R24: 0 | T24: =SUM(L24:S24) -> 27 | U24: c | W24: y | AA24: =IF(AND(L24>0, M24>=8, NOT(OR(U24="C", U24="c"))), "CORTE", "") | AB24: =IF(AND(LEN(U24)>0,LEN(W24)=0),T24,0) -> 0 | AC24: =IF(AND(LEN(U24)>0,TRIM(W24)="Y"),T24,0) -> 27
A25: 24 | B25: TEOFILO BRUNO RAMOS DE LA CRUZ | C25: B | D25: 12 | H25: 1 | I25: 2369 | J25: 2374 | K25: =J25-I25 -> 5 | L25: 5 | M25: 0 | N25: 0 | O25: 0 | P25: 3 | Q25: 0 | R25: 30 | T25: =SUM(L25:S25) -> 38 | AA25: =IF(AND(L25>0, M25>=8, NOT(OR(U25="C", U25="c"))), "CORTE", "") | AB25: =IF(AND(LEN(U25)>0,LEN(W25)=0),T25,0) -> 0 | AC25: =IF(AND(LEN(U25)>0,TRIM(W25)="Y"),T25,0) -> 0 | AD25: =IF(ISBLANK(W25),0,1) -> 0
A26: 25 | B26: ROSMERI SANCHEZ ESPADA | C26: B | D26: 12-A | H26: 1 | I26: 333 | J26: 339 | K26: =J26-I26 -> 6 | L26: 6 | M26: 8 | N26: 0 | O26: 0 | P26: 3 | Q26: 0 | T26: =SUM(L26:S26) -> 17 | U26: c | W26: y | Y26: Debe 30 | AA26: =IF(AND(L26>0, M26>=8, NOT(OR(U26="C", U26="c"))), "CORTE", "") | AB26: =IF(AND(LEN(U26)>0,LEN(W26)=0),T26,0) -> 0 | AC26: =IF(AND(LEN(U26)>0,TRIM(W26)="Y"),T26,0) -> 17 | AD26: =IF(ISBLANK(W26),0,1) -> 1
A27: 26 | B27: SALOME AGUSTINA DIAZ VARGAS | C27: B | D27: 13 | H27: 1 | I27: 260 | J27: 268 | K27: =J27-I27 -> 8 | L27: 8 | M27: 0 | N27: 0 | O27: 0 | P27: 3 | Q27: 0 | R27: 15 | T27: =SUM(L27:S27) -> 26 | U27: c | W27: y | Y27: Debe 15 faena | AA27: =IF(AND(L27>0, M27>=8, NOT(OR(U27="C", U27="c"))), "CORTE", "") | AB27: =IF(AND(LEN(U27)>0,LEN(W27)=0),T27,0) -> 0 | AC27: =IF(AND(LEN(U27)>0,TRIM(W27)="Y"),T27,0) -> 26 | AD27: =IF(ISBLANK(W27),0,1) -> 1
A28: 27 | B28: MELISSA ISABEL PILLACA GARCIA | C28: B | D28: 15 | H28: 1 | I28: 1235 | J28: 1250 | K28: =J28-I28 -> 15 | L28: 15 | M28: 4 | N28: 0 | O28: 0 | P28: 3 | Q28: 0 | R28: 30 | T28: =SUM(L28:S28) -> 52 | U28: c | W28: y | AA28: =IF(AND(L28>0, M28>=8, NOT(OR(U28="C", U28="c"))), "CORTE", "") | AB28: =IF(AND(LEN(U28)>0,LEN(W28)=0),T28,0) -> 0 | AC28: =IF(AND(LEN(U28)>0,TRIM(W28)="Y"),T28,0) -> 52 | AD28: =IF(ISBLANK(W28),0,1) -> 1
A29: 28 | B29: ELEUTERIA DOMITILA PARIAMACHI DE PAZ | C29: B | D29: 16 | H29: 1 | I29: 32 | J29: 32 | K29: =J29-I29 -> 0 | L29: 5 | M29: 0 | N29: 0 | O29: 0 | P29: 3 | Q29: 0 | R29: 30 | T29: =SUM(L29:S29) -> 38 | AA29: =IF(AND(L29>0, M29>=8, NOT(OR(U29="C", U29="c"))), "CORTE", "") | AB29: =IF(AND(LEN(U29)>0,LEN(W29)=0),T29,0) -> 0 | AC29: =IF(AND(LEN(U29)>0,TRIM(W29)="Y"),T29,0) -> 0
A30: 29 | B30: LUZ DINA MIRAVAL HUERTA | C30: B | D30: 17 | H30: 1 | I30: 988 | J30: 1007 | K30: =J30-I30 -> 19 | L30: 19 | M30: 0 | N30: 0 | O30: 0 | P30: 3 | Q30: 0 | R30: 0 | T30: =SUM(L30:S30) -> 22 | U30: c | W30: y | AA30: =IF(AND(L30>0, M30>=8, NOT(OR(U30="C", U30="c"))), "CORTE", "") | AB30: =IF(AND(LEN(U30)>0,LEN(W30)=0),T30,0) -> 0 | AC30: =IF(AND(LEN(U30)>0,TRIM(W30)="Y"),T30,0) -> 22 | AD30: =IF(ISBLANK(W30),0,1) -> 1
A31: 30 | B31: CLETO TENORIO MORI | C31: B | D31: 18 | H31: 1 | I31: 545 | J31: 553 | K31: =J31-I31 -> 8 | L31: 8 | M31: 12 | N31: 0 | O31: 0 | P31: 3 | Q31: 0 | R31: 30 | T31: =SUM(L31:S31) -> 53 | U31: c | AA31: =IF(AND(L31>0, M31>=8, NOT(OR(U31="C", U31="c"))), "CORTE", "") | AB31: =IF(AND(LEN(U31)>0,LEN(W31)=0),T31,0) -> 53 | AC31: =IF(AND(LEN(U31)>0,TRIM(W31)="Y"),T31,0) -> 0 | AD31: =IF(ISBLANK(W31),0,1) -> 0
A32: 31 | B32: CAMILA HIDALGO | C32: B | D32: 21 | H32: 1 | I32: 166 | J32: 172 | K32: =J32-I32 -> 6 | L32: 6 | M32: 0 | N32: 0 | O32: 0 | P32: 3 | Q32: 0 | R32: 30 | T32: =SUM(L32:S32) -> 39 | AA32: =IF(AND(L32>0, M32>=8, NOT(OR(U32="C", U32="c"))), "CORTE", "") | AB32: =IF(AND(LEN(U32)>0,LEN(W32)=0),T32,0) -> 0 | AC32: =IF(AND(LEN(U32)>0,TRIM(W32)="Y"),T32,0) -> 0
A33: 32 | B33: JANET FERNANDEZ MINAYA | C33: B | D33: 29 | E33: N | H33: 1 | I33: 160 | J33: 161 | K33: =J33-I33 -> 1 | L33: 5 | M33: 0 | N33: 0 | O33: 20 | P33: 3 | Q33: 0 | R33: 0 | T33: =SUM(L33:S33) -> 28 | U33: c | Y33: Se le debe 0. Pago (8 consumo, 20 convenio) | AA33: =IF(AND(L33>0, M33>=8, NOT(OR(U33="C", U33="c"))), "CORTE", "") | AB33: =IF(AND(LEN(U33)>0,LEN(W33)=0),T33,0) -> 28 | AC33: =IF(AND(LEN(U33)>0,TRIM(W33)="Y"),T33,0) -> 0 | AD33: =IF(ISBLANK(W33),0,1) -> 0
A34: 33 | B34: ODILON CERNA ROMERO | C34: C | D34: 1 | H34: 1 | I34: 2019 | J34: 2041 | K34: =J34-I34 -> 22 | L34: 22 | M34: 0 | N34: 0 | O34: 0 | P34: 3 | Q34: 0 | T34: =SUM(L34:S34) -> 25 | U34: c | Y34: Se exonero faena. | AA34: =IF(AND(L34>0, M34>=8, NOT(OR(U34="C", U34="c"))), "CORTE", "") | AB34: =IF(AND(LEN(U34)>0,LEN(W34)=0),T34,0) -> 25 | AC34: =IF(AND(LEN(U34)>0,TRIM(W34)="Y"),T34,0) -> 0 | AD34: =IF(ISBLANK(W34),0,1) -> 0
A35: 34 | B35: OLGA FLORENTINA HUERTA AGAMA | C35: C | D35: 2 | H35: 1 | I35: 853 | J35: 856 | K35: =J35-I35 -> 3 | L35: 5 | M35: 0 | N35: 0 | O35: 0 | P35: 3 | Q35: 0 | R35: 30 | T35: =SUM(L35:S35) -> 38 | U35: c | AA35: =IF(AND(L35>0, M35>=8, NOT(OR(U35="C", U35="c"))), "CORTE", "") | AB35: =IF(AND(LEN(U35)>0,LEN(W35)=0),T35,0) -> 38 | AC35: =IF(AND(LEN(U35)>0,TRIM(W35)="Y"),T35,0) -> 0 | AD35: =IF(ISBLANK(W35),0,1) -> 0
A36: 35 | B36: TIMOTEO ROMERO JULCA | C36: C | D36: 4 | H36: 1 | I36: 3336 | J36: 3349 | K36: =J36-I36 -> 13 | L36: 13 | M36: 0 | N36: 0 | O36: 0 | P36: 3 | Q36: 0 | R36: 30 | T36: =SUM(L36:S36) -> 46 | U36: c | W36: y | AA36: =IF(AND(L36>0, M36>=8, NOT(OR(U36="C", U36="c"))), "CORTE", "") | AB36: =IF(AND(LEN(U36)>0,LEN(W36)=0),T36,0) -> 0 | AC36: =IF(AND(LEN(U36)>0,TRIM(W36)="Y"),T36,0) -> 46 | AD36: =IF(ISBLANK(W36),0,1) -> 1
A37: 36 | B37: AGAPITO PRINICIPE SALINAS | C37: C | D37: 5 | H37: 1 | I37: 4106 | J37: 4123 | K37: =J37-I37 -> 17 | L37: 17 | M37: 0 | N37: 0 | O37: 0 | P37: 3 | Q37: 0 | R37: 0 | T37: =SUM(L37:S37) -> 20 | AA37: =IF(AND(L37>0, M37>=8, NOT(OR(U37="C", U37="c"))), "CORTE", "") | AB37: =IF(AND(LEN(U37)>0,LEN(W37)=0),T37,0) -> 0 | AC37: =IF(AND(LEN(U37)>0,TRIM(W37)="Y"),T37,0) -> 0
A38: 37 | B38: DIANA JARA TRUJILLO | C38: C | D38: 6 | H38: 1 | I38: 544 | J38: 555 | K38: =J38-I38 -> 11 | L38: 11 | M38: 0 | N38: 0 | O38: 0 | P38: 3 | Q38: 0 | R38: 0 | T38: =SUM(L38:S38) -> 14 | AA38: =IF(AND(L38>0, M38>=8, NOT(OR(U38="C", U38="c"))), "CORTE", "") | AB38: =IF(AND(LEN(U38)>0,LEN(W38)=0),T38,0) -> 0 | AC38: =IF(AND(LEN(U38)>0,TRIM(W38)="Y"),T38,0) -> 0 | AD38: =IF(ISBLANK(W38),0,1) -> 0
A39: 38 | B39: VICTOR LOPEZ TRUJILLO | C39: C | D39: 7 | H39: 1 | I39: 2525 | J39: 2549 | K39: =J39-I39 -> 24 | L39: 24 | M39: 0 | N39: 0 | O39: 0 | P39: 3 | Q39: 0 | R39: 30 | T39: =SUM(L39:S39) -> 57 | AA39: =IF(AND(L39>0, M39>=8, NOT(OR(U39="C", U39="c"))), "CORTE", "") | AB39: =IF(AND(LEN(U39)>0,LEN(W39)=0),T39,0) -> 0 | AC39: =IF(AND(LEN(U39)>0,TRIM(W39)="Y"),T39,0) -> 0 | AD39: =IF(ISBLANK(W39),0,1) -> 0
A40: 39 | B40: JULISSA BARRETO QUITO | C40: C | D40: 8 | H40: 1 | I40: 248 | J40: 255 | K40: =J40-I40 -> 7 | L40: 7 | M40: 0 | N40: 0 | O40: 0 | P40: 3 | Q40: 0 | R40: 30 | T40: =SUM(L40:S40) -> 40 | AA40: =IF(AND(L40>0, M40>=8, NOT(OR(U40="C", U40="c"))), "CORTE", "") | AB40: =IF(AND(LEN(U40)>0,LEN(W40)=0),T40,0) -> 0 | AC40: =IF(AND(LEN(U40)>0,TRIM(W40)="Y"),T40,0) -> 0 | AD40: =IF(ISBLANK(W40),0,1) -> 0
A41: 40 | B41: JAZMIN QUITO SANCHEZ | C41: C | D41: 8-B | H41: 1 | I41: 923 | J41: 941 | K41: =J41-I41 -> 18 | L41: 18 | M41: 0 | N41: 0 | O41: 0 | P41: 3 | Q41: 0 | R41: 15 | T41: =SUM(L41:S41) -> 36 | U41: c | W41: y | Y41: Debe faena 15 | AA41: =IF(AND(L41>0, M41>=8, NOT(OR(U41="C", U41="c"))), "CORTE", "") | AB41: =IF(AND(LEN(U41)>0,LEN(W41)=0),T41,0) -> 0 | AC41: =IF(AND(LEN(U41)>0,TRIM(W41)="Y"),T41,0) -> 36 | AD41: =IF(ISBLANK(W41),0,1) -> 1
A42: 41 | B42: JUAN UCULMANA SANCHEZ | C42: C | D42: 9 | H42: 1 | I42: 2133 | J42: 2140 | K42: =J42-I42 -> 7 | L42: 7 | M42: 0 | N42: 0 | O42: 0 | P42: 3 | Q42: 0 | R42: 0 | T42: =SUM(L42:S42) -> 10 | U42: c | W42: y | AA42: =IF(AND(L42>0, M42>=8, NOT(OR(U42="C", U42="c"))), "CORTE", "") | AB42: =IF(AND(LEN(U42)>0,LEN(W42)=0),T42,0) -> 0 | AC42: =IF(AND(LEN(U42)>0,TRIM(W42)="Y"),T42,0) -> 10 | AD42: =IF(ISBLANK(W42),0,1) -> 1
A43: 42 | B43: SONIA GLORIA MORENO CASTILLEJO | C43: C | D43: 9-C | H43: 1 | I43: 482 | J43: 489 | K43: =J43-I43 -> 7 | L43: 7 | M43: 0 | N43: 0 | O43: 0 | P43: 3 | Q43: 0 | R43: 0 | T43: =SUM(L43:S43) -> 10 | U43: c | W43: y | AA43: =IF(AND(L43>0, M43>=8, NOT(OR(U43="C", U43="c"))), "CORTE", "") | AB43: =IF(AND(LEN(U43)>0,LEN(W43)=0),T43,0) -> 0 | AC43: =IF(AND(LEN(U43)>0,TRIM(W43)="Y"),T43,0) -> 10 | AD43: =IF(ISBLANK(W43),0,1) -> 1
A44: 43 | B44: CEVERIANO CHAUCA MORALES | C44: C | D44: 11 | H44: 1 | I44: 764 | J44: 781 | K44: =J44-I44 -> 17 | L44: 17 | M44: 0 | N44: 0 | O44: 0 | P44: 3 | Q44: 0 | R44: 30 | T44: =SUM(L44:S44) -> 50 | U44: c | W44: y | AA44: =IF(AND(L44>0, M44>=8, NOT(OR(U44="C", U44="c"))), "CORTE", "") | AB44: =IF(AND(LEN(U44)>0,LEN(W44)=0),T44,0) -> 0 | AC44: =IF(AND(LEN(U44)>0,TRIM(W44)="Y"),T44,0) -> 50 | AD44: =IF(ISBLANK(W44),0,1) -> 1
A45: 44 | B45: MACEDONIO MORALES BENTURO | C45: C | D45: 12 | H45: 1 | I45: 1620 | J45: 1632 | K45: =J45-I45 -> 12 | L45: 12 | M45: 0 | N45: 0 | O45: 0 | P45: 3 | Q45: 0 | T45: =SUM(L45:S45) -> 15 | U45: c | Y45: Asistio a la faena un dia antes | AA45: =IF(AND(L45>0, M45>=8, NOT(OR(U45="C", U45="c"))), "CORTE", "") | AB45: =IF(AND(LEN(U45)>0,LEN(W45)=0),T45,0) -> 15 | AC45: =IF(AND(LEN(U45)>0,TRIM(W45)="Y"),T45,0) -> 0 | AD45: =IF(ISBLANK(W45),0,1) -> 0
A46: 45 | B46: IRMA HUAÑAHUI LOPEZ | C46: C | D46: 13 | H46: 1 | I46: 2084 | J46: 2090 | K46: =J46-I46 -> 6 | L46: 6 | M46: 0 | N46: 0 | O46: 0 | P46: 3 | Q46: 0 | R46: 0 | T46: =SUM(L46:S46) -> 9 | U46: c | W46: y | AA46: =IF(AND(L46>0, M46>=8, NOT(OR(U46="C", U46="c"))), "CORTE", "") | AB46: =IF(AND(LEN(U46)>0,LEN(W46)=0),T46,0) -> 0 | AC46: =IF(AND(LEN(U46)>0,TRIM(W46)="Y"),T46,0) -> 9 | AD46: =IF(ISBLANK(W46),0,1) -> 1
A47: 46 | B47: JUAN RIOS BLAS | C47: C | D47: 14 | H47: 1 | I47: 823 | J47: 845 | K47: =J47-I47 -> 22 | L47: 22 | M47: 0 | N47: 0 | O47: 0 | P47: 3 | Q47: 0 | R47: 30 | T47: =SUM(L47:S47) -> 55 | AA47: =IF(AND(L47>0, M47>=8, NOT(OR(U47="C", U47="c"))), "CORTE", "") | AB47: =IF(AND(LEN(U47)>0,LEN(W47)=0),T47,0) -> 0 | AC47: =IF(AND(LEN(U47)>0,TRIM(W47)="Y"),T47,0) -> 0 | AD47: =IF(ISBLANK(W47),0,1) -> 0
A48: 47 | B48: JULIO RIOS BLAS | C48: C | D48: 15 | H48: 1 | I48: 100 | J48: 106 | K48: =J48-I48 -> 6 | L48: 6 | M48: 0 | N48: 0 | O48: 0 | P48: 3 | Q48: 0 | R48: 30 | T48: =SUM(L48:S48) -> 39 | U48: c | AA48: =IF(AND(L48>0, M48>=8, NOT(OR(U48="C", U48="c"))), "CORTE", "") | AB48: =IF(AND(LEN(U48)>0,LEN(W48)=0),T48,0) -> 39 | AC48: =IF(AND(LEN(U48)>0,TRIM(W48)="Y"),T48,0) -> 0 | AD48: =IF(ISBLANK(W48),0,1) -> 0
A49: 48 | B49: MARTHA MASIAS CASIHUAMAN DE TERAN | C49: C | D49: 16 | H49: 1 | I49: 1827 | J49: 1833 | K49: =J49-I49 -> 6 | L49: 6 | M49: 10 | N49: 0 | O49: 0 | P49: 3 | Q49: 0 | T49: =SUM(L49:S49) -> 19 | U49: c | W49: y | Y49: Debe30 faena | AA49: =IF(AND(L49>0, M49>=8, NOT(OR(U49="C", U49="c"))), "CORTE", "") | AB49: =IF(AND(LEN(U49)>0,LEN(W49)=0),T49,0) -> 0 | AC49: =IF(AND(LEN(U49)>0,TRIM(W49)="Y"),T49,0) -> 19 | AD49: =IF(ISBLANK(W49),0,1) -> 1
A50: 49 | B50: MARCELINO VALLADARES TRUJILLO | C50: C | D50: 18 | H50: 1 | I50: 396 | J50: 403 | K50: =J50-I50 -> 7 | L50: 7 | M50: 0 | N50: 0 | O50: 0 | P50: 3 | Q50: 0 | R50: 0 | T50: =SUM(L50:S50) -> 10 | U50: c | AA50: =IF(AND(L50>0, M50>=8, NOT(OR(U50="C", U50="c"))), "CORTE", "") | AB50: =IF(AND(LEN(U50)>0,LEN(W50)=0),T50,0) -> 10 | AC50: =IF(AND(LEN(U50)>0,TRIM(W50)="Y"),T50,0) -> 0 | AD50: =IF(ISBLANK(W50),0,1) -> 0
A51: 50 | B51: ANTONIO VALLADARES DOMINGUEZ | C51: C | D51: 19 | H51: 1 | I51: 3650 | J51: 3672 | K51: =J51-I51 -> 22 | L51: 22 | M51: -1 | N51: 0 | O51: 0 | P51: 3 | Q51: 0 | R51: 0 | T51: =SUM(L51:S51) -> 24 | U51: c | W51: y | AA51: =IF(AND(L51>0, M51>=8, NOT(OR(U51="C", U51="c"))), "CORTE", "") | AB51: =IF(AND(LEN(U51)>0,LEN(W51)=0),T51,0) -> 0 | AC51: =IF(AND(LEN(U51)>0,TRIM(W51)="Y"),T51,0) -> 24 | AD51: =IF(ISBLANK(W51),0,1) -> 1
A52: 51 | B52: EUSEBIO REYES VILLAFANA | C52: C | D52: 20 | H52: 1 | I52: 2756 | J52: 2769 | K52: =J52-I52 -> 13 | L52: 13 | M52: 0 | N52: 0 | O52: 0 | P52: 3 | Q52: 0 | R52: 0 | T52: =SUM(L52:S52) -> 16 | U52: c | AA52: =IF(AND(L52>0, M52>=8, NOT(OR(U52="C", U52="c"))), "CORTE", "") | AB52: =IF(AND(LEN(U52)>0,LEN(W52)=0),T52,0) -> 16 | AC52: =IF(AND(LEN(U52)>0,TRIM(W52)="Y"),T52,0) -> 0
A53: 52 | B53: PUESTO DE SALUD TUPAC AMARU | C53: C | D53: 21 | F53: 1 | G53: 1 | H53: 1 | I53: 1568 | J53: 1589 | K53: =J53-I53 -> 21 | L53: 21 | M53: 326 | N53: 40 | O53: 0 | P53: 3 | Q53: 0 | R53: 30 | T53: =SUM(L53:S53) -> 420 | Z53: Exonerado | AA53: =IF(AND(L53>0, M53>=8, NOT(OR(U53="C", U53="c"))), "CORTE", "") -> CORTE | AB53: =IF(AND(LEN(U53)>0,LEN(W53)=0),T53,0) -> 0 | AC53: =IF(AND(LEN(U53)>0,TRIM(W53)="Y"),T53,0) -> 0
A54: 53 | B54: ABRAHAM BARRERA VEGA | C54: C | D54: 22 | H54: 1 | I54: 107 | J54: 112 | K54: =J54-I54 -> 5 | L54: 5 | M54: 0 | N54: 0 | O54: 0 | P54: 3 | Q54: 0 | R54: 0 | T54: =SUM(L54:S54) -> 8 | U54: c | W54: y | AA54: =IF(AND(L54>0, M54>=8, NOT(OR(U54="C", U54="c"))), "CORTE", "") | AB54: =IF(AND(LEN(U54)>0,LEN(W54)=0),T54,0) -> 0 | AC54: =IF(AND(LEN(U54)>0,TRIM(W54)="Y"),T54,0) -> 8
A55: 54 | B55: ANTONIA MAYO TRUJILLO | C55: C | D55: 23 | H55: 1 | I55: 156 | J55: 179 | K55: =J55-I55 -> 23 | L55: 23 | M55: 0 | N55: 0 | O55: 0 | P55: 3 | Q55: 0 | R55: 30 | T55: =SUM(L55:S55) -> 56 | U55: c | W55: y | AA55: =IF(AND(L55>0, M55>=8, NOT(OR(U55="C", U55="c"))), "CORTE", "") | AB55: =IF(AND(LEN(U55)>0,LEN(W55)=0),T55,0) -> 0 | AC55: =IF(AND(LEN(U55)>0,TRIM(W55)="Y"),T55,0) -> 56 | AD55: =IF(ISBLANK(W55),0,1) -> 1
A56: 55 | B56: ALFREDO CARLOS VENTURO CAPCHA | C56: C | D56: 24 | H56: 1 | I56: 534 | J56: 537 | K56: =J56-I56 -> 3 | L56: 5 | M56: 0 | N56: 0 | O56: 0 | P56: 3 | Q56: 0 | R56: 0 | T56: =SUM(L56:S56) -> 8 | U56: c | AA56: =IF(AND(L56>0, M56>=8, NOT(OR(U56="C", U56="c"))), "CORTE", "") | AB56: =IF(AND(LEN(U56)>0,LEN(W56)=0),T56,0) -> 8 | AC56: =IF(AND(LEN(U56)>0,TRIM(W56)="Y"),T56,0) -> 0 | AD56: =IF(ISBLANK(W56),0,1) -> 0
A57: 56 | B57: JULIO HUERTA MILLA | C57: C | D57: 25 | H57: 1 | I57: 3914 | J57: 3927 | K57: =J57-I57 -> 13 | L57: 13 | M57: 0 | N57: 0 | O57: 0 | P57: 3 | Q57: 0 | R57: 0 | T57: =SUM(L57:S57) -> 16 | U57: c | AA57: =IF(AND(L57>0, M57>=8, NOT(OR(U57="C", U57="c"))), "CORTE", "") | AB57: =IF(AND(LEN(U57)>0,LEN(W57)=0),T57,0) -> 16 | AC57: =IF(AND(LEN(U57)>0,TRIM(W57)="Y"),T57,0) -> 0 | AD57: =IF(ISBLANK(W57),0,1) -> 0
A58: 57 | B58: CORCINO RODRIGUEZ RIVERA | C58: C | D58: 26 | H58: 1 | I58: 1506 | J58: 1507 | K58: =J58-I58 -> 1 | L58: 5 | M58: 0 | N58: 0 | O58: 0 | P58: 3 | Q58: 0 | R58: 30 | T58: =SUM(L58:S58) -> 38 | U58: c | AA58: =IF(AND(L58>0, M58>=8, NOT(OR(U58="C", U58="c"))), "CORTE", "") | AB58: =IF(AND(LEN(U58)>0,LEN(W58)=0),T58,0) -> 38 | AC58: =IF(AND(LEN(U58)>0,TRIM(W58)="Y"),T58,0) -> 0
A59: 58 | B59: NANCY VALERIANA FLORES LEON | C59: C | D59: 27 | H59: 1 | I59: 175 | J59: 192 | K59: =J59-I59 -> 17 | L59: 17 | M59: 0 | N59: 0 | O59: 0 | P59: 3 | Q59: 0 | R59: 0 | T59: =SUM(L59:S59) -> 20 | U59: c | AA59: =IF(AND(L59>0, M59>=8, NOT(OR(U59="C", U59="c"))), "CORTE", "") | AB59: =IF(AND(LEN(U59)>0,LEN(W59)=0),T59,0) -> 20 | AC59: =IF(AND(LEN(U59)>0,TRIM(W59)="Y"),T59,0) -> 0
A60: 59 | B60: OSTIN AGÜERO TRUJILLO | C60: C | D60: 28 | H60: 1 | I60: 5568 | J60: 5574 | K60: =J60-I60 -> 6 | L60: 6 | M60: 0 | N60: 0 | O60: 0 | P60: 3 | Q60: 0 | R60: 0 | T60: =SUM(L60:S60) -> 9 | U60: c | W60: y | AA60: =IF(AND(L60>0, M60>=8, NOT(OR(U60="C", U60="c"))), "CORTE", "") | AB60: =IF(AND(LEN(U60)>0,LEN(W60)=0),T60,0) -> 0 | AC60: =IF(AND(LEN(U60)>0,TRIM(W60)="Y"),T60,0) -> 9 | AD60: =IF(ISBLANK(W60),0,1) -> 1
A61: 60 | B61: SONIA CERNA MELGAREJO | C61: C | D61: 30 | H61: 1 | I61: 3491 | J61: 3514 | K61: =J61-I61 -> 23 | L61: 23 | M61: 0 | N61: 0 | O61: 0 | P61: 3 | Q61: 0 | R61: 30 | T61: =SUM(L61:S61) -> 56 | U61: c | AA61: =IF(AND(L61>0, M61>=8, NOT(OR(U61="C", U61="c"))), "CORTE", "") | AB61: =IF(AND(LEN(U61)>0,LEN(W61)=0),T61,0) -> 56 | AC61: =IF(AND(LEN(U61)>0,TRIM(W61)="Y"),T61,0) -> 0 | AD61: =IF(ISBLANK(W61),0,1) -> 0
A62: 61 | B62: IGLESIA ADVENTISTA DEL SEPTIMO DIA | C62: C | D62: 31 | H62: 1 | I62: 661 | J62: 668 | K62: =J62-I62 -> 7 | L62: 7 | M62: 0 | N62: 0 | O62: 0 | P62: 3 | Q62: 0 | R62: 30 | T62: =SUM(L62:S62) -> 40 | AA62: =IF(AND(L62>0, M62>=8, NOT(OR(U62="C", U62="c"))), "CORTE", "") | AB62: =IF(AND(LEN(U62)>0,LEN(W62)=0),T62,0) -> 0 | AC62: =IF(AND(LEN(U62)>0,TRIM(W62)="Y"),T62,0) -> 0 | AD62: =IF(ISBLANK(W62),0,1) -> 0
A63: 62 | B63: FAUSTA HUERTA AGAMA | C63: C | D63: 32 | H63: 1 | I63: 1666 | J63: 1669 | K63: =J63-I63 -> 3 | L63: 5 | M63: 0 | N63: 0 | O63: 0 | P63: 3 | Q63: 0 | R63: 30 | T63: =SUM(L63:S63) -> 38 | U63: c | AA63: =IF(AND(L63>0, M63>=8, NOT(OR(U63="C", U63="c"))), "CORTE", "") | AB63: =IF(AND(LEN(U63)>0,LEN(W63)=0),T63,0) -> 38 | AC63: =IF(AND(LEN(U63)>0,TRIM(W63)="Y"),T63,0) -> 0 | AD63: =IF(ISBLANK(W63),0,1) -> 0
A64: 63 | B64: EDITA ROMERO MAYO | C64: C | D64: 33 | H64: 1 | I64: 278 | J64: 292 | K64: =J64-I64 -> 14 | L64: 14 | M64: 0 | N64: 0 | O64: 0 | P64: 3 | Q64: 0 | R64: 0 | T64: =SUM(L64:S64) -> 17 | U64: c | W64: y | AA64: =IF(AND(L64>0, M64>=8, NOT(OR(U64="C", U64="c"))), "CORTE", "") | AB64: =IF(AND(LEN(U64)>0,LEN(W64)=0),T64,0) -> 0 | AC64: =IF(AND(LEN(U64)>0,TRIM(W64)="Y"),T64,0) -> 17 | AD64: =IF(ISBLANK(W64),0,1) -> 1
A65: 64 | B65: EBER AGÜERO TRUJILLO | C65: C | D65: 34 | H65: 1 | I65: 5 | J65: 8 | K65: =J65-I65 -> 3 | L65: 5 | M65: 0 | N65: 0 | O65: 0 | P65: 3 | Q65: 0 | R65: 0 | T65: =SUM(L65:S65) -> 8 | U65: c | W65: y | AA65: =IF(AND(L65>0, M65>=8, NOT(OR(U65="C", U65="c"))), "CORTE", "") | AB65: =IF(AND(LEN(U65)>0,LEN(W65)=0),T65,0) -> 0 | AC65: =IF(AND(LEN(U65)>0,TRIM(W65)="Y"),T65,0) -> 8 | AD65: =IF(ISBLANK(W65),0,1) -> 1
A66: 65 | B66: ANALY QUINECHE MORANTE | C66: C | D66: 35 | E66: C | H66: 1 | I66: 565 | J66: 575 | K66: =J66-I66 -> 10 | L66: 10 | M66: 11 | N66: 0 | P66: 3 | Q66: 0 | T66: =SUM(L66:S66) -> 24 | U66: c | W66: y | Y66: Debe30 faena | AA66: =IF(AND(L66>0, M66>=8, NOT(OR(U66="C", U66="c"))), "CORTE", "") | AB66: =IF(AND(LEN(U66)>0,LEN(W66)=0),T66,0) -> 0 | AC66: =IF(AND(LEN(U66)>0,TRIM(W66)="Y"),T66,0) -> 24 | AD66: =IF(ISBLANK(W66),0,1) -> 1
A67: 66 | B67: MARIA NORABUENA ESPADA | C67: C | D67: 36 | H67: 1 | I67: 251 | J67: 254 | K67: =J67-I67 -> 3 | L67: 5 | M67: 0 | N67: 0 | O67: 0 | P67: 3 | Q67: 0 | T67: =SUM(L67:S67) -> 8 | U67: c | W67: y | Y67: Debe30 faena | AA67: =IF(AND(L67>0, M67>=8, NOT(OR(U67="C", U67="c"))), "CORTE", "") | AB67: =IF(AND(LEN(U67)>0,LEN(W67)=0),T67,0) -> 0 | AC67: =IF(AND(LEN(U67)>0,TRIM(W67)="Y"),T67,0) -> 8 | AD67: =IF(ISBLANK(W67),0,1) -> 1
A68: 67 | B68: RAQUEL SORIA BUSTAMANTE | C68: C | D68: 37 | H68: 1 | I68: 255 | J68: 262 | K68: =J68-I68 -> 7 | L68: 7 | M68: 9 | N68: 0 | O68: 0 | P68: 3 | Q68: 0 | R68: 0 | T68: =SUM(L68:S68) -> 19 | U68: c | W68: y | AA68: =IF(AND(L68>0, M68>=8, NOT(OR(U68="C", U68="c"))), "CORTE", "") | AB68: =IF(AND(LEN(U68)>0,LEN(W68)=0),T68,0) -> 0 | AC68: =IF(AND(LEN(U68)>0,TRIM(W68)="Y"),T68,0) -> 19 | AD68: =IF(ISBLANK(W68),0,1) -> 1
A69: 68 | B69: JANET ROMERO MAYO | C69: C | D69: 42 | H69: 1 | I69: 257 | J69: 265 | K69: =J69-I69 -> 8 | L69: 8 | M69: 0 | N69: 0 | O69: 0 | P69: 3 | Q69: 0 | R69: 30 | T69: =SUM(L69:S69) -> 41 | U69: c | W69: y | AA69: =IF(AND(L69>0, M69>=8, NOT(OR(U69="C", U69="c"))), "CORTE", "") | AB69: =IF(AND(LEN(U69)>0,LEN(W69)=0),T69,0) -> 0 | AC69: =IF(AND(LEN(U69)>0,TRIM(W69)="Y"),T69,0) -> 41 | AD69: =IF(ISBLANK(W69),0,1) -> 1
A70: 69 | B70: JANET EVARISTO COCHACHIN | C70: C | D70: 45 | E70: N | H70: 1 | I70: 0 | J70: 0 | K70: =J70-I70 -> 0 | L70: 5 | M70: 0 | N70: 0 | O70: 100 | P70: 3 | Q70: 0 | R70: 0 | T70: =SUM(L70:S70) -> 108 | AA70: =IF(AND(L70>0, M70>=8, NOT(OR(U70="C", U70="c"))), "CORTE", "") | AB70: =IF(AND(LEN(U70)>0,LEN(W70)=0),T70,0) -> 0 | AC70: =IF(AND(LEN(U70)>0,TRIM(W70)="Y"),T70,0) -> 0
A71: 70 | B71: JUAN VENTURO CAPCHA | C71: D | D71: 1 | H71: 1 | I71: 1760 | J71: 1766 | K71: =J71-I71 -> 6 | L71: 6 | M71: 0 | N71: 0 | O71: 0 | P71: 3 | Q71: 0 | R71: 0 | T71: =SUM(L71:S71) -> 9 | AA71: =IF(AND(L71>0, M71>=8, NOT(OR(U71="C", U71="c"))), "CORTE", "") | AB71: =IF(AND(LEN(U71)>0,LEN(W71)=0),T71,0) -> 0 | AC71: =IF(AND(LEN(U71)>0,TRIM(W71)="Y"),T71,0) -> 0
A72: 71 | B72: VICTOR TRUJILLO POLICARPIO | C72: D | D72: 2 | H72: 1 | I72: 2205 | J72: 2224 | K72: =J72-I72 -> 19 | L72: 19 | M72: 0 | N72: 0 | O72: 0 | P72: 3 | Q72: 0 | R72: 30 | T72: =SUM(L72:S72) -> 52 | AA72: =IF(AND(L72>0, M72>=8, NOT(OR(U72="C", U72="c"))), "CORTE", "") | AB72: =IF(AND(LEN(U72)>0,LEN(W72)=0),T72,0) -> 0 | AC72: =IF(AND(LEN(U72)>0,TRIM(W72)="Y"),T72,0) -> 0
A73: 72 | B73: ANTONIO CASTILLEJO CUEVA | C73: D | D73: 3 | H73: 1 | I73: 1339 | J73: 1349 | K73: =J73-I73 -> 10 | L73: 10 | M73: 0 | N73: 0 | O73: 0 | P73: 3 | Q73: 0 | T73: =SUM(L73:S73) -> 13 | U73: c | Y73: Debe30 faena | AA73: =IF(AND(L73>0, M73>=8, NOT(OR(U73="C", U73="c"))), "CORTE", "") | AB73: =IF(AND(LEN(U73)>0,LEN(W73)=0),T73,0) -> 13 | AC73: =IF(AND(LEN(U73)>0,TRIM(W73)="Y"),T73,0) -> 0 | AD73: =IF(ISBLANK(W73),0,1) -> 0
A74: 73 | B74: JULIO CESAR PRINCIPE LUNA | C74: D | D74: 4 | H74: 1 | I74: 274 | J74: 291 | K74: =J74-I74 -> 17 | L74: 17 | M74: 0 | N74: 0 | O74: 0 | P74: 3 | Q74: 0 | R74: 30 | T74: =SUM(L74:S74) -> 50 | AA74: =IF(AND(L74>0, M74>=8, NOT(OR(U74="C", U74="c"))), "CORTE", "") | AB74: =IF(AND(LEN(U74)>0,LEN(W74)=0),T74,0) -> 0 | AC74: =IF(AND(LEN(U74)>0,TRIM(W74)="Y"),T74,0) -> 0
A75: 74 | B75: TERESA PAULA JARA DE FERNANDEZ | C75: D | D75: 5 | H75: 1 | I75: 509 | J75: 525 | K75: =J75-I75 -> 16 | L75: 16 | M75: 0 | N75: 0 | O75: 0 | P75: 3 | Q75: 0 | R75: 0 | T75: =SUM(L75:S75) -> 19 | U75: c | AA75: =IF(AND(L75>0, M75>=8, NOT(OR(U75="C", U75="c"))), "CORTE", "") | AB75: =IF(AND(LEN(U75)>0,LEN(W75)=0),T75,0) -> 19 | AC75: =IF(AND(LEN(U75)>0,TRIM(W75)="Y"),T75,0) -> 0
A76: 75 | B76: HERMELINDA JARA TRUJILLO | C76: D | D76: 6 | H76: 1 | I76: 8034 | J76: 8092 | K76: =J76-I76 -> 58 | L76: 58 | M76: 25 | N76: 0 | O76: 0 | P76: 3 | Q76: 0 | T76: =SUM(L76:S76) -> 86 | Y76: Exonerado faena | AA76: =IF(AND(L76>0, M76>=8, NOT(OR(U76="C", U76="c"))), "CORTE", "") -> CORTE | AB76: =IF(AND(LEN(U76)>0,LEN(W76)=0),T76,0) -> 0 | AC76: =IF(AND(LEN(U76)>0,TRIM(W76)="Y"),T76,0) -> 0 | AD76: =IF(ISBLANK(W76),0,1) -> 0
A77: 76 | B77: MAXIMILIANO JARA NIETO | C77: D | D77: 7 | F77: 1 | H77: 1 | I77: 5312 | J77: 5378 | K77: =J77-I77 -> 66 | L77: 66 | M77: 0 | N77: 0 | O77: 0 | P77: 3 | Q77: 0 | R77: 0 | T77: =SUM(L77:S77) -> 69 | U77: c | W77: y | AA77: =IF(AND(L77>0, M77>=8, NOT(OR(U77="C", U77="c"))), "CORTE", "") | AB77: =IF(AND(LEN(U77)>0,LEN(W77)=0),T77,0) -> 0 | AC77: =IF(AND(LEN(U77)>0,TRIM(W77)="Y"),T77,0) -> 69
A78: 77 | B78: SANTA ANTONIA SAENZ TICLIO | C78: D | D78: 8 | H78: 1 | I78: 1760 | J78: 1767 | K78: =J78-I78 -> 7 | L78: 7 | M78: 9 | N78: 0 | O78: 0 | P78: 3 | Q78: 0 | R78: 10 | T78: =SUM(L78:S78) -> 29 | U78: c | Y78: Debe 20 faena | AA78: =IF(AND(L78>0, M78>=8, NOT(OR(U78="C", U78="c"))), "CORTE", "") | AB78: =IF(AND(LEN(U78)>0,LEN(W78)=0),T78,0) -> 29 | AC78: =IF(AND(LEN(U78)>0,TRIM(W78)="Y"),T78,0) -> 0 | AD78: =IF(ISBLANK(W78),0,1) -> 0
A79: 78 | B79: RUFINA CABELLO TICLIO | C79: D | D79: 9 | F79: 1 | H79: 1 | I79: 4072 | J79: 4083 | K79: =J79-I79 -> 11 | L79: 11 | M79: 21 | O79: 0 | P79: 3 | Q79: 0 | T79: =SUM(L79:S79) -> 35 | U79: c | W79: y | Y79: Debe 30 faena | AA79: =IF(AND(L79>0, M79>=8, NOT(OR(U79="C", U79="c"))), "CORTE", "") | AB79: =IF(AND(LEN(U79)>0,LEN(W79)=0),T79,0) -> 0 | AC79: =IF(AND(LEN(U79)>0,TRIM(W79)="Y"),T79,0) -> 35
A80: 79 | B80: LIDIA ASTERIA SALES BLAS | C80: D | D80: 10 | H80: 1 | I80: 2827 | J80: 2838 | K80: =J80-I80 -> 11 | L80: 11 | M80: 0 | N80: 0 | O80: 0 | P80: 3 | Q80: 0 | R80: 0 | T80: =SUM(L80:S80) -> 14 | U80: c | W80: y | AA80: =IF(AND(L80>0, M80>=8, NOT(OR(U80="C", U80="c"))), "CORTE", "") | AB80: =IF(AND(LEN(U80)>0,LEN(W80)=0),T80,0) -> 0 | AC80: =IF(AND(LEN(U80)>0,TRIM(W80)="Y"),T80,0) -> 14 | AD80: =IF(ISBLANK(W80),0,1) -> 1
A81: 80 | B81: SALOMON RODRIGUEZ GARCIA | C81: D | D81: 11 | H81: 1 | I81: 1031 | J81: 1042 | K81: =J81-I81 -> 11 | L81: 11 | M81: 0 | N81: 0 | O81: 0 | P81: 3 | Q81: 0 | R81: 30 | T81: =SUM(L81:S81) -> 44 | U81: c | AA81: =IF(AND(L81>0, M81>=8, NOT(OR(U81="C", U81="c"))), "CORTE", "") | AB81: =IF(AND(LEN(U81)>0,LEN(W81)=0),T81,0) -> 44 | AC81: =IF(AND(LEN(U81)>0,TRIM(W81)="Y"),T81,0) -> 0
A82: 81 | B82: MARTINA MENDOZA ROMERO | C82: D | D82: 12 | H82: 1 | I82: 217 | J82: 227 | K82: =J82-I82 -> 10 | L82: 10 | M82: 22 | N82: 0 | O82: 0 | P82: 3 | Q82: 0 | R82: 0 | T82: =SUM(L82:S82) -> 35 | U82: c | W82: y | AA82: =IF(AND(L82>0, M82>=8, NOT(OR(U82="C", U82="c"))), "CORTE", "") | AB82: =IF(AND(LEN(U82)>0,LEN(W82)=0),T82,0) -> 0 | AC82: =IF(AND(LEN(U82)>0,TRIM(W82)="Y"),T82,0) -> 35 | AD82: =IF(ISBLANK(W82),0,1) -> 1
A83: 82 | B83: ROSELA ELVIRA MUÑOZ HERMITAÑO | C83: D | D83: 13 | H83: 1 | I83: 427 | J83: 446 | K83: =J83-I83 -> 19 | L83: 19 | M83: 0 | N83: 0 | O83: 0 | P83: 3 | Q83: 0 | R83: 0 | T83: =SUM(L83:S83) -> 22 | U83: c | W83: y | AA83: =IF(AND(L83>0, M83>=8, NOT(OR(U83="C", U83="c"))), "CORTE", "") | AB83: =IF(AND(LEN(U83)>0,LEN(W83)=0),T83,0) -> 0 | AC83: =IF(AND(LEN(U83)>0,TRIM(W83)="Y"),T83,0) -> 22 | AD83: =IF(ISBLANK(W83),0,1) -> 1
A84: 83 | B84: ESTEBAN GUERRERO CHINGEL | C84: D | D84: 16 | H84: 1 | I84: 1621 | J84: 1628 | K84: =J84-I84 -> 7 | L84: 7 | M84: 0 | N84: 0 | O84: 0 | P84: 3 | Q84: 0 | R84: 0 | T84: =SUM(L84:S84) -> 10 | U84: c | W84: y | AA84: =IF(AND(L84>0, M84>=8, NOT(OR(U84="C", U84="c"))), "CORTE", "") | AB84: =IF(AND(LEN(U84)>0,LEN(W84)=0),T84,0) -> 0 | AC84: =IF(AND(LEN(U84)>0,TRIM(W84)="Y"),T84,0) -> 10
A85: 84 | B85: MACARIO REQUEZ ROMERO | C85: D | D85: 17 | H85: 1 | I85: 3032 | J85: 3056 | K85: =J85-I85 -> 24 | L85: 24 | M85: 0 | N85: 0 | O85: 0 | P85: 3 | Q85: 0 | R85: 30 | T85: =SUM(L85:S85) -> 57 | U85: c | W85: y | AA85: =IF(AND(L85>0, M85>=8, NOT(OR(U85="C", U85="c"))), "CORTE", "") | AB85: =IF(AND(LEN(U85)>0,LEN(W85)=0),T85,0) -> 0 | AC85: =IF(AND(LEN(U85)>0,TRIM(W85)="Y"),T85,0) -> 57
A86: 85 | B86: LUIS GERARDO SAAVEDRA SAAVEDRA | C86: D | D86: 18 | H86: 1 | I86: 882 | J86: 907 | K86: =J86-I86 -> 25 | L86: 25 | M86: 0 | N86: 0 | O86: 0 | P86: 3 | Q86: 0 | R86: 30 | T86: =SUM(L86:S86) -> 58 | U86: c | AA86: =IF(AND(L86>0, M86>=8, NOT(OR(U86="C", U86="c"))), "CORTE", "") | AB86: =IF(AND(LEN(U86)>0,LEN(W86)=0),T86,0) -> 58 | AC86: =IF(AND(LEN(U86)>0,TRIM(W86)="Y"),T86,0) -> 0 | AD86: =IF(ISBLANK(W86),0,1) -> 0
A87: 86 | B87: FELIPE DOMINGO VENTURO CAPCHA | C87: D | D87: 19 | H87: 1 | I87: 1791 | J87: 1800 | K87: =J87-I87 -> 9 | L87: 9 | M87: 0 | N87: 0 | O87: 0 | P87: 3 | Q87: 0 | R87: 30 | T87: =SUM(L87:S87) -> 42 | U87: c | AA87: =IF(AND(L87>0, M87>=8, NOT(OR(U87="C", U87="c"))), "CORTE", "") | AB87: =IF(AND(LEN(U87)>0,LEN(W87)=0),T87,0) -> 42 | AC87: =IF(AND(LEN(U87)>0,TRIM(W87)="Y"),T87,0) -> 0
A88: 87 | B88: YOLANDA MATILDE MONTALVO COSME | C88: E | D88: 1 | H88: 1 | I88: 283 | J88: 287 | K88: =J88-I88 -> 4 | L88: 5 | M88: 0 | N88: 0 | O88: 0 | P88: 3 | Q88: 0 | R88: 0 | T88: =SUM(L88:S88) -> 8 | AA88: =IF(AND(L88>0, M88>=8, NOT(OR(U88="C", U88="c"))), "CORTE", "") | AB88: =IF(AND(LEN(U88)>0,LEN(W88)=0),T88,0) -> 0 | AC88: =IF(AND(LEN(U88)>0,TRIM(W88)="Y"),T88,0) -> 0 | AD88: =IF(ISBLANK(W88),0,1) -> 0
A89: 88 | B89: DARIO ROSALES TICLIO | C89: E | D89: 2 | H89: 1 | I89: 3212 | J89: 3227 | K89: =J89-I89 -> 15 | L89: 15 | M89: 0 | N89: 0 | O89: 0 | P89: 3 | Q89: 0 | R89: 0 | T89: =SUM(L89:S89) -> 18 | U89: c | W89: y | AA89: =IF(AND(L89>0, M89>=8, NOT(OR(U89="C", U89="c"))), "CORTE", "") | AB89: =IF(AND(LEN(U89)>0,LEN(W89)=0),T89,0) -> 0 | AC89: =IF(AND(LEN(U89)>0,TRIM(W89)="Y"),T89,0) -> 18 | AD89: =IF(ISBLANK(W89),0,1) -> 1
A90: 89 | B90: FELIX ENRIQUE VALENCIA FERNANDEZ | C90: E | D90: 3 | H90: 1 | I90: 2845 | J90: 2857 | K90: =J90-I90 -> 12 | L90: 12 | M90: 0 | N90: 0 | O90: 0 | P90: 3 | Q90: 0 | R90: 30 | T90: =SUM(L90:S90) -> 45 | U90: c | W90: y | AA90: =IF(AND(L90>0, M90>=8, NOT(OR(U90="C", U90="c"))), "CORTE", "") | AB90: =IF(AND(LEN(U90)>0,LEN(W90)=0),T90,0) -> 0 | AC90: =IF(AND(LEN(U90)>0,TRIM(W90)="Y"),T90,0) -> 45 | AD90: =IF(ISBLANK(W90),0,1) -> 1
A91: 90 | B91: FELIX VELASQUEZ LOPEZ | C91: E | D91: 4 | H91: 1 | I91: 134 | J91: 145 | K91: =J91-I91 -> 11 | L91: 11 | M91: 0 | N91: 0 | O91: 0 | P91: 3 | Q91: 0 | R91: 30 | T91: =SUM(L91:S91) -> 44 | AA91: =IF(AND(L91>0, M91>=8, NOT(OR(U91="C", U91="c"))), "CORTE", "") | AB91: =IF(AND(LEN(U91)>0,LEN(W91)=0),T91,0) -> 0 | AC91: =IF(AND(LEN(U91)>0,TRIM(W91)="Y"),T91,0) -> 0
A92: 91 | B92: LUIS ALBERTO GOMEZ LAHUANA | C92: E | D92: 6 | H92: 1 | I92: 887 | J92: 900 | K92: =J92-I92 -> 13 | L92: 13 | M92: 0 | N92: 0 | O92: 0 | P92: 3 | Q92: 0 | T92: =SUM(L92:S92) -> 16 | U92: c | W92: y | Y92: Debe 30 faena | AA92: =IF(AND(L92>0, M92>=8, NOT(OR(U92="C", U92="c"))), "CORTE", "") | AB92: =IF(AND(LEN(U92)>0,LEN(W92)=0),T92,0) -> 0 | AC92: =IF(AND(LEN(U92)>0,TRIM(W92)="Y"),T92,0) -> 16 | AD92: =IF(ISBLANK(W92),0,1) -> 1
A93: 92 | B93: GREGORIO TRUJILLO LEON | C93: E | D93: 7 | H93: 1 | I93: 1875 | J93: 1879 | K93: =J93-I93 -> 4 | L93: 5 | M93: 0 | N93: 0 | O93: 0 | P93: 3 | Q93: 0 | R93: 0 | T93: =SUM(L93:S93) -> 8 | U93: c | W93: y | AA93: =IF(AND(L93>0, M93>=8, NOT(OR(U93="C", U93="c"))), "CORTE", "") | AB93: =IF(AND(LEN(U93)>0,LEN(W93)=0),T93,0) -> 0 | AC93: =IF(AND(LEN(U93)>0,TRIM(W93)="Y"),T93,0) -> 8 | AD93: =IF(ISBLANK(W93),0,1) -> 1
A94: 93 | B94: GERTRUDES VIDAL GONZALES | C94: E | D94: 8 | F94: 1 | H94: 1 | I94: 973 | J94: 977 | K94: =J94-I94 -> 4 | L94: 5 | M94: 0 | N94: 0 | O94: 0 | P94: 3 | Q94: 0 | R94: 30 | T94: =SUM(L94:S94) -> 38 | U94: c | W94: y | Y94: Pago Yape de lote G18 (37), C19 (24) | AA94: =IF(AND(L94>0, M94>=8, NOT(OR(U94="C", U94="c"))), "CORTE", "") | AB94: =IF(AND(LEN(U94)>0,LEN(W94)=0),T94,0) -> 0 | AC94: =IF(AND(LEN(U94)>0,TRIM(W94)="Y"),T94,0) -> 38 | AD94: =IF(ISBLANK(W94),0,1) -> 1
A95: 94 | B95: MARIA NANCY SIGUEÑAS UGARTE | C95: E | D95: 9 | H95: 1 | I95: 3592 | J95: 3610 | K95: =J95-I95 -> 18 | L95: 18 | M95: 0 | N95: 0 | O95: 0 | P95: 3 | Q95: 0 | R95: 0 | T95: =SUM(L95:S95) -> 21 | U95: c | AA95: =IF(AND(L95>0, M95>=8, NOT(OR(U95="C", U95="c"))), "CORTE", "") | AB95: =IF(AND(LEN(U95)>0,LEN(W95)=0),T95,0) -> 21 | AC95: =IF(AND(LEN(U95)>0,TRIM(W95)="Y"),T95,0) -> 0 | AD95: =IF(ISBLANK(W95),0,1) -> 0
A96: 95 | B96: GREGORIA SIGUEÑAS UGARTE | C96: E | D96: 10 | H96: 1 | I96: 819 | J96: 858 | K96: =J96-I96 -> 39 | L96: 39 | M96: 33 | N96: 0 | O96: 0 | P96: 3 | Q96: 0 | T96: =SUM(L96:S96) -> 75 | U96: c | Y96: Debe 30 faena | AA96: =IF(AND(L96>0, M96>=8, NOT(OR(U96="C", U96="c"))), "CORTE", "") | AB96: =IF(AND(LEN(U96)>0,LEN(W96)=0),T96,0) -> 75 | AC96: =IF(AND(LEN(U96)>0,TRIM(W96)="Y"),T96,0) -> 0 | AD96: =IF(ISBLANK(W96),0,1) -> 0
A97: 96 | B97: VILMA SIGUEÑAS UGARTE | C97: E | D97: 11 | H97: 1 | I97: 4030 | J97: 4059 | K97: =J97-I97 -> 29 | L97: 29 | M97: 0 | N97: 0 | O97: 0 | P97: 3 | Q97: 0 | T97: =SUM(L97:S97) -> 32 | U97: c | Y97: Debe 30 faena | AA97: =IF(AND(L97>0, M97>=8, NOT(OR(U97="C", U97="c"))), "CORTE", "") | AB97: =IF(AND(LEN(U97)>0,LEN(W97)=0),T97,0) -> 32 | AC97: =IF(AND(LEN(U97)>0,TRIM(W97)="Y"),T97,0) -> 0 | AD97: =IF(ISBLANK(W97),0,1) -> 0
A98: 97 | B98: TEOFILA FERNANDEZ REYES | C98: E | D98: 12 | H98: 1 | I98: 3662 | J98: 3675 | K98: =J98-I98 -> 13 | L98: 13 | M98: 0 | N98: 0 | O98: 0 | P98: 3 | Q98: 0 | R98: 0 | T98: =SUM(L98:S98) -> 16 | U98: c | AA98: =IF(AND(L98>0, M98>=8, NOT(OR(U98="C", U98="c"))), "CORTE", "") | AB98: =IF(AND(LEN(U98)>0,LEN(W98)=0),T98,0) -> 16 | AC98: =IF(AND(LEN(U98)>0,TRIM(W98)="Y"),T98,0) -> 0 | AD98: =IF(ISBLANK(W98),0,1) -> 0
A99: 98 | B99: LINDOLINA MUÑOZ HERMITAÑO | C99: E | D99: 13 | H99: 1 | I99: 3001 | J99: 3014 | K99: =J99-I99 -> 13 | L99: 13 | M99: 3 | N99: 0 | O99: 0 | P99: 3 | Q99: 0 | R99: 0 | T99: =SUM(L99:S99) -> 19 | U99: c | W99: y | AA99: =IF(AND(L99>0, M99>=8, NOT(OR(U99="C", U99="c"))), "CORTE", "") | AB99: =IF(AND(LEN(U99)>0,LEN(W99)=0),T99,0) -> 0 | AC99: =IF(AND(LEN(U99)>0,TRIM(W99)="Y"),T99,0) -> 19 | AD99: =IF(ISBLANK(W99),0,1) -> 1
A100: 99 | B100: FELICIANO SIGUEÑAS UGARTE | C100: E | D100: 14 | H100: 1 | I100: 15 | J100: 26 | K100: =J100-I100 -> 11 | L100: 11 | M100: 11 | N100: 0 | O100: 0 | P100: 3 | Q100: 0 | R100: 0 | T100: =SUM(L100:S100) -> 25 | U100: c | AA100: =IF(AND(L100>0, M100>=8, NOT(OR(U100="C", U100="c"))), "CORTE", "") | AB100: =IF(AND(LEN(U100)>0,LEN(W100)=0),T100,0) -> 25 | AC100: =IF(AND(LEN(U100)>0,TRIM(W100)="Y"),T100,0) -> 0 | AD100: =IF(ISBLANK(W100),0,1) -> 0
...

Sheet INGRESOS Y EGRESOS
A1: 11 | B1: MONEDEROS | F1: EFECTIVO | J1: 3321 | K1: 8291
B2: AGUA | F2: AGUA
A3: FECHA | B3: CONCEPTO | C3: MONTO | F3: CONCEPTO | G3: MONTO
B4: JANET YAPE | C4: =Cobranza!AC498 -> 8291 | F4: YANET EFECTIVO | G4: =Cobranza!AB498 -> 3321
B6: Ingreso yape
B7: Salida yape
B8: Salida yape | C8: -6574.4
F9: Es del Efectivo | G9: 100 | J9: =SUM(J4:J5) -> 0
B10: Es del efectivo | C10: -100
B16: SALDO | C16: =SUM(C4:C15) -> 1616.6 | F16: SALDO | G16: =SUM(G4:G15) -> 3421
B17: Yanet tiene yape Este mes | C17: 1616.6 | F17: Yanet tiene efectivo | G17: 3421
B18: Sobra o falta | C18: =C16-C17 -> 0 | F18: Sobra o falta | G18: =G17-G16 -> 0
B19: El menos 8 nos indica que hay un Yape adelantado que
B20: nohe identificado su dueño
D21: TOTAL | E21: =C16+G16 -> 5037.6

Sheet Yape por MZ
A1: Recaudo por Manzana
A3: Mnz | B3: Reporte Yape-M | C3: Planilla-A | D3: Comentario | E3: Excesos y deudas-A
A4: A | B4: =SUMIF(Reporte!$F$2:$F$349, 'Yape por MZ'!A4, Reporte!$E$2:$E$349) -> 339 | C4: =SUMPRODUCT( (UPPER(Cobranza!C2:C497)=UPPER(A4))* (UPPER(Cobranza!U2:U497)="C")* (UPPER(Cobranza!W2:W497)="Y")* (Cobranza!T2:T497) ) -> 339 | D4: =B4-C4 -> 0 | E4: =SUMPRODUCT( (UPPER(Cobranza!C2:C497)=UPPER(A4))* (UPPER(Cobranza!U2:U497)="C")* (UPPER(Cobranza!W2:W497)="Y")* (Cobranza!X2:X497) ) -> 0 | F4: =IF(OR(C4=B4), 0, 1) -> 0
A5: B | B5: =SUMIF(Reporte!$F$2:$F$349, 'Yape por MZ'!A5, Reporte!$E$2:$E$349) -> 188 | C5: =SUMPRODUCT( (UPPER(Cobranza!C3:C498)=UPPER(A5))* (UPPER(Cobranza!U3:U498)="C")* (UPPER(Cobranza!W3:W498)="Y")* (Cobranza!T3:T498) ) -> 188 | D5: =B5-C5 -> 0 | E5: =SUMPRODUCT( (UPPER(Cobranza!C3:C498)=UPPER(A5))* (UPPER(Cobranza!U3:U498)="C")* (UPPER(Cobranza!W3:W498)="Y")* (Cobranza!X3:X498) ) -> 0 | F5: =IF(OR(C5=B5), 0, 1) -> 0
A6: C | B6: =SUMIF(Reporte!$F$2:$F$349, 'Yape por MZ'!A6, Reporte!$E$2:$E$349) -> 394 | C6: =SUMPRODUCT( (UPPER(Cobranza!C4:C498)=UPPER(A6))* (UPPER(Cobranza!U4:U498)="C")* (UPPER(Cobranza!W4:W498)="Y")* (Cobranza!T4:T498) ) -> 394 | D6: =B6-C6 -> 0 | E6: =SUMPRODUCT( (UPPER(Cobranza!C4:C498)=UPPER(A6))* (UPPER(Cobranza!U4:U498)="C")* (UPPER(Cobranza!W4:W498)="Y")* (Cobranza!X4:X498) ) -> 0 | F6: =IF(OR(C6=B6), 0, 1) -> 0
A7: D | B7: =SUMIF(Reporte!$F$2:$F$349, 'Yape por MZ'!A7, Reporte!$E$2:$E$349) -> 242 | C7: =SUMPRODUCT( (UPPER(Cobranza!C5:C500)=UPPER(A7))* (UPPER(Cobranza!U5:U500)="C")* (UPPER(Cobranza!W5:W500)="Y")* (Cobranza!T5:T500) ) -> 242 | D7: =B7-C7 -> 0 | E7: =SUMPRODUCT( (UPPER(Cobranza!C5:C500)=UPPER(A7))* (UPPER(Cobranza!U5:U500)="C")* (UPPER(Cobranza!W5:W500)="Y")* (Cobranza!X5:X500) ) -> 0 | F7: =IF(OR(C7=B7), 0, 1) -> 0
A8: E | B8: =SUMIF(Reporte!$F$2:$F$349, 'Yape por MZ'!A8, Reporte!$E$2:$E$349) -> 168 | C8: =SUMPRODUCT( (UPPER(Cobranza!C6:C501)=UPPER(A8))* (UPPER(Cobranza!U6:U501)="C")* (UPPER(Cobranza!W6:W501)="Y")* (Cobranza!T6:T501) ) -> 168 | D8: =B8-C8 -> 0 | E8: =SUMPRODUCT( (UPPER(Cobranza!C6:C501)=UPPER(A8))* (UPPER(Cobranza!U6:U501)="C")* (UPPER(Cobranza!W6:W501)="Y")* (Cobranza!X6:X501) ) -> 0 | F8: =IF(OR(C8=B8), 0, 1) -> 0
A9: F | B9: =SUMIF(Reporte!$F$2:$F$349, 'Yape por MZ'!A9, Reporte!$E$2:$E$349) -> 344 | C9: =SUMPRODUCT( (UPPER(Cobranza!C7:C502)=UPPER(A9))* (UPPER(Cobranza!U7:U502)="C")* (UPPER(Cobranza!W7:W502)="Y")* (Cobranza!T7:T502) ) -> 344 | D9: =B9-C9 -> 0 | E9: =SUMPRODUCT( (UPPER(Cobranza!C7:C502)=UPPER(A9))* (UPPER(Cobranza!U7:U502)="C")* (UPPER(Cobranza!W7:W502)="Y")* (Cobranza!X7:X502) ) -> 0 | F9: =IF(OR(C9=B9), 0, 1) -> 0
A10: G | B10: =SUMIF(Reporte!$F$2:$F$349, 'Yape por MZ'!A10, Reporte!$E$2:$E$349) -> 468 | C10: =SUMPRODUCT( (UPPER(Cobranza!C8:C503)=UPPER(A10))* (UPPER(Cobranza!U8:U503)="C")* (UPPER(Cobranza!W8:W503)="Y")* (Cobranza!T8:T503) ) -> 468 | D10: =B10-C10 -> 0 | F10: =IF(OR(C10=B10), 0, 1) -> 0
A11: H | B11: =SUMIF(Reporte!$F$2:$F$349, 'Yape por MZ'!A11, Reporte!$E$2:$E$349) -> 289 | C11: =SUMPRODUCT( (UPPER(Cobranza!C9:C504)=UPPER(A11))* (UPPER(Cobranza!U9:U504)="C")* (UPPER(Cobranza!W9:W504)="Y")* (Cobranza!T9:T504) ) -> 289 | D11: =B11-C11 -> 0 | F11: =IF(OR(C11=B11), 0, 1) -> 0
A12: I | B12: =SUMIF(Reporte!$F$2:$F$349, 'Yape por MZ'!A12, Reporte!$E$2:$E$349) -> 144 | C12: =SUMPRODUCT( (UPPER(Cobranza!C10:C505)=UPPER(A12))* (UPPER(Cobranza!U10:U505)="C")* (UPPER(Cobranza!W10:W505)="Y")* (Cobranza!T10:T505) ) -> 144 | D12: =B12-C12 -> 0 | E12: I10(8) Yape adelantado | F12: =IF(OR(C12=B12), 0, 1) -> 0
A13: J | B13: =SUMIF(Reporte!$F$2:$F$349, 'Yape por MZ'!A13, Reporte!$E$2:$E$349) -> 71 | C13: =SUMPRODUCT( (UPPER(Cobranza!C11:C506)=UPPER(A13))* (UPPER(Cobranza!U11:U506)="C")* (UPPER(Cobranza!W11:W506)="Y")* (Cobranza!T11:T506) ) -> 71 | D13: =B13-C13 -> 0 | F13: =IF(OR(C13=B13), 0, 1) -> 0
A14: K | B14: =SUMIF(Reporte!$F$2:$F$349, 'Yape por MZ'!A14, Reporte!$E$2:$E$349) -> 158 | C14: =SUMPRODUCT( (UPPER(Cobranza!C12:C507)=UPPER(A14))* (UPPER(Cobranza!U12:U507)="C")* (UPPER(Cobranza!W12:W507)="Y")* (Cobranza!T12:T507) ) -> 158 | D14: =B14-C14 -> 0 | E14: K11(13), K17(16) Yape Adelantado | F14: =IF(OR(C14=B14), 0, 1) -> 0
A15: L | B15: =SUMIF(Reporte!$F$2:$F$349, 'Yape por MZ'!A15, Reporte!$E$2:$E$349) -> 189 | C15: =SUMPRODUCT( (UPPER(Cobranza!C13:C508)=UPPER(A15))* (UPPER(Cobranza!U13:U508)="C")* (UPPER(Cobranza!W13:W508)="Y")* (Cobranza!T13:T508) ) -> 189 | D15: =B15-C15 -> 0 | F15: =IF(OR(C15=B15), 0, 1) -> 0
A16: M | B16: =SUMIF(Reporte!$F$2:$F$349, 'Yape por MZ'!A16, Reporte!$E$2:$E$349) -> 322 | C16: =SUMPRODUCT( (UPPER(Cobranza!C14:C509)=UPPER(A16))* (UPPER(Cobranza!U14:U509)="C")* (UPPER(Cobranza!W14:W509)="Y")* (Cobranza!T14:T509) ) -> 322 | D16: =B16-C16 -> 0 | F16: =IF(OR(C16=B16), 0, 1) -> 0
A17: N | B17: =SUMIF(Reporte!$F$2:$F$349, 'Yape por MZ'!A17, Reporte!$E$2:$E$349) -> 79 | C17: =SUMPRODUCT( (UPPER(Cobranza!C15:C510)=UPPER(A17))* (UPPER(Cobranza!U15:U510)="C")* (UPPER(Cobranza!W15:W510)="Y")* (Cobranza!T15:T510) ) -> 79 | D17: =B17-C17 -> 0 | F17: =IF(OR(C17=B17), 0, 1) -> 0
A18: O | B18: =SUMIF(Reporte!$F$2:$F$349, 'Yape por MZ'!A18, Reporte!$E$2:$E$349) -> 402 | C18: =SUMPRODUCT( (UPPER(Cobranza!C16:C511)=UPPER(A18))* (UPPER(Cobranza!U16:U511)="C")* (UPPER(Cobranza!W16:W511)="Y")* (Cobranza!T16:T511) ) -> 402 | D18: =B18-C18 -> 0 | F18: =IF(OR(C18=B18), 0, 1) -> 0
A19: P | B19: =SUMIF(Reporte!$F$2:$F$349, 'Yape por MZ'!A19, Reporte!$E$2:$E$349) -> 313 | C19: =SUMPRODUCT( (UPPER(Cobranza!C17:C512)=UPPER(A19))* (UPPER(Cobranza!U17:U512)="C")* (UPPER(Cobranza!W17:W512)="Y")* (Cobranza!T17:T512) ) -> 313 | D19: =B19-C19 -> 0 | E19: P18(12) Efectivo | F19: =IF(OR(C19=B19), 0, 1) -> 0
A20: Q | B20: =SUMIF(Reporte!$F$2:$F$349, 'Yape por MZ'!A20, Reporte!$E$2:$E$349) -> 255 | C20: =SUMPRODUCT( (UPPER(Cobranza!C18:C513)=UPPER(A20))* (UPPER(Cobranza!U18:U513)="C")* (UPPER(Cobranza!W18:W513)="Y")* (Cobranza!T18:T513) ) -> 255 | D20: =B20-C20 -> 0 | F20: =IF(OR(C20=B20), 0, 1) -> 0
A21: R | B21: =SUMIF(Reporte!$F$2:$F$349, 'Yape por MZ'!A21, Reporte!$E$2:$E$349) -> 72 | C21: =SUMPRODUCT( (UPPER(Cobranza!C19:C514)=UPPER(A21))* (UPPER(Cobranza!U19:U514)="C")* (UPPER(Cobranza!W19:W514)="Y")* (Cobranza!T19:T514) ) -> 72 | D21: =B21-C21 -> 0 | F21: =IF(OR(C21=B21), 0, 1) -> 0
A22: S | B22: =SUMIF(Reporte!$F$2:$F$349, 'Yape por MZ'!A22, Reporte!$E$2:$E$349) -> 352 | C22: =SUMPRODUCT( (UPPER(Cobranza!C20:C515)=UPPER(A22))* (UPPER(Cobranza!U20:U515)="C")* (UPPER(Cobranza!W20:W515)="Y")* (Cobranza!T20:T515) ) -> 352 | D22: =B22-C22 -> 0 | F22: =IF(OR(C22=B22), 0, 1) -> 0
A23: T | B23: =SUMIF(Reporte!$F$2:$F$349, 'Yape por MZ'!A23, Reporte!$E$2:$E$349) -> 365 | C23: =SUMPRODUCT( (UPPER(Cobranza!C21:C516)=UPPER(A23))* (UPPER(Cobranza!U21:U516)="C")* (UPPER(Cobranza!W21:W516)="Y")* (Cobranza!T21:T516) ) -> 365 | D23: =B23-C23 -> 0 | F23: =IF(OR(C23=B23), 0, 1) -> 0
A24: U | B24: =SUMIF(Reporte!$F$2:$F$349, 'Yape por MZ'!A24, Reporte!$E$2:$E$349) -> 77 | C24: =SUMPRODUCT( (UPPER(Cobranza!C22:C517)=UPPER(A24))* (UPPER(Cobranza!U22:U517)="C")* (UPPER(Cobranza!W22:W517)="Y")* (Cobranza!T22:T517) ) -> 77 | D24: =B24-C24 -> 0 | F24: =IF(OR(C24=B24), 0, 1) -> 0
A25: V | B25: =SUMIF(Reporte!$F$2:$F$349, 'Yape por MZ'!A25, Reporte!$E$2:$E$349) -> 180 | C25: =SUMPRODUCT( (UPPER(Cobranza!C23:C518)=UPPER(A25))* (UPPER(Cobranza!U23:U518)="C")* (UPPER(Cobranza!W23:W518)="Y")* (Cobranza!T23:T518) ) -> 180 | D25: =B25-C25 -> 0 | F25: =IF(OR(C25=B25), 0, 1) -> 0
A26: W | B26: =SUMIF(Reporte!$F$2:$F$349, 'Yape por MZ'!A26, Reporte!$E$2:$E$349) -> 244 | C26: =SUMPRODUCT( (UPPER(Cobranza!C24:C519)=UPPER(A26))* (UPPER(Cobranza!U24:U519)="C")* (UPPER(Cobranza!W24:W519)="Y")* (Cobranza!T24:T519) ) -> 244 | D26: =B26-C26 -> 0 | E26: W20(23) Yape adelantado | F26: =IF(OR(C26=B26), 0, 1) -> 0
A27: X | B27: =SUMIF(Reporte!$F$2:$F$349, 'Yape por MZ'!A27, Reporte!$E$2:$E$349) -> 310 | C27: =SUMPRODUCT( (UPPER(Cobranza!C25:C520)=UPPER(A27))* (UPPER(Cobranza!U25:U520)="C")* (UPPER(Cobranza!W25:W520)="Y")* (Cobranza!T25:T520) ) -> 310 | D27: =B27-C27 -> 0 | F27: =IF(OR(C27=B27), 0, 1) -> 0
A28: Y | B28: =SUMIF(Reporte!$F$2:$F$349, 'Yape por MZ'!A28, Reporte!$E$2:$E$349) -> 113 | C28: =SUMPRODUCT( (UPPER(Cobranza!C26:C521)=UPPER(A28))* (UPPER(Cobranza!U26:U521)="C")* (UPPER(Cobranza!W26:W521)="Y")* (Cobranza!T26:T521) ) -> 113 | D28: =B28-C28 -> 0 | F28: =IF(OR(C28=B28), 0, 1) -> 0
A29: Z | B29: =SUMIF(Reporte!$F$2:$F$349, 'Yape por MZ'!A29, Reporte!$E$2:$E$349) -> 282 | C29: =SUMPRODUCT( (UPPER(Cobranza!C27:C522)=UPPER(A29))* (UPPER(Cobranza!U27:U522)="C")* (UPPER(Cobranza!W27:W522)="Y")* (Cobranza!T27:T522) ) -> 282 | D29: =B29-C29 -> 0 | F29: =IF(OR(C29=B29), 0, 1) -> 0
A30: A1 | B30: =SUMIF(Reporte!$F$2:$F$349, 'Yape por MZ'!A30, Reporte!$E$2:$E$349) -> 284 | C30: =SUMPRODUCT( (UPPER(Cobranza!C28:C523)=UPPER(A30))* (UPPER(Cobranza!U28:U523)="C")* (UPPER(Cobranza!W28:W523)="Y")* (Cobranza!T28:T523) ) -> 284 | D30: =B30-C30 -> 0 | F30: =IF(OR(C30=B30), 0, 1) -> 0
A31: B1 | B31: =SUMIF(Reporte!$F$2:$F$349, 'Yape por MZ'!A31, Reporte!$E$2:$E$349) -> 332 | C31: =SUMPRODUCT( (UPPER(Cobranza!C29:C524)=UPPER(A31))* (UPPER(Cobranza!U29:U524)="C")* (UPPER(Cobranza!W29:W524)="Y")* (Cobranza!T29:T524) ) -> 332 | D31: =B31-C31 -> 0 | F31: =IF(OR(C31=B31), 0, 1) -> 0
A32: C1 | B32: =SUMIF(Reporte!$F$2:$F$349, 'Yape por MZ'!A32, Reporte!$E$2:$E$349) -> 309 | C32: =SUMPRODUCT( (UPPER(Cobranza!C30:C525)=UPPER(A32))* (UPPER(Cobranza!U30:U525)="C")* (UPPER(Cobranza!W30:W525)="Y")* (Cobranza!T30:T525) ) -> 309 | D32: =B32-C32 -> 0 | F32: =IF(OR(C32=B32), 0, 1) -> 0
A33: D1 | B33: =SUMIF(Reporte!$F$2:$F$349, 'Yape por MZ'!A33, Reporte!$E$2:$E$349) -> 102 | C33: =SUMPRODUCT( (UPPER(Cobranza!C31:C526)=UPPER(A33))* (UPPER(Cobranza!U31:U526)="C")* (UPPER(Cobranza!W31:W526)="Y")* (Cobranza!T31:T526) ) -> 102 | D33: =B33-C33 -> 0 | F33: =IF(OR(C33=B33), 0, 1) -> 0
A34: E1 | B34: =SUMIF(Reporte!$F$2:$F$349, 'Yape por MZ'!A34, Reporte!$E$2:$E$349) -> 139 | C34: =SUMPRODUCT( (UPPER(Cobranza!C32:C527)=UPPER(A34))* (UPPER(Cobranza!U32:U527)="C")* (UPPER(Cobranza!W32:W527)="Y")* (Cobranza!T32:T527) ) -> 139 | D34: =B34-C34 -> 0 | F34: =IF(OR(C34=B34), 0, 1) -> 0
A35: F1 | B35: =SUMIF(Reporte!$F$2:$F$349, 'Yape por MZ'!A35, Reporte!$E$2:$E$349) -> 193 | C35: =SUMPRODUCT( (UPPER(Cobranza!C33:C528)=UPPER(A35))* (UPPER(Cobranza!U33:U528)="C")* (UPPER(Cobranza!W33:W528)="Y")* (Cobranza!T33:T528) ) -> 193 | D35: =B35-C35 -> 0 | F35: =IF(OR(C35=B35), 0, 1) -> 0
A36: G1 | B36: =SUMIF(Reporte!$F$2:$F$349, 'Yape por MZ'!A36, Reporte!$E$2:$E$349) -> 75 | C36: =SUMPRODUCT( (UPPER(Cobranza!C34:C529)=UPPER(A36))* (UPPER(Cobranza!U34:U529)="C")* (UPPER(Cobranza!W34:W529)="Y")* (Cobranza!T34:T529) ) -> 75 | D36: =B36-C36 -> 0 | F36: =IF(OR(C36=B36), 0, 1) -> 0
A37: H1 | B37: =SUMIF(Reporte!$F$2:$F$349, 'Yape por MZ'!A37, Reporte!$E$2:$E$349) -> 397 | C37: =SUMPRODUCT( (UPPER(Cobranza!C35:C530)=UPPER(A37))* (UPPER(Cobranza!U35:U530)="C")* (UPPER(Cobranza!W35:W530)="Y")* (Cobranza!T35:T530) ) -> 497 | D37: =B37-C37 -> -100 | E37: Es del efectivo | F37: =IF(OR(C37=B37), 0, 1) -> 1
B39: =SUM(B4:B37) -> 8191 | C39: =SUM(C4:C37) -> 8291 | D39: =SUM(D4:D37) -> -100 | E39: =SUM(E4:E37) -> 0
D40: =B39-C39 -> -100
C42: h

Sheet Reporte
A1: Tipo de Transacción | B1: Origen | C1: Destino | D1: Monto | E1: Valor | F1: MZ | G1: LOTE | H1: Mensaje | I1: Fecha de operación | J1: Año | K1: Mes | L1: Dia | M1: Hora
A2: TE PAGÓ | B2: Washington Medrano M. | C2: Janet Villanueva A. | D2: 46.00 | E2: =VALUE(SUBSTITUTE(D2, ".", ",")) -> 46 | F2: W | G2: 5 | H2: MZ W LT 5 | I2: 07/12/2025 21:31:13 | J2: =MID(I2,7,4) -> 2025 | K2: =MID(I2,4,2) -> 12 | L2: =LEFT(I2,2) -> 07 | M2: =RIGHT(I2,8) -> 21:31:13
A3: TE PAGÓ | B3: William Trujillo R. | C3: Janet Villanueva A. | D3: 8.00 | E3: =VALUE(SUBSTITUTE(D3, ".", ",")) -> 8 | F3: E | G3: 7 | H3: mzE lt7 | I3: 07/12/2025 18:25:49 | J3: =MID(I3,7,4) -> 2025 | K3: =MID(I3,4,2) -> 12 | L3: =LEFT(I3,2) -> 07 | M3: =RIGHT(I3,8) -> 18:25:49
A4: TE PAGÓ | B4: Luis F. Paucar Q. | C4: Janet Villanueva A. | D4: 3.00 | E4: =VALUE(SUBSTITUTE(D4, ".", ",")) -> 3 | F4: B1 | G4: 5 | I4: 07/12/2025 14:57:33 | J4: =MID(I4,7,4) -> 2025 | K4: =MID(I4,4,2) -> 12 | L4: =LEFT(I4,2) -> 07 | M4: =RIGHT(I4,8) -> 14:57:33
A5: TE PAGÓ | B5: Mari Celidonio C. | C5: Janet Villanueva A. | D5: 36.00 | E5: =VALUE(SUBSTITUTE(D5, ".", ",")) -> 36 | F5: C1 | G5: 14 | I5: 07/12/2025 13:41:19 | J5: =MID(I5,7,4) -> 2025 | K5: =MID(I5,4,2) -> 12 | L5: =LEFT(I5,2) -> 07 | M5: =RIGHT(I5,8) -> 13:41:19
A6: TE PAGÓ | B6: Washington Medrano M. | C6: Janet Villanueva A. | D6: 47.00 | E6: =VALUE(SUBSTITUTE(D6, ".", ",")) -> 47 | F6: G | G6: 16 | H6: MZ G LT 16 | I6: 07/12/2025 10:14:53 | J6: =MID(I6,7,4) -> 2025 | K6: =MID(I6,4,2) -> 12 | L6: =LEFT(I6,2) -> 07 | M6: =RIGHT(I6,8) -> 10:14:53
A7: TE PAGÓ | B7: Luis F. Paucar Q. | C7: Janet Villanueva A. | D7: 7.00 | E7: =VALUE(SUBSTITUTE(D7, ".", ",")) -> 7 | F7: B1 | G7: 5 | I7: 07/12/2025 10:06:36 | J7: =MID(I7,7,4) -> 2025 | K7: =MID(I7,4,2) -> 12 | L7: =LEFT(I7,2) -> 07 | M7: =RIGHT(I7,8) -> 10:06:36
A8: TE PAGÓ | B8: Jimm P. Zapata M. | C8: Janet Villanueva A. | D8: 46.00 | E8: =VALUE(SUBSTITUTE(D8, ".", ",")) -> 46 | F8: H1 | G8: 8 | H8: Jimm zapata agua - lt 8 mz h1 | I8: 07/12/2025 09:51:28 | J8: =MID(I8,7,4) -> 2025 | K8: =MID(I8,4,2) -> 12 | L8: =LEFT(I8,2) -> 07 | M8: =RIGHT(I8,8) -> 09:51:28
A9: TE PAGÓ | B9: Yicson A. Zapata M. | C9: Janet Villanueva A. | D9: 42.00 | E9: =VALUE(SUBSTITUTE(D9, ".", ",")) -> 42 | F9: H1 | G9: 7 | H9: mz h1 lote 7 yicson Zapata Martinez | I9: 07/12/2025 09:47:58 | J9: =MID(I9,7,4) -> 2025 | K9: =MID(I9,4,2) -> 12 | L9: =LEFT(I9,2) -> 07 | M9: =RIGHT(I9,8) -> 09:47:58
A10: TE PAGÓ | B10: Dante R. Meza M. | C10: Janet Villanueva A. | D10: 42.00 | E10: =VALUE(SUBSTITUTE(D10, ".", ",")) -> 42 | F10: H1 | G10: 12 | H10: mz h1 LT 12 | I10: 07/12/2025 09:14:28 | J10: =MID(I10,7,4) -> 2025 | K10: =MID(I10,4,2) -> 12 | L10: =LEFT(I10,2) -> 07 | M10: =RIGHT(I10,8) -> 09:14:28
A11: TE PAGÓ | B11: Jessica Y. Morales V. | C11: Janet Villanueva A. | D11: 49.00 | E11: =VALUE(SUBSTITUTE(D11, ".", ",")) -> 49 | F11: Q | G11: 12 | H11: MZ.Q LT.12 | I11: 07/12/2025 06:03:01 | J11: =MID(I11,7,4) -> 2025 | K11: =MID(I11,4,2) -> 12 | L11: =LEFT(I11,2) -> 07 | M11: =RIGHT(I11,8) -> 06:03:01
A12: TE PAGÓ | B12: Elizabeth S. Regalado C. | C12: Janet Villanueva A. | D12: 27.00 | E12: =VALUE(SUBSTITUTE(D12, ".", ",")) -> 27 | F12: N | G12: 5 | H12: mz,N lt.5 | I12: 06/12/2025 23:34:14 | J12: =MID(I12,7,4) -> 2025 | K12: =MID(I12,4,2) -> 12 | L12: =LEFT(I12,2) -> 06 | M12: =RIGHT(I12,8) -> 23:34:14
A13: TE PAGÓ | B13: Nelly M. De-la-cruz H. | C13: Janet Villanueva A. | D13: 16.00 | E13: =VALUE(SUBSTITUTE(D13, ".", ",")) -> 16 | F13: O | G13: 15 | I13: 06/12/2025 22:43:26 | J13: =MID(I13,7,4) -> 2025 | K13: =MID(I13,4,2) -> 12 | L13: =LEFT(I13,2) -> 06 | M13: =RIGHT(I13,8) -> 22:43:26
A14: TE PAGÓ | B14: Raul R. Blas Q. | C14: Janet Villanueva A. | D14: 38.00 | E14: =VALUE(SUBSTITUTE(D14, ".", ",")) -> 38 | F14: M | G14: 17 | H14: Mz .M. Lt.17 | I14: 06/12/2025 22:37:43 | J14: =MID(I14,7,4) -> 2025 | K14: =MID(I14,4,2) -> 12 | L14: =LEFT(I14,2) -> 06 | M14: =RIGHT(I14,8) -> 22:37:43
A15: TE PAGÓ | B15: Janet Villanueva A. | C15: Janet Villanueva A. | D15: 36.00 | E15: =VALUE(SUBSTITUTE(D15, ".", ",")) -> 36 | F15: C | G15: 8B | H15: mz c lt 8 B | I15: 06/12/2025 22:36:34 | J15: =MID(I15,7,4) -> 2025 | K15: =MID(I15,4,2) -> 12 | L15: =LEFT(I15,2) -> 06 | M15: =RIGHT(I15,8) -> 22:36:34
A16: TE PAGÓ | B16: Janet Villanueva A. | C16: Janet Villanueva A. | D16: 6.00 | E16: =VALUE(SUBSTITUTE(D16, ".", ",")) -> 6 | F16: E | G16: 13 | H16: mz E lt 13 | I16: 06/12/2025 22:35:16 | J16: =MID(I16,7,4) -> 2025 | K16: =MID(I16,4,2) -> 12 | L16: =LEFT(I16,2) -> 06 | M16: =RIGHT(I16,8) -> 22:35:16
A17: TE PAGÓ | B17: Raul R. Blas Q. | C17: Janet Villanueva A. | D17: 17.00 | E17: =VALUE(SUBSTITUTE(D17, ".", ",")) -> 17 | F17: O | G17: 9 | I17: 06/12/2025 22:34:31 | J17: =MID(I17,7,4) -> 2025 | K17: =MID(I17,4,2) -> 12 | L17: =LEFT(I17,2) -> 06 | M17: =RIGHT(I17,8) -> 22:34:31
A18: TE PAGÓ | B18: Janet Villanueva A. | C18: Janet Villanueva A. | D18: 13.00 | E18: =VALUE(SUBSTITUTE(D18, ".", ",")) -> 13 | F18: E | G18: 13 | H18: mz E lt 13 | I18: 06/12/2025 22:34:08 | J18: =MID(I18,7,4) -> 2025 | K18: =MID(I18,4,2) -> 12 | L18: =LEFT(I18,2) -> 06 | M18: =RIGHT(I18,8) -> 22:34:08
A19: TE PAGÓ | B19: Janet Villanueva A. | C19: Janet Villanueva A. | D19: 22.00 | E19: =VALUE(SUBSTITUTE(D19, ".", ",")) -> 22 | F19: G | G19: 21A | H19: nz G lt 21 A | I19: 06/12/2025 22:33:03 | J19: =MID(I19,7,4) -> 2025 | K19: =MID(I19,4,2) -> 12 | L19: =LEFT(I19,2) -> 06 | M19: =RIGHT(I19,8) -> 22:33:03
A20: TE PAGÓ | B20: Janet Villanueva A. | C20: Janet Villanueva A. | D20: 39.00 | E20: =VALUE(SUBSTITUTE(D20, ".", ",")) -> 39 | F20: G | G20: 3 | H20: mz G lt 3 | I20: 06/12/2025 22:28:51 | J20: =MID(I20,7,4) -> 2025 | K20: =MID(I20,4,2) -> 12 | L20: =LEFT(I20,2) -> 06 | M20: =RIGHT(I20,8) -> 22:28:51
A21: TE PAGÓ | B21: Yolanda E. Sales B. | C21: Janet Villanueva A. | D21: 18.00 | E21: =VALUE(SUBSTITUTE(D21, ".", ",")) -> 18 | F21: B1 | G21: 11 | H21: mz B1 lote 11 | I21: 06/12/2025 22:28:22 | J21: =MID(I21,7,4) -> 2025 | K21: =MID(I21,4,2) -> 12 | L21: =LEFT(I21,2) -> 06 | M21: =RIGHT(I21,8) -> 22:28:22
A22: TE PAGÓ | B22: Vanessa A. Milla C. | C22: Janet Villanueva A. | D22: 43.00 | E22: =VALUE(SUBSTITUTE(D22, ".", ",")) -> 43 | F22: S | G22: 3 | H22: mzn s lt 3 vanessa milla | I22: 06/12/2025 22:27:55 | J22: =MID(I22,7,4) -> 2025 | K22: =MID(I22,4,2) -> 12 | L22: =LEFT(I22,2) -> 06 | M22: =RIGHT(I22,8) -> 22:27:55
A23: TE PAGÓ | B23: Mariluz Romero H. | C23: Janet Villanueva A. | D23: 43.00 | E23: =VALUE(SUBSTITUTE(D23, ".", ",")) -> 43 | F23: Q | G23: 3 | H23: mz Q lote 3 Pablo romero Garcilazo segunda etapa 💧💧💧 | I23: 06/12/2025 22:21:21 | J23: =MID(I23,7,4) -> 2025 | K23: =MID(I23,4,2) -> 12 | L23: =LEFT(I23,2) -> 06 | M23: =RIGHT(I23,8) -> 22:21:21
A24: TE PAGÓ | B24: Salome A. Diaz V. | C24: Janet Villanueva A. | D24: 26.00 | E24: =VALUE(SUBSTITUTE(D24, ".", ",")) -> 26 | F24: B | G24: 13 | H24: MZ:B Lt: 13 / 15 soles de multa | I24: 06/12/2025 21:52:18 | J24: =MID(I24,7,4) -> 2025 | K24: =MID(I24,4,2) -> 12 | L24: =LEFT(I24,2) -> 06 | M24: =RIGHT(I24,8) -> 21:52:18
A25: TE PAGÓ | B25: Juana S. Morales D. | C25: Janet Villanueva A. | D25: 42.00 | E25: =VALUE(SUBSTITUTE(D25, ".", ",")) -> 42 | F25: T | G25: 8 | H25: mz t lt 8 Miguel Meléndez julca | I25: 06/12/2025 21:50:26 | J25: =MID(I25,7,4) -> 2025 | K25: =MID(I25,4,2) -> 12 | L25: =LEFT(I25,2) -> 06 | M25: =RIGHT(I25,8) -> 21:50:26
A26: TE PAGÓ | B26: Leon R. Cosme C. | C26: Janet Villanueva A. | D26: 47.00 | E26: =VALUE(SUBSTITUTE(D26, ".", ",")) -> 47 | F26: S | G26: 13 | H26: Ana Garro Rojas, Mz. S Lt 13 | I26: 06/12/2025 21:27:53 | J26: =MID(I26,7,4) -> 2025 | K26: =MID(I26,4,2) -> 12 | L26: =LEFT(I26,2) -> 06 | M26: =RIGHT(I26,8) -> 21:27:53
A27: TE PAGÓ | B27: Leon R. Cosme C. | C27: Janet Villanueva A. | D27: 38.00 | E27: =VALUE(SUBSTITUTE(D27, ".", ",")) -> 38 | F27: W | G27: 9 | H27: Salma Roena Caballero Cosme Mz. W Lt 9 | I27: 06/12/2025 21:26:02 | J27: =MID(I27,7,4) -> 2025 | K27: =MID(I27,4,2) -> 12 | L27: =LEFT(I27,2) -> 06 | M27: =RIGHT(I27,8) -> 21:26:02
A28: TE PAGÓ | B28: Shelly R. Moreno C. | C28: Janet Villanueva A. | D28: 38.00 | E28: =VALUE(SUBSTITUTE(D28, ".", ",")) -> 38 | F28: S | G28: 7 | H28: rubi moreno cosme mz s lote 7 | I28: 06/12/2025 21:03:23 | J28: =MID(I28,7,4) -> 2025 | K28: =MID(I28,4,2) -> 12 | L28: =LEFT(I28,2) -> 06 | M28: =RIGHT(I28,8) -> 21:03:23
A29: TE PAGÓ | B29: Eloy E. Ramirez V. | C29: Janet Villanueva A. | D29: 41.00 | E29: =VALUE(SUBSTITUTE(D29, ".", ",")) -> 41 | F29: G | G29: 23 | H29: MzG Lt 23 Hipólito Ramírez | I29: 06/12/2025 20:44:33 | J29: =MID(I29,7,4) -> 2025 | K29: =MID(I29,4,2) -> 12 | L29: =LEFT(I29,2) -> 06 | M29: =RIGHT(I29,8) -> 20:44:33
A30: TE PAGÓ | B30: Sonia M. Arquino M. | C30: Janet Villanueva A. | D30: 14.00 | E30: =VALUE(SUBSTITUTE(D30, ".", ",")) -> 14 | F30: V | G30: 6 | H30: MZv LT6 | I30: 06/12/2025 19:46:26 | J30: =MID(I30,7,4) -> 2025 | K30: =MID(I30,4,2) -> 12 | L30: =LEFT(I30,2) -> 06 | M30: =RIGHT(I30,8) -> 19:46:26
A31: TE PAGÓ | B31: Olinda Ascurra C. | C31: Janet Villanueva A. | D31: 9.00 | E31: =VALUE(SUBSTITUTE(D31, ".", ",")) -> 9 | F31: H1 | G31: 35 | H31: pago de consumo de agua | I31: 06/12/2025 19:38:17 | J31: =MID(I31,7,4) -> 2025 | K31: =MID(I31,4,2) -> 12 | L31: =LEFT(I31,2) -> 06 | M31: =RIGHT(I31,8) -> 19:38:17
... A36: TE PAGÓ | B36: Carmen J. Rojas T. | C36: Janet Villanueva A. | D36: 9.00 | E36: =VALUE(SUBSTITUTE(D36, ".", ",")) -> 9 | F36: C1 | G36: 17 | H36: mz c1 lt 09 Roberto Martín marlapulu flores | I36: 06/12/2025 19:06:10 | J36: =MID(I36,7,4) -> 2025 | K36: =MID(I36,4,2) -> 12 | L36: =LEFT(I36,2) -> 06 | M36: =RIGHT(I36,8) -> 19:06:10
A37: TE PAGÓ | B37: Eugenia Utrilla F. | C37: Janet Villanueva A. | D37: 13.00 | E37: =VALUE(SUBSTITUTE(D37, ".", ",")) -> 13 | F37: A1 | G37: 2 | I37: 06/12/2025 19:00:32 | J37: =MID(I37,7,4) -> 2025 | K37: =MID(I37,4,2) -> 12 | L37: =LEFT(I37,2) -> 06 | M37: =RIGHT(I37,8) -> 19:00:32
A38: TE PAGÓ | B38: BCP - MAMANI REYES JOSE ANTONIO | C38: JANET VILLANUEVA ALEGRIA | D38: 38.00 | E38: =VALUE(SUBSTITUTE(D38, ".", ",")) -> 38 | F38: M | G38: 13 | I38: 06/12/2025 18:58:05 | J38: =MID(I38,7,4) -> 2025 | K38: =MID(I38,4,2) -> 12 | L38: =LEFT(I38,2) -> 06 | M38: =RIGHT(I38,8) -> 18:58:05
A39: TE PAGÓ | B39: Mayra C. Jara E. | C39: Janet Villanueva A. | D39: 69.00 | E39: =VALUE(SUBSTITUTE(D39, ".", ",")) -> 69 | F39: D | G39: 7 | H39: Mz.D. Lt.. 7... | I39: 06/12/2025 18:55:46 | J39: =MID(I39,7,4) -> 2025 | K39: =MID(I39,4,2) -> 12 | L39: =LEFT(I39,2) -> 06 | M39: =RIGHT(I39,8) -> 18:55:46
A40: TE PAGÓ | B40: Teodora T. Meza G. | C40: Janet Villanueva A. | D40: 10.00 | E40: =VALUE(SUBSTITUTE(D40, ".", ",")) -> 10 | F40: Q | G40: 14 | I40: 06/12/2025 18:50:17 | J40: =MID(I40,7,4) -> 2025 | K40: =MID(I40,4,2) -> 12 | L40: =LEFT(I40,2) -> 06 | M40: =RIGHT(I40,8) -> 18:50:17
A41: TE PAGÓ | B41: Clemente R. Palmadera M. | C41: Janet Villanueva A. | D41: 45.00 | E41: =VALUE(SUBSTITUTE(D41, ".", ",")) -> 45 | F41: T | G41: 7 | H41: MZ T lote 7 Roberto palmadera milla | I41: 06/12/2025 18:45:48 | J41: =MID(I41,7,4) -> 2025 | K41: =MID(I41,4,2) -> 12 | L41: =LEFT(I41,2) -> 06 | M41: =RIGHT(I41,8) -> 18:45:48
A42: TE PAGÓ | B42: Joneth G. Valladares L. | C42: Janet Villanueva A. | E42: 24 | F42: C | G42: 19 | I42: 06/12/2025 18:40:05 | J42: =MID(I42,7,4) -> 2025 | K42: =MID(I42,4,2) -> 12 | L42: =LEFT(I42,2) -> 06 | M42: =RIGHT(I42,8) -> 18:40:05
A43: TE PAGÓ | B43: Joneth G. Valladares L. | C43: Janet Villanueva A. | E43: 37 | F43: G | G43: 18 | I43: 06/12/2025 18:40:04 | J43: =MID(I43,7,4) -> 2025 | K43: =MID(I43,4,2) -> 12 | L43: =LEFT(I43,2) -> 06 | M43: =RIGHT(I43,8) -> 18:40:04
A44: TE PAGÓ | B44: Joneth G. Valladares L. | C44: Janet Villanueva A. | D44: 99.00 | E44: 38 | F44: E | G44: 8 | H44: Mz E Lt 8 (38 soles)Gertrudes Vidal Gonzales, | I44: 06/12/2025 18:40:03 | J44: =MID(I44,7,4) -> 2025 | K44: =MID(I44,4,2) -> 12 | L44: =LEFT(I44,2) -> 06 | M44: =RIGHT(I44,8) -> 18:40:03
A45: TE PAGÓ | B45: Vanessa A. Milla C. | C45: Janet Villanueva A. | D45: 15.00 | E45: =VALUE(SUBSTITUTE(D45, ".", ",")) -> 15 | F45: O | G45: 20 | H45: mzn o lt 20 Julia cruz | I45: 06/12/2025 18:28:39 | J45: =MID(I45,7,4) -> 2025 | K45: =MID(I45,4,2) -> 12 | L45: =LEFT(I45,2) -> 06 | M45: =RIGHT(I45,8) -> 18:28:39
A46: TE PAGÓ | B46: Luz E. Osorio M. | C46: Janet Villanueva A. | D46: 16.00 | E46: =VALUE(SUBSTITUTE(D46, ".", ",")) -> 16 | F46: X | G46: 32 | H46: mz x lote 32 | I46: 06/12/2025 18:24:56 | J46: =MID(I46,7,4) -> 2025 | K46: =MID(I46,4,2) -> 12 | L46: =LEFT(I46,2) -> 06 | M46: =RIGHT(I46,8) -> 18:24:56
A47: TE PAGÓ | B47: Josue M. Granados H. | C47: Janet Villanueva A. | D47: 27.00 | E47: =VALUE(SUBSTITUTE(D47, ".", ",")) -> 27 | F47: C1 | G47: 8 | H47: Mz.C1 Lt. 8 | I47: 06/12/2025 18:16:56 | J47: =MID(I47,7,4) -> 2025 | K47: =MID(I47,4,2) -> 12 | L47: =LEFT(I47,2) -> 06 | M47: =RIGHT(I47,8) -> 18:16:56
A48: TE PAGÓ | B48: Maritza D. Albornoz S. | C48: Janet Villanueva A. | D48: 55.00 | E48: =VALUE(SUBSTITUTE(D48, ".", ",")) -> 55 | F48: G | G48: 16A | I48: 06/12/2025 18:14:24 | J48: =MID(I48,7,4) -> 2025 | K48: =MID(I48,4,2) -> 12 | L48: =LEFT(I48,2) -> 06 | M48: =RIGHT(I48,8) -> 18:14:24
A49: TE PAGÓ | B49: Anali Quineche M. | C49: Janet Villanueva A. | D49: 24.00 | E49: =VALUE(SUBSTITUTE(D49, ".", ",")) -> 24 | F49: C | G49: 35 | I49: 06/12/2025 18:13:53 | J49: =MID(I49,7,4) -> 2025 | K49: =MID(I49,4,2) -> 12 | L49: =LEFT(I49,2) -> 06 | M49: =RIGHT(I49,8) -> 18:13:53
A50: TE PAGÓ | B50: Alfredo Grados A. | C50: Janet Villanueva A. | D50: 10.00 | E50: =VALUE(SUBSTITUTE(D50, ".", ",")) -> 10 | F50: Z | G50: 15 | H50: x consumo de agua manzana Z lote 15 | I50: 06/12/2025 18:10:43 | J50: =MID(I50,7,4) -> 2025 | K50: =MID(I50,4,2) -> 12 | L50: =LEFT(I50,2) -> 06 | M50: =RIGHT(I50,8) -> 18:10:43
A51: TE PAGÓ | B51: Teodora E. Chavez A. | C51: Janet Villanueva A. | D51: 45.00 | E51: =VALUE(SUBSTITUTE(D51, ".", ",")) -> 45 | F51: G | G51: 7 | H51: avenida soledad MG lote 7 | I51: 06/12/2025 18:10:14 | J51: =MID(I51,7,4) -> 2025 | K51: =MID(I51,4,2) -> 12 | L51: =LEFT(I51,2) -> 06 | M51: =RIGHT(I51,8) -> 18:10:14
A52: TE PAGÓ | B52: Alfredo Grados A. | C52: Janet Villanueva A. | D52: 8.00 | E52: =VALUE(SUBSTITUTE(D52, ".", ",")) -> 8 | F52: Z | G52: 12 | H52: x consumo de agua manzana Z lote 12 | I52: 06/12/2025 18:09:24 | J52: =MID(I52,7,4) -> 2025 | K52: =MID(I52,4,2) -> 12 | L52: =LEFT(I52,2) -> 06 | M52: =RIGHT(I52,8) -> 18:09:24
A53: TE PAGÓ | B53: Christian J. Nieto B. | C53: Janet Villanueva A. | D53: 51.00 | E53: =VALUE(SUBSTITUTE(D53, ".", ",")) -> 51 | F53: H | G53: 17 | H53: Julio Nieto MZ H Lt17 (Me parece injusto pagar $30 de | I53: 06/12/2025 17:54:02 | J53: =MID(I53,7,4) -> 2025 | K53: =MID(I53,4,2) -> 12 | L53: =LEFT(I53,2) -> 06 | M53: =RIGHT(I53,8) -> 17:54:02
A54: TE PAGÓ | B54: Julissa Estrada M. | C54: Janet Villanueva A. | D54: 8.00 | E54: =VALUE(SUBSTITUTE(D54, ".", ",")) -> 8 | F54: T | G54: 3 | H54: FREDY JIMENEZ MONTALVO MZ T LT 3 | I54: 06/12/2025 17:49:27 | J54: =MID(I54,7,4) -> 2025 | K54: =MID(I54,4,2) -> 12 | L54: =LEFT(I54,2) -> 06 | M54: =RIGHT(I54,8) -> 17:49:27
A55: TE PAGÓ | B55: Thalia C. Laurencio C. | C55: Janet Villanueva A. | D55: 14.00 | E55: =VALUE(SUBSTITUTE(D55, ".", ",")) -> 14 | F55: F | G55: 13 | H55: MZ"F" lote"13" | I55: 06/12/2025 17:48:03 | J55: =MID(I55,7,4) -> 2025 | K55: =MID(I55,4,2) -> 12 | L55: =LEFT(I55,2) -> 06 | M55: =RIGHT(I55,8) -> 17:48:03
A56: TE PAGÓ | B56: Luz D. Miraval H. | C56: Janet Villanueva A. | D56: 22.00 | E56: =VALUE(SUBSTITUTE(D56, ".", ",")) -> 22 | F56: B | G56: 17 | H56: LUZ MIRAVAL HUERTA M.Z .B. L.T 17 | I56: 06/12/2025 17:47:37 | J56: =MID(I56,7,4) -> 2025 | K56: =MID(I56,4,2) -> 12 | L56: =LEFT(I56,2) -> 06 | M56: =RIGHT(I56,8) -> 17:47:37
A57: TE PAGÓ | B57: Abigail S. Gaspar V. | C57: Janet Villanueva A. | D57: 8.00 | E57: =VALUE(SUBSTITUTE(D57, ".", ",")) -> 8 | F57: F | G57: 3B | H57: mz.F lt.3.B | I57: 06/12/2025 17:41:55 | J57: =MID(I57,7,4) -> 2025 | K57: =MID(I57,4,2) -> 12 | L57: =LEFT(I57,2) -> 06 | M57: =RIGHT(I57,8) -> 17:41:55
A58: TE PAGÓ | B58: Diego L. Moreno F. | C58: Janet Villanueva A. | D58: 8.00 | E58: =VALUE(SUBSTITUTE(D58, ".", ",")) -> 8 | F58: S | G58: 10 | H58: Mz S Lt 10 | I58: 06/12/2025 17:39:56 | J58: =MID(I58,7,4) -> 2025 | K58: =MID(I58,4,2) -> 12 | L58: =LEFT(I58,2) -> 06 | M58: =RIGHT(I58,8) -> 17:39:56
A59: TE PAGÓ | B59: Charo C. Osorio M. | C59: Janet Villanueva A. | D59: 8.00 | E59: =VALUE(SUBSTITUTE(D59, ".", ",")) -> 8 | F59: X | G59: 33 | H59: mz X LT.33 Nena melendez julca | I59: 06/12/2025 17:27:02 | J59: =MID(I59,7,4) -> 2025 | K59: =MID(I59,4,2) -> 12 | L59: =LEFT(I59,2) -> 06 | M59: =RIGHT(I59,8) -> 17:27:02
A60: TE PAGÓ | B60: Luis A. Silva K. | C60: Janet Villanueva A. | D60: 8.00 | E60: =VALUE(SUBSTITUTE(D60, ".", ",")) -> 8 | F60: C1 | G60: 6 | H60: mzC1 lt6 | I60: 06/12/2025 17:26:08 | J60: =MID(I60,7,4) -> 2025 | K60: =MID(I60,4,2) -> 12 | L60: =LEFT(I60,2) -> 06 | M60: =RIGHT(I60,8) -> 17:26:08
A61: TE PAGÓ | B61: Katherine D. Barboza D. | C61: Janet Villanueva A. | E61: 25 | F61: M | G61: 1 | I61: 06/12/2025 17:22:43 | J61: =MID(I61,7,4) -> 2025 | K61: =MID(I61,4,2) -> 12 | L61: =LEFT(I61,2) -> 06 | M61: =RIGHT(I61,8) -> 17:22:43
A62: TE PAGÓ | B62: Katherine D. Barboza D. | C62: Janet Villanueva A. | D62: 33.00 | E62: 8 | F62: O | G62: 4 | H62: MZ. O Lote 4 y MZ. M Lote 1 | I62: 06/12/2025 17:22:42 | J62: =MID(I62,7,4) -> 2025 | K62: =MID(I62,4,2) -> 12 | L62: =LEFT(I62,2) -> 06 | M62: =RIGHT(I62,8) -> 17:22:42
A63: TE PAGÓ | B63: Nicolasa D. Balderrama S. | C63: Janet Villanueva A. | D63: 8.00 | E63: =VALUE(SUBSTITUTE(D63, ".", ",")) -> 8 | F63: T | G63: 13 | H63: MZ.T LT. 13 | I63: 06/12/2025 17:20:53 | J63: =MID(I63,7,4) -> 2025 | K63: =MID(I63,4,2) -> 12 | L63: =LEFT(I63,2) -> 06 | M63: =RIGHT(I63,8) -> 17:20:53
A64: TE PAGÓ | B64: Maria M. Vega T. | C64: Janet Villanueva A. | D64: 12.00 | E64: =VALUE(SUBSTITUTE(D64, ".", ",")) -> 12 | F64: Z | G64: 8 | H64: Mz.Z Lt.8 | I64: 06/12/2025 17:18:41 | J64: =MID(I64,7,4) -> 2025 | K64: =MID(I64,4,2) -> 12 | L64: =LEFT(I64,2) -> 06 | M64: =RIGHT(I64,8) -> 17:18:41
A65: TE PAGÓ | B65: Magdalena Z. Rosales M. | C65: Janet Villanueva A. | D65: 62.00 | E65: =VALUE(SUBSTITUTE(D65, ".", ",")) -> 62 | F65: S | G65: 1 | H65: Recibo de agua MZ S Lt 1 | I65: 06/12/2025 17:13:46 | J65: =MID(I65,7,4) -> 2025 | K65: =MID(I65,4,2) -> 12 | L65: =LEFT(I65,2) -> 06 | M65: =RIGHT(I65,8) -> 17:13:46
A66: TE PAGÓ | B66: Irma S. Luis A. | C66: Janet Villanueva A. | D66: 67.00 | E66: =VALUE(SUBSTITUTE(D66, ".", ",")) -> 67 | F66: K | G66: 12 | H66: Alejandro Luis Julca MKLT12 | I66: 06/12/2025 17:08:26 | J66: =MID(I66,7,4) -> 2025 | K66: =MID(I66,4,2) -> 12 | L66: =LEFT(I66,2) -> 06 | M66: =RIGHT(I66,8) -> 17:08:26
A67: TE PAGÓ | B67: Renee Medrano M. | C67: Janet Villanueva A. | D67: 8.00 | E67: =VALUE(SUBSTITUTE(D67, ".", ",")) -> 8 | F67: E1 | G67: 1 | H67: Johnny Salomón Niño Ortiz (MzE1 lote 1) | I67: 06/12/2025 16:39:07 | J67: =MID(I67,7,4) -> 2025 | K67: =MID(I67,4,2) -> 12 | L67: =LEFT(I67,2) -> 06 | M67: =RIGHT(I67,8) -> 16:39:07
A68: TE PAGÓ | B68: Rosmery Z. Sanchez E. | C68: Janet Villanueva A. | D68: 17.00 | E68: =VALUE(SUBSTITUTE(D68, ".", ",")) -> 17 | F68: B | G68: 12A | H68: pago de dos meses de MZ B tl 12 Rosmery Sanchez | I68: 06/12/2025 16:36:59 | J68: =MID(I68,7,4) -> 2025 | K68: =MID(I68,4,2) -> 12 | L68: =LEFT(I68,2) -> 06 | M68: =RIGHT(I68,8) -> 16:36:59
A69: TE PAGÓ | B69: William Trujillo R. | C69: Janet Villanueva A. | D69: 10.00 | E69: =VALUE(SUBSTITUTE(D69, ".", ",")) -> 10 | F69: P | G69: 11A | H69: Lote P 11A( Julia Rosales) | I69: 06/12/2025 16:31:08 | J69: =MID(I69,7,4) -> 2025 | K69: =MID(I69,4,2) -> 12 | L69: =LEFT(I69,2) -> 06 | M69: =RIGHT(I69,8) -> 16:31:08
A70: TE PAGÓ | B70: Jose A. Candacho B. | C70: Janet Villanueva A. | D70: 60.00 | E70: =VALUE(SUBSTITUTE(D70, ".", ",")) -> 60 | F70: T | G70: 14 | H70: MzT LT14 | I70: 06/12/2025 16:26:03 | J70: =MID(I70,7,4) -> 2025 | K70: =MID(I70,4,2) -> 12 | L70: =LEFT(I70,2) -> 06 | M70: =RIGHT(I70,8) -> 16:26:03
A71: TE PAGÓ | B71: Noemi Cadillo R. | C71: Janet Villanueva A. | D71: 11.00 | E71: =VALUE(SUBSTITUTE(D71, ".", ",")) -> 11 | F71: E1 | G71: 7 | I71: 06/12/2025 16:17:59 | J71: =MID(I71,7,4) -> 2025 | K71: =MID(I71,4,2) -> 12 | L71: =LEFT(I71,2) -> 06 | M71: =RIGHT(I71,8) -> 16:17:59
A72: TE PAGÓ | B72: Clever I. Lopez T. | C72: Janet Villanueva A. | D72: 11.00 | E72: =VALUE(SUBSTITUTE(D72, ".", ",")) -> 11 | F72: V | G72: 13 | H72: Mz.V lte.13 Clever López Trujillo | I72: 06/12/2025 16:14:49 | J72: =MID(I72,7,4) -> 2025 | K72: =MID(I72,4,2) -> 12 | L72: =LEFT(I72,2) -> 06 | M72: =RIGHT(I72,8) -> 16:14:49
A73: TE PAGÓ | B73: Eleuteria L. Pajuelo A. | C73: Janet Villanueva A. | D73: 14.00 | E73: =VALUE(SUBSTITUTE(D73, ".", ",")) -> 14 | F73: I | G73: 2 | H73: Eleuteria Libia Pajuelo Atanacio Mz I Lt2 | I73: 06/12/2025 16:09:51 | J73: =MID(I73,7,4) -> 2025 | K73: =MID(I73,4,2) -> 12 | L73: =LEFT(I73,2) -> 06 | M73: =RIGHT(I73,8) -> 16:09:51
A74: TE PAGÓ | B74: Paul R. Trujillo C. | C74: Janet Villanueva A. | D74: 8.00 | E74: =VALUE(SUBSTITUTE(D74, ".", ",")) -> 8 | F74: K | G74: 3 | H74: Mz k lt 3 | I74: 06/12/2025 16:07:59 | J74: =MID(I74,7,4) -> 2025 | K74: =MID(I74,4,2) -> 12 | L74: =LEFT(I74,2) -> 06 | M74: =RIGHT(I74,8) -> 16:07:59
A75: TE PAGÓ | B75: Tecla M. Vega C. | C75: Janet Villanueva A. | D75: 40.00 | E75: =VALUE(SUBSTITUTE(D75, ".", ",")) -> 40 | F75: A1 | G75: 4 | H75: Mz A lt 4 raul delgado | I75: 06/12/2025 16:07:43 | J75: =MID(I75,7,4) -> 2025 | K75: =MID(I75,4,2) -> 12 | L75: =LEFT(I75,2) -> 06 | M75: =RIGHT(I75,8) -> 16:07:43
A76: TE PAGÓ | B76: Jose A. Nieto H. | C76: Janet Villanueva A. | D76: 8.00 | E76: =VALUE(SUBSTITUTE(D76, ".", ",")) -> 8 | F76: I | G76: 14 | H76: MZ i Lote 14 Roberto Nieto Huerta | I76: 06/12/2025 16:07:25 | J76: =MID(I76,7,4) -> 2025 | K76: =MID(I76,4,2) -> 12 | L76: =LEFT(I76,2) -> 06 | M76: =RIGHT(I76,8) -> 16:07:25
A77: TE PAGÓ | B77: Paul R. Trujillo C. | C77: Janet Villanueva A. | D77: 31.00 | E77: =VALUE(SUBSTITUTE(D77, ".", ",")) -> 31 | F77: K | G77: 4 | H77: Mz k lt 4 | I77: 06/12/2025 16:07:21 | J77: =MID(I77,7,4) -> 2025 | K77: =MID(I77,4,2) -> 12 | L77: =LEFT(I77,2) -> 06 | M77: =RIGHT(I77,8) -> 16:07:21
A78: TE PAGÓ | B78: Tecla M. Vega C. | C78: Janet Villanueva A. | D78: 135.00 | E78: =VALUE(SUBSTITUTE(D78, ".", ",")) -> 135 | F78: A1 | G78: 3 | H78: Mz A Lt 3 Odelio Delgado | I78: 06/12/2025 16:05:18 | J78: =MID(I78,7,4) -> 2025 | K78: =MID(I78,4,2) -> 12 | L78: =LEFT(I78,2) -> 06 | M78: =RIGHT(I78,8) -> 16:05:18
A79: TE PAGÓ | B79: Tecla M. Vega C. | C79: Janet Villanueva A. | D79: 38.00 | E79: =VALUE(SUBSTITUTE(D79, ".", ",")) -> 38 | F79: A | G79: 11 | H79: mz A lt 11 tesoro avila | I79: 06/12/2025 16:02:38 | J79: =MID(I79,7,4) -> 2025 | K79: =MID(I79,4,2) -> 12 | L79: =LEFT(I79,2) -> 06 | M79: =RIGHT(I79,8) -> 16:02:38
A80: TE PAGÓ | B80: Mayra I. Huerta P. | C80: Janet Villanueva A. | D80: 25.00 | E80: =VALUE(SUBSTITUTE(D80, ".", ",")) -> 25 | F80: A | G80: 10 | H80: Isabel puntillo Vega mzA lt 10 | I80: 06/12/2025 15:53:06 | J80: =MID(I80,7,4) -> 2025 | K80: =MID(I80,4,2) -> 12 | L80: =LEFT(I80,2) -> 06 | M80: =RIGHT(I80,8) -> 15:53:06
A81: TE PAGÓ | B81: Solin H. Jaramillo A. | C81: Janet Villanueva A. | D81: 35.00 | E81: =VALUE(SUBSTITUTE(D81, ".", ",")) -> 35 | F81: D | G81: 12 | H81: pago de agua mes de noviembre Mz D lt 12 | I81: 06/12/2025 15:51:55 | J81: =MID(I81,7,4) -> 2025 | K81: =MID(I81,4,2) -> 12 | L81: =LEFT(I81,2) -> 06 | M81: =RIGHT(I81,8) -> 15:51:55
A82: TE PAGÓ | B82: Alan M. Carranza C. | C82: Janet Villanueva A. | D82: 11.00 | E82: =VALUE(SUBSTITUTE(D82, ".", ",")) -> 11 | F82: L | G82: 1 | H82: mz l lote 1 Luisa Elena caspa días | I82: 06/12/2025 15:48:54 | J82: =MID(I82,7,4) -> 2025 | K82: =MID(I82,4,2) -> 12 | L82: =LEFT(I82,2) -> 06 | M82: =RIGHT(I82,8) -> 15:48:54
A83: TE PAGÓ | B83: Julio C. Vega C. | C83: Janet Villanueva A. | D83: 120.00 | E83: =VALUE(SUBSTITUTE(D83, ".", ",")) -> 120 | F83: E1 | G83: 8 | H83: pago de agua correspondiente diciembre. | I83: 06/12/2025 15:48:00 | J83: =MID(I83,7,4) -> 2025 | K83: =MID(I83,4,2) -> 12 | L83: =LEFT(I83,2) -> 06 | M83: =RIGHT(I83,8) -> 15:48:00
A84: TE PAGÓ | B84: PLIN - Junior Alexis Murillo Lozano | C84: JANET VILLANUEVA ALEGRIA | D84: 49.00 | E84: =VALUE(SUBSTITUTE(D84, ".", ",")) -> 49 | F84: X | G84: 9 | I84: 06/12/2025 15:46:35 | J84: =MID(I84,7,4) -> 2025 | K84: =MID(I84,4,2) -> 12 | L84: =LEFT(I84,2) -> 06 | M84: =RIGHT(I84,8) -> 15:46:35
A85: TE PAGÓ | B85: Rivet Villanueva A. | C85: Janet Villanueva A. | D85: 8.00 | E85: =VALUE(SUBSTITUTE(D85, ".", ",")) -> 8 | F85: T | G85: 11 | H85: Mz t Lt 11 | I85: 06/12/2025 15:45:05 | J85: =MID(I85,7,4) -> 2025 | K85: =MID(I85,4,2) -> 12 | L85: =LEFT(I85,2) -> 06 | M85: =RIGHT(I85,8) -> 15:45:05
A86: TE PAGÓ | B86: Thalia C. Laurencio C. | C86: Janet Villanueva A. | D86: 83.00 | E86: =VALUE(SUBSTITUTE(D86, ".", ",")) -> 83 | F86: F | G86: 7 | H86: MZ "F" lote "7" | I86: 06/12/2025 15:41:38 | J86: =MID(I86,7,4) -> 2025 | K86: =MID(I86,4,2) -> 12 | L86: =LEFT(I86,2) -> 06 | M86: =RIGHT(I86,8) -> 15:41:38
A87: TE PAGÓ | B87: Melany A. Burga Z. | C87: Janet Villanueva A. | D87: 46.00 | E87: =VALUE(SUBSTITUTE(D87, ".", ",")) -> 46 | F87: H1 | G87: 10 | H87: Felicia Zapata flores MZ . H1 LT. 10 | I87: 06/12/2025 15:41:07 | J87: =MID(I87,7,4) -> 2025 | K87: =MID(I87,4,2) -> 12 | L87: =LEFT(I87,2) -> 06 | M87: =RIGHT(I87,8) -> 15:41:07
A88: TE PAGÓ | B88: PLIN - MARIA MAGNA HUERTA MILLA | C88: JANET VILLANUEVA ALEGRIA | D88: 38.00 | E88: =VALUE(SUBSTITUTE(D88, ".", ",")) -> 38 | F88: O | G88: 23 | H88: mz O lt 23 agua y multa | I88: 06/12/2025 15:40:50 | J88: =MID(I88,7,4) -> 2025 | K88: =MID(I88,4,2) -> 12 | L88: =LEFT(I88,2) -> 06 | M88: =RIGHT(I88,8) -> 15:40:50
A89: TE PAGÓ | B89: Carlos O. Candacho H. | C89: Janet Villanueva A. | D89: 42.00 | E89: =VALUE(SUBSTITUTE(D89, ".", ",")) -> 42 | F89: L | G89: 4 | H89: Delia Huamansupa Perez Mz L lte 4 | I89: 06/12/2025 15:38:03 | J89: =MID(I89,7,4) -> 2025 | K89: =MID(I89,4,2) -> 12 | L89: =LEFT(I89,2) -> 06 | M89: =RIGHT(I89,8) -> 15:38:03
A90: TE PAGÓ | B90: Joshelyn R. Rodriguez C. | C90: Janet Villanueva A. | D90: 28.00 | E90: =VALUE(SUBSTITUTE(D90, ".", ",")) -> 28 | F90: I | G90: 7 | H90: mzi Lt 7 | I90: 06/12/2025 15:32:41 | J90: =MID(I90,7,4) -> 2025 | K90: =MID(I90,4,2) -> 12 | L90: =LEFT(I90,2) -> 06 | M90: =RIGHT(I90,8) -> 15:32:41
A91: TE PAGÓ | B91: Angel F. Montalvo T. | C91: Janet Villanueva A. | D91: 8.00 | E91: =VALUE(SUBSTITUTE(D91, ".", ",")) -> 8 | F91: P | G91: 13 | H91: Mz.P.LT.13 | I91: 06/12/2025 15:30:07 | J91: =MID(I91,7,4) -> 2025 | K91: =MID(I91,4,2) -> 12 | L91: =LEFT(I91,2) -> 06 | M91: =RIGHT(I91,8) -> 15:30:07
A92: TE PAGÓ | B92: Mario E. Rosales R. | C92: Janet Villanueva A. | D92: 47.00 | E92: =VALUE(SUBSTITUTE(D92, ".", ",")) -> 47 | F92: T | G92: 4 | H92: Mz.t Lote 4 José Palmadera..!! | I92: 06/12/2025 15:01:06 | J92: =MID(I92,7,4) -> 2025 | K92: =MID(I92,4,2) -> 12 | L92: =LEFT(I92,2) -> 06 | M92: =RIGHT(I92,8) -> 15:01:06
A93: TE PAGÓ | B93: Carmen R. Lopez H. | C93: Janet Villanueva A. | D93: 38.00 | E93: =VALUE(SUBSTITUTE(D93, ".", ",")) -> 38 | F93: L | G93: 13 | H93: Maria Rosita Huacanca huaroma Mz L Lt.13 | I93: 06/12/2025 14:17:24 | J93: =MID(I93,7,4) -> 2025 | K93: =MID(I93,4,2) -> 12 | L93: =LEFT(I93,2) -> 06 | M93: =RIGHT(I93,8) -> 14:17:24
A94: TE PAGÓ | B94: Lucia Moreno R. | C94: Janet Villanueva A. | D94: 8.00 | E94: =VALUE(SUBSTITUTE(D94, ".", ",")) -> 8 | F94: X | G94: 34 | H94: Mz. x lt.34 ,alejandro moreno rosales | I94: 06/12/2025 12:12:40 | J94: =MID(I94,7,4) -> 2025 | K94: =MID(I94,4,2) -> 12 | L94: =LEFT(I94,2) -> 06 | M94: =RIGHT(I94,8) -> 12:12:40
A95: TE PAGÓ | B95: Johan E. Rodriguez F. | C95: Janet Villanueva A. | D95: 38.00 | E95: =VALUE(SUBSTITUTE(D95, ".", ",")) -> 38 | F95: B1 | G95: 3 | H95: MZ,B1. Lt.3- Johan Rodriguez Flores | I95: 06/12/2025 11:46:44 | J95: =MID(I95,7,4) -> 2025 | K95: =MID(I95,4,2) -> 12 | L95: =LEFT(I95,2) -> 06 | M95: =RIGHT(I95,8) -> 11:46:44
A96: TE PAGÓ | B96: Marili S. Regalado C. | C96: Janet Villanueva A. | D96: 16.00 | E96: =VALUE(SUBSTITUTE(D96, ".", ",")) -> 16 | F96: Y | G96: 2 | H96: Mz. Y Lt. 2 | I96: 06/12/2025 11:22:40 | J96: =MID(I96,7,4) -> 2025 | K96: =MID(I96,4,2) -> 12 | L96: =LEFT(I96,2) -> 06 | M96: =RIGHT(I96,8) -> 11:22:40
... A102: TE PAGÓ | B102: Rimenita L. Munoz H. | C102: Janet Villanueva A. | D102: 8.00 | E102: =VALUE(SUBSTITUTE(D102, ".", ",")) -> 8 | F102: E | G102: 19 | H102: M Z _E. LT. 19 mercado | I102: 06/12/2025 10:42:16 | J102: =MID(I102,7,4) -> 2025 | K102: =MID(I102,4,2) -> 12 | L102: =LEFT(I102,2) -> 06 | M102: =RIGHT(I102,8) -> 10:42:16
A103: TE PAGÓ | B103: Luz R. Gaspar V. | C103: Janet Villanueva A. | D103: 13.00 | E103: =VALUE(SUBSTITUTE(D103, ".", ",")) -> 13 | F103: F1 | G103: 10 | I103: 06/12/2025 10:05:10 | J103: =MID(I103,7,4) -> 2025 | K103: =MID(I103,4,2) -> 12 | L103: =LEFT(I103,2) -> 06 | M103: =RIGHT(I103,8) -> 10:05:10
A104: TE PAGÓ | B104: Javier B. Melgarejo M. | C104: Janet Villanueva A. | D104: 40.00 | E104: =VALUE(SUBSTITUTE(D104, ".", ",")) -> 40 | F104: O | G104: 22 | H104: LOPEZ SAMARITANO Teresa. Mz. O Lt. 22 | I104: 06/12/2025 09:40:36 | J104: =MID(I104,7,4) -> 2025 | K104: =MID(I104,4,2) -> 12 | L104: =LEFT(I104,2) -> 06 | M104: =RIGHT(I104,8) -> 09:40:36
A105: TE PAGÓ | B105: Javier B. Melgarejo M. | C105: Janet Villanueva A. | D105: 52.00 | E105: =VALUE(SUBSTITUTE(D105, ".", ",")) -> 52 | F105: O | G105: 21 | H105: MELGAREJO CASTILLO Javier. Mz. O Lt. 21 | I105: 06/12/2025 09:38:05 | J105: =MID(I105,7,4) -> 2025 | K105: =MID(I105,4,2) -> 12 | L105: =LEFT(I105,2) -> 06 | M105: =RIGHT(I105,8) -> 09:38:05
A106: TE PAGÓ | B106: Elio Sanchez O. | C106: Janet Villanueva A. | D106: 67.00 | E106: =VALUE(SUBSTITUTE(D106, ".", ",")) -> 67 | F106: F | G106: 14 | H106: MZ-F- LT-14 Rodrigo Podestad Rosas | I106: 06/12/2025 09:36:49 | J106: =MID(I106,7,4) -> 2025 | K106: =MID(I106,4,2) -> 12 | L106: =LEFT(I106,2) -> 06 | M106: =RIGHT(I106,8) -> 09:36:49
A107: TE PAGÓ | B107: Charo C. Osorio M. | C107: Janet Villanueva A. | D107: 10.00 | E107: =VALUE(SUBSTITUTE(D107, ".", ",")) -> 10 | F107: O | G107: 14 | H107: Mz.O.Lt.14 loida moya valverde | I107: 06/12/2025 09:09:44 | J107: =MID(I107,7,4) -> 2025 | K107: =MID(I107,4,2) -> 12 | L107: =LEFT(I107,2) -> 06 | M107: =RIGHT(I107,8) -> 09:09:44
A108: TE PAGÓ | B108: Nicoll R. Romero G. | C108: Janet Villanueva A. | D108: 39.00 | E108: =VALUE(SUBSTITUTE(D108, ".", ",")) -> 39 | F108: U | G108: 3 | H108: M "u" Lt"3" Marcelina Gomez Bonifacio | I108: 06/12/2025 09:03:36 | J108: =MID(I108,7,4) -> 2025 | K108: =MID(I108,4,2) -> 12 | L108: =LEFT(I108,2) -> 06 | M108: =RIGHT(I108,8) -> 09:03:36
A109: TE PAGÓ | B109: Melina J. Juarez T. | C109: Janet Villanueva A. | D109: 16.00 | E109: =VALUE(SUBSTITUTE(D109, ".", ",")) -> 16 | F109: C1 | G109: 3 | H109: Delfina pumallanqui - Mz C1 lote 3 | I109: 06/12/2025 08:41:38 | J109: =MID(I109,7,4) -> 2025 | K109: =MID(I109,4,2) -> 12 | L109: =LEFT(I109,2) -> 06 | M109: =RIGHT(I109,8) -> 08:41:38
...

Sheet PLANILLA
A1: ITEM | B1: NOMBRES | C1: MZ | D1: LT | E1: MARCACIÓN | F1: m3 | G1: MARCACIÓN | H1: M3 | I1: MARCACIÓN | J1: M3 | K1: MARCACIÓN | L1: M3 | M1: MARCACIÓN | N1: M3 | O1: MARCACIÓN | P1: M3 | Q1: MARCACIÓN | R1: M3 | S1: MARCACIÓN | T1: M3 | U1: MARCACION | V1: m3 | W1: MARCACION | X1: m3 | Y1: MARCACION | Z1: m3 | AA1: MARCACIÓN | AB1: M3 | AC1: Total mes actual | AD1: MES ANTERIOR | AE1: Corte y reconexión | AF1: Convenio | AG1: Manteniminiento | AH1: Multa | AI1: Total a pagar | AJ1: Estado | AK1: Fecha de pago | AL1: Medio de pago | AM1: Comentario
A2: 1 | B2: MARCELINA OBREGON DE AVILA | C2: A | D2: 1 | E2: 2445 | F2: 6 | G2: 2451 | H2: 7 | I2: 2458 | J2: 6 | K2: 2464 | L2: 5 | M2: 2469 | N2: 7 | O2: 2476 | P2: 5 | Q2: 2481 | R2: 5 | S2: 2486 | T2: 5 | U2: 2491 | V2: 5 | W2: 2496 | X2: 5 | Y2: 2502 | Z2: 6 | AA2: 2506 | AB2: 4 | AC2: 5 | AD2: 0 | AE2: 0 | AG2: 3 | AH2: 0 | AI2: 8
A3: 2 | B3: ROSA AURORA ROCA VIDAL | C3: A | D3: 2 | E3: 1975 | F3: 37 | G3: 2012 | H3: 23 | I3: 2035 | J3: 32 | K3: 2067 | L3: 27 | M3: 2094 | N3: 26 | O3: 2120 | P3: 22 | Q3: 2142 | R3: 22 | S3: 2168 | T3: 26 | U3: 2193 | V3: 25 | W3: 2225 | X3: 32 | Y3: 2248 | Z3: 23 | AA3: 2288 | AB3: 40 | AC3: 40 | AD3: 0 | AE3: 0 | AG3: 3 | AH3: 0 | AI3: 43
A4: 3 | B4: LINDA PAJUELO COCHACHÍN | C4: A | D4: 3 | K4: 0 | L4: 0 | M4: 0 | N4: 1 | O4: 1 | P4: 14 | Q4: 15 | R4: 14 | S4: 22 | T4: 7 | U4: 22 | V4: 0 | W4: 22 | X4: 0 | Y4: 22 | Z4: 0 | AA4: 22 | AB4: 0 | AC4: 5 | AD4: 0 | AE4: 0 | AG4: 3 | AH4: 0 | AI4: 8
A5: 4 | B5: YOLANDA ESPINOZA JAIMES | C5: A | D5: 4 | E5: 1759 | F5: 0 | G5: 1759 | H5: 0 | I5: 1759 | J5: 3 | K5: 1762 | L5: 0 | M5: 1762 | N5: 0 | O5: 1762 | P5: 0 | Q5: 1762 | R5: 0 | S5: 1762 | T5: 0 | U5: 1732 | V5: 0 | W5: 1762 | X5: 30 | Y5: 1763 | Z5: 1 | AA5: 1763 | AB5: 0 | AC5: 5 | AD5: 41 | AE5: 40 | AG5: 3 | AH5: 20 | AI5: 109
A6: 5 | B6: JULIA AGAMA CUZCO | C6: A | D6: 5 | E6: 2933 | F6: 35 | G6: 2968 | H6: 34 | I6: 3002 | J6: 23 | K6: 3025 | L6: 23 | M6: 3048 | N6: 16 | O6: 3064 | P6: 14 | Q6: 3078 | R6: 14 | S6: 3092 | T6: 14 | U6: 3108 | V6: 16 | W6: 3120 | X6: 12 | Y6: 3141 | Z6: 21 | AA6: 3162 | AB6: 21 | AC6: 21 | AD6: 0 | AE6: 0 | AG6: 3 | AH6: 0 | AI6: 24
A7: 6 | B7: ESTEBAN REYES SANCHEZ | C7: A | D7: 6 | E7: 1253 | F7: 45 | G7: 1298 | H7: 35 | I7: 1333 | J7: 25 | K7: 1358 | L7: 32 | M7: 1390 | N7: 22 | O7: 1412 | P7: 28 | Q7: 1440 | R7: 28 | S7: 1467 | T7: 27 | U7: 1491 | V7: 24 | W7: 1517 | X7: 26 | Y7: 1544 | Z7: 27 | AA7: 1571 | AB7: 27 | AC7: 27 | AD7: 0 | AE7: 0 | AG7: 3 | AH7: 0 | AI7: 30
A8: 7 | B8: JUAN CARLOS MELGAREJO BEDON | C8: A | D8: 7 | E8: 1358 | F8: 24 | G8: 1382 | H8: 25 | I8: 1407 | J8: 22 | K8: 1429 | L8: 23 | M8: 1452 | N8: 19 | O8: 1471 | P8: 22 | Q8: 1493 | R8: 22 | S8: 1512 | T8: 19 | U8: 1529 | V8: 17 | W8: 1546 | X8: 17 | Y8: 1562 | Z8: 16 | AA8: 1579 | AB8: 17 | AC8: 17 | AD8: 19 | AE8: 0 | AG8: 3 | AH8: 0 | AI8: 39
A9: 8 | B9: VICTOR MELGAREJO CORCINO | C9: A | D9: 8 | E9: 5882 | F9: 35 | G9: 5917 | H9: 33 | I9: 5950 | J9: 25 | K9: 5975 | L9: 36 | M9: 6011 | N9: 21 | O9: 6032 | P9: 13 | Q9: 6045 | R9: 13 | S9: 6055 | T9: 10 | U9: 6067 | V9: 12 | W9: 6078 | X9: 11 | Y9: 6088 | Z9: 10 | AA9: 6103 | AB9: 15 | AC9: 15 | AD9: 0 | AE9: 0 | AG9: 3 | AH9: 0 | AI9: 18
A10: 9 | B10: JHONI MELGAREJO BEDON | C10: A | D10: 8-A | P10: 18 | Q10: 18 | R10: 18 | S10: 26 | T10: 8 | U10: 32 | V10: 6 | W10: 46 | X10: 14 | Y10: 53 | Z10: 7 | AA10: 61 | AB10: 8 | AC10: 8 | AD10: 0 | AE10: 0 | AG10: 3 | AH10: 20 | AI10: 31
A11: 10 | B11: ALEJANDRO MELGAREJO ESPINOZA | C11: A | D11: 9 | E11: 1381 | F11: 32 | G11: 1413 | H11: 30 | I11: 1443 | J11: 40 | K11: 1483 | L11: 33 | M11: 1516 | N11: 33 | O11: 1549 | P11: 27 | Q11: 1576 | R11: 27 | S11: 1601 | T11: 25 | U11: 1624 | V11: 23 | W11: 1646 | X11: 22 | Y11: 1673 | Z11: 27 | AA11: 1703 | AB11: 30 | AC11: 30 | AD11: 0 | AE11: 0 | AG11: 3 | AH11: 0 | AI11: 33
A12: 11 | B12: ISABEL PUNTILLO VEGA | C12: A | D12: 10 | E12: 31 | F12: 10 | G12: 41 | H12: 29 | I12: 70 | J12: 18 | K12: 88 | L12: 29 | M12: 117 | N12: 20 | O12: 137 | P12: 163 | Q12: 300 | R12: 163 | S12: 371 | T12: 71 | U12: 379 | V12: 8 | W12: 384 | X12: 5 | Y12: 389 | Z12: 5 | AA12: 395 | AB12: 6 | AC12: 6 | AD12: 0 | AE12: 0 | AG12: 3 | AH12: 20 | AI12: 29
A13: 12 | B13: FELIX POZO CASTRO | C13: A | D13: 11 | E13: 341 | F13: 0 | G13: 341 | H13: 1 | I13: 342 | J13: 1 | K13: 343 | L13: 0 | M13: 343 | N13: 1 | O13: 344 | P13: 0 | Q13: 344 | R13: 0 | S13: 345 | T13: 1 | U13: 346 | V13: 1 | W13: 346 | X13: 0 | Y13: 346 | Z13: 0 | AA13: 346 | AB13: 0 | AC13: 5 | AD13: 0 | AE13: 0 | AG13: 3 | AH13: 20 | AI13: 28
A14: 13 | B14: BACILIO UTRILLA FRANCISCO | C14: B | D14: 1 | E14: 2078 | F14: 15 | G14: 2093 | H14: 0 | I14: 2093 | J14: 7 | K14: 2100 | L14: 10 | M14: 2110 | N14: 8 | O14: 2118 | P14: 5 | Q14: 2123 | R14: 5 | S14: 2131 | T14: 8 | U14: 2137 | V14: 6 | W14: 2141 | X14: 4 | Y14: 2147 | Z14: 6 | AA14: 2153 | AB14: 6 | AC14: 6 | AD14: 9 | AE14: 0 | AG14: 3 | AH14: 0 | AI14: 18
A15: 14 | B15: ESTEBAN REYNALDO ROSALES | C15: B | D15: 2 | E15: 2104 | F15: 6 | G15: 2110 | H15: 3 | I15: 2113 | J15: 2 | K15: 2115 | L15: 11 | M15: 2126 | N15: 9 | O15: 2135 | P15: 6 | Q15: 2141 | R15: 6 | S15: 2146 | T15: 5 | U15: 2152 | V15: 6 | W15: 2157 | X15: 5 | Y15: 2164 | Z15: 7 | AA15: 2171 | AB15: 7 | AC15: 7 | AD15: 0 | AE15: 0 | AG15: 3 | AH15: 20 | AI15: 30
A16: 15 | B16: EDUARDO REYNALDO ROSALES | C16: B | D16: 3 | E16: 602 | F16: 9 | G16: 611 | H16: 10 | I16: 621 | J16: 10 | K16: 631 | L16: 9 | M16: 640 | N16: 8 | O16: 648 | P16: 10 | Q16: 658 | R16: 10 | S16: 669 | T16: 11 | U16: 676 | V16: 7 | W16: 682 | X16: 6 | Y16: 689 | Z16: 7 | AA16: 695 | AB16: 6 | AC16: 6 | AD16: 0 | AE16: 0 | AG16: 3 | AH16: 0 | AI16: 9
A17: 16 | B17: MELINA J. JUAREZ TOLEDO DE MORENO | C17: B | D17: 4 | E17: 189 | F17: 10 | G17: 199 | H17: 12 | I17: 211 | J17: 15 | K17: 226 | L17: 13 | M17: 239 | N17: 13 | O17: 252 | P17: 21 | Q17: 273 | R17: 21 | S17: 291 | T17: 18 | U17: 311 | V17: 20 | W17: 331 | X17: 20 | Y17: 348 | Z17: 17 | AA17: 369 | AB17: 21 | AC17: 21 | AD17: 0 | AE17: 0 | AG17: 3 | AH17: 0 | AI17: 24
A18: 17 | B18: POMPEYO CELESTINO LLIUYA | C18: B | D18: 5 | E18: 4425 | F18: 58 | G18: 4483 | H18: 45 | I18: 4528 | J18: 39 | K18: 4567 | L18: 33 | M18: 4600 | N18: 39 | O18: 4639 | P18: 34 | Q18: 4673 | R18: 34 | S18: 4706 | T18: 33 | U18: 4742 | V18: 36 | W18: 4775 | X18: 33 | Y18: 4810 | Z18: 35 | AA18: 4848 | AB18: 38 | AC18: 38 | AD18: 0 | AE18: 0 | AG18: 3 | AH18: 20 | AI18: 61
A19: 18 | B19: ROSA VICTORIA MILLA MORALES | C19: B | D19: 6 | E19: 3385 | F19: 34 | G19: 3419 | H19: 35 | I19: 3454 | J19: 23 | K19: 3477 | L19: 23 | M19: 3500 | N19: 20 | O19: 3520 | P19: 26 | Q19: 3546 | R19: 26 | S19: 3570 | T19: 24 | U19: 3592 | V19: 22 | W19: 3612 | X19: 20 | Y19: 3634 | Z19: 22 | AA19: 3656 | AB19: 22 | AC19: 22 | AD19: 25 | AE19: 0 | AG19: 3 | AH19: 0 | AI19: 50
A20: 19 | B20: LIRIA PARIAMACHI DE PAZ | C20: B | D20: 7 | E20: 2289 | F20: 16 | G20: 2305 | H20: 17 | I20: 2322 | J20: 26 | K20: 2348 | L20: 16 | M20: 2364 | N20: 17 | O20: 2381 | P20: 16 | Q20: 2397 | R20: 16 | S20: 2414 | T20: 17 | U20: 2428 | V20: 14 | W20: 2443 | X20: 15 | Y20: 2455 | Z20: 12 | AA20: 2469 | AB20: 14 | AC20: 14 | AD20: 0 | AE20: 0 | AG20: 3 | AH20: 0 | AI20: 17
A21: 20 | B21: ROSALINA OLIMPIA CIRIACO SOTELO | C21: B | D21: 8 | E21: 6347 | F21: 14 | G21: 6361 | H21: 17 | I21: 6378 | J21: 18 | K21: 6396 | L21: 15 | M21: 6411 | N21: 14 | O21: 6425 | P21: 14 | Q21: 6439 | R21: 14 | S21: 6456 | T21: 17 | U21: 6470 | V21: 14 | W21: 6484 | X21: 14 | Y21: 6497 | Z21: 13 | AA21: 6510 | AB21: 13 | AC21: 13 | AD21: 16 | AE21: 0 | AG21: 3 | AH21: 0 | AI21: 32
A22: 21 | B22: ALEJANDRO RAPRAY VELASQUEZ | C22: B | D22: 9 | E22: 5905 | F22: 23 | G22: 5928 | H22: 25 | I22: 5953 | J22: 21 | K22: 5974 | L22: 16 | M22: 5990 | N22: 14 | O22: 6004 | P22: 14 | Q22: 6018 | R22: 14 | S22: 6045 | T22: 27 | U22: 6052 | V22: 7 | W22: 6058 | X22: 6 | Y22: 6062 | Z22: 4 | AA22: 6066 | AB22: 4 | AC22: 5 | AD22: 0 | AE22: 0 | AG22: 3 | AH22: 0 | AI22: 8
... A25: 24 | B25: TEOFILO BRUNO RAMOS DE LA CRUZ | C25: B | D25: 12 | E25: 2213 | F25: 8 | G25: 2221 | H25: 8 | I25: 2229 | J25: 10 | K25: 2239 | L25: 7 | M25: 2246 | N25: 9 | O25: 2255 | P25: 6 | Q25: 2261 | R25: 6 | S25: 2267 | T25: 6 | U25: 2273 | V25: 6 | W25: 2278 | X25: 5 | Y25: 2285 | Z25: 7 | AA25: 2292 | AB25: 7 | AC25: 7 | AD25: 10 | AE25: 0 | AG25: 3 | AH25: 0 | AI25: 20
A26: 25 | B26: ROSMERI SANCHEZ ESPADA | C26: B | D26: 12-A | E26: 198 | F26: 6 | G26: 204 | H26: 7 | I26: 211 | J26: 6 | K26: 217 | L26: 6 | M26: 223 | N26: 6 | O26: 229 | P26: 6 | Q26: 235 | R26: 6 | S26: 239 | T26: 4 | U26: 244 | V26: 5 | W26: 250 | X26: 6 | Y26: 256 | Z26: 6 | AA26: 262 | AB26: 6 | AC26: 6 | AD26: 0 | AE26: 0 | AG26: 3 | AH26: 0 | AI26: 9
A27: 26 | B27: SALOME AGUSTINA DIAZ VARGAS | C27: B | D27: 13 | E27: 90 | F27: 13 | G27: 103 | H27: 12 | I27: 115 | J27: 16 | K27: 131 | L27: 6 | M27: 137 | N27: 5 | O27: 142 | P27: 5 | Q27: 147 | R27: 5 | S27: 152 | T27: 5 | U27: 157 | V27: 5 | W27: 165 | X27: 8 | Y27: 173 | Z27: 8 | AA27: 180 | AB27: 7 | AC27: 7 | AD27: 0 | AE27: 0 | AG27: 3 | AH27: 0 | AI27: 10
A28: 27 | B28: MELISSA ISABEL PILLACA GARCIA | C28: B | D28: 15 | E28: 886 | F28: 12 | G28: 898 | H28: 18 | I28: 916 | J28: 13 | K28: 929 | L28: 18 | M28: 947 | N28: 18 | O28: 965 | P28: 20 | Q28: 985 | R28: 20 | S28: 1006 | T28: 21 | U28: 1028 | V28: 22 | W28: 1052 | X28: 24 | Y28: 1061 | Z28: 9 | AA28: 1105 | AB28: 44 | AC28: 44 | AD28: 0 | AE28: 0 | AG28: 3 | AH28: 0 | AI28: 47
A29: 28 | B29: CLETO TENORIO MORI | C29: B | D29: 16 | E29: 322 | F29: 13 | G29: 335 | H29: 21 | I29: 356 | J29: 16 | K29: 372 | L29: 17 | M29: 389 | N29: 15 | O29: 404 | P29: 10 | Q29: 414 | R29: 10 | S29: 422 | T29: 8 | U29: 428 | V29: 6 | W29: 435 | X29: 7 | Y29: 442 | Z29: 7 | AA29: 452 | AB29: 10 | AC29: 10 | AD29: 0 | AE29: 0 | AG29: 3 | AH29: 20 | AI29: 33
A30: 29 | B30: ELEUTERIA DOMITILA PARIAMACHI DE PAZ | C30: B | D30: 17 | E30: 16 | F30: 0 | G30: 16 | H30: 0 | I30: 16 | J30: 2 | K30: 18 | L30: 3 | M30: 21 | N30: 1 | O30: 22 | P30: 0 | Q30: 22 | R30: 0 | S30: 23 | T30: 1 | U30: 23 | V30: 0 | W30: 23 | X30: 0 | Y30: 24 | Z30: 1 | AA30: 24 | AB30: 0 | AC30: 5 | AD30: 0 | AE30: 0 | AG30: 3 | AH30: 0 | AI30: 8
A31: 30 | B31: LUZ DINA MIRAVAL HUERTA | C31: B | D31: 18 | E31: 632 | F31: 18 | G31: 650 | H31: 22 | I31: 672 | J31: 22 | K31: 694 | L31: 17 | M31: 711 | N31: 15 | O31: 726 | P31: 16 | Q31: 742 | R31: 16 | S31: 753 | T31: 11 | U31: 765 | V31: 12 | W31: 777 | X31: 12 | Y31: 790 | Z31: 13 | AA31: 803 | AB31: 13 | AC31: 13 | AD31: 0 | AE31: 0 | AG31: 3 | AH31: 0 | AI31: 16
A32: 31 | B32: CAMILA HIDALGO | C32: B | D32: 21 | E32: 0 | F32: 0 | G32: 0 | H32: 5 | I32: 5 | J32: 3 | K32: 3 | L32: 4 | M32: 7 | N32: 3 | O32: 10 | P32: 9 | Q32: 19 | R32: 9 | S32: 28 | T32: 9 | U32: 36 | V32: 8 | W32: 47 | X32: 11 | Y32: 60 | Z32: 13 | AA32: 72 | AB32: 12 | AC32: 12 | AD32: 0 | AE32: 0 | AG32: 3 | AH32: 0 | AI32: 15
A33: 32 | B33: JANET FERNANDEZ MINAYA | C33: B | D33: 29 | F33: 0 | H33: 0 | I33: 0 | J33: 19 | K33: 19 | L33: 9 | M33: 28 | N33: 4 | O33: 32 | P33: 5 | Q33: 37 | R33: 5 | S33: 45 | T33: 8 | U33: 52 | V33: 7 | W33: 66 | X33: 14 | Y33: 78 | Z33: 12 | AA33: 88 | AB33: 10 | AC33: 10 | AD33: 0 | AE33: 0 | AF33: 100 | AG33: 3 | AH33: 0 | AI33: 113
A34: 33 | B34: ODILON CERNA ROMERO | C34: C | D34: 1 | E34: 1726 | F34: 16 | G34: 1742 | H34: 15 | I34: 1757 | J34: 13 | K34: 1770 | L34: 14 | M34: 1784 | N34: 13 | O34: 1797 | P34: 12 | Q34: 1809 | R34: 12 | S34: 1819 | T34: 10 | U34: 1831 | V34: 12 | W34: 1845 | X34: 14 | Y34: 1859 | Z34: 14 | AA34: 1873 | AB34: 14 | AC34: 14 | AD34: 0 | AE34: 0 | AG34: 3 | AH34: 20 | AI34: 37
A35: 34 | B35: OLGA FLORENTINA HUERTA AGAMA | C35: C | D35: 2 | E35: 796 | F35: 5 | G35: 801 | H35: 17 | I35: 818 | J35: 2 | K35: 820 | L35: 2 | M35: 822 | N35: 1 | O35: 823 | P35: 2 | Q35: 825 | R35: 2 | S35: 826 | T35: 1 | U35: 827 | V35: 1 | W35: 829 | X35: 2 | Y35: 830 | Z35: 1 | AA35: 833 | AB35: 3 | AC35: 5 | AD35: 0 | AE35: 0 | AG35: 3 | AH35: 0 | AI35: 8
A36: 35 | B36: TIMOTEO ROMERO JULCA | C36: C | D36: 4 | E36: 2918 | F36: 20 | G36: 2938 | H36: 32 | I36: 2970 | J36: 30 | K36: 3000 | L36: 29 | M36: 3029 | N36: 22 | O36: 3051 | P36: 15 | Q36: 3066 | R36: 15 | S36: 3085 | T36: 19 | U36: 3106 | V36: 21 | W36: 3122 | X36: 16 | Y36: 3150 | Z36: 28 | AA36: 3175 | AB36: 25 | AC36: 25 | AD36: 0 | AE36: 0 | AG36: 3 | AH36: 0 | AI36: 28
A37: 36 | B37: AGAPITO PRINICIPE SALINAS | C37: C | D37: 5 | E37: 3725 | F37: 22 | G37: 3747 | H37: 21 | I37: 3768 | J37: 19 | K37: 3787 | L37: 19 | M37: 3806 | N37: 18 | O37: 3824 | P37: 11 | Q37: 3835 | R37: 11 | S37: 3845 | T37: 10 | U37: 3859 | V37: 14 | W37: 3869 | X37: 10 | Y37: 3884 | Z37: 15 | AA37: 3899 | AB37: 15 | AC37: 15 | AD37: 0 | AE37: 0 | AG37: 3 | AH37: 0 | AI37: 18
A38: 37 | B38: DIANA JARA TRUJILLO | C38: C | D38: 6 | E38: 150 | F38: 22 | G38: 172 | H38: 23 | I38: 195 | J38: 19 | K38: 214 | L38: 15 | M38: 229 | N38: 16 | O38: 245 | P38: 21 | Q38: 266 | R38: 21 | S38: 283 | T38: 17 | U38: 299 | V38: 16 | W38: 324 | X38: 25 | Y38: 350 | Z38: 26 | AA38: 370 | AB38: 20 | AC38: 20 | AD38: 0 | AE38: 0 | AG38: 3 | AH38: 40 | AI38: 63
A39: 38 | B39: VICTOR LOPEZ TRUJILLO | C39: C | D39: 7 | E39: 2096 | F39: 43 | G39: 2139 | H39: 27 | I39: 2166 | J39: 20 | K39: 2186 | L39: 15 | M39: 2201 | N39: 14 | O39: 2215 | P39: 11 | Q39: 2226 | R39: 11 | S39: 2236 | T39: 10 | U39: 2246 | V39: 10 | W39: 2260 | X39: 14 | Y39: 2276 | Z39: 16 | AA39: 2288 | AB39: 12 | AC39: 12 | AD39: 0 | AE39: 0 | AG39: 3 | AH39: 40 | AI39: 55
A40: 39 | B40: JULISSA BARRETO QUITO | C40: C | D40: 8 | E40: 156 | F40: 0 | G40: 156 | H40: 1 | I40: 157 | J40: 0 | K40: 157 | L40: 0 | M40: 157 | N40: 1 | O40: 158 | P40: 4 | Q40: 162 | R40: 4 | S40: 167 | T40: 5 | U40: 170 | V40: 3 | W40: 175 | X40: 5 | Y40: 179 | Z40: 4 | AA40: 184 | AB40: 5 | AC40: 5 | AD40: 8 | AE40: 0 | AG40: 3 | AH40: 20 | AI40: 36
A41: 40 | B41: JAZMIN QUITO SANCHEZ | C41: C | D41: 8-B | E41: 509 | F41: 16 | G41: 525 | H41: 22 | I41: 547 | J41: 16 | K41: 563 | L41: 15 | M41: 578 | N41: 14 | O41: 592 | P41: 14 | Q41: 606 | R41: 14 | S41: 618 | T41: 12 | U41: 631 | V41: 13 | W41: 645 | X41: 14 | Y41: 668 | Z41: 23 | AA41: 689 | AB41: 21 | AC41: 21 | AD41: 0 | AE41: 0 | AG41: 3 | AH41: 0 | AI41: 24
A42: 41 | B42: JUAN UCULMANA SANCHEZ | C42: C | D42: 9 | E42: 2002 | F42: 5 | G42: 2007 | H42: 3 | I42: 2010 | J42: 29 | K42: 2039 | L42: 6 | M42: 2045 | N42: 4 | O42: 2049 | P42: 1 | Q42: 2050 | R42: 1 | S42: 2050 | T42: 0 | U42: 2050 | V42: 0 | W42: 2060 | X42: 10 | Y42: 2062 | Z42: 2 | AA42: 2064 | AB42: 2 | AC42: 5 | AD42: 0 | AE42: 0 | AG42: 3 | AH42: 0 | AI42: 8
A43: 42 | B43: SONIA GLORIA MORENO CASTILLEJO | C43: C | D43: 9-C | E43: 306 | F43: 7 | G43: 313 | H43: 9 | I43: 322 | J43: 7 | K43: 329 | L43: 9 | M43: 338 | N43: 6 | O43: 344 | P43: 6 | Q43: 350 | R43: 6 | S43: 355 | T43: 5 | U43: 361 | V43: 6 | W43: 365 | X43: 4 | Y43: 373 | Z43: 8 | AA43: 381 | AB43: 8 | AC43: 8 | AD43: 0 | AE43: 0 | AG43: 3 | AH43: 0 | AI43: 11
A44: 43 | B44: CEVERIANO CHAUCA MORALES | C44: C | D44: 11 | E44: 325 | F44: 16 | G44: 341 | H44: 23 | I44: 364 | J44: 21 | K44: 385 | L44: 24 | M44: 409 | N44: 22 | O44: 431 | P44: 19 | Q44: 450 | R44: 19 | S44: 472 | T44: 22 | U44: 496 | V44: 24 | W44: 510 | X44: 14 | Y44: 526 | Z44: 16 | AA44: 552 | AB44: 26 | AC44: 26 | AD44: 0 | AE44: 0 | AG44: 3 | AH44: 0 | AI44: 29
A45: 44 | B45: MACEDONIO MORALES BENTURO | C45: C | D45: 12 | E45: 1348 | F45: 16 | G45: 1364 | H45: 11 | I45: 1375 | J45: 18 | K45: 1393 | L45: 14 | M45: 1407 | N45: 12 | O45: 1419 | P45: 12 | Q45: 1431 | R45: 12 | S45: 1440 | T45: 9 | U45: 1454 | V45: 14 | W45: 1462 | X45: 8 | Y45: 1471 | Z45: 9 | AA45: 1483 | AB45: 12 | AC45: 12 | AD45: 0 | AE45: 0 | AG45: 3 | AH45: 0 | AI45: 15
A46: 45 | B46: IRMA HUAÑAHUI LOPEZ | C46: C | D46: 13 | E46: 1924 | F46: 9 | G46: 1933 | H46: 9 | I46: 1942 | J46: 7 | K46: 1949 | L46: 7 | M46: 1956 | N46: 11 | O46: 1967 | P46: 6 | Q46: 1973 | R46: 6 | S46: 1988 | T46: 15 | U46: 1993 | V46: 5 | W46: 2002 | X46: 9 | Y46: 2007 | Z46: 5 | AA46: 2012 | AB46: 5 | AC46: 5 | AD46: 0 | AE46: 0 | AG46: 3 | AH46: 0 | AI46: 8
A47: 46 | B47: JUAN RIOS BLAS | C47: C | D47: 14 | E47: 648 | F47: 7 | G47: 655 | H47: 5 | I47: 660 | J47: 11 | K47: 671 | L47: 8 | M47: 679 | N47: 7 | O47: 686 | P47: 5 | Q47: 691 | R47: 5 | S47: 696 | T47: 5 | U47: 699 | V47: 5 | W47: 702 | X47: 3 | Y47: 708 | Z47: 6 | AA47: 714 | AB47: 6 | AC47: 6 | AD47: 0 | AE47: 0 | AG47: 3 | AH47: 0 | AI47: 9
A48: 47 | B48: JULIO RIOS BLAS | C48: C | D48: 15 | E48: 1994 | F48: 6 | G48: 2000 | H48: -5 | I48: 1995 | J48: 0 | K48: 0 | L48: 15 | M48: 15 | N48: 11 | O48: 26 | P48: 7 | Q48: 33 | R48: 7 | S48: 39 | T48: 6 | U48: 45 | V48: 6 | W48: 50 | X48: 5 | Y48: 53 | Z48: 3 | AA48: 56 | AB48: 3 | AC48: 5 | AD48: 0 | AE48: 0 | AG48: 3 | AH48: 0 | AI48: 8
A49: 48 | B49: MARTHA MASIAS CASIHUAMAN DE TERAN | C49: C | D49: 16 | E49: 1692 | F49: 9 | G49: 1701 | H49: 14 | I49: 1715 | J49: 5 | K49: 1720 | L49: 5 | M49: 1725 | N49: 5 | O49: 1730 | P49: 3 | Q49: 1733 | R49: 3 | S49: 1736 | T49: 3 | U49: 1744 | V49: 8 | W49: 1750 | X49: 6 | Y49: 1757 | Z49: 7 | AA49: 1763 | AB49: 6 | AC49: 6 | AD49: 10 | AE49: 0 | AG49: 3 | AH49: 0 | AI49: 19
A50: 49 | B50: MARCELINO VALLADARES TRUJILLO | C50: C | D50: 18 | E50: 263 | F50: 7 | G50: 270 | H50: 12 | I50: 282 | J50: 5 | K50: 287 | L50: 7 | M50: 294 | N50: 5 | O50: 299 | P50: 4 | Q50: 303 | R50: 4 | S50: 308 | T50: 5 | U50: 309 | V50: 1 | W50: 313 | X50: 4 | Y50: 318 | Z50: 5 | AA50: 326 | AB50: 8 | AC50: 8 | AD50: 0 | AE50: 0 | AG50: 3 | AH50: 0 | AI50: 11
A51: 50 | B51: ANTONIO VALLADARES DOMINGUEZ | C51: C | D51: 19 | E51: 3207 | F51: 21 | G51: 3228 | H51: 22 | I51: 3250 | J51: 18 | K51: 3268 | L51: 20 | M51: 3288 | N51: 20 | O51: 3308 | P51: 19 | Q51: 3327 | R51: 19 | S51: 3347 | T51: 20 | U51: 3363 | V51: 16 | W51: 3380 | X51: 17 | Y51: 3402 | Z51: 22 | AA51: 3425 | AB51: 23 | AC51: 23 | AD51: 0 | AE51: 0 | AG51: 3 | AH51: 0 | AI51: 26
A52: 51 | B52: EUSEBIO REYES VILLAFANA | C52: C | D52: 20 | E52: 2433 | F52: 20 | G52: 2453 | H52: 20 | I52: 2473 | J52: 21 | K52: 2494 | L52: 16 | M52: 2510 | N52: 18 | O52: 2528 | P52: 22 | Q52: 2550 | R52: 22 | S52: 2560 | T52: 10 | U52: 2570 | V52: 10 | W52: 2582 | X52: 12 | Y52: 2594 | Z52: 12 | AA52: 2608 | AB52: 14 | AC52: 14 | AD52: 0 | AE52: 0 | AG52: 3 | AH52: 20 | AI52: 37
A53: 53 | B53: ABRAHAM BARRERA VEGA | C53: C | D53: 22 | E53: 0 | F53: 0 | G53: 0 | H53: 0 | I53: 0 | J53: 0 | K53: 0 | L53: 0 | M53: 0 | N53: 6 | O53: 6 | P53: 2 | Q53: 8 | R53: 2 | S53: 10 | T53: 2 | U53: 12 | V53: 2 | W53: 13 | X53: 1 | Y53: 18 | Z53: 5 | AA53: 25 | AB53: 7 | AC53: 7 | AD53: 0 | AE53: 0 | AG53: 3 | AH53: 20 | AI53: 30
A54: 54 | B54: ANTONIA MAYO TRUJILLO | C54: C | D54: 23 | E54: 4089 | F54: 20 | G54: 4109 | H54: 27 | I54: 4136 | J54: 25 | K54: 4161 | L54: 24 | M54: 4185 | N54: 25 | O54: 4210 | P54: 21 | Q54: 4231 | R54: 21 | S54: 4241 | T54: 10 | U54: 4249 | V54: 8 | W54: 4259 | X54: 10 | Y54: 4273 | Z54: 14 | AA54: 4288 | AB54: 15 | AC54: 15 | AD54: 0 | AE54: 0 | AG54: 3 | AH54: 20 | AI54: 38
A55: 55 | B55: ALFREDO CARLOS VENTURO CAPCHA | C55: C | D55: 24 | E55: 490 | F55: 2 | G55: 492 | H55: 2 | I55: 494 | J55: 2 | K55: 496 | L55: 2 | M55: 498 | N55: 2 | O55: 500 | P55: 3 | Q55: 503 | R55: 3 | S55: 505 | T55: 2 | U55: 507 | V55: 2 | W55: 508 | X55: 1 | Y55: 510 | Z55: 2 | AA55: 514 | AB55: 4 | AC55: 5 | AD55: 0 | AE55: 0 | AG55: 3 | AH55: 20 | AI55: 28
... A64: 64 | B64: EBER AGÜERO TRUJILLO | C64: C | D64: 34 | E64: 616 | F64: 4 | G64: 620 | H64: 6 | I64: 626 | J64: 3 | K64: 629 | L64: 3 | M64: 632 | N64: 0 | O64: 632 | P64: 0 | Q64: 632 | R64: 0 | S64: 632 | T64: 0 | U64: 632 | V64: 0 | W64: 632 | X64: 0 | Y64: 632 | Z64: 0 | AA64: 632 | AB64: 0 | AC64: 5 | AD64: 0 | AE64: 0 | AG64: 3 | AH64: 0 | AI64: 8
A65: 65 | B65: ANALY QUINECHE MORANTE | C65: C | D65: 35 | E65: 328 | F65: 11 | G65: 339 | H65: 11 | I65: 350 | J65: 10 | K65: 360 | L65: 10 | M65: 370 | N65: 12 | O65: 382 | P65: 12 | Q65: 394 | R65: 12 | S65: 404 | T65: 10 | U65: 413 | V65: 9 | W65: 425 | X65: 12 | Y65: 435 | Z65: 10 | AA65: 445 | AB65: 10 | AC65: 10 | AD65: 28 | AE65: 0 | AF65: 100 | AG65: 3 | AH65: 20 | AI65: 161
A66: 66 | B66: MARIA NORABUENA ESPADA | C66: C | D66: 36 | E66: 158 | F66: 9 | G66: 167 | H66: 8 | I66: 175 | J66: 5 | K66: 180 | L66: 5 | M66: 185 | N66: 3 | O66: 188 | P66: 5 | Q66: 193 | R66: 5 | S66: 196 | T66: 3 | U66: 199 | V66: 3 | W66: 201 | X66: 2 | Y66: 204 | Z66: 3 | AA66: 208 | AB66: 4 | AC66: 5 | AD66: 0 | AE66: 0 | AG66: 3 | AH66: 0 | AI66: 8
A67: 67 | B67: RAQUEL SORIA BUSTAMANTE | C67: C | D67: 37 | E67: 93 | F67: 7 | G67: 100 | H67: 9 | I67: 109 | J67: 8 | K67: 117 | L67: 9 | M67: 126 | N67: 8 | O67: 134 | P67: 6 | Q67: 140 | R67: 6 | S67: 146 | T67: 6 | U67: 152 | V67: 6 | W67: 157 | X67: 5 | Y67: 163 | Z67: 6 | AA67: 169 | AB67: 6 | AC67: 6 | AD67: 0 | AE67: 0 | AG67: 3 | AH67: 20 | AI67: 29
A68: 68 | B68: JANET ROMERO MAYO | C68: C | D68: 42 | F68: 0 | H68: 4 | I68: 4 | J68: 8 | K68: 12 | L68: 9 | M68: 21 | N68: 6 | O68: 27 | P68: 21 | Q68: 48 | R68: 21 | S68: 62 | T68: 14 | U68: 73 | V68: 11 | W68: 85 | X68: 12 | Y68: 97 | Z68: 12 | AA68: 112 | AB68: 15 | AC68: 15 | AD68: 0 | AE68: 0 | AF68: 100 | AG68: 3 | AH68: 20 | AI68: 138
A69: 69 | B69: JANET EVARISTO COCHACHIN | C69: C | D69: 45 | W69: 0 | X69: 0 | Y69: 0 | Z69: 0 | AA69: 0 | AB69: 0 | AC69: 5 | AD69: 8 | AE69: 0 | AF69: 100 | AG69: 3 | AH69: 0 | AI69: 116
A70: 70 | B70: JUAN VENTURO CAPCHA | C70: D | D70: 1 | E70: 1625 | F70: 7 | G70: 1632 | H70: 7 | I70: 1639 | J70: 7 | K70: 1646 | L70: 7 | M70: 1653 | N70: 6 | O70: 1659 | P70: 6 | Q70: 1665 | R70: 6 | S70: 1669 | T70: 4 | U70: 1675 | V70: 6 | W70: 1680 | X70: 5 | Y70: 1685 | Z70: 5 | AA70: 1693 | AB70: 8 | AC70: 8 | AD70: 0 | AE70: 0 | AG70: 3 | AH70: 0 | AI70: 11
A71: 71 | B71: VICTOR TRUJILLO POLICARPIO | C71: D | D71: 2 | E71: 1772 | F71: 17 | G71: 1789 | H71: 18 | I71: 1807 | J71: 17 | K71: 1824 | L71: 17 | M71: 1841 | N71: 12 | O71: 1853 | P71: 7 | Q71: 1860 | R71: 7 | S71: 1864 | T71: 4 | U71: 1868 | V71: 4 | W71: 1872 | X71: 4 | Y71: 1883 | Z71: 11 | AA71: 1918 | AB71: 35 | AC71: 35 | AD71: 0 | AE71: 0 | AG71: 3 | AH71: 20 | AI71: 58
A72: 72 | B72: ANTONIO CASTILLEJO CUEVA | C72: D | D72: 3 | E72: 1087 | F72: 34 | G72: 1121 | H72: 7 | I72: 1128 | J72: 7 | K72: 1135 | L72: 9 | M72: 1144 | N72: 9 | O72: 1153 | P72: 10 | Q72: 1163 | R72: 10 | S72: 1171 | T72: 8 | U72: 1183 | V72: 12 | W72: 1192 | X72: 9 | Y72: 1201 | Z72: 9 | AA72: 1210 | AB72: 9 | AC72: 9 | AD72: 0 | AE72: 0 | AG72: 3 | AH72: 0 | AI72: 12
A73: 73 | B73: JULIO CESAR PRINCIPE LUNA | C73: D | D73: 4 | E73: 168 | F73: 10 | G73: 178 | H73: -10 | I73: 168 | J73: 0 | K73: 0 | L73: 16 | M73: 16 | N73: 12 | O73: 28 | P73: 20 | Q73: 48 | R73: 20 | S73: 63 | T73: 15 | U73: 74 | V73: 11 | W73: 86 | X73: 12 | Y73: 97 | Z73: 11 | AA73: 113 | AB73: 16 | AC73: 16 | AD73: 0 | AE73: 0 | AG73: 3 | AH73: 20 | AI73: 39
A74: 74 | B74: TERESA PAULA JARA DE FERNANDEZ | C74: D | D74: 5 | E74: 225 | F74: 14 | G74: 239 | H74: 35 | I74: 274 | J74: 14 | K74: 288 | L74: 13 | M74: 301 | N74: 7 | O74: 308 | P74: 8 | Q74: 316 | R74: 8 | S74: 324 | T74: 8 | U74: 333 | V74: 9 | W74: 344 | X74: 11 | Y74: 352 | Z74: 8 | AA74: 367 | AB74: 15 | AC74: 15 | AD74: 0 | AE74: 0 | AG74: 3 | AH74: 0 | AI74: 18
A75: 75 | B75: HERMELINDA JARA TRUJILLO | C75: D | D75: 6 | E75: 7638 | F75: 20 | G75: 7658 | H75: 26 | I75: 7684 | J75: 19 | K75: 7703 | L75: 27 | M75: 7730 | N75: 16 | O75: 7746 | P75: 15 | Q75: 7761 | R75: 15 | S75: 7775 | T75: 14 | U75: 7789 | V75: 14 | W75: 7803 | X75: 14 | Y75: 7822 | Z75: 19 | AA75: 7840 | AB75: 18 | AC75: 18 | AD75: 0 | AE75: 0 | AG75: 3 | AH75: 0 | AI75: 21
A76: 76 | B76: MAXIMILIANO JARA NIETO | C76: D | D76: 7 | E76: 3878 | F76: 73 | G76: 3951 | H76: 74 | I76: 4025 | J76: 65 | K76: 4090 | L76: 71 | M76: 4161 | N76: 61 | O76: 4222 | P76: 58 | Q76: 4280 | R76: 58 | S76: 4331 | T76: 51 | U76: 4382 | V76: 51 | W76: 4445 | X76: 63 | Y76: 4507 | Z76: 62 | AA76: 4584 | AB76: 77 | AC76: 77 | AD76: 65 | AE76: 0 | AG76: 3 | AH76: 0 | AI76: 145
A77: 77 | B77: SANTA ANTONIA SAENZ TICLIO | C77: D | D77: 8 | E77: 1622 | F77: 6 | G77: 1628 | H77: 6 | I77: 1634 | J77: 6 | K77: 1640 | L77: 6 | M77: 1646 | N77: 7 | O77: 1653 | P77: 5 | Q77: 1658 | R77: 5 | S77: 1667 | T77: 9 | U77: 1671 | V77: 4 | W77: 1676 | X77: 5 | Y77: 1681 | Z77: 5 | AA77: 1686 | AB77: 5 | AC77: 5 | AD77: 0 | AE77: 0 | AG77: 3 | AH77: 0 | AI77: 8
A78: 78 | B78: RUFINA CABELLO TICLIO | C78: D | D78: 9 | E78: 3754 | F78: 25 | G78: 3779 | H78: 21 | I78: 3800 | J78: 18 | K78: 3818 | L78: 17 | M78: 3835 | N78: 16 | O78: 3851 | P78: 21 | Q78: 3872 | R78: 21 | S78: 3893 | T78: 21 | U78: 3904 | V78: 11 | W78: 3915 | X78: 11 | Y78: 3929 | Z78: 14 | AA78: 3942 | AB78: 13 | AC78: 13 | AD78: 0 | AE78: 0 | AG78: 3 | AH78: 0 | AI78: 16
A79: 79 | B79: LIDIA ASTERIA SALES BLAS | C79: D | D79: 10 | E79: 2569 | F79: 11 | G79: 2580 | H79: 12 | I79: 2592 | J79: 13 | K79: 2605 | L79: 14 | M79: 2619 | N79: 13 | O79: 2632 | P79: 11 | Q79: 2643 | R79: 11 | S79: 2655 | T79: 12 | U79: 2667 | V79: 12 | W79: 2677 | X79: 10 | Y79: 2687 | Z79: 10 | AA79: 2697 | AB79: 10 | AC79: 10 | AD79: 0 | AE79: 0 | AG79: 3 | AH79: 0 | AI79: 13
A80: 80 | B80: SALOMON RODRIGUEZ GARCIA | C80: D | D80: 11 | E80: 721 | F80: 14 | G80: 735 | H80: 16 | I80: 751 | J80: 14 | K80: 765 | L80: 13 | M80: 778 | N80: 12 | O80: 790 | P80: 12 | Q80: 802 | R80: 12 | S80: 812 | T80: 10 | U80: 823 | V80: 11 | W80: 834 | X80: 11 | Y80: 844 | Z80: 10 | AA80: 855 | AB80: 11 | AC80: 11 | AD80: 0 | AE80: 0 | AG80: 3 | AH80: 20 | AI80: 34
A81: 81 | B81: MARTINA MENDOZA ROMERO | C81: D | D81: 12 | E81: 1033 | F81: 20 | G81: 1053 | H81: -20 | I81: 1033 | J81: 0 | K81: 0 | L81: 36 | M81: 36 | N81: 28 | O81: 64 | P81: 29 | Q81: 93 | R81: 29 | S81: 116 | T81: 23 | U81: 133 | V81: 17 | W81: 153 | X81: 20 | Y81: 175 | Z81: 22 | AA81: 215 | AB81: 40 | AC81: 40 | AD81: 0 | AE81: 0 | AG81: 3 | AH81: 20 | AI81: 63
... A89: 89 | B89: FELIX ENRIQUE VALENCIA FERNANDEZ | C89: E | D89: 3 | E89: 2023 | F89: 78 | G89: 2101 | H89: 66 | I89: 2167 | J89: 74 | K89: 2241 | L89: 73 | M89: 2314 | N89: 72 | O89: 2386 | P89: 73 | Q89: 2459 | R89: 73 | S89: 2527 | T89: 68 | U89: 2584 | V89: 57 | W89: 2601 | X89: 17 | Y89: 2609 | Z89: 8 | AA89: 2619 | AB89: 10 | AC89: 10 | AD89: 0 | AE89: 0 | AG89: 3 | AH89: 20 | AI89: 33
A90: 90 | B90: FELIX VELASQUEZ LOPEZ | C90: E | D90: 4 | E90: 1736 | F90: 11 | G90: 1747 | H90: 12 | I90: 1759 | J90: 9 | K90: 1768 | L90: 14 | M90: 1782 | N90: 12 | O90: 1794 | P90: 5 | Q90: 1799 | R90: 5 | S90: 1803 | T90: 4 | U90: 1810 | V90: 7 | W90: 1822 | X90: 12 | Y90: 0 | Z90: 0 | AA90: 8 | AB90: 8 | AC90: 8 | AD90: 20 | AE90: 0 | AF90: 65 | AG90: 3 | AH90: 0 | AI90: 96
A91: 91 | B91: LUIS ALBERTO GOMEZ LAHUANA | C91: E | D91: 6 | E91: 623 | F91: 16 | G91: 639 | H91: 17 | I91: 656 | J91: 19 | K91: 675 | L91: 14 | M91: 689 | N91: 15 | O91: 704 | P91: 11 | Q91: 715 | R91: 11 | S91: 722 | T91: 7 | U91: 730 | V91: 8 | W91: 740 | X91: 10 | Y91: 750 | Z91: 10 | AA91: 765 | AB91: 15 | AC91: 15 | AD91: 0 | AE91: 0 | AG91: 3 | AH91: 0 | AI91: 18
A92: 92 | B92: GREGORIO TRUJILLO LEON | C92: E | D92: 7 | E92: 1760 | F92: 3 | G92: 1763 | H92: 10 | I92: 1773 | J92: 7 | K92: 1780 | L92: 3 | M92: 1783 | N92: 15 | O92: 1798 | P92: 2 | Q92: 1800 | R92: 2 | S92: 1803 | T92: 3 | U92: 1804 | V92: 1 | W92: 1808 | X92: 4 | Y92: 1814 | Z92: 6 | AA92: 1819 | AB92: 5 | AC92: 5 | AD92: 0 | AE92: 0 | AG92: 3 | AH92: 0 | AI92: 8
A93: 93 | B93: GERTRUDES VIDAL GONZALES | C93: E | D93: 8 | E93: 826 | F93: 4 | G93: 830 | H93: 5 | I93: 835 | J93: 7 | K93: 842 | L93: 9 | M93: 851 | N93: 21 | O93: 872 | P93: 5 | Q93: 877 | R93: 5 | S93: 896 | T93: 19 | U93: 899 | V93: 3 | W93: 904 | X93: 5 | Y93: 913 | Z93: 9 | AA93: 919 | AB93: 6 | AC93: 6 | AD93: 0 | AE93: 0 | AG93: 3 | AH93: 0 | AI93: 9
A94: 94 | B94: MARIA NANCY SIGUEÑAS UGARTE | C94: E | D94: 9 | E94: 3190 | F94: 21 | G94: 3211 | H94: 21 | I94: 3232 | J94: 20 | K94: 3252 | L94: 22 | M94: 3274 | N94: 23 | O94: 3297 | P94: 17 | Q94: 3314 | R94: 17 | S94: 3328 | T94: 14 | U94: 3340 | V94: 12 | W94: 3355 | X94: 15 | Y94: 3375 | Z94: 20 | AA94: 3397 | AB94: 22 | AC94: 22 | AD94: 0 | AE94: 0 | AG94: 3 | AH94: 0 | AI94: 25
A95: 95 | B95: GREGORIA SIGUEÑAS UGARTE | C95: E | D95: 10 | E95: 100 | F95: 51 | G95: 151 | H95: 49 | I95: 200 | J95: 36 | K95: 236 | L95: 32 | M95: 268 | N95: 29 | O95: 297 | P95: 23 | Q95: 320 | R95: 23 | S95: 340 | T95: 20 | U95: 359 | V95: 19 | W95: 386 | X95: 27 | Y95: 411 | Z95: 25 | AA95: 445 | AB95: 34 | AC95: 34 | AD95: 28 | AE95: 0 | AG95: 3 | AH95: 20 | AI95: 85
A96: 96 | B96: VILMA SIGUEÑAS UGARTE | C96: E | D96: 11 | E96: 3342 | F96: 56 | G96: 3398 | H96: 48 | I96: 3446 | J96: 33 | K96: 3479 | L96: 29 | M96: 3508 | N96: 30 | O96: 3538 | P96: 26 | Q96: 3564 | R96: 26 | S96: 3587 | T96: 23 | U96: 3610 | V96: 23 | W96: 3633 | X96: 23 | Y96: 3659 | Z96: 26 | AA96: 3685 | AB96: 26 | AC96: 26 | AD96: 0 | AE96: 0 | AG96: 3 | AH96: 0 | AI96: 29
A97: 97 | B97: TEOFILA FERNANDEZ REYES | C97: E | D97: 12 | E97: 3375 | F97: 16 | G97: 3391 | H97: 13 | I97: 3404 | J97: 13 | K97: 3417 | L97: 12 | M97: 3429 | N97: 13 | O97: 3442 | P97: 10 | Q97: 3452 | R97: 10 | S97: 3463 | T97: 11 | U97: 3473 | V97: 10 | W97: 3489 | X97: 16 | Y97: 3503 | Z97: 14 | AA97: 3516 | AB97: 13 | AC97: 13 | AD97: 17 | AE97: 0 | AG97: 3 | AH97: 0 | AI97: 33
A98: 98 | B98: LINDOLINA MUÑOZ HERMITAÑO | C98: E | D98: 13 | E98: 2528 | F98: 28 | G98: 2556 | H98: 30 | I98: 2586 | J98: 19 | K98: 2605 | L98: 20 | M98: 2625 | N98: 26 | O98: 2651 | P98: 21 | Q98: 2672 | R98: 21 | S98: 2691 | T98: 19 | U98: 2710 | V98: 19 | W98: 2727 | X98: 17 | Y98: 2751 | Z98: 24 | AA98: 2767 | AB98: 16 | AC98: 16 | AD98: 0 | AE98: 0 | AG98: 3 | AH98: 0 | AI98: 19
A99: 99 | B99: FELICIANO SIGUEÑAS UGARTE | C99: E | D99: 14 | E99: 4542 | F99: 18 | G99: 4560 | H99: 18 | I99: 4578 | J99: 18 | K99: 4596 | L99: 27 | M99: 4623 | N99: 33 | O99: 4656 | P99: 14 | Q99: 4670 | R99: 14 | S99: 4683 | T99: 13 | U99: 4695 | V99: 12 | W99: 4708 | X99: 13 | Y99: 4722 | Z99: 14 | AA99: 4740 | AB99: 18 | AC99: 18 | AD99: 0 | AE99: 0 | AG99: 3 | AH99: 0 | AI99: 21
A100: 100 | B100: JUAN SAAVEDRA SAAVEDRA | C100: E | D100: 14-B | E100: 216 | F100: 4 | G100: 220 | H100: 5 | I100: 225 | J100: 6 | K100: 231 | L100: 4 | M100: 235 | N100: 4 | O100: 239 | P100: 4 | Q100: 243 | R100: 4 | S100: 246 | T100: 3 | U100: 249 | V100: 3 | W100: 252 | X100: 3 | Y100: 256 | Z100: 4 | AA100: 260 | AB100: 4 | AC100: 5 | AD100: 8 | AE100: 0 | AG100: 3 | AH100: 0 | AI100: 16
A101: 101 | B101: MERCADO TUPAC AMARU | C101: E | D101: 19 | P101: 1 | Q101: 0 | R101: 0 | S101: 0 | T101: 0 | U101: 0 | V101: 0 | W101: 0 | X101: 0 | Y101: 0 | Z101: 0 | AA101: 0 | AB101: 0 | AC101: 5 | AD101: 0 | AE101: 0 | AG101: 3 | AH101: 0 | AI101: 8
A102: 102 | B102: MARIA GODO SIFUENTES | C102: F | D102: 1 | E102: 344 | F102: 23 | G102: 367 | H102: 20 | I102: 387 | J102: 23 | K102: 410 | L102: 19 | M102: 429 | N102: 20 | O102: 449 | P102: 16 | Q102: 465 | R102: 16 | S102: 481 | T102: 16 | U102: 498 | V102: 17 | W102: 518 | X102: 20 | Y102: 534 | Z102: 16 | AA102: 553 | AB102: 19 | AC102: 19 | AD102: 0 | AE102: 0 | AG102: 3 | AH102: 0 | AI102: 22
A103: 103 | B103: CAMILA DELGADO VEGA | C103: F | D103: 3 | E103: 1 | F103: 0 | G103: 1 | H103: 4 | I103: 5 | J103: 1 | K103: 2 | L103: 3 | M103: 5 | N103: -2 | O103: 3 | P103: 0 | Q103: 3 | R103: 0 | S103: 3 | T103: 0 | U103: 3 | V103: 0 | W103: 3 | X103: 0 | Y103: 3 | Z103: 0 | AA103: 3 | AB103: 0 | AC103: 5 | AD103: 0 | AE103: 0 | AG103: 3 | AH103: 0 | AI103: 8
A104: 104 | B104: ABIGAIL SONIA GASPAR VEGA | C104: F | D104: 3-B | E104: 251 | F104: 4 | G104: 255 | H104: 12 | I104: 267 | J104: 8 | K104: 275 | L104: 9 | M104: 284 | N104: 7 | O104: 291 | P104: 4 | Q104: 295 | R104: 4 | S104: 296 | T104: 1 | U104: 296 | V104: 0 | W104: 297 | X104: 1 | Y104: 297 | Z104: 0 | AA104: 297 | AB104: 0 | AC104: 5 | AD104: 0 | AE104: 0 | AG104: 3 | AH104: 20 | AI104: 28
A105: 105 | B105: TOLENTINO JULCA MORENO | C105: F | D105: 4 | E105: 353 | F105: 11 | G105: 364 | H105: 15 | I105: 379 | J105: 14 | K105: 393 | L105: 15 | M105: 408 | N105: 17 | O105: 425 | P105: 10 | Q105: 435 | R105: 10 | S105: 444 | T105: 9 | U105: 455 | V105: 11 | W105: 465 | X105: 10 | Y105: 476 | Z105: 11 | AA105: 490 | AB105: 14 | AC105: 14 | AD105: 14 | AE105: 0 | AG105: 3 | AH105: 40 | AI105: 71
A106: 106 | B106: TEOFILO AYALA GASPAR | C106: F | D106: 5 | E106: 1428 | F106: 27 | G106: 1455 | H106: 34 | I106: 1489 | J106: 29 | K106: 1518 | L106: 26 | M106: 1544 | N106: 28 | O106: 1572 | P106: 29 | Q106: 1601 | R106: 29 | S106: 1623 | T106: 22 | U106: 1643 | V106: 20 | W106: 1662 | X106: 19 | Y106: 1686 | Z106: 24 | AA106: 1714 | AB106: 28 | AC106: 28 | AD106: 0 | AE106: 0 | AG106: 3 | AH106: 0 | AI106: 31
A107: 107 | B107: ALBERTO TARAZONA CALDAS | C107: F | D107: 6 | E107: 2851 | F107: 20 | G107: 2871 | H107: 20 | I107: 2891 | J107: 16 | K107: 2907 | L107: 16 | M107: 2923 | N107: 16 | O107: 2939 | P107: 11 | Q107: 2950 | R107: 11 | S107: 2960 | T107: 10 | U107: 2971 | V107: 11 | W107: 2978 | X107: 7 | Y107: 2993 | Z107: 15 | AA107: 3012 | AB107: 19 | AC107: 19 | AD107: 0 | AE107: 0 | AG107: 3 | AH107: 0 | AI107: 22
A108: 108 | B108: VICTOR LAURENCIO VALLADARES | C108: F | D108: 7 | E108: 6500 | F108: 33 | G108: 6533 | H108: 40 | I108: 6573 | J108: 26 | K108: 6599 | L108: 33 | M108: 6632 | N108: 19 | O108: 6651 | P108: 23 | Q108: 6674 | R108: 23 | S108: 6692 | T108: 18 | U108: 6708 | V108: 16 | W108: 6727 | X108: 19 | Y108: 6751 | Z108: 24 | AA108: 6780 | AB108: 29 | AC108: 29 | AD108: 27 | AE108: 0 | AG108: 3 | AH108: 0 | AI108: 59
A109: 109 | B109: GUDELIA ELIZABETH MIRANDA VEGA | C109: F | D109: 8 | E109: 1568 | F109: 16 | G109: 1584 | H109: 11 | I109: 1595 | J109: 8 | K109: 1603 | L109: 11 | M109: 1614 | N109: 10 | O109: 1624 | P109: 10 | Q109: 1634 | R109: 10 | S109: 1641 | T109: 7 | U109: 1650 | V109: 9 | W109: 1659 | X109: 9 | Y109: 1665 | Z109: 6 | AA109: 1673 | AB109: 8 | AC109: 8 | AD109: 0 | AE109: 0 | AG109: 3 | AH109: 0 | AI109: 11
A110: 111 | B110: HERMINIO LUCERO TRUJILLO | C110: F | D110: 10 | E110: 2420 | F110: 21 | G110: 2441 | H110: 6 | I110: 2447 | J110: 5 | K110: 5 | L110: 7 | M110: 12 | N110: 7 | O110: 19 | P110: 5 | Q110: 24 | R110: 5 | S110: 30 | T110: 6 | U110: 39 | V110: 9 | W110: 47 | X110: 8 | Y110: 57 | Z110: 10 | AA110: 70 | AB110: 13 | AC110: 13 | AD110: 0 | AE110: 0 | AG110: 3 | AH110: 0 | AI110: 16
A111: 112 | B111: JANETH CHAVEZ CASTILLEJO | C111: F | D111: 11 | E111: 2633 | F111: 21 | G111: 2654 | H111: 28 | I111: 2682 | J111: 20 | K111: 2702 | L111: 19 | M111: 2721 | N111: 16 | O111: 2737 | P111: 13 | Q111: 2750 | R111: 13 | S111: 2762 | T111: 12 | U111: 2773 | V111: 11 | W111: 2783 | X111: 10 | Y111: 2796 | Z111: 13 | AA111: 2811 | AB111: 15 | AC111: 15 | AD111: 0 | AE111: 0 | AG111: 3 | AH111: 0 | AI111: 18
A112: 113 | B112: DARIO OCTAVIO VEGA JULCA | C112: F | D112: 12 | E112: 1044 | F112: 9 | G112: 1053 | H112: 9 | I112: 1062 | J112: 7 | K112: 1069 | L112: 6 | M112: 1075 | N112: 4 | O112: 1079 | P112: 4 | Q112: 1083 | R112: 4 | S112: 1086 | T112: 3 | U112: 1090 | V112: 4 | W112: 1093 | X112: 3 | Y112: 1107 | Z112: 14 | AA112: 1106 | AB112: -1 | AC112: 5 | AD112: 0 | AE112: 0 | AG112: 3 | AH112: 20 | AI112: 28
A113: 114 | B113: RODRIGO PODESTA ROSAS | C113: F | D113: 14 | E113: 717 | F113: 40 | G113: 757 | H113: 33 | I113: 790 | J113: 40 | K113: 830 | L113: 34 | M113: 864 | N113: 38 | O113: 902 | P113: 34 | Q113: 936 | R113: 34 | S113: 969 | T113: 33 | U113: 1001 | V113: 32 | W113: 1033 | X113: 32 | Y113: 1069 | Z113: 36 | AA113: 1134 | AB113: 65 | AC113: 130 | AD113: 0 | AE113: 0 | AG113: 3 | AH113: 20 | AI113: 153
A114: 115 | B114: DARIO SAENZ MURPHY | C114: F | D114: 15 | E114: 432 | F114: 11 | G114: 443 | H114: 12 | I114: 455 | J114: 8 | K114: 463 | L114: 11 | M114: 474 | N114: 13 | O114: 487 | P114: 10 | Q114: 497 | R114: 10 | S114: 504 | T114: 7 | U114: 515 | V114: 11 | W114: 525 | X114: 10 | Y114: 535 | Z114: 10 | AA114: 548 | AB114: 13 | AC114: 13 | AD114: 0 | AE114: 0 | AG114: 3 | AH114: 0 | AI114: 16
A115: 116 | B115: JACINTO MORENO BAUTISTA | C115: G | D115: 1 | E115: 352 | F115: 23 | G115: 375 | H115: 21 | I115: 396 | J115: 17 | K115: 413 | L115: 18 | M115: 431 | N115: 17 | O115: 448 | P115: 16 | Q115: 464 | R115: 16 | S115: 479 | T115: 15 | U115: 493 | V115: 14 | W115: 507 | X115: 14 | Y115: 523 | Z115: 16 | AA115: 540 | AB115: 17 | AC115: 17 | AD115: 0 | AE115: 0 | AG115: 3 | AH115: 0 | AI115: 20
A116: 117 | B116: SANTOS BAUTISTA CAPCHA | C116: G | D116: 2 | E116: 3422 | F116: 27 | G116: 3449 | H116: 26 | I116: 3475 | J116: 23 | K116: 3498 | L116: 22 | M116: 3520 | N116: 18 | O116: 3538 | P116: 16 | Q116: 3554 | R116: 16 | S116: 3568 | T116: 14 | U116: 3583 | V116: 15 | W116: 3599 | X116: 16 | Y116: 3615 | Z116: 16 | AA116: 3635 | AB116: 20 | AC116: 20 | AD116: 19 | AE116: 0 | AG116: 3 | AH116: 0 | AI116: 42
... A129: 130 | B129: CRISOSTOMO ALBORNOZ TICLIO | C129: G | D129: 16 | E129: 4603 | F129: 13 | G129: 4616 | H129: 16 | I129: 4632 | J129: 13 | K129: 4645 | L129: 9 | M129: 4654 | N129: 13 | O129: 4667 | P129: 14 | Q129: 4681 | R129: 14 | S129: 4688 | T129: 7 | U129: 4696 | V129: 8 | W129: 4704 | X129: 8 | Y129: 4713 | Z129: 9 | AA129: 4721 | AB129: 8 | AC129: 8 | AD129: 0 | AE129: 0 | AG129: 3 | AH129: 20 | AI129: 31
...
