Workbook

Sheet Cobranza
A1: n | B1: Nombres | C1: MZ | D1: LT | E1: TIPO CONVENIO | F1: MAYOR 65 | G1: NO COBRO | H1: Costo x m3 | I1: Marcación anterior | J1: Marcación actual | K1: m3 | L1: Total mes actual | M1: MES ANTERIOR | N1: Corte y reconexión | O1: Convenio | P1: Mant. | Q1: Reunion/Faena | R1: techado | S1: Devolucion | T1: blancos | U1: Ajuste | V1: Total | W1: Yape rep | X1: Monto Efectivo | Y1: Estado | Z1: Fecha | AA1: Medio | AB1: Comentario | AC1: Estado del servicio | AD1: corte por consumo | AE1: Corte por faena | AF1: Efectivo | AG1: Yape | AH1: Llave1 | AI1: LLAVE (Mz, Lt)
A2: 1 | B2: MARCELINA OBREGON DE AVILA | C2: A | D2: 1 | H2: 1 | I2: 2 | J2: 11 | K2: 9 | L2: 9 | N2: 0 | O2: 100 | P2: 3 | V2: =SUM(L2:U2) -> 112 | W2: =IFERROR(__xludf.DUMMYFUNCTION("IFERROR( SUM( FILTER( Reporte!$E:$E, REGEXMATCH(Reporte!$A:$A, ""(?i)(TE PAGÓ|PAGASTE)""), Reporte!$H:$H & """" = AH2 & """" ) ), 0 )"),112) -> 112 | X2: =IFERROR(__xludf.DUMMYFUNCTION("IFERROR( SUM( FILTER( Efectivo!$C:$C, Efectivo!$D:$D & """" = AH2 & """" ) ), 0 )"),0) -> 0 | Y2: c | AA2: y | AD2: =IF(AND(L2>0, M2>=8, NOT(OR(Y2="C", Y2="c"))), "CORTE", "") | AE2: =IF( OR( AND(#REF!>0, OR(Y2="C", Y2="c"), U2<0), AND(#REF!>0, Y2="") ), "CORTE", "" ) -> #REF! | AF2: =IF(AND(LEN(Y2)>0,LEN(AA2)=0),V2,0) -> 0 | AG2: =IF(AND(LEN(Y2)>0,TRIM(AA2)="Y"),V2,0) -> 112 | AH2: =TRIM(UPPER(C2)) -> A | AI2: =TRIM(UPPER(C2)) & "-" & TRIM(UPPER(D2)) -> A-1
A3: 2 | B3: ROSA AURORA ROCA VIDAL | C3: A | D3: 2 | H3: 1 | I3: 2678 | J3: 2703 | K3: 25 | L3: 25 | M3: 33 | N3: 0 | O3: 0 | P3: 3 | V3: =SUM(L3:Q3) -> 61 | W3: =IFERROR(__xludf.DUMMYFUNCTION("IFERROR( SUM( FILTER( Reporte!$E:$E, REGEXMATCH(Reporte!$A:$A, ""(?i)(TE PAGÓ|PAGASTE)""), Reporte!$H:$H & """" = AH3 & """" ) ), 0 )"),61) -> 61 | X3: =IFERROR(__xludf.DUMMYFUNCTION("IFERROR( SUM( FILTER( Efectivo!$C:$C, Efectivo!$D:$D & """" = AH3 & """" ) ), 0 )"),0) -> 0 | Y3: c | AA3: y | AD3: =IF(AND(L3>0, M3>=8, NOT(OR(Y3="C", Y3="c"))), "CORTE", "") | AE3: =IF( OR( AND(#REF!>0, OR(Y3="C", Y3="c"), U3<0), AND(#REF!>0, Y3="") ), "CORTE", "" ) -> #REF! | AF3: =IF(AND(LEN(Y3)>0,LEN(AA3)=0),V3,0) -> 0 | AG3: =IF(AND(LEN(Y3)>0,TRIM(AA3)="Y"),V3,0) -> 61 | AH3: =TRIM(UPPER(C3)) -> A | AI3: =TRIM(UPPER(C3)) & "-" & TRIM(UPPER(D3)) -> A-2
A4: 3 | B4: LINDA PAJUELO COCHACHIN | C4: A | D4: 3 | H4: 1 | I4: 22 | J4: 22 | K4: 5 | L4: 5 | N4: 0 | P4: 3 | V4: =SUM(L4:Q4) -> 8 | W4: =IFERROR(__xludf.DUMMYFUNCTION("IFERROR( SUM( FILTER( Reporte!$E:$E, REGEXMATCH(Reporte!$A:$A, ""(?i)(TE PAGÓ|PAGASTE)""), Reporte!$H:$H & """" = AH4 & """" ) ), 0 )"),8) -> 8 | X4: =IFERROR(__xludf.DUMMYFUNCTION("IFERROR( SUM( FILTER( Efectivo!$C:$C, Efectivo!$D:$D & """" = AH4 & """" ) ), 0 )"),0) -> 0 | Y4: c | AA4: y | AD4: =IF(AND(L4>0, M4>=8, NOT(OR(Y4="C", Y4="c"))), "CORTE", "") | AE4: =IF( OR( AND(#REF!>0, OR(Y4="C", Y4="c"), U4<0), AND(#REF!>0, Y4="") ), "CORTE", "" ) -> #REF! | AF4: =IF(AND(LEN(Y4)>0,LEN(AA4)=0),V4,0) -> 0 | AG4: =IF(AND(LEN(Y4)>0,TRIM(AA4)="Y"),V4,0) -> 8 | AH4: =TRIM(UPPER(C4)) -> A | AI4: =TRIM(UPPER(C4)) & "-" & TRIM(UPPER(D4)) -> A-3
A5: 4 | B5: YOLANDA ESPINOZA JAIMES | C5: A | D5: 4 | H5: 1 | I5: 0 | J5: 2 | K5: 2 | L5: 5 | N5: 0 | O5: 0 | P5: 3 | V5: =SUM(L5:Q5) -> 8 | W5: =IFERROR(__xludf.DUMMYFUNCTION("IFERROR( SUM( FILTER( Reporte!$E:$E, REGEXMATCH(Reporte!$A:$A, ""(?i)(TE PAGÓ|PAGASTE)""), Reporte!$H:$H & """" = AH5 & """" ) ), 0 )"),0) -> 0 | X5: =IFERROR(__xludf.DUMMYFUNCTION("IFERROR( SUM( FILTER( Efectivo!$C:$C, Efectivo!$D:$D & """" = AH5 & """" ) ), 0 )"),0) -> 0 | AD5: =IF(AND(L5>0, M5>=8, NOT(OR(Y5="C", Y5="c"))), "CORTE", "") | AE5: =IF( OR( AND(#REF!>0, OR(Y5="C", Y5="c"), U5<0), AND(#REF!>0, Y5="") ), "CORTE", "" ) -> #REF! | AF5: =IF(AND(LEN(Y5)>0,LEN(AA5)=0),V5,0) -> 0 | AG5: =IF(AND(LEN(Y5)>0,TRIM(AA5)="Y"),V5,0) -> 0 | AH5: =TRIM(UPPER(C5)) -> A | AI5: =TRIM(UPPER(C5)) & "-" & TRIM(UPPER(D5)) -> A-4
A6: 5 | B6: JULIA AGAMA CUZCO | C6: A | D6: 5 | H6: 1 | I6: 3441 | J6: 16 | K6: 16 | L6: 16 | N6: 0 | O6: 25 | P6: 3 | V6: =SUM(L6:Q6) -> 44 | W6: =IFERROR(__xludf.DUMMYFUNCTION("IFERROR( SUM( FILTER( Reporte!$E:$E, REGEXMATCH(Reporte!$A:$A, ""(?i)(TE PAGÓ|PAGASTE)""), Reporte!$H:$H & """" = AH6 & """" ) ), 0 )"),0) -> 0 | X6: =IFERROR(__xludf.DUMMYFUNCTION("IFERROR( SUM( FILTER( Efectivo!$C:$C, Efectivo!$D:$D & """" = AH6 & """" ) ), 0 )"),44) -> 44 | Y6: c | AD6: =IF(AND(L6>0, M6>=8, NOT(OR(Y6="C", Y6="c"))), "CORTE", "") | AE6: =IF( OR( AND(#REF!>0, OR(Y6="C", Y6="c"), U6<0), AND(#REF!>0, Y6="") ), "CORTE", "" ) -> #REF! | AF6: =IF(AND(LEN(Y6)>0,LEN(AA6)=0),V6,0) -> 44 | AG6: =IF(AND(LEN(Y6)>0,TRIM(AA6)="Y"),V6,0) -> 0 | AH6: =TRIM(UPPER(C6)) -> A | AI6: =TRIM(UPPER(C6)) & "-" & TRIM(UPPER(D6)) -> A-5
A7: 6 | B7: ESTEBAN REYES SANCHEZ | C7: A | D7: 6 | H7: 1 | I7: 2 | J7: 26 | K7: 24 | L7: 24 | N7: 0 | O7: 25 | P7: 3 | V7: =SUM(L7:Q7) -> 52 | W7: =IFERROR(__xludf.DUMMYFUNCTION("IFERROR( SUM( FILTER( Reporte!$E:$E, REGEXMATCH(Reporte!$A:$A, ""(?i)(TE PAGÓ|PAGASTE)""), Reporte!$H:$H & """" = AH7 & """" ) ), 0 )"),52) -> 52 | X7: =IFERROR(__xludf.DUMMYFUNCTION("IFERROR( SUM( FILTER( Efectivo!$C:$C, Efectivo!$D:$D & """" = AH7 & """" ) ), 0 )"),0) -> 0 | Y7: c | AA7: y | AD7: =IF(AND(L7>0, M7>=8, NOT(OR(Y7="C", Y7="c"))), "CORTE", "") | AE7: =IF( OR( AND(#REF!>0, OR(Y7="C", Y7="c"), U7<0), AND(#REF!>0, Y7="") ), "CORTE", "" ) -> #REF! | AF7: =IF(AND(LEN(Y7)>0,LEN(AA7)=0),V7,0) -> 0 | AG7: =IF(AND(LEN(Y7)>0,TRIM(AA7)="Y"),V7,0) -> 52 | AH7: =TRIM(UPPER(C7)) -> A | AI7: =TRIM(UPPER(C7)) & "-" & TRIM(UPPER(D7)) -> A-6
A8: 7 | B8: JUAN CARLOS MELGAREJO BEDON | C8: A | D8: 7 | H8: 1 | I8: 1752 | J8: 1766 | K8: 14 | L8: 14 | N8: 0 | P8: 3 | V8: =SUM(L8:U8) -> 17 | W8: =IFERROR(__xludf.DUMMYFUNCTION("IFERROR( SUM( FILTER( Reporte!$E:$E, REGEXMATCH(Reporte!$A:$A, ""(?i)(TE PAGÓ|PAGASTE)""), Reporte!$H:$H & """" = AH8 & """" ) ), 0 )"),17) -> 17 | X8: =IFERROR(__xludf.DUMMYFUNCTION("IFERROR( SUM( FILTER( Efectivo!$C:$C, Efectivo!$D:$D & """" = AH8 & """" ) ), 0 )"),0) -> 0 | Y8: c | AA8: y | AD8: =IF(AND(L8>0, M8>=8, NOT(OR(Y8="C", Y8="c"))), "CORTE", "") | AE8: =IF( OR( AND(#REF!>0, OR(Y8="C", Y8="c"), U8<0), AND(#REF!>0, Y8="") ), "CORTE", "" ) -> #REF! | AF8: =IF(AND(LEN(Y8)>0,LEN(AA8)=0),V8,0) -> 0 | AG8: =IF(AND(LEN(Y8)>0,TRIM(AA8)="Y"),V8,0) -> 17 | AH8: =TRIM(UPPER(C8)) -> A | AI8: =TRIM(UPPER(C8)) & "-" & TRIM(UPPER(D8)) -> A-7
A9: 8 | B9: VICTOR MELGAREJO CORCINO | C9: A | D9: 8 | H9: 1 | I9: 6395 | J9: 26 | K9: 26 | L9: 26 | M9: 27 | N9: 20 | O9: 25 | P9: 3 | V9: =SUM(L9:U9) -> 101 | W9: =IFERROR(__xludf.DUMMYFUNCTION("IFERROR( SUM( FILTER( Reporte!$E:$E, REGEXMATCH(Reporte!$A:$A, ""(?i)(TE PAGÓ|PAGASTE)""), Reporte!$H:$H & """" = AH9 & """" ) ), 0 )"),101) -> 101 | X9: =IFERROR(__xludf.DUMMYFUNCTION("IFERROR( SUM( FILTER( Efectivo!$C:$C, Efectivo!$D:$D & """" = AH9 & """" ) ), 0 )"),0) -> 0 | Y9: c | AA9: y | AD9: =IF(AND(L9>0, M9>=8, NOT(OR(Y9="C", Y9="c"))), "CORTE", "") | AE9: =IF( OR( AND(#REF!>0, OR(Y9="C", Y9="c"), U9<0), AND(#REF!>0, Y9="") ), "CORTE", "" ) -> #REF! | AF9: =IF(AND(LEN(Y9)>0,LEN(AA9)=0),V9,0) -> 0 | AG9: =IF(AND(LEN(Y9)>0,TRIM(AA9)="Y"),V9,0) -> 101 | AH9: =TRIM(UPPER(C9)) -> A | AI9: =TRIM(UPPER(C9)) & "-" & TRIM(UPPER(D9)) -> A-8
A10: 9 | B10: JHONI MELGAREJO BEDON | C10: A | D10: 8A | H10: 1 | I10: 182 | J10: 186 | K10: 4 | L10: 5 | N10: 0 | P10: 3 | V10: =SUM(L10:Q10) -> 8 | W10: =IFERROR(__xludf.DUMMYFUNCTION("IFERROR( SUM( FILTER( Reporte!$E:$E, REGEXMATCH(Reporte!$A:$A, ""(?i)(TE PAGÓ|PAGASTE)""), Reporte!$H:$H & """" = AH10 & """" ) ), 0 )"),8) -> 8 | X10: =IFERROR(__xludf.DUMMYFUNCTION("IFERROR( SUM( FILTER( Efectivo!$C:$C, Efectivo!$D:$D & """" = AH10 & """" ) ), 0 )"),0) -> 0 | Y10: c | AA10: y | AD10: =IF(AND(L10>0, M10>=8, NOT(OR(Y10="C", Y10="c"))), "CORTE", "") | AE10: =IF( OR( AND(#REF!>0, OR(Y10="C", Y10="c"), U10<0), AND(#REF!>0, Y10="") ), "CORTE", "" ) -> #REF! | AF10: =IF(AND(LEN(Y10)>0,LEN(AA10)=0),V10,0) -> 0 | AG10: =IF(AND(LEN(Y10)>0,TRIM(AA10)="Y"),V10,0) -> 8 | AH10: =TRIM(UPPER(C10)) -> A | AI10: =TRIM(UPPER(C10)) & "-" & TRIM(UPPER(D10)) -> A-8A
A11: 10 | B11: ALEJANDRO MELGAREJO ESPINOZA | C11: A | D11: 9 | H11: 1 | I11: 2198 | J11: 2240 | K11: 42 | L11: 42 | N11: 0 | P11: 3 | V11: =SUM(L11:Q11) -> 45 | W11: =IFERROR(__xludf.DUMMYFUNCTION("IFERROR( SUM( FILTER( Reporte!$E:$E, REGEXMATCH(Reporte!$A:$A, ""(?i)(TE PAGÓ|PAGASTE)""), Reporte!$H:$H & """" = AH11 & """" ) ), 0 )"),45) -> 45 | X11: =IFERROR(__xludf.DUMMYFUNCTION("IFERROR( SUM( FILTER( Efectivo!$C:$C, Efectivo!$D:$D & """" = AH11 & """" ) ), 0 )"),0) -> 0 | Y11: c | AA11: y | AD11: =IF(AND(L11>0, M11>=8, NOT(OR(Y11="C", Y11="c"))), "CORTE", "") | AE11: =IF( OR( AND(#REF!>0, OR(Y11="C", Y11="c"), U11<0), AND(#REF!>0, Y11="") ), "CORTE", "" ) -> #REF! | AF11: =IF(AND(LEN(Y11)>0,LEN(AA11)=0),V11,0) -> 0 | AG11: =IF(AND(LEN(Y11)>0,TRIM(AA11)="Y"),V11,0) -> 45 | AH11: =TRIM(UPPER(C11)) -> A | AI11: =TRIM(UPPER(C11)) & "-" & TRIM(UPPER(D11)) -> A-9
A12: 11 | B12: ISABEL PUNTILLO VEGA | C12: A | D12: 10 | H12: 1 | I12: 672 | J12: 679 | K12: 7 | L12: 7 | N12: 0 | P12: 3 | V12: =SUM(L12:Q12) -> 10 | W12: =IFERROR(__xludf.DUMMYFUNCTION("IFERROR( SUM( FILTER( Reporte!$E:$E, REGEXMATCH(Reporte!$A:$A, ""(?i)(TE PAGÓ|PAGASTE)""), Reporte!$H:$H & """" = AH12 & """" ) ), 0 )"),0) -> 0 | X12: =IFERROR(__xludf.DUMMYFUNCTION("IFERROR( SUM( FILTER( Efectivo!$C:$C, Efectivo!$D:$D & """" = AH12 & """" ) ), 0 )"),0) -> 0 | AD12: =IF(AND(L12>0, M12>=8, NOT(OR(Y12="C", Y12="c"))), "CORTE", "") | AE12: =IF( OR( AND(#REF!>0, OR(Y12="C", Y12="c"), U12<0), AND(#REF!>0, Y12="") ), "CORTE", "" ) -> #REF! | AF12: =IF(AND(LEN(Y12)>0,LEN(AA12)=0),V12,0) -> 0 | AG12: =IF(AND(LEN(Y12)>0,TRIM(AA12)="Y"),V12,0) -> 0 | AH12: =TRIM(UPPER(C12)) -> A | AI12: =TRIM(UPPER(C12)) & "-" & TRIM(UPPER(D12)) -> A-10
A13: 12 | B13: FELIX POZO CASTRO | C13: A | D13: 11 | H13: 1 | I13: 361 | J13: 363 | K13: 2 | L13: 5 | M13: 8 | N13: 0 | P13: 3 | V13: =SUM(L13:U13) -> 16 | W13: =IFERROR(__xludf.DUMMYFUNCTION("IFERROR( SUM( FILTER( Reporte!$E:$E, REGEXMATCH(Reporte!$A:$A, ""(?i)(TE PAGÓ|PAGASTE)""), Reporte!$H:$H & """" = AH13 & """" ) ), 0 )"),0) -> 0 | X13: =IFERROR(__xludf.DUMMYFUNCTION("IFERROR( SUM( FILTER( Efectivo!$C:$C, Efectivo!$D:$D & """" = AH13 & """" ) ), 0 )"),0) -> 0 | AD13: =IF(AND(L13>0, M13>=8, NOT(OR(Y13="C", Y13="c"))), "CORTE", "") -> CORTE | AE13: =IF( OR( AND(#REF!>0, OR(Y13="C", Y13="c"), U13<0), AND(#REF!>0, Y13="") ), "CORTE", "" ) -> #REF! | AF13: =IF(AND(LEN(Y13)>0,LEN(AA13)=0),V13,0) -> 0 | AG13: =IF(AND(LEN(Y13)>0,TRIM(AA13)="Y"),V13,0) -> 0 | AH13: =TRIM(UPPER(C13)) -> A | AI13: =TRIM(UPPER(C13)) & "-" & TRIM(UPPER(D13)) -> A-11
A14: 13 | B14: BACILIO UTRILLA FRANCISCO | C14: B | D14: 1 | H14: 1 | I14: 1 | J14: 13 | K14: 12 | L14: 12 | N14: 0 | P14: 3 | V14: =SUM(L14:Q14) -> 15 | W14: =IFERROR(__xludf.DUMMYFUNCTION("IFERROR( SUM( FILTER( Reporte!$E:$E, REGEXMATCH(Reporte!$A:$A, ""(?i)(TE PAGÓ|PAGASTE)""), Reporte!$H:$H & """" = AH14 & """" ) ), 0 )"),0) -> 0 | X14: =IFERROR(__xludf.DUMMYFUNCTION("IFERROR( SUM( FILTER( Efectivo!$C:$C, Efectivo!$D:$D & """" = AH14 & """" ) ), 0 )"),15) -> 15 | Y14: c | AD14: =IF(AND(L14>0, M14>=8, NOT(OR(Y14="C", Y14="c"))), "CORTE", "") | AE14: =IF( OR( AND(#REF!>0, OR(Y14="C", Y14="c"), U14<0), AND(#REF!>0, Y14="") ), "CORTE", "" ) -> #REF! | AF14: =IF(AND(LEN(Y14)>0,LEN(AA14)=0),V14,0) -> 15 | AG14: =IF(AND(LEN(Y14)>0,TRIM(AA14)="Y"),V14,0) -> 0 | AH14: =TRIM(UPPER(C14)) -> B | AI14: =TRIM(UPPER(C14)) & "-" & TRIM(UPPER(D14)) -> B-1
A15: 14 | B15: ESTEBAN REYNALDO ROSALES | C15: B | D15: 2 | H15: 1 | I15: 2294 | J15: 16 | K15: 16 | L15: 16 | N15: 0 | O15: 25 | P15: 3 | V15: =SUM(L15:Q15) -> 44 | W15: =IFERROR(__xludf.DUMMYFUNCTION("IFERROR( SUM( FILTER( Reporte!$E:$E, REGEXMATCH(Reporte!$A:$A, ""(?i)(TE PAGÓ|PAGASTE)""), Reporte!$H:$H & """" = AH15 & """" ) ), 0 )"),0) -> 0 | X15: =IFERROR(__xludf.DUMMYFUNCTION("IFERROR( SUM( FILTER( Efectivo!$C:$C, Efectivo!$D:$D & """" = AH15 & """" ) ), 0 )"),44) -> 44 | Y15: c | AD15: =IF(AND(L15>0, M15>=8, NOT(OR(Y15="C", Y15="c"))), "CORTE", "") | AE15: =IF( OR( AND(#REF!>0, OR(Y15="C", Y15="c"), U15<0), AND(#REF!>0, Y15="") ), "CORTE", "" ) -> #REF! | AF15: =IF(AND(LEN(Y15)>0,LEN(AA15)=0),V15,0) -> 44 | AG15: =IF(AND(LEN(Y15)>0,TRIM(AA15)="Y"),V15,0) -> 0 | AH15: =TRIM(UPPER(C15)) -> B | AI15: =TRIM(UPPER(C15)) & "-" & TRIM(UPPER(D15)) -> B-2
A16: 15 | B16: EDUARDO REYNALDO ROSALES | C16: B | D16: 3 | H16: 1 | I16: 822 | J16: 837 | K16: 15 | L16: 15 | N16: 0 | P16: 3 | V16: =SUM(L16:Q16) -> 18 | W16: =IFERROR(__xludf.DUMMYFUNCTION("IFERROR( SUM( FILTER( Reporte!$E:$E, REGEXMATCH(Reporte!$A:$A, ""(?i)(TE PAGÓ|PAGASTE)""), Reporte!$H:$H & """" = AH16 & """" ) ), 0 )"),0) -> 0 | X16: =IFERROR(__xludf.DUMMYFUNCTION("IFERROR( SUM( FILTER( Efectivo!$C:$C, Efectivo!$D:$D & """" = AH16 & """" ) ), 0 )"),18) -> 18 | Y16: c | AD16: =IF(AND(L16>0, M16>=8, NOT(OR(Y16="C", Y16="c"))), "CORTE", "") | AE16: =IF( OR( AND(#REF!>0, OR(Y16="C", Y16="c"), U16<0), AND(#REF!>0, Y16="") ), "CORTE", "" ) -> #REF! | AF16: =IF(AND(LEN(Y16)>0,LEN(AA16)=0),V16,0) -> 18 | AG16: =IF(AND(LEN(Y16)>0,TRIM(AA16)="Y"),V16,0) -> 0 | AH16: =TRIM(UPPER(C16)) -> B | AI16: =TRIM(UPPER(C16)) & "-" & TRIM(UPPER(D16)) -> B-3
A17: 16 | B17: MELINA J. JUAREZ TOLEDO DE MORENO | C17: B | D17: 4 | H17: 1 | I17: 626 | J17: 641 | K17: 15 | L17: 15 | N17: 0 | P17: 3 | V17: =SUM(L17:Q17) -> 18 | W17: =IFERROR(__xludf.DUMMYFUNCTION("IFERROR( SUM( FILTER( Reporte!$E:$E, REGEXMATCH(Reporte!$A:$A, ""(?i)(TE PAGÓ|PAGASTE)""), Reporte!$H:$H & """" = AH17 & """" ) ), 0 )"),0) -> 0 | X17: =IFERROR(__xludf.DUMMYFUNCTION("IFERROR( SUM( FILTER( Efectivo!$C:$C, Efectivo!$D:$D & """" = AH17 & """" ) ), 0 )"),0) -> 0 | AD17: =IF(AND(L17>0, M17>=8, NOT(OR(Y17="C", Y17="c"))), "CORTE", "") | AE17: =IF( OR( AND(#REF!>0, OR(Y17="C", Y17="c"), U17<0), AND(#REF!>0, Y17="") ), "CORTE", "" ) -> #REF! | AF17: =IF(AND(LEN(Y17)>0,LEN(AA17)=0),V17,0) -> 0 | AG17: =IF(AND(LEN(Y17)>0,TRIM(AA17)="Y"),V17,0) -> 0 | AH17: =TRIM(UPPER(C17)) -> B | AI17: =TRIM(UPPER(C17)) & "-" & TRIM(UPPER(D17)) -> B-4
A18: 17 | B18: POMPEYO CELESTINO LLIUYA | C18: B | D18: 5 | H18: 1 | I18: 23 | J18: 59 | K18: 36 | L18: 36 | N18: 0 | O18: 25 | P18: 3 | V18: =SUM(L18:Q18) -> 64 | W18: =IFERROR(__xludf.DUMMYFUNCTION("IFERROR( SUM( FILTER( Reporte!$E:$E, REGEXMATCH(Reporte!$A:$A, ""(?i)(TE PAGÓ|PAGASTE)""), Reporte!$H:$H & """" = AH18 & """" ) ), 0 )"),0) -> 0 | X18: =IFERROR(__xludf.DUMMYFUNCTION("IFERROR( SUM( FILTER( Efectivo!$C:$C, Efectivo!$D:$D & """" = AH18 & """" ) ), 0 )"),0) -> 0 | AD18: =IF(AND(L18>0, M18>=8, NOT(OR(Y18="C", Y18="c"))), "CORTE", "") | AE18: =IF( OR( AND(#REF!>0, OR(Y18="C", Y18="c"), U18<0), AND(#REF!>0, Y18="") ), "CORTE", "" ) -> #REF! | AF18: =IF(AND(LEN(Y18)>0,LEN(AA18)=0),V18,0) -> 0 | AG18: =IF(AND(LEN(Y18)>0,TRIM(AA18)="Y"),V18,0) -> 0 | AH18: =TRIM(UPPER(C18)) -> B | AI18: =TRIM(UPPER(C18)) & "-" & TRIM(UPPER(D18)) -> B-5
A19: 18 | B19: ROSA VICTORIA MILLA MORALES | C19: B | D19: 6 | H19: 1 | I19: 11 | J19: 32 | K19: 21 | L19: 21 | N19: 0 | O19: 25 | P19: 3 | V19: =SUM(L19:U19) -> 49 | W19: =IFERROR(__xludf.DUMMYFUNCTION("IFERROR( SUM( FILTER( Reporte!$E:$E, REGEXMATCH(Reporte!$A:$A, ""(?i)(TE PAGÓ|PAGASTE)""), Reporte!$H:$H & """" = AH19 & """" ) ), 0 )"),49) -> 49 | X19: =IFERROR(__xludf.DUMMYFUNCTION("IFERROR( SUM( FILTER( Efectivo!$C:$C, Efectivo!$D:$D & """" = AH19 & """" ) ), 0 )"),0) -> 0 | Y19: c | AA19: y | AD19: =IF(AND(L19>0, M19>=8, NOT(OR(Y19="C", Y19="c"))), "CORTE", "") | AE19: =IF( OR( AND(#REF!>0, OR(Y19="C", Y19="c"), U19<0), AND(#REF!>0, Y19="") ), "CORTE", "" ) -> #REF! | AF19: =IF(AND(LEN(Y19)>0,LEN(AA19)=0),V19,0) -> 0 | AG19: =IF(AND(LEN(Y19)>0,TRIM(AA19)="Y"),V19,0) -> 49 | AH19: =TRIM(UPPER(C19)) -> B | AI19: =TRIM(UPPER(C19)) & "-" & TRIM(UPPER(D19)) -> B-6
A20: 19 | B20: LIRIA PARIAMACHI DE PAZ | C20: B | D20: 7 | H20: 1 | I20: 2713 | J20: 99978 | K20: 14 | L20: 14 | N20: 0 | O20: 25 | P20: 3 | Q20: 30 | V20: =SUM(L20:Q20) -> 72 | W20: =IFERROR(__xludf.DUMMYFUNCTION("IFERROR( SUM( FILTER( Reporte!$E:$E, REGEXMATCH(Reporte!$A:$A, ""(?i)(TE PAGÓ|PAGASTE)""), Reporte!$H:$H & """" = AH20 & """" ) ), 0 )"),0) -> 0 | X20: =IFERROR(__xludf.DUMMYFUNCTION("IFERROR( SUM( FILTER( Efectivo!$C:$C, Efectivo!$D:$D & """" = AH20 & """" ) ), 0 )"),0) -> 0 | AD20: =IF(AND(L20>0, M20>=8, NOT(OR(Y20="C", Y20="c"))), "CORTE", "") | AE20: =IF( OR( AND(#REF!>0, OR(Y20="C", Y20="c"), U20<0), AND(#REF!>0, Y20="") ), "CORTE", "" ) -> #REF! | AF20: =IF(AND(LEN(Y20)>0,LEN(AA20)=0),V20,0) -> 0 | AG20: =IF(AND(LEN(Y20)>0,TRIM(AA20)="Y"),V20,0) -> 0 | AH20: =TRIM(UPPER(C20)) -> B | AI20: =TRIM(UPPER(C20)) & "-" & TRIM(UPPER(D20)) -> B-7
A21: 20 | B21: ROSALINA OLIMPIA CIRIACO SOTELO | C21: B | D21: 8 | H21: 1 | I21: 7 | J21: 21 | K21: 14 | L21: 14 | M21: 15 | N21: 0 | O21: 25 | P21: 3 | V21: =SUM(L21:Q21) -> 57 | W21: =IFERROR(__xludf.DUMMYFUNCTION("IFERROR( SUM( FILTER( Reporte!$E:$E, REGEXMATCH(Reporte!$A:$A, ""(?i)(TE PAGÓ|PAGASTE)""), Reporte!$H:$H & """" = AH21 & """" ) ), 0 )"),57) -> 57 | X21: =IFERROR(__xludf.DUMMYFUNCTION("IFERROR( SUM( FILTER( Efectivo!$C:$C, Efectivo!$D:$D & """" = AH21 & """" ) ), 0 )"),0) -> 0 | Y21: c | AA21: y | AD21: =IF(AND(L21>0, M21>=8, NOT(OR(Y21="C", Y21="c"))), "CORTE", "") | AE21: =IF( OR( AND(#REF!>0, OR(Y21="C", Y21="c"), U21<0), AND(#REF!>0, Y21="") ), "CORTE", "" ) -> #REF! | AF21: =IF(AND(LEN(Y21)>0,LEN(AA21)=0),V21,0) -> 0 | AG21: =IF(AND(LEN(Y21)>0,TRIM(AA21)="Y"),V21,0) -> 57 | AH21: =TRIM(UPPER(C21)) -> B | AI21: =TRIM(UPPER(C21)) & "-" & TRIM(UPPER(D21)) -> B-8
A22: 21 | B22: ALEJANDRO RAPRAY VELASQUEZ | C22: B | D22: 9 | F22: 1 | H22: 1 | I22: 65 | J22: 72 | K22: 7 | L22: 7 | N22: 0 | P22: 3 | V22: =SUM(L22:Q22) -> 10 | W22: =IFERROR(__xludf.DUMMYFUNCTION("IFERROR( SUM( FILTER( Reporte!$E:$E, REGEXMATCH(Reporte!$A:$A, ""(?i)(TE PAGÓ|PAGASTE)""), Reporte!$H:$H & """" = AH22 & """" ) ), 0 )"),0) -> 0 | X22: =IFERROR(__xludf.DUMMYFUNCTION("IFERROR( SUM( FILTER( Efectivo!$C:$C, Efectivo!$D:$D & """" = AH22 & """" ) ), 0 )"),0) -> 0 | AD22: =IF(AND(L22>0, M22>=8, NOT(OR(Y22="C", Y22="c"))), "CORTE", "") | AE22: =IF( OR( AND(#REF!>0, OR(Y22="C", Y22="c"), U22<0), AND(#REF!>0, Y22="") ), "CORTE", "" ) -> #REF! | AF22: =IF(AND(LEN(Y22)>0,LEN(AA22)=0),V22,0) -> 0 | AG22: =IF(AND(LEN(Y22)>0,TRIM(AA22)="Y"),V22,0) -> 0 | AH22: =TRIM(UPPER(C22)) -> B | AI22: =TRIM(UPPER(C22)) & "-" & TRIM(UPPER(D22)) -> B-9
A23: 22 | B23: ELVIRA PASCUALA MINAYA TAHUA | C23: B | D23: 11 | H23: 1 | I23: 10 | J23: 26 | K23: 16 | L23: 16 | N23: 0 | O23: 25 | P23: 3 | V23: =SUM(L23:Q23) -> 44 | W23: =IFERROR(__xludf.DUMMYFUNCTION("IFERROR( SUM( FILTER( Reporte!$E:$E, REGEXMATCH(Reporte!$A:$A, ""(?i)(TE PAGÓ|PAGASTE)""), Reporte!$H:$H & """" = AH23 & """" ) ), 0 )"),0) -> 0 | X23: =IFERROR(__xludf.DUMMYFUNCTION("IFERROR( SUM( FILTER( Efectivo!$C:$C, Efectivo!$D:$D & """" = AH23 & """" ) ), 0 )"),0) -> 0 | AD23: =IF(AND(L23>0, M23>=8, NOT(OR(Y23="C", Y23="c"))), "CORTE", "") | AE23: =IF( OR( AND(#REF!>0, OR(Y23="C", Y23="c"), U23<0), AND(#REF!>0, Y23="") ), "CORTE", "" ) -> #REF! | AF23: =IF(AND(LEN(Y23)>0,LEN(AA23)=0),V23,0) -> 0 | AG23: =IF(AND(LEN(Y23)>0,TRIM(AA23)="Y"),V23,0) -> 0 | AH23: =TRIM(UPPER(C23)) -> B | AI23: =TRIM(UPPER(C23)) & "-" & TRIM(UPPER(D23)) -> B-11
A24: 23 | B24: MARCELINO FELIX VILLAFANA PALLACA | C24: B | D24: 10 | H24: 1 | I24: 391 | J24: 399 | K24: 8 | L24: 8 | N24: 0 | P24: 3 | V24: =SUM(L24:Q24) -> 11 | W24: =IFERROR(__xludf.DUMMYFUNCTION("IFERROR( SUM( FILTER( Reporte!$E:$E, REGEXMATCH(Reporte!$A:$A, ""(?i)(TE PAGÓ|PAGASTE)""), Reporte!$H:$H & """" = AH24 & """" ) ), 0 )"),11) -> 11 | X24: =IFERROR(__xludf.DUMMYFUNCTION("IFERROR( SUM( FILTER( Efectivo!$C:$C, Efectivo!$D:$D & """" = AH24 & """" ) ), 0 )"),0) -> 0 | Y24: c | AA24: y | AD24: =IF(AND(L24>0, M24>=8, NOT(OR(Y24="C", Y24="c"))), "CORTE", "") | AE24: =IF( OR( AND(#REF!>0, OR(Y24="C", Y24="c"), U24<0), AND(#REF!>0, Y24="") ), "CORTE", "" ) -> #REF! | AF24: =IF(AND(LEN(Y24)>0,LEN(AA24)=0),V24,0) -> 0 | AG24: =IF(AND(LEN(Y24)>0,TRIM(AA24)="Y"),V24,0) -> 11 | AH24: =TRIM(UPPER(C24)) -> B | AI24: =TRIM(UPPER(C24)) & "-" & TRIM(UPPER(D24)) -> B-10
A25: 24 | B25: TEOFILO BRUNO RAMOS DE LA CRUZ | C25: B | D25: 12 | H25: 1 | I25: 2 | J25: 9 | K25: 7 | L25: 7 | M25: 11 | N25: 0 | P25: 3 | V25: =SUM(L25:U25) -> 21 | W25: =IFERROR(__xludf.DUMMYFUNCTION("IFERROR( SUM( FILTER( Reporte!$E:$E, REGEXMATCH(Reporte!$A:$A, ""(?i)(TE PAGÓ|PAGASTE)""), Reporte!$H:$H & """" = AH25 & """" ) ), 0 )"),0) -> 0 | X25: =IFERROR(__xludf.DUMMYFUNCTION("IFERROR( SUM( FILTER( Efectivo!$C:$C, Efectivo!$D:$D & """" = AH25 & """" ) ), 0 )"),21) -> 21 | Y25: c | AD25: =IF(AND(L25>0, M25>=8, NOT(OR(Y25="C", Y25="c"))), "CORTE", "") | AE25: =IF( OR( AND(#REF!>0, OR(Y25="C", Y25="c"), U25<0), AND(#REF!>0, Y25="") ), "CORTE", "" ) -> #REF! | AF25: =IF(AND(LEN(Y25)>0,LEN(AA25)=0),V25,0) -> 21 | AG25: =IF(AND(LEN(Y25)>0,TRIM(AA25)="Y"),V25,0) -> 0 | AH25: =TRIM(UPPER(C25)) -> B | AI25: =TRIM(UPPER(C25)) & "-" & TRIM(UPPER(D25)) -> B-12
A26: 25 | B26: ROSMERI SANCHEZ ESPADA | C26: B | D26: 12A | H26: 1 | I26: 359 | J26: 365 | K26: 6 | L26: 6 | N26: 0 | P26: 3 | V26: =SUM(L26:Q26) -> 9 | W26: =IFERROR(__xludf.DUMMYFUNCTION("IFERROR( SUM( FILTER( Reporte!$E:$E, REGEXMATCH(Reporte!$A:$A, ""(?i)(TE PAGÓ|PAGASTE)""), Reporte!$H:$H & """" = AH26 & """" ) ), 0 )"),0) -> 0 | X26: =IFERROR(__xludf.DUMMYFUNCTION("IFERROR( SUM( FILTER( Efectivo!$C:$C, Efectivo!$D:$D & """" = AH26 & """" ) ), 0 )"),0) -> 0 | AD26: =IF(AND(L26>0, M26>=8, NOT(OR(Y26="C", Y26="c"))), "CORTE", "") | AE26: =IF( OR( AND(#REF!>0, OR(Y26="C", Y26="c"), U26<0), AND(#REF!>0, Y26="") ), "CORTE", "" ) -> #REF! | AF26: =IF(AND(LEN(Y26)>0,LEN(AA26)=0),V26,0) -> 0 | AG26: =IF(AND(LEN(Y26)>0,TRIM(AA26)="Y"),V26,0) -> 0 | AH26: =TRIM(UPPER(C26)) -> B | AI26: =TRIM(UPPER(C26)) & "-" & TRIM(UPPER(D26)) -> B-12A
A27: 26 | B27: SALOME AGUSTINA DIAZ VARGAS | C27: B | D27: 13 | H27: 1 | I27: 293 | J27: 300 | K27: 7 | L27: 7 | N27: 0 | P27: 3 | V27: =SUM(L27:Q27) -> 10 | W27: =IFERROR(__xludf.DUMMYFUNCTION("IFERROR( SUM( FILTER( Reporte!$E:$E, REGEXMATCH(Reporte!$A:$A, ""(?i)(TE PAGÓ|PAGASTE)""), Reporte!$H:$H & """" = AH27 & """" ) ), 0 )"),10) -> 10 | X27: =IFERROR(__xludf.DUMMYFUNCTION("IFERROR( SUM( FILTER( Efectivo!$C:$C, Efectivo!$D:$D & """" = AH27 & """" ) ), 0 )"),0) -> 0 | Y27: c | AA27: y | AD27: =IF(AND(L27>0, M27>=8, NOT(OR(Y27="C", Y27="c"))), "CORTE", "") | AE27: =IF( OR( AND(#REF!>0, OR(Y27="C", Y27="c"), U27<0), AND(#REF!>0, Y27="") ), "CORTE", "" ) -> #REF! | AF27: =IF(AND(LEN(Y27)>0,LEN(AA27)=0),V27,0) -> 0 | AG27: =IF(AND(LEN(Y27)>0,TRIM(AA27)="Y"),V27,0) -> 10 | AH27: =TRIM(UPPER(C27)) -> B | AI27: =TRIM(UPPER(C27)) & "-" & TRIM(UPPER(D27)) -> B-13
A28: 27 | B28: MELISSA ISABEL PILLACA GARCIA | C28: B | D28: 15 | H28: 1 | I28: 1285 | J28: 1295 | K28: 10 | L28: 10 | N28: 0 | P28: 3 | V28: =SUM(L28:Q28) -> 13 | W28: =IFERROR(__xludf.DUMMYFUNCTION("IFERROR( SUM( FILTER( Reporte!$E:$E, REGEXMATCH(Reporte!$A:$A, ""(?i)(TE PAGÓ|PAGASTE)""), Reporte!$H:$H & """" = AH28 & """" ) ), 0 )"),13) -> 13 | X28: =IFERROR(__xludf.DUMMYFUNCTION("IFERROR( SUM( FILTER( Efectivo!$C:$C, Efectivo!$D:$D & """" = AH28 & """" ) ), 0 )"),0) -> 0 | Y28: c | AA28: y | AD28: =IF(AND(L28>0, M28>=8, NOT(OR(Y28="C", Y28="c"))), "CORTE", "") | AE28: =IF( OR( AND(#REF!>0, OR(Y28="C", Y28="c"), U28<0), AND(#REF!>0, Y28="") ), "CORTE", "" ) -> #REF! | AF28: =IF(AND(LEN(Y28)>0,LEN(AA28)=0),V28,0) -> 0 | AG28: =IF(AND(LEN(Y28)>0,TRIM(AA28)="Y"),V28,0) -> 13 | AH28: =TRIM(UPPER(C28)) -> B | AI28: =TRIM(UPPER(C28)) & "-" & TRIM(UPPER(D28)) -> B-15
A29: 28 | B29: ELEUTERIA DOMITILA PARIAMACHI DE PAZ | C29: B | D29: 16 | H29: 1 | I29: 34 | J29: 34 | K29: 5 | L29: 5 | N29: 0 | P29: 3 | V29: =SUM(L29:Q29) -> 8 | W29: =IFERROR(__xludf.DUMMYFUNCTION("IFERROR( SUM( FILTER( Reporte!$E:$E, REGEXMATCH(Reporte!$A:$A, ""(?i)(TE PAGÓ|PAGASTE)""), Reporte!$H:$H & """" = AH29 & """" ) ), 0 )"),0) -> 0 | X29: =IFERROR(__xludf.DUMMYFUNCTION("IFERROR( SUM( FILTER( Efectivo!$C:$C, Efectivo!$D:$D & """" = AH29 & """" ) ), 0 )"),0) -> 0 | AD29: =IF(AND(L29>0, M29>=8, NOT(OR(Y29="C", Y29="c"))), "CORTE", "") | AE29: =IF( OR( AND(#REF!>0, OR(Y29="C", Y29="c"), U29<0), AND(#REF!>0, Y29="") ), "CORTE", "" ) -> #REF! | AF29: =IF(AND(LEN(Y29)>0,LEN(AA29)=0),V29,0) -> 0 | AG29: =IF(AND(LEN(Y29)>0,TRIM(AA29)="Y"),V29,0) -> 0 | AH29: =TRIM(UPPER(C29)) -> B | AI29: =TRIM(UPPER(C29)) & "-" & TRIM(UPPER(D29)) -> B-16
A30: 29 | B30: LUZ DINA MIRAVAL HUERTA | C30: B | D30: 17 | H30: 1 | I30: 1065 | J30: 1093 | K30: 28 | L30: 28 | N30: 0 | P30: 3 | V30: =SUM(L30:Q30) -> 31 | W30: =IFERROR(__xludf.DUMMYFUNCTION("IFERROR( SUM( FILTER( Reporte!$E:$E, REGEXMATCH(Reporte!$A:$A, ""(?i)(TE PAGÓ|PAGASTE)""), Reporte!$H:$H & """" = AH30 & """" ) ), 0 )"),0) -> 0 | X30: =IFERROR(__xludf.DUMMYFUNCTION("IFERROR( SUM( FILTER( Efectivo!$C:$C, Efectivo!$D:$D & """" = AH30 & """" ) ), 0 )"),0) -> 0 | AD30: =IF(AND(L30>0, M30>=8, NOT(OR(Y30="C", Y30="c"))), "CORTE", "") | AE30: =IF( OR( AND(#REF!>0, OR(Y30="C", Y30="c"), U30<0), AND(#REF!>0, Y30="") ), "CORTE", "" ) -> #REF! | AF30: =IF(AND(LEN(Y30)>0,LEN(AA30)=0),V30,0) -> 0 | AG30: =IF(AND(LEN(Y30)>0,TRIM(AA30)="Y"),V30,0) -> 0 | AH30: =TRIM(UPPER(C30)) -> B | AI30: =TRIM(UPPER(C30)) & "-" & TRIM(UPPER(D30)) -> B-17
A31: 30 | B31: CLETO TENORIO MORI | C31: B | D31: 18 | H31: 1 | I31: 573 | J31: 577 | K31: 4 | L31: 5 | N31: 0 | P31: 3 | V31: =SUM(L31:Q31) -> 8 | W31: =IFERROR(__xludf.DUMMYFUNCTION("IFERROR( SUM( FILTER( Reporte!$E:$E, REGEXMATCH(Reporte!$A:$A, ""(?i)(TE PAGÓ|PAGASTE)""), Reporte!$H:$H & """" = AH31 & """" ) ), 0 )"),0) -> 0 | X31: =IFERROR(__xludf.DUMMYFUNCTION("IFERROR( SUM( FILTER( Efectivo!$C:$C, Efectivo!$D:$D & """" = AH31 & """" ) ), 0 )"),0) -> 0 | AD31: =IF(AND(L31>0, M31>=8, NOT(OR(Y31="C", Y31="c"))), "CORTE", "") | AE31: =IF( OR( AND(#REF!>0, OR(Y31="C", Y31="c"), U31<0), AND(#REF!>0, Y31="") ), "CORTE", "" ) -> #REF! | AF31: =IF(AND(LEN(Y31)>0,LEN(AA31)=0),V31,0) -> 0 | AG31: =IF(AND(LEN(Y31)>0,TRIM(AA31)="Y"),V31,0) -> 0 | AH31: =TRIM(UPPER(C31)) -> B | AI31: =TRIM(UPPER(C31)) & "-" & TRIM(UPPER(D31)) -> B-18
A32: 31 | B32: CAMILA HIDALGO | C32: B | D32: 21 | H32: 1 | I32: 187 | J32: 199 | K32: 12 | L32: 12 | P32: 3 | Q32: 0 | V32: =SUM(L32:Q32) -> 15 | W32: =IFERROR(__xludf.DUMMYFUNCTION("IFERROR( SUM( FILTER( Reporte!$E:$E, REGEXMATCH(Reporte!$A:$A, ""(?i)(TE PAGÓ|PAGASTE)""), Reporte!$H:$H & """" = AH32 & """" ) ), 0 )"),0) -> 0 | X32: =IFERROR(__xludf.DUMMYFUNCTION("IFERROR( SUM( FILTER( Efectivo!$C:$C, Efectivo!$D:$D & """" = AH32 & """" ) ), 0 )"),0) -> 0 | AB32: Pago | AD32: =IF(AND(L32>0, M32>=8, NOT(OR(Y32="C", Y32="c"))), "CORTE", "") | AE32: =IF( OR( AND(#REF!>0, OR(Y32="C", Y32="c"), U32<0), AND(#REF!>0, Y32="") ), "CORTE", "" ) -> #REF! | AF32: =IF(AND(LEN(Y32)>0,LEN(AA32)=0),V32,0) -> 0 | AG32: =IF(AND(LEN(Y32)>0,TRIM(AA32)="Y"),V32,0) -> 0 | AH32: =TRIM(UPPER(C32)) -> B | AI32: =TRIM(UPPER(C32)) & "-" & TRIM(UPPER(D32)) -> B-21
A33: 32 | B33: JANET FERNANDEZ MINAYA | C33: B | D33: 29 | E33: N | H33: 1 | I33: 183 | J33: 187 | K33: 4 | L33: 5 | M33: 8 | N33: 0 | O33: 40 | P33: 3 | V33: =SUM(L33:Q33) -> 56 | W33: =IFERROR(__xludf.DUMMYFUNCTION("IFERROR( SUM( FILTER( Reporte!$E:$E, REGEXMATCH(Reporte!$A:$A, ""(?i)(TE PAGÓ|PAGASTE)""), Reporte!$H:$H & """" = AH33 & """" ) ), 0 )"),56) -> 56 | X33: =IFERROR(__xludf.DUMMYFUNCTION("IFERROR( SUM( FILTER( Efectivo!$C:$C, Efectivo!$D:$D & """" = AH33 & """" ) ), 0 )"),0) -> 0 | Y33: c | AA33: y | AD33: =IF(AND(L33>0, M33>=8, NOT(OR(Y33="C", Y33="c"))), "CORTE", "") | AE33: =IF( OR( AND(#REF!>0, OR(Y33="C", Y33="c"), U33<0), AND(#REF!>0, Y33="") ), "CORTE", "" ) -> #REF! | AF33: =IF(AND(LEN(Y33)>0,LEN(AA33)=0),V33,0) -> 0 | AG33: =IF(AND(LEN(Y33)>0,TRIM(AA33)="Y"),V33,0) -> 56 | AH33: =TRIM(UPPER(C33)) -> B | AI33: =TRIM(UPPER(C33)) & "-" & TRIM(UPPER(D33)) -> B-29
A34: 33 | B34: ODILON CERNA ROMERO | C34: C | D34: 1 | H34: 1 | I34: 6 | J34: 21 | K34: 15 | L34: 15 | N34: 0 | O34: 25 | P34: 3 | V34: =SUM(L34:Q34) -> 43 | W34: =IFERROR(__xludf.DUMMYFUNCTION("IFERROR( SUM( FILTER( Reporte!$E:$E, REGEXMATCH(Reporte!$A:$A, ""(?i)(TE PAGÓ|PAGASTE)""), Reporte!$H:$H & """" = AH34 & """" ) ), 0 )"),0) -> 0 | X34: =IFERROR(__xludf.DUMMYFUNCTION("IFERROR( SUM( FILTER( Efectivo!$C:$C, Efectivo!$D:$D & """" = AH34 & """" ) ), 0 )"),0) -> 0 | AD34: =IF(AND(L34>0, M34>=8, NOT(OR(Y34="C", Y34="c"))), "CORTE", "") | AE34: =IF( OR( AND(#REF!>0, OR(Y34="C", Y34="c"), U34<0), AND(#REF!>0, Y34="") ), "CORTE", "" ) -> #REF! | AF34: =IF(AND(LEN(Y34)>0,LEN(AA34)=0),V34,0) -> 0 | AG34: =IF(AND(LEN(Y34)>0,TRIM(AA34)="Y"),V34,0) -> 0 | AH34: =TRIM(UPPER(C34)) -> C | AI34: =TRIM(UPPER(C34)) & "-" & TRIM(UPPER(D34)) -> C-1
A35: 34 | B35: OLGA FLORENTINA HUERTA AGAMA | C35: C | D35: 2 | H35: 1 | I35: 0 | J35: 6 | K35: 6 | L35: 6 | N35: 0 | O35: 25 | P35: 3 | V35: =SUM(L35:Q35) -> 34 | W35: =IFERROR(__xludf.DUMMYFUNCTION("IFERROR( SUM( FILTER( Reporte!$E:$E, REGEXMATCH(Reporte!$A:$A, ""(?i)(TE PAGÓ|PAGASTE)""), Reporte!$H:$H & """" = AH35 & """" ) ), 0 )"),0) -> 0 | X35: =IFERROR(__xludf.DUMMYFUNCTION("IFERROR( SUM( FILTER( Efectivo!$C:$C, Efectivo!$D:$D & """" = AH35 & """" ) ), 0 )"),34) -> 34 | Y35: c | AD35: =IF(AND(L35>0, M35>=8, NOT(OR(Y35="C", Y35="c"))), "CORTE", "") | AE35: =IF( OR( AND(#REF!>0, OR(Y35="C", Y35="c"), U35<0), AND(#REF!>0, Y35="") ), "CORTE", "" ) -> #REF! | AF35: =IF(AND(LEN(Y35)>0,LEN(AA35)=0),V35,0) -> 34 | AG35: =IF(AND(LEN(Y35)>0,TRIM(AA35)="Y"),V35,0) -> 0 | AH35: =TRIM(UPPER(C35)) -> C | AI35: =TRIM(UPPER(C35)) & "-" & TRIM(UPPER(D35)) -> C-2
A36: 35 | B36: TIMOTEO ROMERO JULCA | C36: C | D36: 4 | H36: 1 | I36: 4 | J36: 21 | K36: 17 | L36: 17 | N36: 0 | O36: 25 | P36: 3 | V36: =SUM(L36:Q36) -> 45 | W36: =IFERROR(__xludf.DUMMYFUNCTION("IFERROR( SUM( FILTER( Reporte!$E:$E, REGEXMATCH(Reporte!$A:$A, ""(?i)(TE PAGÓ|PAGASTE)""), Reporte!$H:$H & """" = AH36 & """" ) ), 0 )"),0) -> 0 | X36: =IFERROR(__xludf.DUMMYFUNCTION("IFERROR( SUM( FILTER( Efectivo!$C:$C, Efectivo!$D:$D & """" = AH36 & """" ) ), 0 )"),45) -> 45 | Y36: c | AD36: =IF(AND(L36>0, M36>=8, NOT(OR(Y36="C", Y36="c"))), "CORTE", "") | AE36: =IF( OR( AND(#REF!>0, OR(Y36="C", Y36="c"), U36<0), AND(#REF!>0, Y36="") ), "CORTE", "" ) -> #REF! | AF36: =IF(AND(LEN(Y36)>0,LEN(AA36)=0),V36,0) -> 45 | AG36: =IF(AND(LEN(Y36)>0,TRIM(AA36)="Y"),V36,0) -> 0 | AH36: =TRIM(UPPER(C36)) -> C | AI36: =TRIM(UPPER(C36)) & "-" & TRIM(UPPER(D36)) -> C-4
A37: 36 | B37: AGAPITO PRINCIPE SALINAS | C37: C | D37: 5 | H37: 1 | I37: 8 | J37: 26 | K37: 18 | L37: 18 | N37: 0 | O37: 25 | P37: 3 | V37: =SUM(L37:Q37) -> 46 | W37: =IFERROR(__xludf.DUMMYFUNCTION("IFERROR( SUM( FILTER( Reporte!$E:$E, REGEXMATCH(Reporte!$A:$A, ""(?i)(TE PAGÓ|PAGASTE)""), Reporte!$H:$H & """" = AH37 & """" ) ), 0 )"),46) -> 46 | X37: =IFERROR(__xludf.DUMMYFUNCTION("IFERROR( SUM( FILTER( Efectivo!$C:$C, Efectivo!$D:$D & """" = AH37 & """" ) ), 0 )"),0) -> 0 | Y37: c | AA37: y | AD37: =IF(AND(L37>0, M37>=8, NOT(OR(Y37="C", Y37="c"))), "CORTE", "") | AE37: =IF( OR( AND(#REF!>0, OR(Y37="C", Y37="c"), U37<0), AND(#REF!>0, Y37="") ), "CORTE", "" ) -> #REF! | AF37: =IF(AND(LEN(Y37)>0,LEN(AA37)=0),V37,0) -> 0 | AG37: =IF(AND(LEN(Y37)>0,TRIM(AA37)="Y"),V37,0) -> 46 | AH37: =TRIM(UPPER(C37)) -> C | AI37: =TRIM(UPPER(C37)) & "-" & TRIM(UPPER(D37)) -> C-5
A38: 37 | B38: DIANA JARA TRUJILLO | C38: C | D38: 6 | H38: 1 | I38: 592 | J38: 598 | K38: 6 | L38: 6 | M38: 16 | N38: 0 | P38: 3 | V38: =SUM(L38:Q38) -> 25 | W38: =IFERROR(__xludf.DUMMYFUNCTION("IFERROR( SUM( FILTER( Reporte!$E:$E, REGEXMATCH(Reporte!$A:$A, ""(?i)(TE PAGÓ|PAGASTE)""), Reporte!$H:$H & """" = AH38 & """" ) ), 0 )"),25) -> 25 | X38: =IFERROR(__xludf.DUMMYFUNCTION("IFERROR( SUM( FILTER( Efectivo!$C:$C, Efectivo!$D:$D & """" = AH38 & """" ) ), 0 )"),0) -> 0 | Y38: c | AA38: y | AD38: =IF(AND(L38>0, M38>=8, NOT(OR(Y38="C", Y38="c"))), "CORTE", "") | AE38: =IF( OR( AND(#REF!>0, OR(Y38="C", Y38="c"), U38<0), AND(#REF!>0, Y38="") ), "CORTE", "" ) -> #REF! | AF38: =IF(AND(LEN(Y38)>0,LEN(AA38)=0),V38,0) -> 0 | AG38: =IF(AND(LEN(Y38)>0,TRIM(AA38)="Y"),V38,0) -> 25 | AH38: =TRIM(UPPER(C38)) -> C | AI38: =TRIM(UPPER(C38)) & "-" & TRIM(UPPER(D38)) -> C-6
A39: 38 | B39: VICTOR LOPEZ TRUJILLO | C39: C | D39: 7 | H39: 1 | I39: 15 | J39: 53 | K39: 38 | L39: 38 | N39: 0 | O39: 25 | P39: 3 | V39: =SUM(L39:Q39) -> 66 | W39: =IFERROR(__xludf.DUMMYFUNCTION("IFERROR( SUM( FILTER( Reporte!$E:$E, REGEXMATCH(Reporte!$A:$A, ""(?i)(TE PAGÓ|PAGASTE)""), Reporte!$H:$H & """" = AH39 & """" ) ), 0 )"),66) -> 66 | X39: =IFERROR(__xludf.DUMMYFUNCTION("IFERROR( SUM( FILTER( Efectivo!$C:$C, Efectivo!$D:$D & """" = AH39 & """" ) ), 0 )"),0) -> 0 | Y39: c | AA39: y | AD39: =IF(AND(L39>0, M39>=8, NOT(OR(Y39="C", Y39="c"))), "CORTE", "") | AE39: =IF( OR( AND(#REF!>0, OR(Y39="C", Y39="c"), U39<0), AND(#REF!>0, Y39="") ), "CORTE", "" ) -> #REF! | AF39: =IF(AND(LEN(Y39)>0,LEN(AA39)=0),V39,0) -> 0 | AG39: =IF(AND(LEN(Y39)>0,TRIM(AA39)="Y"),V39,0) -> 66 | AH39: =TRIM(UPPER(C39)) -> C | AI39: =TRIM(UPPER(C39)) & "-" & TRIM(UPPER(D39)) -> C-7
A40: 39 | B40: JULISSA BARRETO QUITO | C40: C | D40: 8 | H40: 1 | I40: 279 | J40: 287 | K40: 8 | L40: 8 | M40: 11 | N40: 0 | P40: 3 | V40: =SUM(L40:Q40) -> 22 | W40: =IFERROR(__xludf.DUMMYFUNCTION("IFERROR( SUM( FILTER( Reporte!$E:$E, REGEXMATCH(Reporte!$A:$A, ""(?i)(TE PAGÓ|PAGASTE)""), Reporte!$H:$H & """" = AH40 & """" ) ), 0 )"),22) -> 22 | X40: =IFERROR(__xludf.DUMMYFUNCTION("IFERROR( SUM( FILTER( Efectivo!$C:$C, Efectivo!$D:$D & """" = AH40 & """" ) ), 0 )"),0) -> 0 | Y40: c | AA40: y | AD40: =IF(AND(L40>0, M40>=8, NOT(OR(Y40="C", Y40="c"))), "CORTE", "") | AE40: =IF( OR( AND(#REF!>0, OR(Y40="C", Y40="c"), U40<0), AND(#REF!>0, Y40="") ), "CORTE", "" ) -> #REF! | AF40: =IF(AND(LEN(Y40)>0,LEN(AA40)=0),V40,0) -> 0 | AG40: =IF(AND(LEN(Y40)>0,TRIM(AA40)="Y"),V40,0) -> 22 | AH40: =TRIM(UPPER(C40)) -> C | AI40: =TRIM(UPPER(C40)) & "-" & TRIM(UPPER(D40)) -> C-8
A41: 40 | B41: JAZMIN QUITO SANCHEZ | C41: C | D41: 8B | H41: 1 | I41: 996 | J41: 1017 | K41: 21 | L41: 21 | N41: 0 | P41: 3 | V41: =SUM(L41:Q41) -> 24 | W41: =IFERROR(__xludf.DUMMYFUNCTION("IFERROR( SUM( FILTER( Reporte!$E:$E, REGEXMATCH(Reporte!$A:$A, ""(?i)(TE PAGÓ|PAGASTE)""), Reporte!$H:$H & """" = AH41 & """" ) ), 0 )"),24) -> 24 | X41: =IFERROR(__xludf.DUMMYFUNCTION("IFERROR( SUM( FILTER( Efectivo!$C:$C, Efectivo!$D:$D & """" = AH41 & """" ) ), 0 )"),0) -> 0 | Y41: c | AA41: y | AD41: =IF(AND(L41>0, M41>=8, NOT(OR(Y41="C", Y41="c"))), "CORTE", "") | AE41: =IF( OR( AND(#REF!>0, OR(Y41="C", Y41="c"), U41<0), AND(#REF!>0, Y41="") ), "CORTE", "" ) -> #REF! | AF41: =IF(AND(LEN(Y41)>0,LEN(AA41)=0),V41,0) -> 0 | AG41: =IF(AND(LEN(Y41)>0,TRIM(AA41)="Y"),V41,0) -> 24 | AH41: =TRIM(UPPER(C41)) -> C | AI41: =TRIM(UPPER(C41)) & "-" & TRIM(UPPER(D41)) -> C-8B
A42: 41 | B42: JUAN UCULMANA SANCHEZ | C42: C | D42: 9 | H42: 1 | I42: 2142 | J42: 2142 | K42: 5 | L42: 5 | N42: 0 | P42: 3 | V42: =SUM(L42:Q42) -> 8 | W42: =IFERROR(__xludf.DUMMYFUNCTION("IFERROR( SUM( FILTER( Reporte!$E:$E, REGEXMATCH(Reporte!$A:$A, ""(?i)(TE PAGÓ|PAGASTE)""), Reporte!$H:$H & """" = AH42 & """" ) ), 0 )"),8) -> 8 | X42: =IFERROR(__xludf.DUMMYFUNCTION("IFERROR( SUM( FILTER( Efectivo!$C:$C, Efectivo!$D:$D & """" = AH42 & """" ) ), 0 )"),0) -> 0 | Y42: c | AA42: y | AD42: =IF(AND(L42>0, M42>=8, NOT(OR(Y42="C", Y42="c"))), "CORTE", "") | AE42: =IF( OR( AND(#REF!>0, OR(Y42="C", Y42="c"), U42<0), AND(#REF!>0, Y42="") ), "CORTE", "" ) -> #REF! | AF42: =IF(AND(LEN(Y42)>0,LEN(AA42)=0),V42,0) -> 0 | AG42: =IF(AND(LEN(Y42)>0,TRIM(AA42)="Y"),V42,0) -> 8 | AH42: =TRIM(UPPER(C42)) -> C | AI42: =TRIM(UPPER(C42)) & "-" & TRIM(UPPER(D42)) -> C-9
A43: 42 | B43: SONIA GLORIA MORENO CASTILLEJO | C43: C | D43: 9C | H43: 1 | I43: 515 | J43: 522 | K43: 7 | L43: 7 | N43: 0 | P43: 3 | V43: =SUM(L43:Q43) -> 10 | W43: =IFERROR(__xludf.DUMMYFUNCTION("IFERROR( SUM( FILTER( Reporte!$E:$E, REGEXMATCH(Reporte!$A:$A, ""(?i)(TE PAGÓ|PAGASTE)""), Reporte!$H:$H & """" = AH43 & """" ) ), 0 )"),10) -> 10 | X43: =IFERROR(__xludf.DUMMYFUNCTION("IFERROR( SUM( FILTER( Efectivo!$C:$C, Efectivo!$D:$D & """" = AH43 & """" ) ), 0 )"),0) -> 0 | Y43: c | AA43: y | AD43: =IF(AND(L43>0, M43>=8, NOT(OR(Y43="C", Y43="c"))), "CORTE", "") | AE43: =IF( OR( AND(#REF!>0, OR(Y43="C", Y43="c"), U43<0), AND(#REF!>0, Y43="") ), "CORTE", "" ) -> #REF! | AF43: =IF(AND(LEN(Y43)>0,LEN(AA43)=0),V43,0) -> 0 | AG43: =IF(AND(LEN(Y43)>0,TRIM(AA43)="Y"),V43,0) -> 10 | AH43: =TRIM(UPPER(C43)) -> C | AI43: =TRIM(UPPER(C43)) & "-" & TRIM(UPPER(D43)) -> C-9C
A44: 43 | B44: CEVERIANO CHAUCA MORALES | C44: C | D44: 11 | H44: 1 | I44: 835 | J44: 851 | K44: 16 | L44: 16 | N44: 0 | P44: 3 | V44: =SUM(L44:Q44) -> 19 | W44: =IFERROR(__xludf.DUMMYFUNCTION("IFERROR( SUM( FILTER( Reporte!$E:$E, REGEXMATCH(Reporte!$A:$A, ""(?i)(TE PAGÓ|PAGASTE)""), Reporte!$H:$H & """" = AH44 & """" ) ), 0 )"),0) -> 0 | X44: =IFERROR(__xludf.DUMMYFUNCTION("IFERROR( SUM( FILTER( Efectivo!$C:$C, Efectivo!$D:$D & """" = AH44 & """" ) ), 0 )"),19) -> 19 | Y44: c | AD44: =IF(AND(L44>0, M44>=8, NOT(OR(Y44="C", Y44="c"))), "CORTE", "") | AE44: =IF( OR( AND(#REF!>0, OR(Y44="C", Y44="c"), U44<0), AND(#REF!>0, Y44="") ), "CORTE", "" ) -> #REF! | AF44: =IF(AND(LEN(Y44)>0,LEN(AA44)=0),V44,0) -> 19 | AG44: =IF(AND(LEN(Y44)>0,TRIM(AA44)="Y"),V44,0) -> 0 | AH44: =TRIM(UPPER(C44)) -> C | AI44: =TRIM(UPPER(C44)) & "-" & TRIM(UPPER(D44)) -> C-11
A45: 44 | B45: MACEDONIO MORALES BENTURO | C45: C | D45: 12 | H45: 1 | I45: 1672 | J45: 1684 | K45: 12 | L45: 12 | N45: 0 | P45: 3 | V45: =SUM(L45:Q45) -> 15 | W45: =IFERROR(__xludf.DUMMYFUNCTION("IFERROR( SUM( FILTER( Reporte!$E:$E, REGEXMATCH(Reporte!$A:$A, ""(?i)(TE PAGÓ|PAGASTE)""), Reporte!$H:$H & """" = AH45 & """" ) ), 0 )"),0) -> 0 | X45: =IFERROR(__xludf.DUMMYFUNCTION("IFERROR( SUM( FILTER( Efectivo!$C:$C, Efectivo!$D:$D & """" = AH45 & """" ) ), 0 )"),15) -> 15 | Y45: c | AD45: =IF(AND(L45>0, M45>=8, NOT(OR(Y45="C", Y45="c"))), "CORTE", "") | AE45: =IF( OR( AND(#REF!>0, OR(Y45="C", Y45="c"), U45<0), AND(#REF!>0, Y45="") ), "CORTE", "" ) -> #REF! | AF45: =IF(AND(LEN(Y45)>0,LEN(AA45)=0),V45,0) -> 15 | AG45: =IF(AND(LEN(Y45)>0,TRIM(AA45)="Y"),V45,0) -> 0 | AH45: =TRIM(UPPER(C45)) -> C | AI45: =TRIM(UPPER(C45)) & "-" & TRIM(UPPER(D45)) -> C-12
A46: 45 | B46: IRMA HUAÑAHUI LOPEZ | C46: C | D46: 13 | H46: 1 | I46: 2 | J46: 12 | K46: 10 | L46: 10 | N46: 0 | O46: 25 | P46: 3 | V46: =SUM(L46:Q46) -> 38 | W46: =IFERROR(__xludf.DUMMYFUNCTION("IFERROR( SUM( FILTER( Reporte!$E:$E, REGEXMATCH(Reporte!$A:$A, ""(?i)(TE PAGÓ|PAGASTE)""), Reporte!$H:$H & """" = AH46 & """" ) ), 0 )"),38) -> 38 | X46: =IFERROR(__xludf.DUMMYFUNCTION("IFERROR( SUM( FILTER( Efectivo!$C:$C, Efectivo!$D:$D & """" = AH46 & """" ) ), 0 )"),0) -> 0 | Y46: c | AA46: y | AD46: =IF(AND(L46>0, M46>=8, NOT(OR(Y46="C", Y46="c"))), "CORTE", "") | AE46: =IF( OR( AND(#REF!>0, OR(Y46="C", Y46="c"), U46<0), AND(#REF!>0, Y46="") ), "CORTE", "" ) -> #REF! | AF46: =IF(AND(LEN(Y46)>0,LEN(AA46)=0),V46,0) -> 0 | AG46: =IF(AND(LEN(Y46)>0,TRIM(AA46)="Y"),V46,0) -> 38 | AH46: =TRIM(UPPER(C46)) -> C | AI46: =TRIM(UPPER(C46)) & "-" & TRIM(UPPER(D46)) -> C-13
A47: 46 | B47: JUAN RIOS BLAS | C47: C | D47: 14 | H47: 1 | I47: 4 | J47: 9 | K47: 5 | L47: 5 | N47: 0 | P47: 3 | V47: =SUM(L47:Q47) -> 8 | W47: =IFERROR(__xludf.DUMMYFUNCTION("IFERROR( SUM( FILTER( Reporte!$E:$E, REGEXMATCH(Reporte!$A:$A, ""(?i)(TE PAGÓ|PAGASTE)""), Reporte!$H:$H & """" = AH47 & """" ) ), 0 )"),0) -> 0 | X47: =IFERROR(__xludf.DUMMYFUNCTION("IFERROR( SUM( FILTER( Efectivo!$C:$C, Efectivo!$D:$D & """" = AH47 & """" ) ), 0 )"),0) -> 0 | AD47: =IF(AND(L47>0, M47>=8, NOT(OR(Y47="C", Y47="c"))), "CORTE", "") | AE47: =IF( OR( AND(#REF!>0, OR(Y47="C", Y47="c"), U47<0), AND(#REF!>0, Y47="") ), "CORTE", "" ) -> #REF! | AF47: =IF(AND(LEN(Y47)>0,LEN(AA47)=0),V47,0) -> 0 | AG47: =IF(AND(LEN(Y47)>0,TRIM(AA47)="Y"),V47,0) -> 0 | AH47: =TRIM(UPPER(C47)) -> C | AI47: =TRIM(UPPER(C47)) & "-" & TRIM(UPPER(D47)) -> C-14
A48: 47 | B48: JULIO RIOS BLAS | C48: C | D48: 15 | H48: 1 | I48: 125 | J48: 136 | K48: 11 | L48: 11 | N48: 0 | P48: 3 | V48: =SUM(L48:Q48) -> 14 | W48: =IFERROR(__xludf.DUMMYFUNCTION("IFERROR( SUM( FILTER( Reporte!$E:$E, REGEXMATCH(Reporte!$A:$A, ""(?i)(TE PAGÓ|PAGASTE)""), Reporte!$H:$H & """" = AH48 & """" ) ), 0 )"),14) -> 14 | X48: =IFERROR(__xludf.DUMMYFUNCTION("IFERROR( SUM( FILTER( Efectivo!$C:$C, Efectivo!$D:$D & """" = AH48 & """" ) ), 0 )"),0) -> 0 | Y48: c | AA48: y | AD48: =IF(AND(L48>0, M48>=8, NOT(OR(Y48="C", Y48="c"))), "CORTE", "") | AE48: =IF( OR( AND(#REF!>0, OR(Y48="C", Y48="c"), U48<0), AND(#REF!>0, Y48="") ), "CORTE", "" ) -> #REF! | AF48: =IF(AND(LEN(Y48)>0,LEN(AA48)=0),V48,0) -> 0 | AG48: =IF(AND(LEN(Y48)>0,TRIM(AA48)="Y"),V48,0) -> 14 | AH48: =TRIM(UPPER(C48)) -> C | AI48: =TRIM(UPPER(C48)) & "-" & TRIM(UPPER(D48)) -> C-15
A49: 48 | B49: MARTHA MASIAS CASIHUAMAN DE TERAN | C49: C | D49: 16 | H49: 1 | I49: 1542 | J49: 26 | K49: 26 | L49: 5 | N49: 0 | P49: 3 | V49: =SUM(L49:U49) -> 8 | W49: =IFERROR(__xludf.DUMMYFUNCTION("IFERROR( SUM( FILTER( Reporte!$E:$E, REGEXMATCH(Reporte!$A:$A, ""(?i)(TE PAGÓ|PAGASTE)""), Reporte!$H:$H & """" = AH49 & """" ) ), 0 )"),0) -> 0 | X49: =IFERROR(__xludf.DUMMYFUNCTION("IFERROR( SUM( FILTER( Efectivo!$C:$C, Efectivo!$D:$D & """" = AH49 & """" ) ), 0 )"),8) -> 8 | Y49: c | AB49: Debe 25 medidor. 21 consumo | AD49: =IF(AND(L49>0, M49>=8, NOT(OR(Y49="C", Y49="c"))), "CORTE", "") | AE49: =IF( OR( AND(#REF!>0, OR(Y49="C", Y49="c"), U49<0), AND(#REF!>0, Y49="") ), "CORTE", "" ) -> #REF! | AF49: =IF(AND(LEN(Y49)>0,LEN(AA49)=0),V49,0) -> 8 | AG49: =IF(AND(LEN(Y49)>0,TRIM(AA49)="Y"),V49,0) -> 0 | AH49: =TRIM(UPPER(C49)) -> C | AI49: =TRIM(UPPER(C49)) & "-" & TRIM(UPPER(D49)) -> C-16
A50: 49 | B50: MARCELINO VALLADARES TRUJILLO | C50: C | D50: 18 | H50: 1 | I50: 2 | J50: 12 | K50: 10 | L50: 10 | N50: 0 | O50: 25 | P50: 3 | V50: =SUM(L50:Q50) -> 38 | W50: =IFERROR(__xludf.DUMMYFUNCTION("IFERROR( SUM( FILTER( Reporte!$E:$E, REGEXMATCH(Reporte!$A:$A, ""(?i)(TE PAGÓ|PAGASTE)""), Reporte!$H:$H & """" = AH50 & """" ) ), 0 )"),0) -> 0 | X50: =IFERROR(__xludf.DUMMYFUNCTION("IFERROR( SUM( FILTER( Efectivo!$C:$C, Efectivo!$D:$D & """" = AH50 & """" ) ), 0 )"),38) -> 38 | Y50: c | AD50: =IF(AND(L50>0, M50>=8, NOT(OR(Y50="C", Y50="c"))), "CORTE", "") | AE50: =IF( OR( AND(#REF!>0, OR(Y50="C", Y50="c"), U50<0), AND(#REF!>0, Y50="") ), "CORTE", "" ) -> #REF! | AF50: =IF(AND(LEN(Y50)>0,LEN(AA50)=0),V50,0) -> 38 | AG50: =IF(AND(LEN(Y50)>0,TRIM(AA50)="Y"),V50,0) -> 0 | AH50: =TRIM(UPPER(C50)) -> C | AI50: =TRIM(UPPER(C50)) & "-" & TRIM(UPPER(D50)) -> C-18
A51: 50 | B51: ANTONIO VALLADARES DOMINGUEZ | C51: C | D51: 19 | H51: 1 | I51: 11 | J51: 37 | K51: 26 | L51: 26 | N51: 0 | O51: 47 | P51: 3 | V51: =SUM(L51:U51) -> 76 | W51: =IFERROR(__xludf.DUMMYFUNCTION("IFERROR( SUM( FILTER( Reporte!$E:$E, REGEXMATCH(Reporte!$A:$A, ""(?i)(TE PAGÓ|PAGASTE)""), Reporte!$H:$H & """" = AH51 & """" ) ), 0 )"),0) -> 0 | X51: =IFERROR(__xludf.DUMMYFUNCTION("IFERROR( SUM( FILTER( Efectivo!$C:$C, Efectivo!$D:$D & """" = AH51 & """" ) ), 0 )"),76) -> 76 | Y51: c | AD51: =IF(AND(L51>0, M51>=8, NOT(OR(Y51="C", Y51="c"))), "CORTE", "") | AE51: =IF( OR( AND(#REF!>0, OR(Y51="C", Y51="c"), U51<0), AND(#REF!>0, Y51="") ), "CORTE", "" ) -> #REF! | AF51: =IF(AND(LEN(Y51)>0,LEN(AA51)=0),V51,0) -> 76 | AG51: =IF(AND(LEN(Y51)>0,TRIM(AA51)="Y"),V51,0) -> 0 | AH51: =TRIM(UPPER(C51)) -> C | AI51: =TRIM(UPPER(C51)) & "-" & TRIM(UPPER(D51)) -> C-19
A52: 51 | B52: EUSEBIO REYES VILLAFANA | C52: C | D52: 20 | H52: 1 | I52: 9 | J52: 25 | K52: 16 | L52: 16 | N52: 0 | O52: 25 | P52: 3 | V52: =SUM(L52:U52) -> 44 | W52: =IFERROR(__xludf.DUMMYFUNCTION("IFERROR( SUM( FILTER( Reporte!$E:$E, REGEXMATCH(Reporte!$A:$A, ""(?i)(TE PAGÓ|PAGASTE)""), Reporte!$H:$H & """" = AH52 & """" ) ), 0 )"),19) -> 19 | X52: =IFERROR(__xludf.DUMMYFUNCTION("IFERROR( SUM( FILTER( Efectivo!$C:$C, Efectivo!$D:$D & """" = AH52 & """" ) ), 0 )"),25) -> 25 | Y52: c | AA52: y | AB52: 25 es del efectivo | AD52: =IF(AND(L52>0, M52>=8, NOT(OR(Y52="C", Y52="c"))), "CORTE", "") | AE52: =IF( OR( AND(#REF!>0, OR(Y52="C", Y52="c"), U52<0), AND(#REF!>0, Y52="") ), "CORTE", "" ) -> #REF! | AF52: =IF(AND(LEN(Y52)>0,LEN(AA52)=0),V52,0) -> 0 | AG52: =IF(AND(LEN(Y52)>0,TRIM(AA52)="Y"),V52,0) -> 44 | AH52: =TRIM(UPPER(C52)) -> C | AI52: =TRIM(UPPER(C52)) & "-" & TRIM(UPPER(D52)) -> C-20
A53: 52 | B53: PUESTO DE SALUD TUPAC AMARU | C53: C | D53: 21 | H53: 1 | J53: 1700 | K53: 24 | L53: 24 | N53: 0 | P53: 3 | V53: =SUM(L53:Q53) -> 27 | W53: =IFERROR(__xludf.DUMMYFUNCTION("IFERROR( SUM( FILTER( Reporte!$E:$E, REGEXMATCH(Reporte!$A:$A, ""(?i)(TE PAGÓ|PAGASTE)""), Reporte!$H:$H & """" = AH53 & """" ) ), 0 )"),0) -> 0 | X53: =IFERROR(__xludf.DUMMYFUNCTION("IFERROR( SUM( FILTER( Efectivo!$C:$C, Efectivo!$D:$D & """" = AH53 & """" ) ), 0 )"),0) -> 0 | AC53: Exonerado | AD53: =IF(AND(L53>0, M53>=8, NOT(OR(Y53="C", Y53="c"))), "CORTE", "") | AE53: =IF( OR( AND(#REF!>0, OR(Y53="C", Y53="c"), U53<0), AND(#REF!>0, Y53="") ), "CORTE", "" ) -> #REF! | AF53: =IF(AND(LEN(Y53)>0,LEN(AA53)=0),V53,0) -> 0 | AG53: =IF(AND(LEN(Y53)>0,TRIM(AA53)="Y"),V53,0) -> 0 | AH53: =TRIM(UPPER(C53)) -> C | AI53: =TRIM(UPPER(C53)) & "-" & TRIM(UPPER(D53)) -> C-21
A54: 53 | B54: ABRAHAM BARRERA VEGA | C54: C | D54: 22 | H54: 1 | I54: 126 | J54: 134 | K54: 8 | L54: 8 | N54: 0 | P54: 3 | V54: =SUM(L54:Q54) -> 11 | W54: =IFERROR(__xludf.DUMMYFUNCTION("IFERROR( SUM( FILTER( Reporte!$E:$E, REGEXMATCH(Reporte!$A:$A, ""(?i)(TE PAGÓ|PAGASTE)""), Reporte!$H:$H & """" = AH54 & """" ) ), 0 )"),11) -> 11 | X54: =IFERROR(__xludf.DUMMYFUNCTION("IFERROR( SUM( FILTER( Efectivo!$C:$C, Efectivo!$D:$D & """" = AH54 & """" ) ), 0 )"),0) -> 0 | Y54: c | AA54: y | AD54: =IF(AND(L54>0, M54>=8, NOT(OR(Y54="C", Y54="c"))), "CORTE", "") | AE54: =IF( OR( AND(#REF!>0, OR(Y54="C", Y54="c"), U54<0), AND(#REF!>0, Y54="") ), "CORTE", "" ) -> #REF! | AF54: =IF(AND(LEN(Y54)>0,LEN(AA54)=0),V54,0) -> 0 | AG54: =IF(AND(LEN(Y54)>0,TRIM(AA54)="Y"),V54,0) -> 11 | AH54: =TRIM(UPPER(C54)) -> C | AI54: =TRIM(UPPER(C54)) & "-" & TRIM(UPPER(D54)) -> C-22
A55: 54 | B55: ANTONIA MAYO TRUJILLO | C55: C | D55: 23 | H55: 1 | I55: 257 | J55: 280 | K55: 23 | L55: 23 | N55: 0 | P55: 3 | V55: =SUM(L55:U55) -> 26 | W55: =IFERROR(__xludf.DUMMYFUNCTION("IFERROR( SUM( FILTER( Reporte!$E:$E, REGEXMATCH(Reporte!$A:$A, ""(?i)(TE PAGÓ|PAGASTE)""), Reporte!$H:$H & """" = AH55 & """" ) ), 0 )"),0) -> 0 | X55: =IFERROR(__xludf.DUMMYFUNCTION("IFERROR( SUM( FILTER( Efectivo!$C:$C, Efectivo!$D:$D & """" = AH55 & """" ) ), 0 )"),26) -> 26 | Y55: c | AD55: =IF(AND(L55>0, M55>=8, NOT(OR(Y55="C", Y55="c"))), "CORTE", "") | AE55: =IF( OR( AND(#REF!>0, OR(Y55="C", Y55="c"), U55<0), AND(#REF!>0, Y55="") ), "CORTE", "" ) -> #REF! | AF55: =IF(AND(LEN(Y55)>0,LEN(AA55)=0),V55,0) -> 26 | AG55: =IF(AND(LEN(Y55)>0,TRIM(AA55)="Y"),V55,0) -> 0 | AH55: =TRIM(UPPER(C55)) -> C | AI55: =TRIM(UPPER(C55)) & "-" & TRIM(UPPER(D55)) -> C-23
A56: 55 | B56: ALFREDO CARLOS VENTURO CAPCHA | C56: C | D56: 24 | H56: 1 | I56: 543 | J56: 546 | K56: 3 | L56: 5 | N56: 0 | P56: 3 | V56: =SUM(L56:Q56) -> 8 | W56: =IFERROR(__xludf.DUMMYFUNCTION("IFERROR( SUM( FILTER( Reporte!$E:$E, REGEXMATCH(Reporte!$A:$A, ""(?i)(TE PAGÓ|PAGASTE)""), Reporte!$H:$H & """" = AH56 & """" ) ), 0 )"),0) -> 0 | X56: =IFERROR(__xludf.DUMMYFUNCTION("IFERROR( SUM( FILTER( Efectivo!$C:$C, Efectivo!$D:$D & """" = AH56 & """" ) ), 0 )"),8) -> 8 | Y56: c | AD56: =IF(AND(L56>0, M56>=8, NOT(OR(Y56="C", Y56="c"))), "CORTE", "") | AE56: =IF( OR( AND(#REF!>0, OR(Y56="C", Y56="c"), U56<0), AND(#REF!>0, Y56="") ), "CORTE", "" ) -> #REF! | AF56: =IF(AND(LEN(Y56)>0,LEN(AA56)=0),V56,0) -> 8 | AG56: =IF(AND(LEN(Y56)>0,TRIM(AA56)="Y"),V56,0) -> 0 | AH56: =TRIM(UPPER(C56)) -> C | AI56: =TRIM(UPPER(C56)) & "-" & TRIM(UPPER(D56)) -> C-24
A57: 56 | B57: JULIO HUERTA MILLA | C57: C | D57: 25 | H57: 1 | I57: 6 | J57: 22 | K57: 16 | L57: 16 | N57: 0 | O57: 15 | P57: 3 | V57: =SUM(L57:U57) -> 34 | W57: =IFERROR(__xludf.DUMMYFUNCTION("IFERROR( SUM( FILTER( Reporte!$E:$E, REGEXMATCH(Reporte!$A:$A, ""(?i)(TE PAGÓ|PAGASTE)""), Reporte!$H:$H & """" = AH57 & """" ) ), 0 )"),0) -> 0 | X57: =IFERROR(__xludf.DUMMYFUNCTION("IFERROR( SUM( FILTER( Efectivo!$C:$C, Efectivo!$D:$D & """" = AH57 & """" ) ), 0 )"),34) -> 34 | Y57: c | AD57: =IF(AND(L57>0, M57>=8, NOT(OR(Y57="C", Y57="c"))), "CORTE", "") | AE57: =IF( OR( AND(#REF!>0, OR(Y57="C", Y57="c"), U57<0), AND(#REF!>0, Y57="") ), "CORTE", "" ) -> #REF! | AF57: =IF(AND(LEN(Y57)>0,LEN(AA57)=0),V57,0) -> 34 | AG57: =IF(AND(LEN(Y57)>0,TRIM(AA57)="Y"),V57,0) -> 0 | AH57: =TRIM(UPPER(C57)) -> C | AI57: =TRIM(UPPER(C57)) & "-" & TRIM(UPPER(D57)) -> C-25
A58: 57 | B58: CORCINO RODRIGUEZ RIVERA | C58: C | D58: 26 | H58: 1 | I58: 1509 | J58: 1510 | K58: 1 | L58: 5 | N58: 0 | P58: 3 | V58: =SUM(L58:Q58) -> 8 | W58: =IFERROR(__xludf.DUMMYFUNCTION("IFERROR( SUM( FILTER( Reporte!$E:$E, REGEXMATCH(Reporte!$A:$A, ""(?i)(TE PAGÓ|PAGASTE)""), Reporte!$H:$H & """" = AH58 & """" ) ), 0 )"),0) -> 0 | X58: =IFERROR(__xludf.DUMMYFUNCTION("IFERROR( SUM( FILTER( Efectivo!$C:$C, Efectivo!$D:$D & """" = AH58 & """" ) ), 0 )"),0) -> 0 | AD58: =IF(AND(L58>0, M58>=8, NOT(OR(Y58="C", Y58="c"))), "CORTE", "") | AE58: =IF( OR( AND(#REF!>0, OR(Y58="C", Y58="c"), U58<0), AND(#REF!>0, Y58="") ), "CORTE", "" ) -> #REF! | AF58: =IF(AND(LEN(Y58)>0,LEN(AA58)=0),V58,0) -> 0 | AG58: =IF(AND(LEN(Y58)>0,TRIM(AA58)="Y"),V58,0) -> 0 | AH58: =TRIM(UPPER(C58)) -> C | AI58: =TRIM(UPPER(C58)) & "-" & TRIM(UPPER(D58)) -> C-26
A59: 58 | B59: NANCY VALERIANA FLORES LEON | C59: C | D59: 27 | H59: 1 | I59: 240 | J59: 256 | K59: 16 | L59: 16 | N59: 0 | P59: 3 | V59: =SUM(L59:U59) -> 19 | W59: =IFERROR(__xludf.DUMMYFUNCTION("IFERROR( SUM( FILTER( Reporte!$E:$E, REGEXMATCH(Reporte!$A:$A, ""(?i)(TE PAGÓ|PAGASTE)""), Reporte!$H:$H & """" = AH59 & """" ) ), 0 )"),0) -> 0 | X59: =IFERROR(__xludf.DUMMYFUNCTION("IFERROR( SUM( FILTER( Efectivo!$C:$C, Efectivo!$D:$D & """" = AH59 & """" ) ), 0 )"),19) -> 19 | Y59: c | AD59: =IF(AND(L59>0, M59>=8, NOT(OR(Y59="C", Y59="c"))), "CORTE", "") | AE59: =IF( OR( AND(#REF!>0, OR(Y59="C", Y59="c"), U59<0), AND(#REF!>0, Y59="") ), "CORTE", "" ) -> #REF! | AF59: =IF(AND(LEN(Y59)>0,LEN(AA59)=0),V59,0) -> 19 | AG59: =IF(AND(LEN(Y59)>0,TRIM(AA59)="Y"),V59,0) -> 0 | AH59: =TRIM(UPPER(C59)) -> C | AI59: =TRIM(UPPER(C59)) & "-" & TRIM(UPPER(D59)) -> C-27
A60: 59 | B60: OSTIN AGÜERO TRUJILLO | C60: C | D60: 28 | H60: 1 | I60: 2 | J60: 10 | K60: 8 | L60: 8 | N60: 0 | P60: 3 | V60: =SUM(L60:Q60) -> 11 | W60: =IFERROR(__xludf.DUMMYFUNCTION("IFERROR( SUM( FILTER( Reporte!$E:$E, REGEXMATCH(Reporte!$A:$A, ""(?i)(TE PAGÓ|PAGASTE)""), Reporte!$H:$H & """" = AH60 & """" ) ), 0 )"),11) -> 11 | X60: =IFERROR(__xludf.DUMMYFUNCTION("IFERROR( SUM( FILTER( Efectivo!$C:$C, Efectivo!$D:$D & """" = AH60 & """" ) ), 0 )"),0) -> 0 | Y60: c | AA60: y | AD60: =IF(AND(L60>0, M60>=8, NOT(OR(Y60="C", Y60="c"))), "CORTE", "") | AE60: =IF( OR( AND(#REF!>0, OR(Y60="C", Y60="c"), U60<0), AND(#REF!>0, Y60="") ), "CORTE", "" ) -> #REF! | AF60: =IF(AND(LEN(Y60)>0,LEN(AA60)=0),V60,0) -> 0 | AG60: =IF(AND(LEN(Y60)>0,TRIM(AA60)="Y"),V60,0) -> 11 | AH60: =TRIM(UPPER(C60)) -> C | AI60: =TRIM(UPPER(C60)) & "-" & TRIM(UPPER(D60)) -> C-28
A61: 60 | B61: SONIA CERNA MELGAREJO | C61: C | D61: 30 | H61: 1 | I61: 3572 | J61: 3591 | K61: 19 | L61: 19 | N61: 0 | P61: 3 | V61: =SUM(L61:Q61) -> 22 | W61: =IFERROR(__xludf.DUMMYFUNCTION("IFERROR( SUM( FILTER( Reporte!$E:$E, REGEXMATCH(Reporte!$A:$A, ""(?i)(TE PAGÓ|PAGASTE)""), Reporte!$H:$H & """" = AH61 & """" ) ), 0 )"),0) -> 0 | X61: =IFERROR(__xludf.DUMMYFUNCTION("IFERROR( SUM( FILTER( Efectivo!$C:$C, Efectivo!$D:$D & """" = AH61 & """" ) ), 0 )"),0) -> 0 | AD61: =IF(AND(L61>0, M61>=8, NOT(OR(Y61="C", Y61="c"))), "CORTE", "") | AE61: =IF( OR( AND(#REF!>0, OR(Y61="C", Y61="c"), U61<0), AND(#REF!>0, Y61="") ), "CORTE", "" ) -> #REF! | AF61: =IF(AND(LEN(Y61)>0,LEN(AA61)=0),V61,0) -> 0 | AG61: =IF(AND(LEN(Y61)>0,TRIM(AA61)="Y"),V61,0) -> 0 | AH61: =TRIM(UPPER(C61)) -> C | AI61: =TRIM(UPPER(C61)) & "-" & TRIM(UPPER(D61)) -> C-30
A62: 61 | B62: IGLESIA ADVENTISTA DEL SEPTIMO DIA | C62: C | D62: 31 | H62: 1 | I62: 692 | J62: 701 | K62: 9 | L62: 9 | N62: 0 | P62: 3 | V62: =SUM(L62:Q62) -> 12 | W62: =IFERROR(__xludf.DUMMYFUNCTION("IFERROR( SUM( FILTER( Reporte!$E:$E, REGEXMATCH(Reporte!$A:$A, ""(?i)(TE PAGÓ|PAGASTE)""), Reporte!$H:$H & """" = AH62 & """" ) ), 0 )"),0) -> 0 | X62: =IFERROR(__xludf.DUMMYFUNCTION("IFERROR( SUM( FILTER( Efectivo!$C:$C, Efectivo!$D:$D & """" = AH62 & """" ) ), 0 )"),0) -> 0 | AD62: =IF(AND(L62>0, M62>=8, NOT(OR(Y62="C", Y62="c"))), "CORTE", "") | AE62: =IF( OR( AND(#REF!>0, OR(Y62="C", Y62="c"), U62<0), AND(#REF!>0, Y62="") ), "CORTE", "" ) -> #REF! | AF62: =IF(AND(LEN(Y62)>0,LEN(AA62)=0),V62,0) -> 0 | AG62: =IF(AND(LEN(Y62)>0,TRIM(AA62)="Y"),V62,0) -> 0 | AH62: =TRIM(UPPER(C62)) -> C | AI62: =TRIM(UPPER(C62)) & "-" & TRIM(UPPER(D62)) -> C-31
A63: 62 | B63: FAUSTA HUERTA AGAMA | C63: C | D63: 32 | H63: 1 | I63: 1 | J63: 5 | K63: 4 | L63: 5 | N63: 0 | O63: 25 | P63: 3 | V63: =SUM(L63:Q63) -> 33 | W63: =IFERROR(__xludf.DUMMYFUNCTION("IFERROR( SUM( FILTER( Reporte!$E:$E, REGEXMATCH(Reporte!$A:$A, ""(?i)(TE PAGÓ|PAGASTE)""), Reporte!$H:$H & """" = AH63 & """" ) ), 0 )"),0) -> 0 | X63: =IFERROR(__xludf.DUMMYFUNCTION("IFERROR( SUM( FILTER( Efectivo!$C:$C, Efectivo!$D:$D & """" = AH63 & """" ) ), 0 )"),33) -> 33 | Y63: c | AD63: =IF(AND(L63>0, M63>=8, NOT(OR(Y63="C", Y63="c"))), "CORTE", "") | AE63: =IF( OR( AND(#REF!>0, OR(Y63="C", Y63="c"), U63<0), AND(#REF!>0, Y63="") ), "CORTE", "" ) -> #REF! | AF63: =IF(AND(LEN(Y63)>0,LEN(AA63)=0),V63,0) -> 33 | AG63: =IF(AND(LEN(Y63)>0,TRIM(AA63)="Y"),V63,0) -> 0 | AH63: =TRIM(UPPER(C63)) -> C | AI63: =TRIM(UPPER(C63)) & "-" & TRIM(UPPER(D63)) -> C-32
A64: 63 | B64: EDITA ROMERO MAYO | C64: C | D64: 33 | H64: 1 | I64: 334 | J64: 348 | K64: 14 | L64: 14 | N64: 0 | P64: 3 | V64: =SUM(L64:Q64) -> 17 | W64: =IFERROR(__xludf.DUMMYFUNCTION("IFERROR( SUM( FILTER( Reporte!$E:$E, REGEXMATCH(Reporte!$A:$A, ""(?i)(TE PAGÓ|PAGASTE)""), Reporte!$H:$H & """" = AH64 & """" ) ), 0 )"),0) -> 0 | X64: =IFERROR(__xludf.DUMMYFUNCTION("IFERROR( SUM( FILTER( Efectivo!$C:$C, Efectivo!$D:$D & """" = AH64 & """" ) ), 0 )"),17) -> 17 | Y64: c | AD64: =IF(AND(L64>0, M64>=8, NOT(OR(Y64="C", Y64="c"))), "CORTE", "") | AE64: =IF( OR( AND(#REF!>0, OR(Y64="C", Y64="c"), U64<0), AND(#REF!>0, Y64="") ), "CORTE", "" ) -> #REF! | AF64: =IF(AND(LEN(Y64)>0,LEN(AA64)=0),V64,0) -> 17 | AG64: =IF(AND(LEN(Y64)>0,TRIM(AA64)="Y"),V64,0) -> 0 | AH64: =TRIM(UPPER(C64)) -> C | AI64: =TRIM(UPPER(C64)) & "-" & TRIM(UPPER(D64)) -> C-33
A65: 64 | B65: EBER AGÜERO TRUJILLO | C65: C | D65: 34 | E65: C | H65: 1 | I65: 18 | J65: 23 | K65: 5 | L65: 5 | N65: 0 | P65: 3 | V65: =SUM(L65:Q65) -> 8 | W65: =IFERROR(__xludf.DUMMYFUNCTION("IFERROR( SUM( FILTER( Reporte!$E:$E, REGEXMATCH(Reporte!$A:$A, ""(?i)(TE PAGÓ|PAGASTE)""), Reporte!$H:$H & """" = AH65 & """" ) ), 0 )"),8) -> 8 | X65: =IFERROR(__xludf.DUMMYFUNCTION("IFERROR( SUM( FILTER( Efectivo!$C:$C, Efectivo!$D:$D & """" = AH65 & """" ) ), 0 )"),0) -> 0 | Y65: c | AA65: y | AD65: =IF(AND(L65>0, M65>=8, NOT(OR(Y65="C", Y65="c"))), "CORTE", "") | AE65: =IF( OR( AND(#REF!>0, OR(Y65="C", Y65="c"), U65<0), AND(#REF!>0, Y65="") ), "CORTE", "" ) -> #REF! | AF65: =IF(AND(LEN(Y65)>0,LEN(AA65)=0),V65,0) -> 0 | AG65: =IF(AND(LEN(Y65)>0,TRIM(AA65)="Y"),V65,0) -> 8 | AH65: =TRIM(UPPER(C65)) -> C | AI65: =TRIM(UPPER(C65)) & "-" & TRIM(UPPER(D65)) -> C-34
A66: 65 | B66: ANALY QUINECHE MORANTE | C66: C | D66: 35 | H66: 1 | I66: 616 | J66: 634 | K66: 18 | L66: 18 | M66: 18 | N66: 20 | P66: 3 | Q66: 20 | V66: =SUM(L66:U66) -> 79 | W66: =IFERROR(__xludf.DUMMYFUNCTION("IFERROR( SUM( FILTER( Reporte!$E:$E, REGEXMATCH(Reporte!$A:$A, ""(?i)(TE PAGÓ|PAGASTE)""), Reporte!$H:$H & """" = AH66 & """" ) ), 0 )"),79) -> 79 | X66: =IFERROR(__xludf.DUMMYFUNCTION("IFERROR( SUM( FILTER( Efectivo!$C:$C, Efectivo!$D:$D & """" = AH66 & """" ) ), 0 )"),0) -> 0 | Y66: c | AA66: y | AB66: Debe 10 faena | AD66: =IF(AND(L66>0, M66>=8, NOT(OR(Y66="C", Y66="c"))), "CORTE", "") | AE66: =IF( OR( AND(#REF!>0, OR(Y66="C", Y66="c"), U66<0), AND(#REF!>0, Y66="") ), "CORTE", "" ) -> #REF! | AF66: =IF(AND(LEN(Y66)>0,LEN(AA66)=0),V66,0) -> 0 | AG66: =IF(AND(LEN(Y66)>0,TRIM(AA66)="Y"),V66,0) -> 79 | AH66: =TRIM(UPPER(C66)) -> C | AI66: =TRIM(UPPER(C66)) & "-" & TRIM(UPPER(D66)) -> C-35
A67: 66 | B67: MARIA NORABUENA ESPADA | C67: C | D67: 36 | H67: 1 | I67: 265 | J67: 271 | K67: 6 | L67: 6 | N67: 0 | P67: 3 | V67: =SUM(L67:Q67) -> 9 | W67: =IFERROR(__xludf.DUMMYFUNCTION("IFERROR( SUM( FILTER( Reporte!$E:$E, REGEXMATCH(Reporte!$A:$A, ""(?i)(TE PAGÓ|PAGASTE)""), Reporte!$H:$H & """" = AH67 & """" ) ), 0 )"),9) -> 9 | X67: =IFERROR(__xludf.DUMMYFUNCTION("IFERROR( SUM( FILTER( Efectivo!$C:$C, Efectivo!$D:$D & """" = AH67 & """" ) ), 0 )"),0) -> 0 | Y67: c | AA67: y | AD67: =IF(AND(L67>0, M67>=8, NOT(OR(Y67="C", Y67="c"))), "CORTE", "") | AE67: =IF( OR( AND(#REF!>0, OR(Y67="C", Y67="c"), U67<0), AND(#REF!>0, Y67="") ), "CORTE", "" ) -> #REF! | AF67: =IF(AND(LEN(Y67)>0,LEN(AA67)=0),V67,0) -> 0 | AG67: =IF(AND(LEN(Y67)>0,TRIM(AA67)="Y"),V67,0) -> 9 | AH67: =TRIM(UPPER(C67)) -> C | AI67: =TRIM(UPPER(C67)) & "-" & TRIM(UPPER(D67)) -> C-36
A68: 67 | B68: RAQUEL SORIA BUSTAMANTE | C68: C | D68: 37 | H68: 1 | I68: 286 | J68: 296 | K68: 10 | L68: 10 | N68: 0 | P68: 3 | V68: =SUM(L68:Q68) -> 13 | W68: =IFERROR(__xludf.DUMMYFUNCTION("IFERROR( SUM( FILTER( Reporte!$E:$E, REGEXMATCH(Reporte!$A:$A, ""(?i)(TE PAGÓ|PAGASTE)""), Reporte!$H:$H & """" = AH68 & """" ) ), 0 )"),0) -> 0 | X68: =IFERROR(__xludf.DUMMYFUNCTION("IFERROR( SUM( FILTER( Efectivo!$C:$C, Efectivo!$D:$D & """" = AH68 & """" ) ), 0 )"),13) -> 13 | Y68: c | AD68: =IF(AND(L68>0, M68>=8, NOT(OR(Y68="C", Y68="c"))), "CORTE", "") | AE68: =IF( OR( AND(#REF!>0, OR(Y68="C", Y68="c"), U68<0), AND(#REF!>0, Y68="") ), "CORTE", "" ) -> #REF! | AF68: =IF(AND(LEN(Y68)>0,LEN(AA68)=0),V68,0) -> 13 | AG68: =IF(AND(LEN(Y68)>0,TRIM(AA68)="Y"),V68,0) -> 0 | AH68: =TRIM(UPPER(C68)) -> C | AI68: =TRIM(UPPER(C68)) & "-" & TRIM(UPPER(D68)) -> C-37
A69: 68 | B69: JANET ROMERO MAYO | C69: C | D69: 42 | E69: N | H69: 1 | I69: 312 | J69: 327 | K69: 15 | L69: 15 | N69: 0 | P69: 3 | V69: =SUM(L69:Q69) -> 18 | W69: =IFERROR(__xludf.DUMMYFUNCTION("IFERROR( SUM( FILTER( Reporte!$E:$E, REGEXMATCH(Reporte!$A:$A, ""(?i)(TE PAGÓ|PAGASTE)""), Reporte!$H:$H & """" = AH69 & """" ) ), 0 )"),0) -> 0 | X69: =IFERROR(__xludf.DUMMYFUNCTION("IFERROR( SUM( FILTER( Efectivo!$C:$C, Efectivo!$D:$D & """" = AH69 & """" ) ), 0 )"),0) -> 0 | AD69: =IF(AND(L69>0, M69>=8, NOT(OR(Y69="C", Y69="c"))), "CORTE", "") | AE69: =IF( OR( AND(#REF!>0, OR(Y69="C", Y69="c"), U69<0), AND(#REF!>0, Y69="") ), "CORTE", "" ) -> #REF! | AF69: =IF(AND(LEN(Y69)>0,LEN(AA69)=0),V69,0) -> 0 | AG69: =IF(AND(LEN(Y69)>0,TRIM(AA69)="Y"),V69,0) -> 0 | AH69: =TRIM(UPPER(C69)) -> C | AI69: =TRIM(UPPER(C69)) & "-" & TRIM(UPPER(D69)) -> C-42
A70: 69 | B70: JANET EVARISTO COCHACHIN | C70: C | D70: 45 | H70: 1 | I70: 0 | J70: 0 | K70: 5 | L70: 5 | N70: 0 | O70: 50 | P70: 3 | V70: =SUM(L70:U70) -> 58 | W70: =IFERROR(__xludf.DUMMYFUNCTION("IFERROR( SUM( FILTER( Reporte!$E:$E, REGEXMATCH(Reporte!$A:$A, ""(?i)(TE PAGÓ|PAGASTE)""), Reporte!$H:$H & """" = AH70 & """" ) ), 0 )"),58) -> 58 | X70: =IFERROR(__xludf.DUMMYFUNCTION("IFERROR( SUM( FILTER( Efectivo!$C:$C, Efectivo!$D:$D & """" = AH70 & """" ) ), 0 )"),0) -> 0 | Y70: c | AA70: y | AD70: =IF(AND(L70>0, M70>=8, NOT(OR(Y70="C", Y70="c"))), "CORTE", "") | AE70: =IF( OR( AND(#REF!>0, OR(Y70="C", Y70="c"), U70<0), AND(#REF!>0, Y70="") ), "CORTE", "" ) -> #REF! | AF70: =IF(AND(LEN(Y70)>0,LEN(AA70)=0),V70,0) -> 0 | AG70: =IF(AND(LEN(Y70)>0,TRIM(AA70)="Y"),V70,0) -> 58 | AH70: =TRIM(UPPER(C70)) -> C | AI70: =TRIM(UPPER(C70)) & "-" & TRIM(UPPER(D70)) -> C-45
A71: 70 | B71: JUAN VENTURO CAPCHA | C71: D | D71: 1 | H71: 1 | I71: 1787 | J71: 13 | K71: 13 | L71: 13 | M71: 14 | N71: 0 | O71: 25 | P71: 3 | V71: =SUM(L71:Q71) -> 55 | W71: =IFERROR(__xludf.DUMMYFUNCTION("IFERROR( SUM( FILTER( Reporte!$E:$E, REGEXMATCH(Reporte!$A:$A, ""(?i)(TE PAGÓ|PAGASTE)""), Reporte!$H:$H & """" = AH71 & """" ) ), 0 )"),55) -> 55 | X71: =IFERROR(__xludf.DUMMYFUNCTION("IFERROR( SUM( FILTER( Efectivo!$C:$C, Efectivo!$D:$D & """" = AH71 & """" ) ), 0 )"),0) -> 0 | Y71: c | AA71: y | AD71: =IF(AND(L71>0, M71>=8, NOT(OR(Y71="C", Y71="c"))), "CORTE", "") | AE71: =IF( OR( AND(#REF!>0, OR(Y71="C", Y71="c"), U71<0), AND(#REF!>0, Y71="") ), "CORTE", "" ) -> #REF! | AF71: =IF(AND(LEN(Y71)>0,LEN(AA71)=0),V71,0) -> 0 | AG71: =IF(AND(LEN(Y71)>0,TRIM(AA71)="Y"),V71,0) -> 55 | AH71: =TRIM(UPPER(C71)) -> D | AI71: =TRIM(UPPER(C71)) & "-" & TRIM(UPPER(D71)) -> D-1
A72: 71 | B72: VICTOR TRUJILLO POLICARPIO | C72: D | D72: 2 | H72: 1 | I72: 2276 | J72: 2303 | K72: 27 | L72: 27 | M72: 17 | N72: 0 | P72: 3 | V72: =SUM(L72:Q72) -> 47 | W72: =IFERROR(__xludf.DUMMYFUNCTION("IFERROR( SUM( FILTER( Reporte!$E:$E, REGEXMATCH(Reporte!$A:$A, ""(?i)(TE PAGÓ|PAGASTE)""), Reporte!$H:$H & """" = AH72 & """" ) ), 0 )"),47) -> 47 | X72: =IFERROR(__xludf.DUMMYFUNCTION("IFERROR( SUM( FILTER( Efectivo!$C:$C, Efectivo!$D:$D & """" = AH72 & """" ) ), 0 )"),0) -> 0 | Y72: c | AA72: y | AD72: =IF(AND(L72>0, M72>=8, NOT(OR(Y72="C", Y72="c"))), "CORTE", "") | AE72: =IF( OR( AND(#REF!>0, OR(Y72="C", Y72="c"), U72<0), AND(#REF!>0, Y72="") ), "CORTE", "" ) -> #REF! | AF72: =IF(AND(LEN(Y72)>0,LEN(AA72)=0),V72,0) -> 0 | AG72: =IF(AND(LEN(Y72)>0,TRIM(AA72)="Y"),V72,0) -> 47 | AH72: =TRIM(UPPER(C72)) -> D | AI72: =TRIM(UPPER(C72)) & "-" & TRIM(UPPER(D72)) -> D-2
A73: 72 | B73: ANTONIO CASTILLEJO CUEVA | C73: D | D73: 3 | H73: 1 | I73: 4 | J73: 16 | K73: 12 | L73: 12 | N73: 0 | O73: 25 | P73: 3 | V73: =SUM(L73:Q73) -> 40 | W73: =IFERROR(__xludf.DUMMYFUNCTION("IFERROR( SUM( FILTER( Reporte!$E:$E, REGEXMATCH(Reporte!$A:$A, ""(?i)(TE PAGÓ|PAGASTE)""), Reporte!$H:$H & """" = AH73 & """" ) ), 0 )"),40) -> 40 | X73: =IFERROR(__xludf.DUMMYFUNCTION("IFERROR( SUM( FILTER( Efectivo!$C:$C, Efectivo!$D:$D & """" = AH73 & """" ) ), 0 )"),0) -> 0 | Y73: c | AA73: y | AD73: =IF(AND(L73>0, M73>=8, NOT(OR(Y73="C", Y73="c"))), "CORTE", "") | AE73: =IF( OR( AND(#REF!>0, OR(Y73="C", Y73="c"), U73<0), AND(#REF!>0, Y73="") ), "CORTE", "" ) -> #REF! | AF73: =IF(AND(LEN(Y73)>0,LEN(AA73)=0),V73,0) -> 0 | AG73: =IF(AND(LEN(Y73)>0,TRIM(AA73)="Y"),V73,0) -> 40 | AH73: =TRIM(UPPER(C73)) -> D | AI73: =TRIM(UPPER(C73)) & "-" & TRIM(UPPER(D73)) -> D-3
A74: 73 | B74: JULIO CESAR PRINCIPE LUNA | C74: D | D74: 4 | H74: 1 | I74: 346 | J74: 368 | K74: 22 | L74: 22 | N74: 0 | P74: 3 | V74: =SUM(L74:Q74) -> 25 | W74: =IFERROR(__xludf.DUMMYFUNCTION("IFERROR( SUM( FILTER( Reporte!$E:$E, REGEXMATCH(Reporte!$A:$A, ""(?i)(TE PAGÓ|PAGASTE)""), Reporte!$H:$H & """" = AH74 & """" ) ), 0 )"),25) -> 25 | X74: =IFERROR(__xludf.DUMMYFUNCTION("IFERROR( SUM( FILTER( Efectivo!$C:$C, Efectivo!$D:$D & """" = AH74 & """" ) ), 0 )"),0) -> 0 | Y74: c | AA74: y | AD74: =IF(AND(L74>0, M74>=8, NOT(OR(Y74="C", Y74="c"))), "CORTE", "") | AE74: =IF( OR( AND(#REF!>0, OR(Y74="C", Y74="c"), U74<0), AND(#REF!>0, Y74="") ), "CORTE", "" ) -> #REF! | AF74: =IF(AND(LEN(Y74)>0,LEN(AA74)=0),V74,0) -> 0 | AG74: =IF(AND(LEN(Y74)>0,TRIM(AA74)="Y"),V74,0) -> 25 | AH74: =TRIM(UPPER(C74)) -> D | AI74: =TRIM(UPPER(C74)) & "-" & TRIM(UPPER(D74)) -> D-4
A75: 74 | B75: TERESA PAULA JARA DE FERNANDEZ | C75: D | D75: 5 | H75: 1 | I75: 573 | J75: 609 | K75: 36 | L75: 36 | N75: 0 | P75: 3 | V75: =SUM(L75:Q75) -> 39 | W75: =IFERROR(__xludf.DUMMYFUNCTION("IFERROR( SUM( FILTER( Reporte!$E:$E, REGEXMATCH(Reporte!$A:$A, ""(?i)(TE PAGÓ|PAGASTE)""), Reporte!$H:$H & """" = AH75 & """" ) ), 0 )"),0) -> 0 | X75: =IFERROR(__xludf.DUMMYFUNCTION("IFERROR( SUM( FILTER( Efectivo!$C:$C, Efectivo!$D:$D & """" = AH75 & """" ) ), 0 )"),39) -> 39 | Y75: c | AD75: =IF(AND(L75>0, M75>=8, NOT(OR(Y75="C", Y75="c"))), "CORTE", "") | AE75: =IF( OR( AND(#REF!>0, OR(Y75="C", Y75="c"), U75<0), AND(#REF!>0, Y75="") ), "CORTE", "" ) -> #REF! | AF75: =IF(AND(LEN(Y75)>0,LEN(AA75)=0),V75,0) -> 39 | AG75: =IF(AND(LEN(Y75)>0,TRIM(AA75)="Y"),V75,0) -> 0 | AH75: =TRIM(UPPER(C75)) -> D | AI75: =TRIM(UPPER(C75)) & "-" & TRIM(UPPER(D75)) -> D-5
A76: 75 | B76: HERMELINDA JARA TRUJILLO | C76: D | D76: 6 | F76: 1 | H76: 1 | I76: 32 | J76: 99 | K76: 67 | L76: 67 | N76: 0 | O76: 25 | P76: 3 | V76: =SUM(L76:Q76) -> 95 | W76: =IFERROR(__xludf.DUMMYFUNCTION("IFERROR( SUM( FILTER( Reporte!$E:$E, REGEXMATCH(Reporte!$A:$A, ""(?i)(TE PAGÓ|PAGASTE)""), Reporte!$H:$H & """" = AH76 & """" ) ), 0 )"),95) -> 95 | X76: =IFERROR(__xludf.DUMMYFUNCTION("IFERROR( SUM( FILTER( Efectivo!$C:$C, Efectivo!$D:$D & """" = AH76 & """" ) ), 0 )"),0) -> 0 | Y76: c | AA76: y | AD76: =IF(AND(L76>0, M76>=8, NOT(OR(Y76="C", Y76="c"))), "CORTE", "") | AE76: =IF( OR( AND(#REF!>0, OR(Y76="C", Y76="c"), U76<0), AND(#REF!>0, Y76="") ), "CORTE", "" ) -> #REF! | AF76: =IF(AND(LEN(Y76)>0,LEN(AA76)=0),V76,0) -> 0 | AG76: =IF(AND(LEN(Y76)>0,TRIM(AA76)="Y"),V76,0) -> 95 | AH76: =TRIM(UPPER(C76)) -> D | AI76: =TRIM(UPPER(C76)) & "-" & TRIM(UPPER(D76)) -> D-6
A77: 76 | B77: MAXIMILIANO JARA NIETO | C77: D | D77: 7 | H77: 1 | I77: 5641 | J77: 5733 | K77: 92 | L77: 92 | N77: 0 | P77: 3 | V77: =SUM(L77:Q77) -> 95 | W77: =IFERROR(__xludf.DUMMYFUNCTION("IFERROR( SUM( FILTER( Reporte!$E:$E, REGEXMATCH(Reporte!$A:$A, ""(?i)(TE PAGÓ|PAGASTE)""), Reporte!$H:$H & """" = AH77 & """" ) ), 0 )"),0) -> 0 | X77: =IFERROR(__xludf.DUMMYFUNCTION("IFERROR( SUM( FILTER( Efectivo!$C:$C, Efectivo!$D:$D & """" = AH77 & """" ) ), 0 )"),0) -> 0 | AD77: =IF(AND(L77>0, M77>=8, NOT(OR(Y77="C", Y77="c"))), "CORTE", "") | AE77: =IF( OR( AND(#REF!>0, OR(Y77="C", Y77="c"), U77<0), AND(#REF!>0, Y77="") ), "CORTE", "" ) -> #REF! | AF77: =IF(AND(LEN(Y77)>0,LEN(AA77)=0),V77,0) -> 0 | AG77: =IF(AND(LEN(Y77)>0,TRIM(AA77)="Y"),V77,0) -> 0 | AH77: =TRIM(UPPER(C77)) -> D | AI77: =TRIM(UPPER(C77)) & "-" & TRIM(UPPER(D77)) -> D-7
A78: 77 | B78: SANTA ANTONIA SAENZ TICLIO | C78: D | D78: 8 | F78: 1 | H78: 1 | I78: 4 | J78: 17 | K78: 13 | L78: 13 | M78: 8 | N78: 0 | O78: 25 | P78: 3 | V78: =SUM(L78:U78) -> 49 | W78: =IFERROR(__xludf.DUMMYFUNCTION("IFERROR( SUM( FILTER( Reporte!$E:$E, REGEXMATCH(Reporte!$A:$A, ""(?i)(TE PAGÓ|PAGASTE)""), Reporte!$H:$H & """" = AH78 & """" ) ), 0 )"),49) -> 49 | X78: =IFERROR(__xludf.DUMMYFUNCTION("IFERROR( SUM( FILTER( Efectivo!$C:$C, Efectivo!$D:$D & """" = AH78 & """" ) ), 0 )"),0) -> 0 | Y78: c | AA78: y | AB78: Debe 20 faena | AD78: =IF(AND(L78>0, M78>=8, NOT(OR(Y78="C", Y78="c"))), "CORTE", "") | AE78: =IF( OR( AND(#REF!>0, OR(Y78="C", Y78="c"), U78<0), AND(#REF!>0, Y78="") ), "CORTE", "" ) -> #REF! | AF78: =IF(AND(LEN(Y78)>0,LEN(AA78)=0),V78,0) -> 0 | AG78: =IF(AND(LEN(Y78)>0,TRIM(AA78)="Y"),V78,0) -> 49 | AH78: =TRIM(UPPER(C78)) -> D | AI78: =TRIM(UPPER(C78)) & "-" & TRIM(UPPER(D78)) -> D-8
A79: 78 | B79: RUFINA CABELLO TICLIO | C79: D | D79: 9 | H79: 1 | I79: 4108 | J79: 4120 | K79: 12 | L79: 6 | N79: 0 | P79: 3 | V79: =SUM(L79:U79) -> 9 | W79: =IFERROR(__xludf.DUMMYFUNCTION("IFERROR( SUM( FILTER( Reporte!$E:$E, REGEXMATCH(Reporte!$A:$A, ""(?i)(TE PAGÓ|PAGASTE)""), Reporte!$H:$H & """" = AH79 & """" ) ), 0 )"),9) -> 9 | X79: =IFERROR(__xludf.DUMMYFUNCTION("IFERROR( SUM( FILTER( Efectivo!$C:$C, Efectivo!$D:$D & """" = AH79 & """" ) ), 0 )"),0) -> 0 | Y79: c | AA79: y | AB79: Debe 21 mes anterior. Exonerado faena por edad | AD79: =IF(AND(L79>0, M79>=8, NOT(OR(Y79="C", Y79="c"))), "CORTE", "") | AE79: =IF( OR( AND(#REF!>0, OR(Y79="C", Y79="c"), U79<0), AND(#REF!>0, Y79="") ), "CORTE", "" ) -> #REF! | AF79: =IF(AND(LEN(Y79)>0,LEN(AA79)=0),V79,0) -> 0 | AG79: =IF(AND(LEN(Y79)>0,TRIM(AA79)="Y"),V79,0) -> 9 | AH79: =TRIM(UPPER(C79)) -> D | AI79: =TRIM(UPPER(C79)) & "-" & TRIM(UPPER(D79)) -> D-9
A80: 79 | B80: LIDIA ASTERIA SALES BLAS | C80: D | D80: 10 | H80: 1 | I80: 2882 | J80: 2895 | K80: 13 | L80: 13 | N80: 0 | P80: 3 | V80: =SUM(L80:Q80) -> 16 | W80: =IFERROR(__xludf.DUMMYFUNCTION("IFERROR( SUM( FILTER( Reporte!$E:$E, REGEXMATCH(Reporte!$A:$A, ""(?i)(TE PAGÓ|PAGASTE)""), Reporte!$H:$H & """" = AH80 & """" ) ), 0 )"),0) -> 0 | X80: =IFERROR(__xludf.DUMMYFUNCTION("IFERROR( SUM( FILTER( Efectivo!$C:$C, Efectivo!$D:$D & """" = AH80 & """" ) ), 0 )"),0) -> 0 | AD80: =IF(AND(L80>0, M80>=8, NOT(OR(Y80="C", Y80="c"))), "CORTE", "") | AE80: =IF( OR( AND(#REF!>0, OR(Y80="C", Y80="c"), U80<0), AND(#REF!>0, Y80="") ), "CORTE", "" ) -> #REF! | AF80: =IF(AND(LEN(Y80)>0,LEN(AA80)=0),V80,0) -> 0 | AG80: =IF(AND(LEN(Y80)>0,TRIM(AA80)="Y"),V80,0) -> 0 | AH80: =TRIM(UPPER(C80)) -> D | AI80: =TRIM(UPPER(C80)) & "-" & TRIM(UPPER(D80)) -> D-10
A81: 80 | B81: SALOMON RODRIGUEZ GARCIA | C81: D | D81: 11 | H81: 1 | I81: 1087 | J81: 1103 | K81: 16 | L81: 16 | N81: 0 | P81: 3 | V81: =SUM(L81:Q81) -> 19 | W81: =IFERROR(__xludf.DUMMYFUNCTION("IFERROR( SUM( FILTER( Reporte!$E:$E, REGEXMATCH(Reporte!$A:$A, ""(?i)(TE PAGÓ|PAGASTE)""), Reporte!$H:$H & """" = AH81 & """" ) ), 0 )"),0) -> 0 | X81: =IFERROR(__xludf.DUMMYFUNCTION("IFERROR( SUM( FILTER( Efectivo!$C:$C, Efectivo!$D:$D & """" = AH81 & """" ) ), 0 )"),0) -> 0 | AD81: =IF(AND(L81>0, M81>=8, NOT(OR(Y81="C", Y81="c"))), "CORTE", "") | AE81: =IF( OR( AND(#REF!>0, OR(Y81="C", Y81="c"), U81<0), AND(#REF!>0, Y81="") ), "CORTE", "" ) -> #REF! | AF81: =IF(AND(LEN(Y81)>0,LEN(AA81)=0),V81,0) -> 0 | AG81: =IF(AND(LEN(Y81)>0,TRIM(AA81)="Y"),V81,0) -> 0 | AH81: =TRIM(UPPER(C81)) -> D | AI81: =TRIM(UPPER(C81)) & "-" & TRIM(UPPER(D81)) -> D-11
A82: 81 | B82: MARTINA MENDOZA ROMERO | C82: D | D82: 12 | H82: 1 | I82: 268 | J82: 274 | K82: 6 | L82: 6 | N82: 0 | P82: 3 | V82: =SUM(L82:Q82) -> 9 | W82: =IFERROR(__xludf.DUMMYFUNCTION("IFERROR( SUM( FILTER( Reporte!$E:$E, REGEXMATCH(Reporte!$A:$A, ""(?i)(TE PAGÓ|PAGASTE)""), Reporte!$H:$H & """" = AH82 & """" ) ), 0 )"),0) -> 0 | X82: =IFERROR(__xludf.DUMMYFUNCTION("IFERROR( SUM( FILTER( Efectivo!$C:$C, Efectivo!$D:$D & """" = AH82 & """" ) ), 0 )"),0) -> 0 | AD82: =IF(AND(L82>0, M82>=8, NOT(OR(Y82="C", Y82="c"))), "CORTE", "") | AE82: =IF( OR( AND(#REF!>0, OR(Y82="C", Y82="c"), U82<0), AND(#REF!>0, Y82="") ), "CORTE", "" ) -> #REF! | AF82: =IF(AND(LEN(Y82)>0,LEN(AA82)=0),V82,0) -> 0 | AG82: =IF(AND(LEN(Y82)>0,TRIM(AA82)="Y"),V82,0) -> 0 | AH82: =TRIM(UPPER(C82)) -> D | AI82: =TRIM(UPPER(C82)) & "-" & TRIM(UPPER(D82)) -> D-12
A83: 82 | B83: ROSELA ELVIRA MUÑOZ HERMITAÑO | C83: D | D83: 13 | H83: 1 | I83: 512 | J83: 534 | K83: 22 | L83: 22 | N83: 0 | P83: 3 | V83: =SUM(L83:Q83) -> 25 | W83: =IFERROR(__xludf.DUMMYFUNCTION("IFERROR( SUM( FILTER( Reporte!$E:$E, REGEXMATCH(Reporte!$A:$A, ""(?i)(TE PAGÓ|PAGASTE)""), Reporte!$H:$H & """" = AH83 & """" ) ), 0 )"),25) -> 25 | X83: =IFERROR(__xludf.DUMMYFUNCTION("IFERROR( SUM( FILTER( Efectivo!$C:$C, Efectivo!$D:$D & """" = AH83 & """" ) ), 0 )"),0) -> 0 | Y83: c | AA83: y | AD83: =IF(AND(L83>0, M83>=8, NOT(OR(Y83="C", Y83="c"))), "CORTE", "") | AE83: =IF( OR( AND(#REF!>0, OR(Y83="C", Y83="c"), U83<0), AND(#REF!>0, Y83="") ), "CORTE", "" ) -> #REF! | AF83: =IF(AND(LEN(Y83)>0,LEN(AA83)=0),V83,0) -> 0 | AG83: =IF(AND(LEN(Y83)>0,TRIM(AA83)="Y"),V83,0) -> 25 | AH83: =TRIM(UPPER(C83)) -> D | AI83: =TRIM(UPPER(C83)) & "-" & TRIM(UPPER(D83)) -> D-13
A84: 83 | B84: ESTEBAN GUERRERO CHINGEL | C84: D | D84: 16 | H84: 1 | I84: 1652 | J84: 10 | K84: 10 | L84: 10 | N84: 0 | O84: 25 | P84: 3 | V84: =SUM(L84:Q84) -> 38 | W84: =IFERROR(__xludf.DUMMYFUNCTION("IFERROR( SUM( FILTER( Reporte!$E:$E, REGEXMATCH(Reporte!$A:$A, ""(?i)(TE PAGÓ|PAGASTE)""), Reporte!$H:$H & """" = AH84 & """" ) ), 0 )"),0) -> 0 | X84: =IFERROR(__xludf.DUMMYFUNCTION("IFERROR( SUM( FILTER( Efectivo!$C:$C, Efectivo!$D:$D & """" = AH84 & """" ) ), 0 )"),0) -> 0 | AD84: =IF(AND(L84>0, M84>=8, NOT(OR(Y84="C", Y84="c"))), "CORTE", "") | AE84: =IF( OR( AND(#REF!>0, OR(Y84="C", Y84="c"), U84<0), AND(#REF!>0, Y84="") ), "CORTE", "" ) -> #REF! | AF84: =IF(AND(LEN(Y84)>0,LEN(AA84)=0),V84,0) -> 0 | AG84: =IF(AND(LEN(Y84)>0,TRIM(AA84)="Y"),V84,0) -> 0 | AH84: =TRIM(UPPER(C84)) -> D | AI84: =TRIM(UPPER(C84)) & "-" & TRIM(UPPER(D84)) -> D-16
A85: 84 | B85: MACARIO REQUEZ ROMERO | C85: D | D85: 17 | H85: 1 | I85: 3125 | J85: 3153 | K85: 28 | L85: 28 | N85: 0 | P85: 3 | V85: =SUM(L85:Q85) -> 31 | W85: =IFERROR(__xludf.DUMMYFUNCTION("IFERROR( SUM( FILTER( Reporte!$E:$E, REGEXMATCH(Reporte!$A:$A, ""(?i)(TE PAGÓ|PAGASTE)""), Reporte!$H:$H & """" = AH85 & """" ) ), 0 )"),0) -> 0 | X85: =IFERROR(__xludf.DUMMYFUNCTION("IFERROR( SUM( FILTER( Efectivo!$C:$C, Efectivo!$D:$D & """" = AH85 & """" ) ), 0 )"),0) -> 0 | AD85: =IF(AND(L85>0, M85>=8, NOT(OR(Y85="C", Y85="c"))), "CORTE", "") | AE85: =IF( OR( AND(#REF!>0, OR(Y85="C", Y85="c"), U85<0), AND(#REF!>0, Y85="") ), "CORTE", "" ) -> #REF! | AF85: =IF(AND(LEN(Y85)>0,LEN(AA85)=0),V85,0) -> 0 | AG85: =IF(AND(LEN(Y85)>0,TRIM(AA85)="Y"),V85,0) -> 0 | AH85: =TRIM(UPPER(C85)) -> D | AI85: =TRIM(UPPER(C85)) & "-" & TRIM(UPPER(D85)) -> D-17
A86: 85 | B86: LUIS GERARDO SAAVEDRA SAAVEDRA | C86: D | D86: 18 | H86: 1 | I86: 981 | J86: 1013 | K86: 32 | L86: 32 | N86: 0 | P86: 3 | V86: =SUM(L86:U86) -> 35 | W86: =IFERROR(__xludf.DUMMYFUNCTION("IFERROR( SUM( FILTER( Reporte!$E:$E, REGEXMATCH(Reporte!$A:$A, ""(?i)(TE PAGÓ|PAGASTE)""), Reporte!$H:$H & """" = AH86 & """" ) ), 0 )"),35) -> 35 | X86: =IFERROR(__xludf.DUMMYFUNCTION("IFERROR( SUM( FILTER( Efectivo!$C:$C, Efectivo!$D:$D & """" = AH86 & """" ) ), 0 )"),0) -> 0 | Y86: c | AA86: y | AD86: =IF(AND(L86>0, M86>=8, NOT(OR(Y86="C", Y86="c"))), "CORTE", "") | AE86: =IF( OR( AND(#REF!>0, OR(Y86="C", Y86="c"), U86<0), AND(#REF!>0, Y86="") ), "CORTE", "" ) -> #REF! | AF86: =IF(AND(LEN(Y86)>0,LEN(AA86)=0),V86,0) -> 0 | AG86: =IF(AND(LEN(Y86)>0,TRIM(AA86)="Y"),V86,0) -> 35 | AH86: =TRIM(UPPER(C86)) -> D | AI86: =TRIM(UPPER(C86)) & "-" & TRIM(UPPER(D86)) -> D-18
A87: 86 | B87: FELIPE DOMINGO VENTURO CAPCHA | C87: D | D87: 19 | H87: 1 | I87: 8 | J87: 28 | K87: 20 | L87: 20 | N87: 0 | O87: 25 | P87: 3 | V87: =SUM(L87:Q87) -> 48 | W87: =IFERROR(__xludf.DUMMYFUNCTION("IFERROR( SUM( FILTER( Reporte!$E:$E, REGEXMATCH(Reporte!$A:$A, ""(?i)(TE PAGÓ|PAGASTE)""), Reporte!$H:$H & """" = AH87 & """" ) ), 0 )"),48) -> 48 | X87: =IFERROR(__xludf.DUMMYFUNCTION("IFERROR( SUM( FILTER( Efectivo!$C:$C, Efectivo!$D:$D & """" = AH87 & """" ) ), 0 )"),0) -> 0 | Y87: c | AA87: y | AD87: =IF(AND(L87>0, M87>=8, NOT(OR(Y87="C", Y87="c"))), "CORTE", "") | AE87: =IF( OR( AND(#REF!>0, OR(Y87="C", Y87="c"), U87<0), AND(#REF!>0, Y87="") ), "CORTE", "" ) -> #REF! | AF87: =IF(AND(LEN(Y87)>0,LEN(AA87)=0),V87,0) -> 0 | AG87: =IF(AND(LEN(Y87)>0,TRIM(AA87)="Y"),V87,0) -> 48 | AH87: =TRIM(UPPER(C87)) -> D | AI87: =TRIM(UPPER(C87)) & "-" & TRIM(UPPER(D87)) -> D-19
A88: 87 | B88: YOLANDA MATILDE MONTALVO COSME | C88: E | D88: 1 | H88: 1 | I88: 298 | J88: 303 | K88: 5 | L88: 5 | N88: 0 | P88: 3 | V88: =SUM(L88:Q88) -> 8 | W88: =IFERROR(__xludf.DUMMYFUNCTION("IFERROR( SUM( FILTER( Reporte!$E:$E, REGEXMATCH(Reporte!$A:$A, ""(?i)(TE PAGÓ|PAGASTE)""), Reporte!$H:$H & """" = AH88 & """" ) ), 0 )"),0) -> 0 | X88: =IFERROR(__xludf.DUMMYFUNCTION("IFERROR( SUM( FILTER( Efectivo!$C:$C, Efectivo!$D:$D & """" = AH88 & """" ) ), 0 )"),8) -> 8 | Y88: c | AD88: =IF(AND(L88>0, M88>=8, NOT(OR(Y88="C", Y88="c"))), "CORTE", "") | AE88: =IF( OR( AND(#REF!>0, OR(Y88="C", Y88="c"), U88<0), AND(#REF!>0, Y88="") ), "CORTE", "" ) -> #REF! | AF88: =IF(AND(LEN(Y88)>0,LEN(AA88)=0),V88,0) -> 8 | AG88: =IF(AND(LEN(Y88)>0,TRIM(AA88)="Y"),V88,0) -> 0 | AH88: =TRIM(UPPER(C88)) -> E | AI88: =TRIM(UPPER(C88)) & "-" & TRIM(UPPER(D88)) -> E-1
A89: 88 | B89: DARIO ROSALES TICLIO | C89: E | D89: 2 | H89: 1 | I89: 3282 | J89: 29 | K89: 29 | L89: 29 | N89: 0 | O89: 25 | P89: 3 | V89: =SUM(L89:U89) -> 57 | W89: =IFERROR(__xludf.DUMMYFUNCTION("IFERROR( SUM( FILTER( Reporte!$E:$E, REGEXMATCH(Reporte!$A:$A, ""(?i)(TE PAGÓ|PAGASTE)""), Reporte!$H:$H & """" = AH89 & """" ) ), 0 )"),57) -> 57 | X89: =IFERROR(__xludf.DUMMYFUNCTION("IFERROR( SUM( FILTER( Efectivo!$C:$C, Efectivo!$D:$D & """" = AH89 & """" ) ), 0 )"),0) -> 0 | Y89: c | AA89: y | AD89: =IF(AND(L89>0, M89>=8, NOT(OR(Y89="C", Y89="c"))), "CORTE", "") | AE89: =IF( OR( AND(#REF!>0, OR(Y89="C", Y89="c"), U89<0), AND(#REF!>0, Y89="") ), "CORTE", "" ) -> #REF! | AF89: =IF(AND(LEN(Y89)>0,LEN(AA89)=0),V89,0) -> 0 | AG89: =IF(AND(LEN(Y89)>0,TRIM(AA89)="Y"),V89,0) -> 57 | AH89: =TRIM(UPPER(C89)) -> E | AI89: =TRIM(UPPER(C89)) & "-" & TRIM(UPPER(D89)) -> E-2
A90: 89 | B90: FELIX ENRIQUE VALENCIA FERNANDEZ | C90: E | D90: 3 | H90: 1 | I90: 2932 | J90: 2973 | K90: 41 | L90: 41 | M90: 3 | N90: 0 | P90: 3 | V90: =SUM(L90:Q90) -> 47 | W90: =IFERROR(__xludf.DUMMYFUNCTION("IFERROR( SUM( FILTER( Reporte!$E:$E, REGEXMATCH(Reporte!$A:$A, ""(?i)(TE PAGÓ|PAGASTE)""), Reporte!$H:$H & """" = AH90 & """" ) ), 0 )"),47) -> 47 | X90: =IFERROR(__xludf.DUMMYFUNCTION("IFERROR( SUM( FILTER( Efectivo!$C:$C, Efectivo!$D:$D & """" = AH90 & """" ) ), 0 )"),0) -> 0 | Y90: c | AA90: y | AD90: =IF(AND(L90>0, M90>=8, NOT(OR(Y90="C", Y90="c"))), "CORTE", "") | AE90: =IF( OR( AND(#REF!>0, OR(Y90="C", Y90="c"), U90<0), AND(#REF!>0, Y90="") ), "CORTE", "" ) -> #REF! | AF90: =IF(AND(LEN(Y90)>0,LEN(AA90)=0),V90,0) -> 0 | AG90: =IF(AND(LEN(Y90)>0,TRIM(AA90)="Y"),V90,0) -> 47 | AH90: =TRIM(UPPER(C90)) -> E | AI90: =TRIM(UPPER(C90)) & "-" & TRIM(UPPER(D90)) -> E-3
A91: 90 | B91: FELIX VELASQUEZ LOPEZ | C91: E | D91: 4 | H91: 1 | I91: 185 | J91: 201 | K91: 16 | L91: 16 | N91: 0 | P91: 3 | V91: =SUM(L91:U91) -> 19 | W91: =IFERROR(__xludf.DUMMYFUNCTION("IFERROR( SUM( FILTER( Reporte!$E:$E, REGEXMATCH(Reporte!$A:$A, ""(?i)(TE PAGÓ|PAGASTE)""), Reporte!$H:$H & """" = AH91 & """" ) ), 0 )"),0) -> 0 | X91: =IFERROR(__xludf.DUMMYFUNCTION("IFERROR( SUM( FILTER( Efectivo!$C:$C, Efectivo!$D:$D & """" = AH91 & """" ) ), 0 )"),0) -> 0 | AD91: =IF(AND(L91>0, M91>=8, NOT(OR(Y91="C", Y91="c"))), "CORTE", "") | AE91: =IF( OR( AND(#REF!>0, OR(Y91="C", Y91="c"), U91<0), AND(#REF!>0, Y91="") ), "CORTE", "" ) -> #REF! | AF91: =IF(AND(LEN(Y91)>0,LEN(AA91)=0),V91,0) -> 0 | AG91: =IF(AND(LEN(Y91)>0,TRIM(AA91)="Y"),V91,0) -> 0 | AH91: =TRIM(UPPER(C91)) -> E | AI91: =TRIM(UPPER(C91)) & "-" & TRIM(UPPER(D91)) -> E-4
A92: 91 | B92: LUIS ALBERTO GOMEZ LAHUANA | C92: E | D92: 6 | H92: 1 | I92: 941 | J92: 953 | K92: 12 | L92: 12 | M92: 3 | N92: 0 | P92: 3 | V92: =SUM(L92:U92) -> 18 | W92: =IFERROR(__xludf.DUMMYFUNCTION("IFERROR( SUM( FILTER( Reporte!$E:$E, REGEXMATCH(Reporte!$A:$A, ""(?i)(TE PAGÓ|PAGASTE)""), Reporte!$H:$H & """" = AH92 & """" ) ), 0 )"),18) -> 18 | X92: =IFERROR(__xludf.DUMMYFUNCTION("IFERROR( SUM( FILTER( Efectivo!$C:$C, Efectivo!$D:$D & """" = AH92 & """" ) ), 0 )"),0) -> 0 | Y92: c | AA92: y | AD92: =IF(AND(L92>0, M92>=8, NOT(OR(Y92="C", Y92="c"))), "CORTE", "") | AE92: =IF( OR( AND(#REF!>0, OR(Y92="C", Y92="c"), U92<0), AND(#REF!>0, Y92="") ), "CORTE", "" ) -> #REF! | AF92: =IF(AND(LEN(Y92)>0,LEN(AA92)=0),V92,0) -> 0 | AG92: =IF(AND(LEN(Y92)>0,TRIM(AA92)="Y"),V92,0) -> 18 | AH92: =TRIM(UPPER(C92)) -> E | AI92: =TRIM(UPPER(C92)) & "-" & TRIM(UPPER(D92)) -> E-6
A93: 92 | B93: GREGORIO TRUJILLO LEON | C93: E | D93: 7 | F93: 1 | H93: 1 | I93: 1 | J93: 5 | K93: 4 | L93: 5 | N93: 0 | P93: 3 | V93: =SUM(L93:Q93) -> 8 | W93: =IFERROR(__xludf.DUMMYFUNCTION("IFERROR( SUM( FILTER( Reporte!$E:$E, REGEXMATCH(Reporte!$A:$A, ""(?i)(TE PAGÓ|PAGASTE)""), Reporte!$H:$H & """" = AH93 & """" ) ), 0 )"),8) -> 8 | X93: =IFERROR(__xludf.DUMMYFUNCTION("IFERROR( SUM( FILTER( Efectivo!$C:$C, Efectivo!$D:$D & """" = AH93 & """" ) ), 0 )"),0) -> 0 | Y93: c | AA93: y | AD93: =IF(AND(L93>0, M93>=8, NOT(OR(Y93="C", Y93="c"))), "CORTE", "") | AE93: =IF( OR( AND(#REF!>0, OR(Y93="C", Y93="c"), U93<0), AND(#REF!>0, Y93="") ), "CORTE", "" ) -> #REF! | AF93: =IF(AND(LEN(Y93)>0,LEN(AA93)=0),V93,0) -> 0 | AG93: =IF(AND(LEN(Y93)>0,TRIM(AA93)="Y"),V93,0) -> 8 | AH93: =TRIM(UPPER(C93)) -> E | AI93: =TRIM(UPPER(C93)) & "-" & TRIM(UPPER(D93)) -> E-7
A94: 93 | B94: GERTRUDES VIDAL GONZALES | C94: E | D94: 8 | H94: 1 | I94: 995 | J94: 1003 | K94: 8 | L94: 8 | N94: 0 | P94: 3 | V94: =SUM(L94:U94) -> 11 | W94: =IFERROR(__xludf.DUMMYFUNCTION("IFERROR( SUM( FILTER( Reporte!$E:$E, REGEXMATCH(Reporte!$A:$A, ""(?i)(TE PAGÓ|PAGASTE)""), Reporte!$H:$H & """" = AH94 & """" ) ), 0 )"),0) -> 0 | X94: =IFERROR(__xludf.DUMMYFUNCTION("IFERROR( SUM( FILTER( Efectivo!$C:$C, Efectivo!$D:$D & """" = AH94 & """" ) ), 0 )"),11) -> 11 | Y94: c | AD94: =IF(AND(L94>0, M94>=8, NOT(OR(Y94="C", Y94="c"))), "CORTE", "") | AE94: =IF( OR( AND(#REF!>0, OR(Y94="C", Y94="c"), U94<0), AND(#REF!>0, Y94="") ), "CORTE", "" ) -> #REF! | AF94: =IF(AND(LEN(Y94)>0,LEN(AA94)=0),V94,0) -> 11 | AG94: =IF(AND(LEN(Y94)>0,TRIM(AA94)="Y"),V94,0) -> 0 | AH94: =TRIM(UPPER(C94)) -> E | AI94: =TRIM(UPPER(C94)) & "-" & TRIM(UPPER(D94)) -> E-8
A95: 94 | B95: MARIA NANCY SIGUEÑAS UGARTE | C95: E | D95: 9 | H95: 1 | I95: 99995 | J95: 99993 | K95: 2 | L95: 5 | N95: 0 | O95: 100 | P95: 3 | V95: =SUM(L95:Q95) -> 108 | W95: =IFERROR(__xludf.DUMMYFUNCTION("IFERROR( SUM( FILTER( Reporte!$E:$E, REGEXMATCH(Reporte!$A:$A, ""(?i)(TE PAGÓ|PAGASTE)""), Reporte!$H:$H & """" = AH95 & """" ) ), 0 )"),0) -> 0 | X95: =IFERROR(__xludf.DUMMYFUNCTION("IFERROR( SUM( FILTER( Efectivo!$C:$C, Efectivo!$D:$D & """" = AH95 & """" ) ), 0 )"),108) -> 108 | Y95: c | AD95: =IF(AND(L95>0, M95>=8, NOT(OR(Y95="C", Y95="c"))), "CORTE", "") | AE95: =IF( OR( AND(#REF!>0, OR(Y95="C", Y95="c"), U95<0), AND(#REF!>0, Y95="") ), "CORTE", "" ) -> #REF! | AF95: =IF(AND(LEN(Y95)>0,LEN(AA95)=0),V95,0) -> 108 | AG95: =IF(AND(LEN(Y95)>0,TRIM(AA95)="Y"),V95,0) -> 0 | AH95: =TRIM(UPPER(C95)) -> E | AI95: =TRIM(UPPER(C95)) & "-" & TRIM(UPPER(D95)) -> E-9
A96: 95 | B96: GREGORIA SIGUEÑAS UGARTE | C96: E | D96: 10 | H96: 1 | I96: 986 | J96: 1025 | K96: 39 | L96: 39 | N96: 0 | P96: 3 | V96: =SUM(L96:Q96) -> 42 | W96: =IFERROR(__xludf.DUMMYFUNCTION("IFERROR( SUM( FILTER( Reporte!$E:$E, REGEXMATCH(Reporte!$A:$A, ""(?i)(TE PAGÓ|PAGASTE)""), Reporte!$H:$H & """" = AH96 & """" ) ), 0 )"),0) -> 0 | X96: =IFERROR(__xludf.DUMMYFUNCTION("IFERROR( SUM( FILTER( Efectivo!$C:$C, Efectivo!$D:$D & """" = AH96 & """" ) ), 0 )"),0) -> 0 | AD96: =IF(AND(L96>0, M96>=8, NOT(OR(Y96="C", Y96="c"))), "CORTE", "") | AE96: =IF( OR( AND(#REF!>0, OR(Y96="C", Y96="c"), U96<0), AND(#REF!>0, Y96="") ), "CORTE", "" ) -> #REF! | AF96: =IF(AND(LEN(Y96)>0,LEN(AA96)=0),V96,0) -> 0 | AG96: =IF(AND(LEN(Y96)>0,TRIM(AA96)="Y"),V96,0) -> 0 | AH96: =TRIM(UPPER(C96)) -> E | AI96: =TRIM(UPPER(C96)) & "-" & TRIM(UPPER(D96)) -> E-10
A97: 96 | B97: VILMA SIGUEÑAS UGARTE | C97: E | D97: 11 | H97: 1 | I97: 4171 | J97: 4213 | K97: 42 | L97: 42 | N97: 0 | P97: 3 | V97: =SUM(L97:U97) -> 45 | W97: =IFERROR(__xludf.DUMMYFUNCTION("IFERROR( SUM( FILTER( Reporte!$E:$E, REGEXMATCH(Reporte!$A:$A, ""(?i)(TE PAGÓ|PAGASTE)""), Reporte!$H:$H & """" = AH97 & """" ) ), 0 )"),0) -> 0 | X97: =IFERROR(__xludf.DUMMYFUNCTION("IFERROR( SUM( FILTER( Efectivo!$C:$C, Efectivo!$D:$D & """" = AH97 & """" ) ), 0 )"),45) -> 45 | Y97: c | AD97: =IF(AND(L97>0, M97>=8, NOT(OR(Y97="C", Y97="c"))), "CORTE", "") | AE97: =IF( OR( AND(#REF!>0, OR(Y97="C", Y97="c"), U97<0), AND(#REF!>0, Y97="") ), "CORTE", "" ) -> #REF! | AF97: =IF(AND(LEN(Y97)>0,LEN(AA97)=0),V97,0) -> 45 | AG97: =IF(AND(LEN(Y97)>0,TRIM(AA97)="Y"),V97,0) -> 0 | AH97: =TRIM(UPPER(C97)) -> E | AI97: =TRIM(UPPER(C97)) & "-" & TRIM(UPPER(D97)) -> E-11
A98: 97 | B98: TEOFILA FERNANDEZ REYES | C98: E | D98: 12 | H98: 1 | I98: 6 | J98: 19 | K98: 13 | L98: 13 | M98: 1 | N98: 0 | O98: 25 | P98: 3 | V98: =SUM(L98:Q98) -> 42 | W98: =IFERROR(__xludf.DUMMYFUNCTION("IFERROR( SUM( FILTER( Reporte!$E:$E, REGEXMATCH(Reporte!$A:$A, ""(?i)(TE PAGÓ|PAGASTE)""), Reporte!$H:$H & """" = AH98 & """" ) ), 0 )"),42) -> 42 | X98: =IFERROR(__xludf.DUMMYFUNCTION("IFERROR( SUM( FILTER( Efectivo!$C:$C, Efectivo!$D:$D & """" = AH98 & """" ) ), 0 )"),0) -> 0 | Y98: c | AA98: y | AD98: =IF(AND(L98>0, M98>=8, NOT(OR(Y98="C", Y98="c"))), "CORTE", "") | AE98: =IF( OR( AND(#REF!>0, OR(Y98="C", Y98="c"), U98<0), AND(#REF!>0, Y98="") ), "CORTE", "" ) -> #REF! | AF98: =IF(AND(LEN(Y98)>0,LEN(AA98)=0),V98,0) -> 0 | AG98: =IF(AND(LEN(Y98)>0,TRIM(AA98)="Y"),V98,0) -> 42 | AH98: =TRIM(UPPER(C98)) -> E | AI98: =TRIM(UPPER(C98)) & "-" & TRIM(UPPER(D98)) -> E-12
A99: 98 | B99: LINDOLINA MUÑOZ HERMITAÑO | C99: E | D99: 13 | H99: 1 | I99: 3089 | J99: 3107 | K99: 18 | L99: 18 | N99: 0 | P99: 3 | V99: =SUM(L99:Q99) -> 21 | W99: =IFERROR(__xludf.DUMMYFUNCTION("IFERROR( SUM( FILTER( Reporte!$E:$E, REGEXMATCH(Reporte!$A:$A, ""(?i)(TE PAGÓ|PAGASTE)""), Reporte!$H:$H & """" = AH99 & """" ) ), 0 )"),21) -> 21 | X99: =IFERROR(__xludf.DUMMYFUNCTION("IFERROR( SUM( FILTER( Efectivo!$C:$C, Efectivo!$D:$D & """" = AH99 & """" ) ), 0 )"),0) -> 0 | Y99: c | AA99: y | AD99: =IF(AND(L99>0, M99>=8, NOT(OR(Y99="C", Y99="c"))), "CORTE", "") | AE99: =IF( OR( AND(#REF!>0, OR(Y99="C", Y99="c"), U99<0), AND(#REF!>0, Y99="") ), "CORTE", "" ) -> #REF! | AF99: =IF(AND(LEN(Y99)>0,LEN(AA99)=0),V99,0) -> 0 | AG99: =IF(AND(LEN(Y99)>0,TRIM(AA99)="Y"),V99,0) -> 21 | AH99: =TRIM(UPPER(C99)) -> E | AI99: =TRIM(UPPER(C99)) & "-" & TRIM(UPPER(D99)) -> E-13
A100: 99 | B100: FELICIANO SIGUEÑAS UGARTE | C100: E | D100: 14 | H100: 1 | I100: 59 | J100: 77 | K100: 18 | L100: 18 | N100: 0 | P100: 3 | V100: =SUM(L100:Q100) -> 21 | W100: =IFERROR(__xludf.DUMMYFUNCTION("IFERROR( SUM( FILTER( Reporte!$E:$E, REGEXMATCH(Reporte!$A:$A, ""(?i)(TE PAGÓ|PAGASTE)""), Reporte!$H:$H & """" = AH100 & """" ) ), 0 )"),0) -> 0 | X100: =IFERROR(__xludf.DUMMYFUNCTION("IFERROR( SUM( FILTER( Efectivo!$C:$C, Efectivo!$D:$D & """" = AH100 & """" ) ), 0 )"),0) -> 0 | AD100: =IF(AND(L100>0, M100>=8, NOT(OR(Y100="C", Y100="c"))), "CORTE", "") | AE100: =IF( OR( AND(#REF!>0, OR(Y100="C", Y100="c"), U100<0), AND(#REF!>0, Y100="") ), "CORTE", "" ) -> #REF! | AF100: =IF(AND(LEN(Y100)>0,LEN(AA100)=0),V100,0) -> 0 | AG100: =IF(AND(LEN(Y100)>0,TRIM(AA100)="Y"),V100,0) -> 0 | AH100: =TRIM(UPPER(C100)) -> E | AI100: =TRIM(UPPER(C100)) & "-" & TRIM(UPPER(D100)) -> E-14
...

Sheet PLANILLA
A1: ITEM | B1: NOMBRES | C1: MZ | D1: LT | E1: MARCACIÓN | F1: m3 | G1: MARCACIÓN | H1: M3 | I1: MARCACIÓN | J1: M3 | K1: MARCACIÓN | L1: M3 | M1: MARCACIÓN | N1: M3 | O1: MARCACIÓN | P1: M3 | Q1: MARCACIÓN | R1: M3 | S1: MARCACIÓN | T1: M3 | U1: MARCACION | V1: m3 | W1: MARCACION | X1: m3 | Y1: MARCACION | Z1: m3 | AA1: MARCACIÓN | AB1: M3 | AC1: Total mes actual | AD1: MES ANTERIOR | AE1: Corte y reconexión | AF1: Convenio | AG1: Manteniminiento | AH1: Multa | AI1: Total a pagar | AJ1: Estado | AK1: Fecha de pago | AL1: Medio de pago | AM1: Comentario
A2: 1 | B2: MARCELINA OBREGON DE AVILA | C2: A | D2: 1 | E2: 2445 | F2: 6 | G2: 2451 | H2: 7 | I2: 2458 | J2: 6 | K2: 2464 | L2: 5 | M2: 2469 | N2: 7 | O2: 2476 | P2: 5 | Q2: 2481 | R2: 5 | S2: 2486 | T2: 5 | U2: 2491 | V2: 5 | W2: 2496 | X2: 5 | Y2: 2502 | Z2: 6 | AA2: 2506 | AB2: 4 | AC2: 5 | AD2: 0 | AE2: 0 | AG2: 3 | AH2: 0 | AI2: 8
A3: 2 | B3: ROSA AURORA ROCA VIDAL | C3: A | D3: 2 | E3: 1975 | F3: 37 | G3: 2012 | H3: 23 | I3: 2035 | J3: 32 | K3: 2067 | L3: 27 | M3: 2094 | N3: 26 | O3: 2120 | P3: 22 | Q3: 2142 | R3: 22 | S3: 2168 | T3: 26 | U3: 2193 | V3: 25 | W3: 2225 | X3: 32 | Y3: 2248 | Z3: 23 | AA3: 2288 | AB3: 40 | AC3: 40 | AD3: 0 | AE3: 0 | AG3: 3 | AH3: 0 | AI3: 43
A4: 3 | B4: LINDA PAJUELO COCHACHÍN | C4: A | D4: 3 | K4: 0 | L4: 0 | M4: 0 | N4: 1 | O4: 1 | P4: 14 | Q4: 15 | R4: 14 | S4: 22 | T4: 7 | U4: 22 | V4: 0 | W4: 22 | X4: 0 | Y4: 22 | Z4: 0 | AA4: 22 | AB4: 0 | AC4: 5 | AD4: 0 | AE4: 0 | AG4: 3 | AH4: 0 | AI4: 8
A5: 4 | B5: YOLANDA ESPINOZA JAIMES | C5: A | D5: 4 | E5: 1759 | F5: 0 | G5: 1759 | H5: 0 | I5: 1759 | J5: 3 | K5: 1762 | L5: 0 | M5: 1762 | N5: 0 | O5: 1762 | P5: 0 | Q5: 1762 | R5: 0 | S5: 1762 | T5: 0 | U5: 1732 | V5: 0 | W5: 1762 | X5: 30 | Y5: 1763 | Z5: 1 | AA5: 1763 | AB5: 0 | AC5: 5 | AD5: 41 | AE5: 40 | AG5: 3 | AH5: 20 | AI5: 109
A6: 5 | B6: JULIA AGAMA CUZCO | C6: A | D6: 5 | E6: 2933 | F6: 35 | G6: 2968 | H6: 34 | I6: 3002 | J6: 23 | K6: 3025 | L6: 23 | M6: 3048 | N6: 16 | O6: 3064 | P6: 14 | Q6: 3078 | R6: 14 | S6: 3092 | T6: 14 | U6: 3108 | V6: 16 | W6: 3120 | X6: 12 | Y6: 3141 | Z6: 21 | AA6: 3162 | AB6: 21 | AC6: 21 | AD6: 0 | AE6: 0 | AG6: 3 | AH6: 0 | AI6: 24
A7: 6 | B7: ESTEBAN REYES SANCHEZ | C7: A | D7: 6 | E7: 1253 | F7: 45 | G7: 1298 | H7: 35 | I7: 1333 | J7: 25 | K7: 1358 | L7: 32 | M7: 1390 | N7: 22 | O7: 1412 | P7: 28 | Q7: 1440 | R7: 28 | S7: 1467 | T7: 27 | U7: 1491 | V7: 24 | W7: 1517 | X7: 26 | Y7: 1544 | Z7: 27 | AA7: 1571 | AB7: 27 | AC7: 27 | AD7: 0 | AE7: 0 | AG7: 3 | AH7: 0 | AI7: 30
A8: 7 | B8: JUAN CARLOS MELGAREJO BEDON | C8: A | D8: 7 | E8: 1358 | F8: 24 | G8: 1382 | H8: 25 | I8: 1407 | J8: 22 | K8: 1429 | L8: 23 | M8: 1452 | N8: 19 | O8: 1471 | P8: 22 | Q8: 1493 | R8: 22 | S8: 1512 | T8: 19 | U8: 1529 | V8: 17 | W8: 1546 | X8: 17 | Y8: 1562 | Z8: 16 | AA8: 1579 | AB8: 17 | AC8: 17 | AD8: 19 | AE8: 0 | AG8: 3 | AH8: 0 | AI8: 39
A9: 8 | B9: VICTOR MELGAREJO CORCINO | C9: A | D9: 8 | E9: 5882 | F9: 35 | G9: 5917 | H9: 33 | I9: 5950 | J9: 25 | K9: 5975 | L9: 36 | M9: 6011 | N9: 21 | O9: 6032 | P9: 13 | Q9: 6045 | R9: 13 | S9: 6055 | T9: 10 | U9: 6067 | V9: 12 | W9: 6078 | X9: 11 | Y9: 6088 | Z9: 10 | AA9: 6103 | AB9: 15 | AC9: 15 | AD9: 0 | AE9: 0 | AG9: 3 | AH9: 0 | AI9: 18
A10: 9 | B10: JHONI MELGAREJO BEDON | C10: A | D10: 8-A | P10: 18 | Q10: 18 | R10: 18 | S10: 26 | T10: 8 | U10: 32 | V10: 6 | W10: 46 | X10: 14 | Y10: 53 | Z10: 7 | AA10: 61 | AB10: 8 | AC10: 8 | AD10: 0 | AE10: 0 | AG10: 3 | AH10: 20 | AI10: 31
A11: 10 | B11: ALEJANDRO MELGAREJO ESPINOZA | C11: A | D11: 9 | E11: 1381 | F11: 32 | G11: 1413 | H11: 30 | I11: 1443 | J11: 40 | K11: 1483 | L11: 33 | M11: 1516 | N11: 33 | O11: 1549 | P11: 27 | Q11: 1576 | R11: 27 | S11: 1601 | T11: 25 | U11: 1624 | V11: 23 | W11: 1646 | X11: 22 | Y11: 1673 | Z11: 27 | AA11: 1703 | AB11: 30 | AC11: 30 | AD11: 0 | AE11: 0 | AG11: 3 | AH11: 0 | AI11: 33
A12: 11 | B12: ISABEL PUNTILLO VEGA | C12: A | D12: 10 | E12: 31 | F12: 10 | G12: 41 | H12: 29 | I12: 70 | J12: 18 | K12: 88 | L12: 29 | M12: 117 | N12: 20 | O12: 137 | P12: 163 | Q12: 300 | R12: 163 | S12: 371 | T12: 71 | U12: 379 | V12: 8 | W12: 384 | X12: 5 | Y12: 389 | Z12: 5 | AA12: 395 | AB12: 6 | AC12: 6 | AD12: 0 | AE12: 0 | AG12: 3 | AH12: 20 | AI12: 29
A13: 12 | B13: FELIX POZO CASTRO | C13: A | D13: 11 | E13: 341 | F13: 0 | G13: 341 | H13: 1 | I13: 342 | J13: 1 | K13: 343 | L13: 0 | M13: 343 | N13: 1 | O13: 344 | P13: 0 | Q13: 344 | R13: 0 | S13: 345 | T13: 1 | U13: 346 | V13: 1 | W13: 346 | X13: 0 | Y13: 346 | Z13: 0 | AA13: 346 | AB13: 0 | AC13: 5 | AD13: 0 | AE13: 0 | AG13: 3 | AH13: 20 | AI13: 28
A14: 13 | B14: BACILIO UTRILLA FRANCISCO | C14: B | D14: 1 | E14: 2078 | F14: 15 | G14: 2093 | H14: 0 | I14: 2093 | J14: 7 | K14: 2100 | L14: 10 | M14: 2110 | N14: 8 | O14: 2118 | P14: 5 | Q14: 2123 | R14: 5 | S14: 2131 | T14: 8 | U14: 2137 | V14: 6 | W14: 2141 | X14: 4 | Y14: 2147 | Z14: 6 | AA14: 2153 | AB14: 6 | AC14: 6 | AD14: 9 | AE14: 0 | AG14: 3 | AH14: 0 | AI14: 18
A15: 14 | B15: ESTEBAN REYNALDO ROSALES | C15: B | D15: 2 | E15: 2104 | F15: 6 | G15: 2110 | H15: 3 | I15: 2113 | J15: 2 | K15: 2115 | L15: 11 | M15: 2126 | N15: 9 | O15: 2135 | P15: 6 | Q15: 2141 | R15: 6 | S15: 2146 | T15: 5 | U15: 2152 | V15: 6 | W15: 2157 | X15: 5 | Y15: 2164 | Z15: 7 | AA15: 2171 | AB15: 7 | AC15: 7 | AD15: 0 | AE15: 0 | AG15: 3 | AH15: 20 | AI15: 30
A16: 15 | B16: EDUARDO REYNALDO ROSALES | C16: B | D16: 3 | E16: 602 | F16: 9 | G16: 611 | H16: 10 | I16: 621 | J16: 10 | K16: 631 | L16: 9 | M16: 640 | N16: 8 | O16: 648 | P16: 10 | Q16: 658 | R16: 10 | S16: 669 | T16: 11 | U16: 676 | V16: 7 | W16: 682 | X16: 6 | Y16: 689 | Z16: 7 | AA16: 695 | AB16: 6 | AC16: 6 | AD16: 0 | AE16: 0 | AG16: 3 | AH16: 0 | AI16: 9
A17: 16 | B17: MELINA J. JUAREZ TOLEDO DE MORENO | C17: B | D17: 4 | E17: 189 | F17: 10 | G17: 199 | H17: 12 | I17: 211 | J17: 15 | K17: 226 | L17: 13 | M17: 239 | N17: 13 | O17: 252 | P17: 21 | Q17: 273 | R17: 21 | S17: 291 | T17: 18 | U17: 311 | V17: 20 | W17: 331 | X17: 20 | Y17: 348 | Z17: 17 | AA17: 369 | AB17: 21 | AC17: 21 | AD17: 0 | AE17: 0 | AG17: 3 | AH17: 0 | AI17: 24
A18: 17 | B18: POMPEYO CELESTINO LLIUYA | C18: B | D18: 5 | E18: 4425 | F18: 58 | G18: 4483 | H18: 45 | I18: 4528 | J18: 39 | K18: 4567 | L18: 33 | M18: 4600 | N18: 39 | O18: 4639 | P18: 34 | Q18: 4673 | R18: 34 | S18: 4706 | T18: 33 | U18: 4742 | V18: 36 | W18: 4775 | X18: 33 | Y18: 4810 | Z18: 35 | AA18: 4848 | AB18: 38 | AC18: 38 | AD18: 0 | AE18: 0 | AG18: 3 | AH18: 20 | AI18: 61
A19: 18 | B19: ROSA VICTORIA MILLA MORALES | C19: B | D19: 6 | E19: 3385 | F19: 34 | G19: 3419 | H19: 35 | I19: 3454 | J19: 23 | K19: 3477 | L19: 23 | M19: 3500 | N19: 20 | O19: 3520 | P19: 26 | Q19: 3546 | R19: 26 | S19: 3570 | T19: 24 | U19: 3592 | V19: 22 | W19: 3612 | X19: 20 | Y19: 3634 | Z19: 22 | AA19: 3656 | AB19: 22 | AC19: 22 | AD19: 25 | AE19: 0 | AG19: 3 | AH19: 0 | AI19: 50
A20: 19 | B20: LIRIA PARIAMACHI DE PAZ | C20: B | D20: 7 | E20: 2289 | F20: 16 | G20: 2305 | H20: 17 | I20: 2322 | J20: 26 | K20: 2348 | L20: 16 | M20: 2364 | N20: 17 | O20: 2381 | P20: 16 | Q20: 2397 | R20: 16 | S20: 2414 | T20: 17 | U20: 2428 | V20: 14 | W20: 2443 | X20: 15 | Y20: 2455 | Z20: 12 | AA20: 2469 | AB20: 14 | AC20: 14 | AD20: 0 | AE20: 0 | AG20: 3 | AH20: 0 | AI20: 17
A21: 20 | B21: ROSALINA OLIMPIA CIRIACO SOTELO | C21: B | D21: 8 | E21: 6347 | F21: 14 | G21: 6361 | H21: 17 | I21: 6378 | J21: 18 | K21: 6396 | L21: 15 | M21: 6411 | N21: 14 | O21: 6425 | P21: 14 | Q21: 6439 | R21: 14 | S21: 6456 | T21: 17 | U21: 6470 | V21: 14 | W21: 6484 | X21: 14 | Y21: 6497 | Z21: 13 | AA21: 6510 | AB21: 13 | AC21: 13 | AD21: 16 | AE21: 0 | AG21: 3 | AH21: 0 | AI21: 32
A22: 21 | B22: ALEJANDRO RAPRAY VELASQUEZ | C22: B | D22: 9 | E22: 5905 | F22: 23 | G22: 5928 | H22: 25 | I22: 5953 | J22: 21 | K22: 5974 | L22: 16 | M22: 5990 | N22: 14 | O22: 6004 | P22: 14 | Q22: 6018 | R22: 14 | S22: 6045 | T22: 27 | U22: 6052 | V22: 7 | W22: 6058 | X22: 6 | Y22: 6062 | Z22: 4 | AA22: 6066 | AB22: 4 | AC22: 5 | AD22: 0 | AE22: 0 | AG22: 3 | AH22: 0 | AI22: 8
... A25: 24 | B25: TEOFILO BRUNO RAMOS DE LA CRUZ | C25: B | D25: 12 | E25: 2213 | F25: 8 | G25: 2221 | H25: 8 | I25: 2229 | J25: 10 | K25: 2239 | L25: 7 | M25: 2246 | N25: 9 | O25: 2255 | P25: 6 | Q25: 2261 | R25: 6 | S25: 2267 | T25: 6 | U25: 2273 | V25: 6 | W25: 2278 | X25: 5 | Y25: 2285 | Z25: 7 | AA25: 2292 | AB25: 7 | AC25: 7 | AD25: 10 | AE25: 0 | AG25: 3 | AH25: 0 | AI25: 20
A26: 25 | B26: ROSMERI SANCHEZ ESPADA | C26: B | D26: 12-A | E26: 198 | F26: 6 | G26: 204 | H26: 7 | I26: 211 | J26: 6 | K26: 217 | L26: 6 | M26: 223 | N26: 6 | O26: 229 | P26: 6 | Q26: 235 | R26: 6 | S26: 239 | T26: 4 | U26: 244 | V26: 5 | W26: 250 | X26: 6 | Y26: 256 | Z26: 6 | AA26: 262 | AB26: 6 | AC26: 6 | AD26: 0 | AE26: 0 | AG26: 3 | AH26: 0 | AI26: 9
A27: 26 | B27: SALOME AGUSTINA DIAZ VARGAS | C27: B | D27: 13 | E27: 90 | F27: 13 | G27: 103 | H27: 12 | I27: 115 | J27: 16 | K27: 131 | L27: 6 | M27: 137 | N27: 5 | O27: 142 | P27: 5 | Q27: 147 | R27: 5 | S27: 152 | T27: 5 | U27: 157 | V27: 5 | W27: 165 | X27: 8 | Y27: 173 | Z27: 8 | AA27: 180 | AB27: 7 | AC27: 7 | AD27: 0 | AE27: 0 | AG27: 3 | AH27: 0 | AI27: 10
A28: 27 | B28: MELISSA ISABEL PILLACA GARCIA | C28: B | D28: 15 | E28: 886 | F28: 12 | G28: 898 | H28: 18 | I28: 916 | J28: 13 | K28: 929 | L28: 18 | M28: 947 | N28: 18 | O28: 965 | P28: 20 | Q28: 985 | R28: 20 | S28: 1006 | T28: 21 | U28: 1028 | V28: 22 | W28: 1052 | X28: 24 | Y28: 1061 | Z28: 9 | AA28: 1105 | AB28: 44 | AC28: 44 | AD28: 0 | AE28: 0 | AG28: 3 | AH28: 0 | AI28: 47
A29: 28 | B29: CLETO TENORIO MORI | C29: B | D29: 16 | E29: 322 | F29: 13 | G29: 335 | H29: 21 | I29: 356 | J29: 16 | K29: 372 | L29: 17 | M29: 389 | N29: 15 | O29: 404 | P29: 10 | Q29: 414 | R29: 10 | S29: 422 | T29: 8 | U29: 428 | V29: 6 | W29: 435 | X29: 7 | Y29: 442 | Z29: 7 | AA29: 452 | AB29: 10 | AC29: 10 | AD29: 0 | AE29: 0 | AG29: 3 | AH29: 20 | AI29: 33
A30: 29 | B30: ELEUTERIA DOMITILA PARIAMACHI DE PAZ | C30: B | D30: 17 | E30: 16 | F30: 0 | G30: 16 | H30: 0 | I30: 16 | J30: 2 | K30: 18 | L30: 3 | M30: 21 | N30: 1 | O30: 22 | P30: 0 | Q30: 22 | R30: 0 | S30: 23 | T30: 1 | U30: 23 | V30: 0 | W30: 23 | X30: 0 | Y30: 24 | Z30: 1 | AA30: 24 | AB30: 0 | AC30: 5 | AD30: 0 | AE30: 0 | AG30: 3 | AH30: 0 | AI30: 8
A31: 30 | B31: LUZ DINA MIRAVAL HUERTA | C31: B | D31: 18 | E31: 632 | F31: 18 | G31: 650 | H31: 22 | I31: 672 | J31: 22 | K31: 694 | L31: 17 | M31: 711 | N31: 15 | O31: 726 | P31: 16 | Q31: 742 | R31: 16 | S31: 753 | T31: 11 | U31: 765 | V31: 12 | W31: 777 | X31: 12 | Y31: 790 | Z31: 13 | AA31: 803 | AB31: 13 | AC31: 13 | AD31: 0 | AE31: 0 | AG31: 3 | AH31: 0 | AI31: 16
A32: 31 | B32: CAMILA HIDALGO | C32: B | D32: 21 | E32: 0 | F32: 0 | G32: 0 | H32: 5 | I32: 5 | J32: 3 | K32: 3 | L32: 4 | M32: 7 | N32: 3 | O32: 10 | P32: 9 | Q32: 19 | R32: 9 | S32: 28 | T32: 9 | U32: 36 | V32: 8 | W32: 47 | X32: 11 | Y32: 60 | Z32: 13 | AA32: 72 | AB32: 12 | AC32: 12 | AD32: 0 | AE32: 0 | AG32: 3 | AH32: 0 | AI32: 15
A33: 32 | B33: JANET FERNANDEZ MINAYA | C33: B | D33: 29 | F33: 0 | H33: 0 | I33: 0 | J33: 19 | K33: 19 | L33: 9 | M33: 28 | N33: 4 | O33: 32 | P33: 5 | Q33: 37 | R33: 5 | S33: 45 | T33: 8 | U33: 52 | V33: 7 | W33: 66 | X33: 14 | Y33: 78 | Z33: 12 | AA33: 88 | AB33: 10 | AC33: 10 | AD33: 0 | AE33: 0 | AF33: 100 | AG33: 3 | AH33: 0 | AI33: 113
A34: 33 | B34: ODILON CERNA ROMERO | C34: C | D34: 1 | E34: 1726 | F34: 16 | G34: 1742 | H34: 15 | I34: 1757 | J34: 13 | K34: 1770 | L34: 14 | M34: 1784 | N34: 13 | O34: 1797 | P34: 12 | Q34: 1809 | R34: 12 | S34: 1819 | T34: 10 | U34: 1831 | V34: 12 | W34: 1845 | X34: 14 | Y34: 1859 | Z34: 14 | AA34: 1873 | AB34: 14 | AC34: 14 | AD34: 0 | AE34: 0 | AG34: 3 | AH34: 20 | AI34: 37
A35: 34 | B35: OLGA FLORENTINA HUERTA AGAMA | C35: C | D35: 2 | E35: 796 | F35: 5 | G35: 801 | H35: 17 | I35: 818 | J35: 2 | K35: 820 | L35: 2 | M35: 822 | N35: 1 | O35: 823 | P35: 2 | Q35: 825 | R35: 2 | S35: 826 | T35: 1 | U35: 827 | V35: 1 | W35: 829 | X35: 2 | Y35: 830 | Z35: 1 | AA35: 833 | AB35: 3 | AC35: 5 | AD35: 0 | AE35: 0 | AG35: 3 | AH35: 0 | AI35: 8
A36: 35 | B36: TIMOTEO ROMERO JULCA | C36: C | D36: 4 | E36: 2918 | F36: 20 | G36: 2938 | H36: 32 | I36: 2970 | J36: 30 | K36: 3000 | L36: 29 | M36: 3029 | N36: 22 | O36: 3051 | P36: 15 | Q36: 3066 | R36: 15 | S36: 3085 | T36: 19 | U36: 3106 | V36: 21 | W36: 3122 | X36: 16 | Y36: 3150 | Z36: 28 | AA36: 3175 | AB36: 25 | AC36: 25 | AD36: 0 | AE36: 0 | AG36: 3 | AH36: 0 | AI36: 28
A37: 36 | B37: AGAPITO PRINICIPE SALINAS | C37: C | D37: 5 | E37: 3725 | F37: 22 | G37: 3747 | H37: 21 | I37: 3768 | J37: 19 | K37: 3787 | L37: 19 | M37: 3806 | N37: 18 | O37: 3824 | P37: 11 | Q37: 3835 | R37: 11 | S37: 3845 | T37: 10 | U37: 3859 | V37: 14 | W37: 3869 | X37: 10 | Y37: 3884 | Z37: 15 | AA37: 3899 | AB37: 15 | AC37: 15 | AD37: 0 | AE37: 0 | AG37: 3 | AH37: 0 | AI37: 18
A38: 37 | B38: DIANA JARA TRUJILLO | C38: C | D38: 6 | E38: 150 | F38: 22 | G38: 172 | H38: 23 | I38: 195 | J38: 19 | K38: 214 | L38: 15 | M38: 229 | N38: 16 | O38: 245 | P38: 21 | Q38: 266 | R38: 21 | S38: 283 | T38: 17 | U38: 299 | V38: 16 | W38: 324 | X38: 25 | Y38: 350 | Z38: 26 | AA38: 370 | AB38: 20 | AC38: 20 | AD38: 0 | AE38: 0 | AG38: 3 | AH38: 40 | AI38: 63
A39: 38 | B39: VICTOR LOPEZ TRUJILLO | C39: C | D39: 7 | E39: 2096 | F39: 43 | G39: 2139 | H39: 27 | I39: 2166 | J39: 20 | K39: 2186 | L39: 15 | M39: 2201 | N39: 14 | O39: 2215 | P39: 11 | Q39: 2226 | R39: 11 | S39: 2236 | T39: 10 | U39: 2246 | V39: 10 | W39: 2260 | X39: 14 | Y39: 2276 | Z39: 16 | AA39: 2288 | AB39: 12 | AC39: 12 | AD39: 0 | AE39: 0 | AG39: 3 | AH39: 40 | AI39: 55
A40: 39 | B40: JULISSA BARRETO QUITO | C40: C | D40: 8 | E40: 156 | F40: 0 | G40: 156 | H40: 1 | I40: 157 | J40: 0 | K40: 157 | L40: 0 | M40: 157 | N40: 1 | O40: 158 | P40: 4 | Q40: 162 | R40: 4 | S40: 167 | T40: 5 | U40: 170 | V40: 3 | W40: 175 | X40: 5 | Y40: 179 | Z40: 4 | AA40: 184 | AB40: 5 | AC40: 5 | AD40: 8 | AE40: 0 | AG40: 3 | AH40: 20 | AI40: 36
A41: 40 | B41: JAZMIN QUITO SANCHEZ | C41: C | D41: 8-B | E41: 509 | F41: 16 | G41: 525 | H41: 22 | I41: 547 | J41: 16 | K41: 563 | L41: 15 | M41: 578 | N41: 14 | O41: 592 | P41: 14 | Q41: 606 | R41: 14 | S41: 618 | T41: 12 | U41: 631 | V41: 13 | W41: 645 | X41: 14 | Y41: 668 | Z41: 23 | AA41: 689 | AB41: 21 | AC41: 21 | AD41: 0 | AE41: 0 | AG41: 3 | AH41: 0 | AI41: 24
A42: 41 | B42: JUAN UCULMANA SANCHEZ | C42: C | D42: 9 | E42: 2002 | F42: 5 | G42: 2007 | H42: 3 | I42: 2010 | J42: 29 | K42: 2039 | L42: 6 | M42: 2045 | N42: 4 | O42: 2049 | P42: 1 | Q42: 2050 | R42: 1 | S42: 2050 | T42: 0 | U42: 2050 | V42: 0 | W42: 2060 | X42: 10 | Y42: 2062 | Z42: 2 | AA42: 2064 | AB42: 2 | AC42: 5 | AD42: 0 | AE42: 0 | AG42: 3 | AH42: 0 | AI42: 8
A43: 42 | B43: SONIA GLORIA MORENO CASTILLEJO | C43: C | D43: 9-C | E43: 306 | F43: 7 | G43: 313 | H43: 9 | I43: 322 | J43: 7 | K43: 329 | L43: 9 | M43: 338 | N43: 6 | O43: 344 | P43: 6 | Q43: 350 | R43: 6 | S43: 355 | T43: 5 | U43: 361 | V43: 6 | W43: 365 | X43: 4 | Y43: 373 | Z43: 8 | AA43: 381 | AB43: 8 | AC43: 8 | AD43: 0 | AE43: 0 | AG43: 3 | AH43: 0 | AI43: 11
A44: 43 | B44: CEVERIANO CHAUCA MORALES | C44: C | D44: 11 | E44: 325 | F44: 16 | G44: 341 | H44: 23 | I44: 364 | J44: 21 | K44: 385 | L44: 24 | M44: 409 | N44: 22 | O44: 431 | P44: 19 | Q44: 450 | R44: 19 | S44: 472 | T44: 22 | U44: 496 | V44: 24 | W44: 510 | X44: 14 | Y44: 526 | Z44: 16 | AA44: 552 | AB44: 26 | AC44: 26 | AD44: 0 | AE44: 0 | AG44: 3 | AH44: 0 | AI44: 29
A45: 44 | B45: MACEDONIO MORALES BENTURO | C45: C | D45: 12 | E45: 1348 | F45: 16 | G45: 1364 | H45: 11 | I45: 1375 | J45: 18 | K45: 1393 | L45: 14 | M45: 1407 | N45: 12 | O45: 1419 | P45: 12 | Q45: 1431 | R45: 12 | S45: 1440 | T45: 9 | U45: 1454 | V45: 14 | W45: 1462 | X45: 8 | Y45: 1471 | Z45: 9 | AA45: 1483 | AB45: 12 | AC45: 12 | AD45: 0 | AE45: 0 | AG45: 3 | AH45: 0 | AI45: 15
A46: 45 | B46: IRMA HUAÑAHUI LOPEZ | C46: C | D46: 13 | E46: 1924 | F46: 9 | G46: 1933 | H46: 9 | I46: 1942 | J46: 7 | K46: 1949 | L46: 7 | M46: 1956 | N46: 11 | O46: 1967 | P46: 6 | Q46: 1973 | R46: 6 | S46: 1988 | T46: 15 | U46: 1993 | V46: 5 | W46: 2002 | X46: 9 | Y46: 2007 | Z46: 5 | AA46: 2012 | AB46: 5 | AC46: 5 | AD46: 0 | AE46: 0 | AG46: 3 | AH46: 0 | AI46: 8
A47: 46 | B47: JUAN RIOS BLAS | C47: C | D47: 14 | E47: 648 | F47: 7 | G47: 655 | H47: 5 | I47: 660 | J47: 11 | K47: 671 | L47: 8 | M47: 679 | N47: 7 | O47: 686 | P47: 5 | Q47: 691 | R47: 5 | S47: 696 | T47: 5 | U47: 699 | V47: 5 | W47: 702 | X47: 3 | Y47: 708 | Z47: 6 | AA47: 714 | AB47: 6 | AC47: 6 | AD47: 0 | AE47: 0 | AG47: 3 | AH47: 0 | AI47: 9
A48: 47 | B48: JULIO RIOS BLAS | C48: C | D48: 15 | E48: 1994 | F48: 6 | G48: 2000 | H48: -5 | I48: 1995 | J48: 0 | K48: 0 | L48: 15 | M48: 15 | N48: 11 | O48: 26 | P48: 7 | Q48: 33 | R48: 7 | S48: 39 | T48: 6 | U48: 45 | V48: 6 | W48: 50 | X48: 5 | Y48: 53 | Z48: 3 | AA48: 56 | AB48: 3 | AC48: 5 | AD48: 0 | AE48: 0 | AG48: 3 | AH48: 0 | AI48: 8
A49: 48 | B49: MARTHA MASIAS CASIHUAMAN DE TERAN | C49: C | D49: 16 | E49: 1692 | F49: 9 | G49: 1701 | H49: 14 | I49: 1715 | J49: 5 | K49: 1720 | L49: 5 | M49: 1725 | N49: 5 | O49: 1730 | P49: 3 | Q49: 1733 | R49: 3 | S49: 1736 | T49: 3 | U49: 1744 | V49: 8 | W49: 1750 | X49: 6 | Y49: 1757 | Z49: 7 | AA49: 1763 | AB49: 6 | AC49: 6 | AD49: 10 | AE49: 0 | AG49: 3 | AH49: 0 | AI49: 19
A50: 49 | B50: MARCELINO VALLADARES TRUJILLO | C50: C | D50: 18 | E50: 263 | F50: 7 | G50: 270 | H50: 12 | I50: 282 | J50: 5 | K50: 287 | L50: 7 | M50: 294 | N50: 5 | O50: 299 | P50: 4 | Q50: 303 | R50: 4 | S50: 308 | T50: 5 | U50: 309 | V50: 1 | W50: 313 | X50: 4 | Y50: 318 | Z50: 5 | AA50: 326 | AB50: 8 | AC50: 8 | AD50: 0 | AE50: 0 | AG50: 3 | AH50: 0 | AI50: 11
A51: 50 | B51: ANTONIO VALLADARES DOMINGUEZ | C51: C | D51: 19 | E51: 3207 | F51: 21 | G51: 3228 | H51: 22 | I51: 3250 | J51: 18 | K51: 3268 | L51: 20 | M51: 3288 | N51: 20 | O51: 3308 | P51: 19 | Q51: 3327 | R51: 19 | S51: 3347 | T51: 20 | U51: 3363 | V51: 16 | W51: 3380 | X51: 17 | Y51: 3402 | Z51: 22 | AA51: 3425 | AB51: 23 | AC51: 23 | AD51: 0 | AE51: 0 | AG51: 3 | AH51: 0 | AI51: 26
A52: 51 | B52: EUSEBIO REYES VILLAFANA | C52: C | D52: 20 | E52: 2433 | F52: 20 | G52: 2453 | H52: 20 | I52: 2473 | J52: 21 | K52: 2494 | L52: 16 | M52: 2510 | N52: 18 | O52: 2528 | P52: 22 | Q52: 2550 | R52: 22 | S52: 2560 | T52: 10 | U52: 2570 | V52: 10 | W52: 2582 | X52: 12 | Y52: 2594 | Z52: 12 | AA52: 2608 | AB52: 14 | AC52: 14 | AD52: 0 | AE52: 0 | AG52: 3 | AH52: 20 | AI52: 37
A53: 53 | B53: ABRAHAM BARRERA VEGA | C53: C | D53: 22 | E53: 0 | F53: 0 | G53: 0 | H53: 0 | I53: 0 | J53: 0 | K53: 0 | L53: 0 | M53: 0 | N53: 6 | O53: 6 | P53: 2 | Q53: 8 | R53: 2 | S53: 10 | T53: 2 | U53: 12 | V53: 2 | W53: 13 | X53: 1 | Y53: 18 | Z53: 5 | AA53: 25 | AB53: 7 | AC53: 7 | AD53: 0 | AE53: 0 | AG53: 3 | AH53: 20 | AI53: 30
A54: 54 | B54: ANTONIA MAYO TRUJILLO | C54: C | D54: 23 | E54: 4089 | F54: 20 | G54: 4109 | H54: 27 | I54: 4136 | J54: 25 | K54: 4161 | L54: 24 | M54: 4185 | N54: 25 | O54: 4210 | P54: 21 | Q54: 4231 | R54: 21 | S54: 4241 | T54: 10 | U54: 4249 | V54: 8 | W54: 4259 | X54: 10 | Y54: 4273 | Z54: 14 | AA54: 4288 | AB54: 15 | AC54: 15 | AD54: 0 | AE54: 0 | AG54: 3 | AH54: 20 | AI54: 38
A55: 55 | B55: ALFREDO CARLOS VENTURO CAPCHA | C55: C | D55: 24 | E55: 490 | F55: 2 | G55: 492 | H55: 2 | I55: 494 | J55: 2 | K55: 496 | L55: 2 | M55: 498 | N55: 2 | O55: 500 | P55: 3 | Q55: 503 | R55: 3 | S55: 505 | T55: 2 | U55: 507 | V55: 2 | W55: 508 | X55: 1 | Y55: 510 | Z55: 2 | AA55: 514 | AB55: 4 | AC55: 5 | AD55: 0 | AE55: 0 | AG55: 3 | AH55: 20 | AI55: 28
... A64: 64 | B64: EBER AGÜERO TRUJILLO | C64: C | D64: 34 | E64: 616 | F64: 4 | G64: 620 | H64: 6 | I64: 626 | J64: 3 | K64: 629 | L64: 3 | M64: 632 | N64: 0 | O64: 632 | P64: 0 | Q64: 632 | R64: 0 | S64: 632 | T64: 0 | U64: 632 | V64: 0 | W64: 632 | X64: 0 | Y64: 632 | Z64: 0 | AA64: 632 | AB64: 0 | AC64: 5 | AD64: 0 | AE64: 0 | AG64: 3 | AH64: 0 | AI64: 8
A65: 65 | B65: ANALY QUINECHE MORANTE | C65: C | D65: 35 | E65: 328 | F65: 11 | G65: 339 | H65: 11 | I65: 350 | J65: 10 | K65: 360 | L65: 10 | M65: 370 | N65: 12 | O65: 382 | P65: 12 | Q65: 394 | R65: 12 | S65: 404 | T65: 10 | U65: 413 | V65: 9 | W65: 425 | X65: 12 | Y65: 435 | Z65: 10 | AA65: 445 | AB65: 10 | AC65: 10 | AD65: 28 | AE65: 0 | AF65: 100 | AG65: 3 | AH65: 20 | AI65: 161
A66: 66 | B66: MARIA NORABUENA ESPADA | C66: C | D66: 36 | E66: 158 | F66: 9 | G66: 167 | H66: 8 | I66: 175 | J66: 5 | K66: 180 | L66: 5 | M66: 185 | N66: 3 | O66: 188 | P66: 5 | Q66: 193 | R66: 5 | S66: 196 | T66: 3 | U66: 199 | V66: 3 | W66: 201 | X66: 2 | Y66: 204 | Z66: 3 | AA66: 208 | AB66: 4 | AC66: 5 | AD66: 0 | AE66: 0 | AG66: 3 | AH66: 0 | AI66: 8
A67: 67 | B67: RAQUEL SORIA BUSTAMANTE | C67: C | D67: 37 | E67: 93 | F67: 7 | G67: 100 | H67: 9 | I67: 109 | J67: 8 | K67: 117 | L67: 9 | M67: 126 | N67: 8 | O67: 134 | P67: 6 | Q67: 140 | R67: 6 | S67: 146 | T67: 6 | U67: 152 | V67: 6 | W67: 157 | X67: 5 | Y67: 163 | Z67: 6 | AA67: 169 | AB67: 6 | AC67: 6 | AD67: 0 | AE67: 0 | AG67: 3 | AH67: 20 | AI67: 29
A68: 68 | B68: JANET ROMERO MAYO | C68: C | D68: 42 | F68: 0 | H68: 4 | I68: 4 | J68: 8 | K68: 12 | L68: 9 | M68: 21 | N68: 6 | O68: 27 | P68: 21 | Q68: 48 | R68: 21 | S68: 62 | T68: 14 | U68: 73 | V68: 11 | W68: 85 | X68: 12 | Y68: 97 | Z68: 12 | AA68: 112 | AB68: 15 | AC68: 15 | AD68: 0 | AE68: 0 | AF68: 100 | AG68: 3 | AH68: 20 | AI68: 138
A69: 69 | B69: JANET EVARISTO COCHACHIN | C69: C | D69: 45 | W69: 0 | X69: 0 | Y69: 0 | Z69: 0 | AA69: 0 | AB69: 0 | AC69: 5 | AD69: 8 | AE69: 0 | AF69: 100 | AG69: 3 | AH69: 0 | AI69: 116
A70: 70 | B70: JUAN VENTURO CAPCHA | C70: D | D70: 1 | E70: 1625 | F70: 7 | G70: 1632 | H70: 7 | I70: 1639 | J70: 7 | K70: 1646 | L70: 7 | M70: 1653 | N70: 6 | O70: 1659 | P70: 6 | Q70: 1665 | R70: 6 | S70: 1669 | T70: 4 | U70: 1675 | V70: 6 | W70: 1680 | X70: 5 | Y70: 1685 | Z70: 5 | AA70: 1693 | AB70: 8 | AC70: 8 | AD70: 0 | AE70: 0 | AG70: 3 | AH70: 0 | AI70: 11
A71: 71 | B71: VICTOR TRUJILLO POLICARPIO | C71: D | D71: 2 | E71: 1772 | F71: 17 | G71: 1789 | H71: 18 | I71: 1807 | J71: 17 | K71: 1824 | L71: 17 | M71: 1841 | N71: 12 | O71: 1853 | P71: 7 | Q71: 1860 | R71: 7 | S71: 1864 | T71: 4 | U71: 1868 | V71: 4 | W71: 1872 | X71: 4 | Y71: 1883 | Z71: 11 | AA71: 1918 | AB71: 35 | AC71: 35 | AD71: 0 | AE71: 0 | AG71: 3 | AH71: 20 | AI71: 58
A72: 72 | B72: ANTONIO CASTILLEJO CUEVA | C72: D | D72: 3 | E72: 1087 | F72: 34 | G72: 1121 | H72: 7 | I72: 1128 | J72: 7 | K72: 1135 | L72: 9 | M72: 1144 | N72: 9 | O72: 1153 | P72: 10 | Q72: 1163 | R72: 10 | S72: 1171 | T72: 8 | U72: 1183 | V72: 12 | W72: 1192 | X72: 9 | Y72: 1201 | Z72: 9 | AA72: 1210 | AB72: 9 | AC72: 9 | AD72: 0 | AE72: 0 | AG72: 3 | AH72: 0 | AI72: 12
A73: 73 | B73: JULIO CESAR PRINCIPE LUNA | C73: D | D73: 4 | E73: 168 | F73: 10 | G73: 178 | H73: -10 | I73: 168 | J73: 0 | K73: 0 | L73: 16 | M73: 16 | N73: 12 | O73: 28 | P73: 20 | Q73: 48 | R73: 20 | S73: 63 | T73: 15 | U73: 74 | V73: 11 | W73: 86 | X73: 12 | Y73: 97 | Z73: 11 | AA73: 113 | AB73: 16 | AC73: 16 | AD73: 0 | AE73: 0 | AG73: 3 | AH73: 20 | AI73: 39
A74: 74 | B74: TERESA PAULA JARA DE FERNANDEZ | C74: D | D74: 5 | E74: 225 | F74: 14 | G74: 239 | H74: 35 | I74: 274 | J74: 14 | K74: 288 | L74: 13 | M74: 301 | N74: 7 | O74: 308 | P74: 8 | Q74: 316 | R74: 8 | S74: 324 | T74: 8 | U74: 333 | V74: 9 | W74: 344 | X74: 11 | Y74: 352 | Z74: 8 | AA74: 367 | AB74: 15 | AC74: 15 | AD74: 0 | AE74: 0 | AG74: 3 | AH74: 0 | AI74: 18
A75: 75 | B75: HERMELINDA JARA TRUJILLO | C75: D | D75: 6 | E75: 7638 | F75: 20 | G75: 7658 | H75: 26 | I75: 7684 | J75: 19 | K75: 7703 | L75: 27 | M75: 7730 | N75: 16 | O75: 7746 | P75: 15 | Q75: 7761 | R75: 15 | S75: 7775 | T75: 14 | U75: 7789 | V75: 14 | W75: 7803 | X75: 14 | Y75: 7822 | Z75: 19 | AA75: 7840 | AB75: 18 | AC75: 18 | AD75: 0 | AE75: 0 | AG75: 3 | AH75: 0 | AI75: 21
A76: 76 | B76: MAXIMILIANO JARA NIETO | C76: D | D76: 7 | E76: 3878 | F76: 73 | G76: 3951 | H76: 74 | I76: 4025 | J76: 65 | K76: 4090 | L76: 71 | M76: 4161 | N76: 61 | O76: 4222 | P76: 58 | Q76: 4280 | R76: 58 | S76: 4331 | T76: 51 | U76: 4382 | V76: 51 | W76: 4445 | X76: 63 | Y76: 4507 | Z76: 62 | AA76: 4584 | AB76: 77 | AC76: 77 | AD76: 65 | AE76: 0 | AG76: 3 | AH76: 0 | AI76: 145
A77: 77 | B77: SANTA ANTONIA SAENZ TICLIO | C77: D | D77: 8 | E77: 1622 | F77: 6 | G77: 1628 | H77: 6 | I77: 1634 | J77: 6 | K77: 1640 | L77: 6 | M77: 1646 | N77: 7 | O77: 1653 | P77: 5 | Q77: 1658 | R77: 5 | S77: 1667 | T77: 9 | U77: 1671 | V77: 4 | W77: 1676 | X77: 5 | Y77: 1681 | Z77: 5 | AA77: 1686 | AB77: 5 | AC77: 5 | AD77: 0 | AE77: 0 | AG77: 3 | AH77: 0 | AI77: 8
A78: 78 | B78: RUFINA CABELLO TICLIO | C78: D | D78: 9 | E78: 3754 | F78: 25 | G78: 3779 | H78: 21 | I78: 3800 | J78: 18 | K78: 3818 | L78: 17 | M78: 3835 | N78: 16 | O78: 3851 | P78: 21 | Q78: 3872 | R78: 21 | S78: 3893 | T78: 21 | U78: 3904 | V78: 11 | W78: 3915 | X78: 11 | Y78: 3929 | Z78: 14 | AA78: 3942 | AB78: 13 | AC78: 13 | AD78: 0 | AE78: 0 | AG78: 3 | AH78: 0 | AI78: 16
A79: 79 | B79: LIDIA ASTERIA SALES BLAS | C79: D | D79: 10 | E79: 2569 | F79: 11 | G79: 2580 | H79: 12 | I79: 2592 | J79: 13 | K79: 2605 | L79: 14 | M79: 2619 | N79: 13 | O79: 2632 | P79: 11 | Q79: 2643 | R79: 11 | S79: 2655 | T79: 12 | U79: 2667 | V79: 12 | W79: 2677 | X79: 10 | Y79: 2687 | Z79: 10 | AA79: 2697 | AB79: 10 | AC79: 10 | AD79: 0 | AE79: 0 | AG79: 3 | AH79: 0 | AI79: 13
A80: 80 | B80: SALOMON RODRIGUEZ GARCIA | C80: D | D80: 11 | E80: 721 | F80: 14 | G80: 735 | H80: 16 | I80: 751 | J80: 14 | K80: 765 | L80: 13 | M80: 778 | N80: 12 | O80: 790 | P80: 12 | Q80: 802 | R80: 12 | S80: 812 | T80: 10 | U80: 823 | V80: 11 | W80: 834 | X80: 11 | Y80: 844 | Z80: 10 | AA80: 855 | AB80: 11 | AC80: 11 | AD80: 0 | AE80: 0 | AG80: 3 | AH80: 20 | AI80: 34
A81: 81 | B81: MARTINA MENDOZA ROMERO | C81: D | D81: 12 | E81: 1033 | F81: 20 | G81: 1053 | H81: -20 | I81: 1033 | J81: 0 | K81: 0 | L81: 36 | M81: 36 | N81: 28 | O81: 64 | P81: 29 | Q81: 93 | R81: 29 | S81: 116 | T81: 23 | U81: 133 | V81: 17 | W81: 153 | X81: 20 | Y81: 175 | Z81: 22 | AA81: 215 | AB81: 40 | AC81: 40 | AD81: 0 | AE81: 0 | AG81: 3 | AH81: 20 | AI81: 63
... A89: 89 | B89: FELIX ENRIQUE VALENCIA FERNANDEZ | C89: E | D89: 3 | E89: 2023 | F89: 78 | G89: 2101 | H89: 66 | I89: 2167 | J89: 74 | K89: 2241 | L89: 73 | M89: 2314 | N89: 72 | O89: 2386 | P89: 73 | Q89: 2459 | R89: 73 | S89: 2527 | T89: 68 | U89: 2584 | V89: 57 | W89: 2601 | X89: 17 | Y89: 2609 | Z89: 8 | AA89: 2619 | AB89: 10 | AC89: 10 | AD89: 0 | AE89: 0 | AG89: 3 | AH89: 20 | AI89: 33
A90: 90 | B90: FELIX VELASQUEZ LOPEZ | C90: E | D90: 4 | E90: 1736 | F90: 11 | G90: 1747 | H90: 12 | I90: 1759 | J90: 9 | K90: 1768 | L90: 14 | M90: 1782 | N90: 12 | O90: 1794 | P90: 5 | Q90: 1799 | R90: 5 | S90: 1803 | T90: 4 | U90: 1810 | V90: 7 | W90: 1822 | X90: 12 | Y90: 0 | Z90: 0 | AA90: 8 | AB90: 8 | AC90: 8 | AD90: 20 | AE90: 0 | AF90: 65 | AG90: 3 | AH90: 0 | AI90: 96
A91: 91 | B91: LUIS ALBERTO GOMEZ LAHUANA | C91: E | D91: 6 | E91: 623 | F91: 16 | G91: 639 | H91: 17 | I91: 656 | J91: 19 | K91: 675 | L91: 14 | M91: 689 | N91: 15 | O91: 704 | P91: 11 | Q91: 715 | R91: 11 | S91: 722 | T91: 7 | U91: 730 | V91: 8 | W91: 740 | X91: 10 | Y91: 750 | Z91: 10 | AA91: 765 | AB91: 15 | AC91: 15 | AD91: 0 | AE91: 0 | AG91: 3 | AH91: 0 | AI91: 18
A92: 92 | B92: GREGORIO TRUJILLO LEON | C92: E | D92: 7 | E92: 1760 | F92: 3 | G92: 1763 | H92: 10 | I92: 1773 | J92: 7 | K92: 1780 | L92: 3 | M92: 1783 | N92: 15 | O92: 1798 | P92: 2 | Q92: 1800 | R92: 2 | S92: 1803 | T92: 3 | U92: 1804 | V92: 1 | W92: 1808 | X92: 4 | Y92: 1814 | Z92: 6 | AA92: 1819 | AB92: 5 | AC92: 5 | AD92: 0 | AE92: 0 | AG92: 3 | AH92: 0 | AI92: 8
A93: 93 | B93: GERTRUDES VIDAL GONZALES | C93: E | D93: 8 | E93: 826 | F93: 4 | G93: 830 | H93: 5 | I93: 835 | J93: 7 | K93: 842 | L93: 9 | M93: 851 | N93: 21 | O93: 872 | P93: 5 | Q93: 877 | R93: 5 | S93: 896 | T93: 19 | U93: 899 | V93: 3 | W93: 904 | X93: 5 | Y93: 913 | Z93: 9 | AA93: 919 | AB93: 6 | AC93: 6 | AD93: 0 | AE93: 0 | AG93: 3 | AH93: 0 | AI93: 9
A94: 94 | B94: MARIA NANCY SIGUEÑAS UGARTE | C94: E | D94: 9 | E94: 3190 | F94: 21 | G94: 3211 | H94: 21 | I94: 3232 | J94: 20 | K94: 3252 | L94: 22 | M94: 3274 | N94: 23 | O94: 3297 | P94: 17 | Q94: 3314 | R94: 17 | S94: 3328 | T94: 14 | U94: 3340 | V94: 12 | W94: 3355 | X94: 15 | Y94: 3375 | Z94: 20 | AA94: 3397 | AB94: 22 | AC94: 22 | AD94: 0 | AE94: 0 | AG94: 3 | AH94: 0 | AI94: 25
A95: 95 | B95: GREGORIA SIGUEÑAS UGARTE | C95: E | D95: 10 | E95: 100 | F95: 51 | G95: 151 | H95: 49 | I95: 200 | J95: 36 | K95: 236 | L95: 32 | M95: 268 | N95: 29 | O95: 297 | P95: 23 | Q95: 320 | R95: 23 | S95: 340 | T95: 20 | U95: 359 | V95: 19 | W95: 386 | X95: 27 | Y95: 411 | Z95: 25 | AA95: 445 | AB95: 34 | AC95: 34 | AD95: 28 | AE95: 0 | AG95: 3 | AH95: 20 | AI95: 85
A96: 96 | B96: VILMA SIGUEÑAS UGARTE | C96: E | D96: 11 | E96: 3342 | F96: 56 | G96: 3398 | H96: 48 | I96: 3446 | J96: 33 | K96: 3479 | L96: 29 | M96: 3508 | N96: 30 | O96: 3538 | P96: 26 | Q96: 3564 | R96: 26 | S96: 3587 | T96: 23 | U96: 3610 | V96: 23 | W96: 3633 | X96: 23 | Y96: 3659 | Z96: 26 | AA96: 3685 | AB96: 26 | AC96: 26 | AD96: 0 | AE96: 0 | AG96: 3 | AH96: 0 | AI96: 29
A97: 97 | B97: TEOFILA FERNANDEZ REYES | C97: E | D97: 12 | E97: 3375 | F97: 16 | G97: 3391 | H97: 13 | I97: 3404 | J97: 13 | K97: 3417 | L97: 12 | M97: 3429 | N97: 13 | O97: 3442 | P97: 10 | Q97: 3452 | R97: 10 | S97: 3463 | T97: 11 | U97: 3473 | V97: 10 | W97: 3489 | X97: 16 | Y97: 3503 | Z97: 14 | AA97: 3516 | AB97: 13 | AC97: 13 | AD97: 17 | AE97: 0 | AG97: 3 | AH97: 0 | AI97: 33
A98: 98 | B98: LINDOLINA MUÑOZ HERMITAÑO | C98: E | D98: 13 | E98: 2528 | F98: 28 | G98: 2556 | H98: 30 | I98: 2586 | J98: 19 | K98: 2605 | L98: 20 | M98: 2625 | N98: 26 | O98: 2651 | P98: 21 | Q98: 2672 | R98: 21 | S98: 2691 | T98: 19 | U98: 2710 | V98: 19 | W98: 2727 | X98: 17 | Y98: 2751 | Z98: 24 | AA98: 2767 | AB98: 16 | AC98: 16 | AD98: 0 | AE98: 0 | AG98: 3 | AH98: 0 | AI98: 19
A99: 99 | B99: FELICIANO SIGUEÑAS UGARTE | C99: E | D99: 14 | E99: 4542 | F99: 18 | G99: 4560 | H99: 18 | I99: 4578 | J99: 18 | K99: 4596 | L99: 27 | M99: 4623 | N99: 33 | O99: 4656 | P99: 14 | Q99: 4670 | R99: 14 | S99: 4683 | T99: 13 | U99: 4695 | V99: 12 | W99: 4708 | X99: 13 | Y99: 4722 | Z99: 14 | AA99: 4740 | AB99: 18 | AC99: 18 | AD99: 0 | AE99: 0 | AG99: 3 | AH99: 0 | AI99: 21
A100: 100 | B100: JUAN SAAVEDRA SAAVEDRA | C100: E | D100: 14-B | E100: 216 | F100: 4 | G100: 220 | H100: 5 | I100: 225 | J100: 6 | K100: 231 | L100: 4 | M100: 235 | N100: 4 | O100: 239 | P100: 4 | Q100: 243 | R100: 4 | S100: 246 | T100: 3 | U100: 249 | V100: 3 | W100: 252 | X100: 3 | Y100: 256 | Z100: 4 | AA100: 260 | AB100: 4 | AC100: 5 | AD100: 8 | AE100: 0 | AG100: 3 | AH100: 0 | AI100: 16
A101: 101 | B101: MERCADO TUPAC AMARU | C101: E | D101: 19 | P101: 1 | Q101: 0 | R101: 0 | S101: 0 | T101: 0 | U101: 0 | V101: 0 | W101: 0 | X101: 0 | Y101: 0 | Z101: 0 | AA101: 0 | AB101: 0 | AC101: 5 | AD101: 0 | AE101: 0 | AG101: 3 | AH101: 0 | AI101: 8
A102: 102 | B102: MARIA GODO SIFUENTES | C102: F | D102: 1 | E102: 344 | F102: 23 | G102: 367 | H102: 20 | I102: 387 | J102: 23 | K102: 410 | L102: 19 | M102: 429 | N102: 20 | O102: 449 | P102: 16 | Q102: 465 | R102: 16 | S102: 481 | T102: 16 | U102: 498 | V102: 17 | W102: 518 | X102: 20 | Y102: 534 | Z102: 16 | AA102: 553 | AB102: 19 | AC102: 19 | AD102: 0 | AE102: 0 | AG102: 3 | AH102: 0 | AI102: 22
A103: 103 | B103: CAMILA DELGADO VEGA | C103: F | D103: 3 | E103: 1 | F103: 0 | G103: 1 | H103: 4 | I103: 5 | J103: 1 | K103: 2 | L103: 3 | M103: 5 | N103: -2 | O103: 3 | P103: 0 | Q103: 3 | R103: 0 | S103: 3 | T103: 0 | U103: 3 | V103: 0 | W103: 3 | X103: 0 | Y103: 3 | Z103: 0 | AA103: 3 | AB103: 0 | AC103: 5 | AD103: 0 | AE103: 0 | AG103: 3 | AH103: 0 | AI103: 8
A104: 104 | B104: ABIGAIL SONIA GASPAR VEGA | C104: F | D104: 3-B | E104: 251 | F104: 4 | G104: 255 | H104: 12 | I104: 267 | J104: 8 | K104: 275 | L104: 9 | M104: 284 | N104: 7 | O104: 291 | P104: 4 | Q104: 295 | R104: 4 | S104: 296 | T104: 1 | U104: 296 | V104: 0 | W104: 297 | X104: 1 | Y104: 297 | Z104: 0 | AA104: 297 | AB104: 0 | AC104: 5 | AD104: 0 | AE104: 0 | AG104: 3 | AH104: 20 | AI104: 28
A105: 105 | B105: TOLENTINO JULCA MORENO | C105: F | D105: 4 | E105: 353 | F105: 11 | G105: 364 | H105: 15 | I105: 379 | J105: 14 | K105: 393 | L105: 15 | M105: 408 | N105: 17 | O105: 425 | P105: 10 | Q105: 435 | R105: 10 | S105: 444 | T105: 9 | U105: 455 | V105: 11 | W105: 465 | X105: 10 | Y105: 476 | Z105: 11 | AA105: 490 | AB105: 14 | AC105: 14 | AD105: 14 | AE105: 0 | AG105: 3 | AH105: 40 | AI105: 71
A106: 106 | B106: TEOFILO AYALA GASPAR | C106: F | D106: 5 | E106: 1428 | F106: 27 | G106: 1455 | H106: 34 | I106: 1489 | J106: 29 | K106: 1518 | L106: 26 | M106: 1544 | N106: 28 | O106: 1572 | P106: 29 | Q106: 1601 | R106: 29 | S106: 1623 | T106: 22 | U106: 1643 | V106: 20 | W106: 1662 | X106: 19 | Y106: 1686 | Z106: 24 | AA106: 1714 | AB106: 28 | AC106: 28 | AD106: 0 | AE106: 0 | AG106: 3 | AH106: 0 | AI106: 31
A107: 107 | B107: ALBERTO TARAZONA CALDAS | C107: F | D107: 6 | E107: 2851 | F107: 20 | G107: 2871 | H107: 20 | I107: 2891 | J107: 16 | K107: 2907 | L107: 16 | M107: 2923 | N107: 16 | O107: 2939 | P107: 11 | Q107: 2950 | R107: 11 | S107: 2960 | T107: 10 | U107: 2971 | V107: 11 | W107: 2978 | X107: 7 | Y107: 2993 | Z107: 15 | AA107: 3012 | AB107: 19 | AC107: 19 | AD107: 0 | AE107: 0 | AG107: 3 | AH107: 0 | AI107: 22
A108: 108 | B108: VICTOR LAURENCIO VALLADARES | C108: F | D108: 7 | E108: 6500 | F108: 33 | G108: 6533 | H108: 40 | I108: 6573 | J108: 26 | K108: 6599 | L108: 33 | M108: 6632 | N108: 19 | O108: 6651 | P108: 23 | Q108: 6674 | R108: 23 | S108: 6692 | T108: 18 | U108: 6708 | V108: 16 | W108: 6727 | X108: 19 | Y108: 6751 | Z108: 24 | AA108: 6780 | AB108: 29 | AC108: 29 | AD108: 27 | AE108: 0 | AG108: 3 | AH108: 0 | AI108: 59
A109: 109 | B109: GUDELIA ELIZABETH MIRANDA VEGA | C109: F | D109: 8 | E109: 1568 | F109: 16 | G109: 1584 | H109: 11 | I109: 1595 | J109: 8 | K109: 1603 | L109: 11 | M109: 1614 | N109: 10 | O109: 1624 | P109: 10 | Q109: 1634 | R109: 10 | S109: 1641 | T109: 7 | U109: 1650 | V109: 9 | W109: 1659 | X109: 9 | Y109: 1665 | Z109: 6 | AA109: 1673 | AB109: 8 | AC109: 8 | AD109: 0 | AE109: 0 | AG109: 3 | AH109: 0 | AI109: 11
A110: 111 | B110: HERMINIO LUCERO TRUJILLO | C110: F | D110: 10 | E110: 2420 | F110: 21 | G110: 2441 | H110: 6 | I110: 2447 | J110: 5 | K110: 5 | L110: 7 | M110: 12 | N110: 7 | O110: 19 | P110: 5 | Q110: 24 | R110: 5 | S110: 30 | T110: 6 | U110: 39 | V110: 9 | W110: 47 | X110: 8 | Y110: 57 | Z110: 10 | AA110: 70 | AB110: 13 | AC110: 13 | AD110: 0 | AE110: 0 | AG110: 3 | AH110: 0 | AI110: 16
A111: 112 | B111: JANETH CHAVEZ CASTILLEJO | C111: F | D111: 11 | E111: 2633 | F111: 21 | G111: 2654 | H111: 28 | I111: 2682 | J111: 20 | K111: 2702 | L111: 19 | M111: 2721 | N111: 16 | O111: 2737 | P111: 13 | Q111: 2750 | R111: 13 | S111: 2762 | T111: 12 | U111: 2773 | V111: 11 | W111: 2783 | X111: 10 | Y111: 2796 | Z111: 13 | AA111: 2811 | AB111: 15 | AC111: 15 | AD111: 0 | AE111: 0 | AG111: 3 | AH111: 0 | AI111: 18
A112: 113 | B112: DARIO OCTAVIO VEGA JULCA | C112: F | D112: 12 | E112: 1044 | F112: 9 | G112: 1053 | H112: 9 | I112: 1062 | J112: 7 | K112: 1069 | L112: 6 | M112: 1075 | N112: 4 | O112: 1079 | P112: 4 | Q112: 1083 | R112: 4 | S112: 1086 | T112: 3 | U112: 1090 | V112: 4 | W112: 1093 | X112: 3 | Y112: 1107 | Z112: 14 | AA112: 1106 | AB112: -1 | AC112: 5 | AD112: 0 | AE112: 0 | AG112: 3 | AH112: 20 | AI112: 28
A113: 114 | B113: RODRIGO PODESTA ROSAS | C113: F | D113: 14 | E113: 717 | F113: 40 | G113: 757 | H113: 33 | I113: 790 | J113: 40 | K113: 830 | L113: 34 | M113: 864 | N113: 38 | O113: 902 | P113: 34 | Q113: 936 | R113: 34 | S113: 969 | T113: 33 | U113: 1001 | V113: 32 | W113: 1033 | X113: 32 | Y113: 1069 | Z113: 36 | AA113: 1134 | AB113: 65 | AC113: 130 | AD113: 0 | AE113: 0 | AG113: 3 | AH113: 20 | AI113: 153
A114: 115 | B114: DARIO SAENZ MURPHY | C114: F | D114: 15 | E114: 432 | F114: 11 | G114: 443 | H114: 12 | I114: 455 | J114: 8 | K114: 463 | L114: 11 | M114: 474 | N114: 13 | O114: 487 | P114: 10 | Q114: 497 | R114: 10 | S114: 504 | T114: 7 | U114: 515 | V114: 11 | W114: 525 | X114: 10 | Y114: 535 | Z114: 10 | AA114: 548 | AB114: 13 | AC114: 13 | AD114: 0 | AE114: 0 | AG114: 3 | AH114: 0 | AI114: 16
A115: 116 | B115: JACINTO MORENO BAUTISTA | C115: G | D115: 1 | E115: 352 | F115: 23 | G115: 375 | H115: 21 | I115: 396 | J115: 17 | K115: 413 | L115: 18 | M115: 431 | N115: 17 | O115: 448 | P115: 16 | Q115: 464 | R115: 16 | S115: 479 | T115: 15 | U115: 493 | V115: 14 | W115: 507 | X115: 14 | Y115: 523 | Z115: 16 | AA115: 540 | AB115: 17 | AC115: 17 | AD115: 0 | AE115: 0 | AG115: 3 | AH115: 0 | AI115: 20
A116: 117 | B116: SANTOS BAUTISTA CAPCHA | C116: G | D116: 2 | E116: 3422 | F116: 27 | G116: 3449 | H116: 26 | I116: 3475 | J116: 23 | K116: 3498 | L116: 22 | M116: 3520 | N116: 18 | O116: 3538 | P116: 16 | Q116: 3554 | R116: 16 | S116: 3568 | T116: 14 | U116: 3583 | V116: 15 | W116: 3599 | X116: 16 | Y116: 3615 | Z116: 16 | AA116: 3635 | AB116: 20 | AC116: 20 | AD116: 19 | AE116: 0 | AG116: 3 | AH116: 0 | AI116: 42
... A129: 130 | B129: CRISOSTOMO ALBORNOZ TICLIO | C129: G | D129: 16 | E129: 4603 | F129: 13 | G129: 4616 | H129: 16 | I129: 4632 | J129: 13 | K129: 4645 | L129: 9 | M129: 4654 | N129: 13 | O129: 4667 | P129: 14 | Q129: 4681 | R129: 14 | S129: 4688 | T129: 7 | U129: 4696 | V129: 8 | W129: 4704 | X129: 8 | Y129: 4713 | Z129: 9 | AA129: 4721 | AB129: 8 | AC129: 8 | AD129: 0 | AE129: 0 | AG129: 3 | AH129: 20 | AI129: 31
...
