Workbook

Sheet Cobranza
A1: nª | B1: NOMBRES | C1: MZ | D1: LT | E1: TIPO CONVENIO | F1: MAYOR 65 | G1: NO COBRO | H1: Costo x m3 | I1: Marcación anterior | J1: Marcacion altual | K1: M3 | L1: Total mes actual | M1: MES ANTERIOR | N1: Corte y reconexion | O1: Convenio | P1: Mantenimiento | Q1: Multa (faena + reunión) | R1: Devoluciones | S1: Ajuste | T1: Total | U1: Yape rep | V1: Monto Efectivo | W1: Estado | X1: Fecha | Y1: Medio | Z1: Comentario | AA1: Estado del servicio | AB1: corte por consumo | AC1: Corte por faena | AD1: Efectivo | AE1: Yape | AF1: Llave1 | AG1: LLAVE (Mz, Lt)
A2: 1 | B2: MARCELINA OBREGON DE AVILA | C2: A | D2: 1 | H2: 1 | I2: 11 | J2: 19 | K2: 8 | L2: 8 | M2: 0 | N2: 0 | O2: 75 | P2: 3 | Q2: 0 | T2: =SUM(L2:S2) -> 86 | U2: =IFERROR(__xludf.DUMMYFUNCTION("IFERROR( SUM( FILTER( Reporte!$E:$E, REGEXMATCH(Reporte!$A:$A, ""(?i)(TE PAGÓ|PAGASTE)""), Reporte!$H:$H & """" = AG2 & """" ) ), 0 )"),11) -> 11 | V2: =IFERROR(__xludf.DUMMYFUNCTION("IFERROR( SUM( FILTER( Efectivo!$C:$C, Efectivo!$D:$D & """" = AG2 & """" ) ), 0 )"),75) -> 75 | W2: c | Y2: y | Z2: Debe 0. 75 esta en el efectivo | AB2: =IF(AND(L2>0, M2>=8, NOT(OR(W2="C", W2="c"))), "CORTE", "") | AC2: =IF( OR( AND(Q2>0, OR(W2="C", W2="c"), S2<0), AND(Q2>0, W2="") ), "CORTE", "" ) | AD2: =IF(AND(LEN(W2)>0,LEN(Y2)=0),T2,0) -> 0 | AE2: =IF(AND(LEN(W2)>0,TRIM(Y2)="Y"),T2,0) -> 86 | AF2: =TRIM(UPPER(C2)) -> A | AG2: =TRIM(UPPER(C2)) & "-" & TRIM(UPPER(D2)) -> A-1
A3: 2 | B3: ROSA AURORA ROCA VIDAL | C3: A | D3: 2 | H3: 1 | I3: 2703 | J3: 2723 | K3: 20 | L3: 20 | M3: 0 | N3: 0 | O3: 0 | P3: 3 | Q3: 0 | T3: =SUM(L3:S3) -> 23 | U3: =IFERROR(__xludf.DUMMYFUNCTION("IFERROR( SUM( FILTER( Reporte!$E:$E, REGEXMATCH(Reporte!$A:$A, ""(?i)(TE PAGÓ|PAGASTE)""), Reporte!$H:$H & """" = AG3 & """" ) ), 0 )"),0) -> 0 | V3: =IFERROR(__xludf.DUMMYFUNCTION("IFERROR( SUM( FILTER( Efectivo!$C:$C, Efectivo!$D:$D & """" = AG3 & """" ) ), 0 )"),0) -> 0 | AB3: =IF(AND(L3>0, M3>=8, NOT(OR(W3="C", W3="c"))), "CORTE", "") | AC3: =IF( OR( AND(Q3>0, OR(W3="C", W3="c"), S3<0), AND(Q3>0, W3="") ), "CORTE", "" ) | AD3: =IF(AND(LEN(W3)>0,LEN(Y3)=0),T3,0) -> 0 | AE3: =IF(AND(LEN(W3)>0,TRIM(Y3)="Y"),T3,0) -> 0 | AF3: =TRIM(UPPER(C3)) -> A | AG3: =TRIM(UPPER(C3)) & "-" & TRIM(UPPER(D3)) -> A-2
A4: 3 | B4: LINDA PAJUELO COCHACHIN | C4: A | D4: 3 | H4: 1 | I4: 22 | J4: 22 | K4: 5 | L4: 5 | M4: 0 | N4: 0 | O4: 0 | P4: 3 | Q4: 0 | T4: =SUM(L4:S4) -> 8 | U4: =IFERROR(__xludf.DUMMYFUNCTION("IFERROR( SUM( FILTER( Reporte!$E:$E, REGEXMATCH(Reporte!$A:$A, ""(?i)(TE PAGÓ|PAGASTE)""), Reporte!$H:$H & """" = AG4 & """" ) ), 0 )"),8) -> 8 | V4: =IFERROR(__xludf.DUMMYFUNCTION("IFERROR( SUM( FILTER( Efectivo!$C:$C, Efectivo!$D:$D & """" = AG4 & """" ) ), 0 )"),0) -> 0 | W4: c | Y4: y | AB4: =IF(AND(L4>0, M4>=8, NOT(OR(W4="C", W4="c"))), "CORTE", "") | AC4: =IF( OR( AND(Q4>0, OR(W4="C", W4="c"), S4<0), AND(Q4>0, W4="") ), "CORTE", "" ) | AD4: =IF(AND(LEN(W4)>0,LEN(Y4)=0),T4,0) -> 0 | AE4: =IF(AND(LEN(W4)>0,TRIM(Y4)="Y"),T4,0) -> 8 | AF4: =TRIM(UPPER(C4)) -> A | AG4: =TRIM(UPPER(C4)) & "-" & TRIM(UPPER(D4)) -> A-3
A5: 4 | B5: YOLANDA ESPINOZA JAIMES | C5: A | D5: 4 | H5: 1 | I5: 2 | J5: 2 | K5: 5 | N5: 40 | O5: 0 | P5: 1 | Q5: 0 | T5: =SUM(L5:S5) -> 41 | U5: =IFERROR(__xludf.DUMMYFUNCTION("IFERROR( SUM( FILTER( Reporte!$E:$E, REGEXMATCH(Reporte!$A:$A, ""(?i)(TE PAGÓ|PAGASTE)""), Reporte!$H:$H & """" = AG5 & """" ) ), 0 )"),41) -> 41 | V5: =IFERROR(__xludf.DUMMYFUNCTION("IFERROR( SUM( FILTER( Efectivo!$C:$C, Efectivo!$D:$D & """" = AG5 & """" ) ), 0 )"),0) -> 0 | W5: c | Y5: y | Z5: Debe 15 mes anterior | AB5: =IF(AND(L5>0, M5>=8, NOT(OR(W5="C", W5="c"))), "CORTE", "") | AC5: =IF( OR( AND(Q5>0, OR(W5="C", W5="c"), S5<0), AND(Q5>0, W5="") ), "CORTE", "" ) | AD5: =IF(AND(LEN(W5)>0,LEN(Y5)=0),T5,0) -> 0 | AE5: =IF(AND(LEN(W5)>0,TRIM(Y5)="Y"),T5,0) -> 41 | AF5: =TRIM(UPPER(C5)) -> A | AG5: =TRIM(UPPER(C5)) & "-" & TRIM(UPPER(D5)) -> A-4
A6: 5 | B6: JULIA AGAMA CUZCO | C6: A | D6: 5 | H6: 1 | I6: 16 | J6: 32 | K6: 16 | L6: 16 | M6: 0 | N6: 0 | O6: 25 | P6: 3 | Q6: 0 | T6: =SUM(L6:S6) -> 44 | U6: =IFERROR(__xludf.DUMMYFUNCTION("IFERROR( SUM( FILTER( Reporte!$E:$E, REGEXMATCH(Reporte!$A:$A, ""(?i)(TE PAGÓ|PAGASTE)""), Reporte!$H:$H & """" = AG6 & """" ) ), 0 )"),0) -> 0 | V6: =IFERROR(__xludf.DUMMYFUNCTION("IFERROR( SUM( FILTER( Efectivo!$C:$C, Efectivo!$D:$D & """" = AG6 & """" ) ), 0 )"),44) -> 44 | W6: c | AB6: =IF(AND(L6>0, M6>=8, NOT(OR(W6="C", W6="c"))), "CORTE", "") | AC6: =IF( OR( AND(Q6>0, OR(W6="C", W6="c"), S6<0), AND(Q6>0, W6="") ), "CORTE", "" ) | AD6: =IF(AND(LEN(W6)>0,LEN(Y6)=0),T6,0) -> 44 | AE6: =IF(AND(LEN(W6)>0,TRIM(Y6)="Y"),T6,0) -> 0 | AF6: =TRIM(UPPER(C6)) -> A | AG6: =TRIM(UPPER(C6)) & "-" & TRIM(UPPER(D6)) -> A-5
A7: 6 | B7: ESTEBAN REYES SANCHEZ | C7: A | D7: 6 | H7: 1 | I7: 26 | J7: 52 | K7: 26 | L7: 26 | M7: 0 | N7: 0 | O7: 25 | P7: 3 | Q7: 0 | T7: =SUM(L7:S7) -> 54 | U7: =IFERROR(__xludf.DUMMYFUNCTION("IFERROR( SUM( FILTER( Reporte!$E:$E, REGEXMATCH(Reporte!$A:$A, ""(?i)(TE PAGÓ|PAGASTE)""), Reporte!$H:$H & """" = AG7 & """" ) ), 0 )"),54) -> 54 | V7: =IFERROR(__xludf.DUMMYFUNCTION("IFERROR( SUM( FILTER( Efectivo!$C:$C, Efectivo!$D:$D & """" = AG7 & """" ) ), 0 )"),0) -> 0 | W7: c | Y7: y | AB7: =IF(AND(L7>0, M7>=8, NOT(OR(W7="C", W7="c"))), "CORTE", "") | AC7: =IF( OR( AND(Q7>0, OR(W7="C", W7="c"), S7<0), AND(Q7>0, W7="") ), "CORTE", "" ) | AD7: =IF(AND(LEN(W7)>0,LEN(Y7)=0),T7,0) -> 0 | AE7: =IF(AND(LEN(W7)>0,TRIM(Y7)="Y"),T7,0) -> 54 | AF7: =TRIM(UPPER(C7)) -> A | AG7: =TRIM(UPPER(C7)) & "-" & TRIM(UPPER(D7)) -> A-6
A8: 7 | B8: JUAN CARLOS MELGAREJO BEDON | C8: A | D8: 7 | H8: 1 | I8: 1766 | J8: 1777 | K8: 11 | L8: 11 | M8: 0 | N8: 0 | O8: 0 | P8: 3 | Q8: 0 | T8: =SUM(L8:S8) -> 14 | U8: =IFERROR(__xludf.DUMMYFUNCTION("IFERROR( SUM( FILTER( Reporte!$E:$E, REGEXMATCH(Reporte!$A:$A, ""(?i)(TE PAGÓ|PAGASTE)""), Reporte!$H:$H & """" = AG8 & """" ) ), 0 )"),14) -> 14 | V8: =IFERROR(__xludf.DUMMYFUNCTION("IFERROR( SUM( FILTER( Efectivo!$C:$C, Efectivo!$D:$D & """" = AG8 & """" ) ), 0 )"),0) -> 0 | W8: c | Y8: y | AB8: =IF(AND(L8>0, M8>=8, NOT(OR(W8="C", W8="c"))), "CORTE", "") | AC8: =IF( OR( AND(Q8>0, OR(W8="C", W8="c"), S8<0), AND(Q8>0, W8="") ), "CORTE", "" ) | AD8: =IF(AND(LEN(W8)>0,LEN(Y8)=0),T8,0) -> 0 | AE8: =IF(AND(LEN(W8)>0,TRIM(Y8)="Y"),T8,0) -> 14 | AF8: =TRIM(UPPER(C8)) -> A | AG8: =TRIM(UPPER(C8)) & "-" & TRIM(UPPER(D8)) -> A-7
A9: 8 | B9: VICTOR MELGAREJO CORCINO | C9: A | D9: 8 | H9: 1 | I9: 26 | J9: 49 | K9: 23 | L9: 23 | M9: 0 | N9: 0 | O9: 25 | P9: 3 | Q9: 0 | T9: =SUM(L9:S9) -> 51 | U9: =IFERROR(__xludf.DUMMYFUNCTION("IFERROR( SUM( FILTER( Reporte!$E:$E, REGEXMATCH(Reporte!$A:$A, ""(?i)(TE PAGÓ|PAGASTE)""), Reporte!$H:$H & """" = AG9 & """" ) ), 0 )"),0) -> 0 | V9: =IFERROR(__xludf.DUMMYFUNCTION("IFERROR( SUM( FILTER( Efectivo!$C:$C, Efectivo!$D:$D & """" = AG9 & """" ) ), 0 )"),0) -> 0 | AB9: =IF(AND(L9>0, M9>=8, NOT(OR(W9="C", W9="c"))), "CORTE", "") | AC9: =IF( OR( AND(Q9>0, OR(W9="C", W9="c"), S9<0), AND(Q9>0, W9="") ), "CORTE", "" ) | AD9: =IF(AND(LEN(W9)>0,LEN(Y9)=0),T9,0) -> 0 | AE9: =IF(AND(LEN(W9)>0,TRIM(Y9)="Y"),T9,0) -> 0 | AF9: =TRIM(UPPER(C9)) -> A | AG9: =TRIM(UPPER(C9)) & "-" & TRIM(UPPER(D9)) -> A-8
A10: 9 | B10: JHONI MELGAREJO BEDON | C10: A | D10: 8A | H10: 1 | I10: 186 | J10: 198 | K10: 12 | L10: 12 | M10: 0 | N10: 0 | O10: 0 | P10: 3 | Q10: 0 | T10: =SUM(L10:S10) -> 15 | U10: =IFERROR(__xludf.DUMMYFUNCTION("IFERROR( SUM( FILTER( Reporte!$E:$E, REGEXMATCH(Reporte!$A:$A, ""(?i)(TE PAGÓ|PAGASTE)""), Reporte!$H:$H & """" = AG10 & """" ) ), 0 )"),15) -> 15 | V10: =IFERROR(__xludf.DUMMYFUNCTION("IFERROR( SUM( FILTER( Efectivo!$C:$C, Efectivo!$D:$D & """" = AG10 & """" ) ), 0 )"),0) -> 0 | W10: c | Y10: y | AB10: =IF(AND(L10>0, M10>=8, NOT(OR(W10="C", W10="c"))), "CORTE", "") | AC10: =IF( OR( AND(Q10>0, OR(W10="C", W10="c"), S10<0), AND(Q10>0, W10="") ), "CORTE", "" ) | AD10: =IF(AND(LEN(W10)>0,LEN(Y10)=0),T10,0) -> 0 | AE10: =IF(AND(LEN(W10)>0,TRIM(Y10)="Y"),T10,0) -> 15 | AF10: =TRIM(UPPER(C10)) -> A | AG10: =TRIM(UPPER(C10)) & "-" & TRIM(UPPER(D10)) -> A-8A
A11: 10 | B11: ALEJANDRO MELGAREJO ESPINOZA | C11: A | D11: 9 | H11: 1 | I11: 2240 | J11: 2288 | K11: 48 | L11: 48 | M11: 0 | N11: 0 | O11: 0 | P11: 3 | Q11: 0 | T11: =SUM(L11:S11) -> 51 | U11: =IFERROR(__xludf.DUMMYFUNCTION("IFERROR( SUM( FILTER( Reporte!$E:$E, REGEXMATCH(Reporte!$A:$A, ""(?i)(TE PAGÓ|PAGASTE)""), Reporte!$H:$H & """" = AG11 & """" ) ), 0 )"),51) -> 51 | V11: =IFERROR(__xludf.DUMMYFUNCTION("IFERROR( SUM( FILTER( Efectivo!$C:$C, Efectivo!$D:$D & """" = AG11 & """" ) ), 0 )"),0) -> 0 | W11: c | Y11: y | AB11: =IF(AND(L11>0, M11>=8, NOT(OR(W11="C", W11="c"))), "CORTE", "") | AC11: =IF( OR( AND(Q11>0, OR(W11="C", W11="c"), S11<0), AND(Q11>0, W11="") ), "CORTE", "" ) | AD11: =IF(AND(LEN(W11)>0,LEN(Y11)=0),T11,0) -> 0 | AE11: =IF(AND(LEN(W11)>0,TRIM(Y11)="Y"),T11,0) -> 51 | AF11: =TRIM(UPPER(C11)) -> A | AG11: =TRIM(UPPER(C11)) & "-" & TRIM(UPPER(D11)) -> A-9
A12: 11 | B12: ISABEL PUNTILLO VEGA | C12: A | D12: 10 | H12: 1 | I12: 679 | J12: 683 | K12: 5 | L12: 5 | M12: 10 | N12: 0 | O12: 0 | P12: 3 | Q12: 0 | T12: =SUM(L12:S12) -> 18 | U12: =IFERROR(__xludf.DUMMYFUNCTION("IFERROR( SUM( FILTER( Reporte!$E:$E, REGEXMATCH(Reporte!$A:$A, ""(?i)(TE PAGÓ|PAGASTE)""), Reporte!$H:$H & """" = AG12 & """" ) ), 0 )"),18) -> 18 | V12: =IFERROR(__xludf.DUMMYFUNCTION("IFERROR( SUM( FILTER( Efectivo!$C:$C, Efectivo!$D:$D & """" = AG12 & """" ) ), 0 )"),0) -> 0 | W12: c | Y12: y | AB12: =IF(AND(L12>0, M12>=8, NOT(OR(W12="C", W12="c"))), "CORTE", "") | AC12: =IF( OR( AND(Q12>0, OR(W12="C", W12="c"), S12<0), AND(Q12>0, W12="") ), "CORTE", "" ) | AD12: =IF(AND(LEN(W12)>0,LEN(Y12)=0),T12,0) -> 0 | AE12: =IF(AND(LEN(W12)>0,TRIM(Y12)="Y"),T12,0) -> 18 | AF12: =TRIM(UPPER(C12)) -> A | AG12: =TRIM(UPPER(C12)) & "-" & TRIM(UPPER(D12)) -> A-10
A13: 12 | B13: FELIX POZO CASTRO | C13: A | D13: 11 | H13: 1 | I13: 363 | J13: 365 | K13: 5 | L13: 5 | M13: 8 | O13: 0 | P13: 3 | Q13: 0 | T13: =SUM(L13:S13) -> 16 | U13: =IFERROR(__xludf.DUMMYFUNCTION("IFERROR( SUM( FILTER( Reporte!$E:$E, REGEXMATCH(Reporte!$A:$A, ""(?i)(TE PAGÓ|PAGASTE)""), Reporte!$H:$H & """" = AG13 & """" ) ), 0 )"),16) -> 16 | V13: =IFERROR(__xludf.DUMMYFUNCTION("IFERROR( SUM( FILTER( Efectivo!$C:$C, Efectivo!$D:$D & """" = AG13 & """" ) ), 0 )"),0) -> 0 | W13: c | Y13: y | Z13: Debe 48. Corte reconexion 40, mes anterior 8 | AB13: =IF(AND(L13>0, M13>=8, NOT(OR(W13="C", W13="c"))), "CORTE", "") | AC13: =IF( OR( AND(Q13>0, OR(W13="C", W13="c"), S13<0), AND(Q13>0, W13="") ), "CORTE", "" ) | AD13: =IF(AND(LEN(W13)>0,LEN(Y13)=0),T13,0) -> 0 | AE13: =IF(AND(LEN(W13)>0,TRIM(Y13)="Y"),T13,0) -> 16 | AF13: =TRIM(UPPER(C13)) -> A | AG13: =TRIM(UPPER(C13)) & "-" & TRIM(UPPER(D13)) -> A-11
A14: 13 | B14: BACILIO UTRILLA FRANCISCO | C14: B | D14: 1 | H14: 1 | I14: 13 | J14: 23 | K14: 10 | L14: 10 | M14: 0 | N14: 0 | O14: 0 | P14: 3 | Q14: 0 | T14: =SUM(L14:S14) -> 13 | U14: =IFERROR(__xludf.DUMMYFUNCTION("IFERROR( SUM( FILTER( Reporte!$E:$E, REGEXMATCH(Reporte!$A:$A, ""(?i)(TE PAGÓ|PAGASTE)""), Reporte!$H:$H & """" = AG14 & """" ) ), 0 )"),13) -> 13 | V14: =IFERROR(__xludf.DUMMYFUNCTION("IFERROR( SUM( FILTER( Efectivo!$C:$C, Efectivo!$D:$D & """" = AG14 & """" ) ), 0 )"),0) -> 0 | W14: c | Y14: y | AB14: =IF(AND(L14>0, M14>=8, NOT(OR(W14="C", W14="c"))), "CORTE", "") | AC14: =IF( OR( AND(Q14>0, OR(W14="C", W14="c"), S14<0), AND(Q14>0, W14="") ), "CORTE", "" ) | AD14: =IF(AND(LEN(W14)>0,LEN(Y14)=0),T14,0) -> 0 | AE14: =IF(AND(LEN(W14)>0,TRIM(Y14)="Y"),T14,0) -> 13 | AF14: =TRIM(UPPER(C14)) -> B | AG14: =TRIM(UPPER(C14)) & "-" & TRIM(UPPER(D14)) -> B-1
A15: 14 | B15: ESTEBAN REYNALDO ROSALES | C15: B | D15: 2 | H15: 1 | I15: 16 | J15: 26 | K15: 10 | L15: 10 | M15: 0 | N15: 0 | O15: 25 | P15: 3 | Q15: 0 | T15: =SUM(L15:S15) -> 38 | U15: =IFERROR(__xludf.DUMMYFUNCTION("IFERROR( SUM( FILTER( Reporte!$E:$E, REGEXMATCH(Reporte!$A:$A, ""(?i)(TE PAGÓ|PAGASTE)""), Reporte!$H:$H & """" = AG15 & """" ) ), 0 )"),0) -> 0 | V15: =IFERROR(__xludf.DUMMYFUNCTION("IFERROR( SUM( FILTER( Efectivo!$C:$C, Efectivo!$D:$D & """" = AG15 & """" ) ), 0 )"),38) -> 38 | W15: c | AB15: =IF(AND(L15>0, M15>=8, NOT(OR(W15="C", W15="c"))), "CORTE", "") | AC15: =IF( OR( AND(Q15>0, OR(W15="C", W15="c"), S15<0), AND(Q15>0, W15="") ), "CORTE", "" ) | AD15: =IF(AND(LEN(W15)>0,LEN(Y15)=0),T15,0) -> 38 | AE15: =IF(AND(LEN(W15)>0,TRIM(Y15)="Y"),T15,0) -> 0 | AF15: =TRIM(UPPER(C15)) -> B | AG15: =TRIM(UPPER(C15)) & "-" & TRIM(UPPER(D15)) -> B-2
A16: 15 | B16: EDUARDO REYNALDO ROSALES | C16: B | D16: 3 | H16: 1 | I16: 837 | J16: 846 | K16: 9 | L16: 9 | M16: 0 | N16: 0 | O16: 0 | P16: 3 | Q16: 0 | T16: =SUM(L16:S16) -> 12 | U16: =IFERROR(__xludf.DUMMYFUNCTION("IFERROR( SUM( FILTER( Reporte!$E:$E, REGEXMATCH(Reporte!$A:$A, ""(?i)(TE PAGÓ|PAGASTE)""), Reporte!$H:$H & """" = AG16 & """" ) ), 0 )"),0) -> 0 | V16: =IFERROR(__xludf.DUMMYFUNCTION("IFERROR( SUM( FILTER( Efectivo!$C:$C, Efectivo!$D:$D & """" = AG16 & """" ) ), 0 )"),12) -> 12 | W16: c | AB16: =IF(AND(L16>0, M16>=8, NOT(OR(W16="C", W16="c"))), "CORTE", "") | AC16: =IF( OR( AND(Q16>0, OR(W16="C", W16="c"), S16<0), AND(Q16>0, W16="") ), "CORTE", "" ) | AD16: =IF(AND(LEN(W16)>0,LEN(Y16)=0),T16,0) -> 12 | AE16: =IF(AND(LEN(W16)>0,TRIM(Y16)="Y"),T16,0) -> 0 | AF16: =TRIM(UPPER(C16)) -> B | AG16: =TRIM(UPPER(C16)) & "-" & TRIM(UPPER(D16)) -> B-3
A17: 16 | B17: MELINA J. JUAREZ TOLEDO DE MORENO | C17: B | D17: 4 | H17: 1 | I17: 641 | J17: 655 | K17: 14 | L17: 14 | M17: 18 | N17: 0 | O17: 0 | P17: 3 | Q17: 0 | T17: =SUM(L17:S17) -> 35 | U17: =IFERROR(__xludf.DUMMYFUNCTION("IFERROR( SUM( FILTER( Reporte!$E:$E, REGEXMATCH(Reporte!$A:$A, ""(?i)(TE PAGÓ|PAGASTE)""), Reporte!$H:$H & """" = AG17 & """" ) ), 0 )"),35) -> 35 | V17: =IFERROR(__xludf.DUMMYFUNCTION("IFERROR( SUM( FILTER( Efectivo!$C:$C, Efectivo!$D:$D & """" = AG17 & """" ) ), 0 )"),0) -> 0 | W17: c | Y17: y | AB17: =IF(AND(L17>0, M17>=8, NOT(OR(W17="C", W17="c"))), "CORTE", "") | AC17: =IF( OR( AND(Q17>0, OR(W17="C", W17="c"), S17<0), AND(Q17>0, W17="") ), "CORTE", "" ) | AD17: =IF(AND(LEN(W17)>0,LEN(Y17)=0),T17,0) -> 0 | AE17: =IF(AND(LEN(W17)>0,TRIM(Y17)="Y"),T17,0) -> 35 | AF17: =TRIM(UPPER(C17)) -> B | AG17: =TRIM(UPPER(C17)) & "-" & TRIM(UPPER(D17)) -> B-4
A18: 17 | B18: POMPEYO CELESTINO LLIUYA | C18: B | D18: 5 | H18: 1 | I18: 59 | J18: 100 | K18: 41 | L18: 41 | M18: 39 | N18: 0 | O18: 25 | P18: 3 | Q18: 0 | T18: =SUM(L18:S18) -> 108 | U18: =IFERROR(__xludf.DUMMYFUNCTION("IFERROR( SUM( FILTER( Reporte!$E:$E, REGEXMATCH(Reporte!$A:$A, ""(?i)(TE PAGÓ|PAGASTE)""), Reporte!$H:$H & """" = AG18 & """" ) ), 0 )"),0) -> 0 | V18: =IFERROR(__xludf.DUMMYFUNCTION("IFERROR( SUM( FILTER( Efectivo!$C:$C, Efectivo!$D:$D & """" = AG18 & """" ) ), 0 )"),108) -> 108 | W18: c | AB18: =IF(AND(L18>0, M18>=8, NOT(OR(W18="C", W18="c"))), "CORTE", "") | AC18: =IF( OR( AND(Q18>0, OR(W18="C", W18="c"), S18<0), AND(Q18>0, W18="") ), "CORTE", "" ) | AD18: =IF(AND(LEN(W18)>0,LEN(Y18)=0),T18,0) -> 108 | AE18: =IF(AND(LEN(W18)>0,TRIM(Y18)="Y"),T18,0) -> 0 | AF18: =TRIM(UPPER(C18)) -> B | AG18: =TRIM(UPPER(C18)) & "-" & TRIM(UPPER(D18)) -> B-5
A19: 18 | B19: ROSA VICTORIA MILLA MORALES | C19: B | D19: 6 | H19: 1 | I19: 32 | J19: 62 | K19: 30 | L19: 30 | M19: 0 | N19: 0 | O19: 25 | P19: 3 | Q19: 0 | T19: =SUM(L19:S19) -> 58 | U19: =IFERROR(__xludf.DUMMYFUNCTION("IFERROR( SUM( FILTER( Reporte!$E:$E, REGEXMATCH(Reporte!$A:$A, ""(?i)(TE PAGÓ|PAGASTE)""), Reporte!$H:$H & """" = AG19 & """" ) ), 0 )"),58) -> 58 | V19: =IFERROR(__xludf.DUMMYFUNCTION("IFERROR( SUM( FILTER( Efectivo!$C:$C, Efectivo!$D:$D & """" = AG19 & """" ) ), 0 )"),0) -> 0 | W19: c | Y19: y | AB19: =IF(AND(L19>0, M19>=8, NOT(OR(W19="C", W19="c"))), "CORTE", "") | AC19: =IF( OR( AND(Q19>0, OR(W19="C", W19="c"), S19<0), AND(Q19>0, W19="") ), "CORTE", "" ) | AD19: =IF(AND(LEN(W19)>0,LEN(Y19)=0),T19,0) -> 0 | AE19: =IF(AND(LEN(W19)>0,TRIM(Y19)="Y"),T19,0) -> 58 | AF19: =TRIM(UPPER(C19)) -> B | AG19: =TRIM(UPPER(C19)) & "-" & TRIM(UPPER(D19)) -> B-6
A20: 19 | B20: LIRIA PARIAMACHI DE PAZ | C20: B | D20: 7 | H20: 1 | I20: 52 | J20: 65 | K20: 13 | L20: 13 | M20: 17 | N20: 0 | O20: 25 | P20: 3 | T20: =SUM(L20:S20) -> 58 | U20: =IFERROR(__xludf.DUMMYFUNCTION("IFERROR( SUM( FILTER( Reporte!$E:$E, REGEXMATCH(Reporte!$A:$A, ""(?i)(TE PAGÓ|PAGASTE)""), Reporte!$H:$H & """" = AG20 & """" ) ), 0 )"),58) -> 58 | V20: =IFERROR(__xludf.DUMMYFUNCTION("IFERROR( SUM( FILTER( Efectivo!$C:$C, Efectivo!$D:$D & """" = AG20 & """" ) ), 0 )"),0) -> 0 | W20: c | Y20: y | Z20: Debe 30. Faena | AB20: =IF(AND(L20>0, M20>=8, NOT(OR(W20="C", W20="c"))), "CORTE", "") | AC20: =IF( OR( AND(Q20>0, OR(W20="C", W20="c"), S20<0), AND(Q20>0, W20="") ), "CORTE", "" ) | AD20: =IF(AND(LEN(W20)>0,LEN(Y20)=0),T20,0) -> 0 | AE20: =IF(AND(LEN(W20)>0,TRIM(Y20)="Y"),T20,0) -> 58 | AF20: =TRIM(UPPER(C20)) -> B | AG20: =TRIM(UPPER(C20)) & "-" & TRIM(UPPER(D20)) -> B-7
A21: 20 | B21: ROSALINA OLIMPIA CIRIACO SOTELO | C21: B | D21: 8 | H21: 1 | I21: 21 | J21: 39 | K21: 18 | L21: 18 | M21: 0 | N21: 0 | O21: 25 | P21: 3 | Q21: 0 | T21: =SUM(L21:S21) -> 46 | U21: =IFERROR(__xludf.DUMMYFUNCTION("IFERROR( SUM( FILTER( Reporte!$E:$E, REGEXMATCH(Reporte!$A:$A, ""(?i)(TE PAGÓ|PAGASTE)""), Reporte!$H:$H & """" = AG21 & """" ) ), 0 )"),0) -> 0 | V21: =IFERROR(__xludf.DUMMYFUNCTION("IFERROR( SUM( FILTER( Efectivo!$C:$C, Efectivo!$D:$D & """" = AG21 & """" ) ), 0 )"),0) -> 0 | AB21: =IF(AND(L21>0, M21>=8, NOT(OR(W21="C", W21="c"))), "CORTE", "") | AC21: =IF( OR( AND(Q21>0, OR(W21="C", W21="c"), S21<0), AND(Q21>0, W21="") ), "CORTE", "" ) | AD21: =IF(AND(LEN(W21)>0,LEN(Y21)=0),T21,0) -> 0 | AE21: =IF(AND(LEN(W21)>0,TRIM(Y21)="Y"),T21,0) -> 0 | AF21: =TRIM(UPPER(C21)) -> B | AG21: =TRIM(UPPER(C21)) & "-" & TRIM(UPPER(D21)) -> B-8
A22: 21 | B22: ALEJANDRO RAPRAY VELASQUEZ | C22: B | D22: 9 | F22: 1 | H22: 1 | I22: 72 | J22: 78 | K22: 6 | L22: 6 | M22: 10 | N22: 40 | O22: 0 | P22: 3 | Q22: 0 | T22: =SUM(L22:S22) -> 59 | U22: =IFERROR(__xludf.DUMMYFUNCTION("IFERROR( SUM( FILTER( Reporte!$E:$E, REGEXMATCH(Reporte!$A:$A, ""(?i)(TE PAGÓ|PAGASTE)""), Reporte!$H:$H & """" = AG22 & """" ) ), 0 )"),0) -> 0 | V22: =IFERROR(__xludf.DUMMYFUNCTION("IFERROR( SUM( FILTER( Efectivo!$C:$C, Efectivo!$D:$D & """" = AG22 & """" ) ), 0 )"),59) -> 59 | W22: c | AB22: =IF(AND(L22>0, M22>=8, NOT(OR(W22="C", W22="c"))), "CORTE", "") | AC22: =IF( OR( AND(Q22>0, OR(W22="C", W22="c"), S22<0), AND(Q22>0, W22="") ), "CORTE", "" ) | AD22: =IF(AND(LEN(W22)>0,LEN(Y22)=0),T22,0) -> 59 | AE22: =IF(AND(LEN(W22)>0,TRIM(Y22)="Y"),T22,0) -> 0 | AF22: =TRIM(UPPER(C22)) -> B | AG22: =TRIM(UPPER(C22)) & "-" & TRIM(UPPER(D22)) -> B-9
A23: 22 | B23: ELVIRA PASCUALA MINAYA TAHUA | C23: B | D23: 11 | H23: 1 | I23: 26 | J23: 48 | K23: 22 | L23: 22 | M23: 19 | N23: 0 | O23: 25 | P23: 3 | Q23: 0 | T23: =SUM(L23:S23) -> 69 | U23: =IFERROR(__xludf.DUMMYFUNCTION("IFERROR( SUM( FILTER( Reporte!$E:$E, REGEXMATCH(Reporte!$A:$A, ""(?i)(TE PAGÓ|PAGASTE)""), Reporte!$H:$H & """" = AG23 & """" ) ), 0 )"),0) -> 0 | V23: =IFERROR(__xludf.DUMMYFUNCTION("IFERROR( SUM( FILTER( Efectivo!$C:$C, Efectivo!$D:$D & """" = AG23 & """" ) ), 0 )"),69) -> 69 | W23: c | AB23: =IF(AND(L23>0, M23>=8, NOT(OR(W23="C", W23="c"))), "CORTE", "") | AC23: =IF( OR( AND(Q23>0, OR(W23="C", W23="c"), S23<0), AND(Q23>0, W23="") ), "CORTE", "" ) | AD23: =IF(AND(LEN(W23)>0,LEN(Y23)=0),T23,0) -> 69 | AE23: =IF(AND(LEN(W23)>0,TRIM(Y23)="Y"),T23,0) -> 0 | AF23: =TRIM(UPPER(C23)) -> B | AG23: =TRIM(UPPER(C23)) & "-" & TRIM(UPPER(D23)) -> B-11
A24: 23 | B24: MARCELINO FELIX VILLAFANA PALLACA | C24: B | D24: 10 | H24: 1 | I24: 399 | J24: 421 | K24: 22 | L24: 22 | M24: 0 | N24: 0 | O24: 0 | P24: 3 | Q24: 0 | T24: =SUM(L24:S24) -> 25 | U24: =IFERROR(__xludf.DUMMYFUNCTION("IFERROR( SUM( FILTER( Reporte!$E:$E, REGEXMATCH(Reporte!$A:$A, ""(?i)(TE PAGÓ|PAGASTE)""), Reporte!$H:$H & """" = AG24 & """" ) ), 0 )"),0) -> 0 | V24: =IFERROR(__xludf.DUMMYFUNCTION("IFERROR( SUM( FILTER( Efectivo!$C:$C, Efectivo!$D:$D & """" = AG24 & """" ) ), 0 )"),0) -> 0 | AB24: =IF(AND(L24>0, M24>=8, NOT(OR(W24="C", W24="c"))), "CORTE", "") | AC24: =IF( OR( AND(Q24>0, OR(W24="C", W24="c"), S24<0), AND(Q24>0, W24="") ), "CORTE", "" ) | AD24: =IF(AND(LEN(W24)>0,LEN(Y24)=0),T24,0) -> 0 | AE24: =IF(AND(LEN(W24)>0,TRIM(Y24)="Y"),T24,0) -> 0 | AF24: =TRIM(UPPER(C24)) -> B | AG24: =TRIM(UPPER(C24)) & "-" & TRIM(UPPER(D24)) -> B-10
A25: 24 | B25: TEOFILO BRUNO RAMOS DE LA CRUZ | C25: B | D25: 12 | H25: 1 | I25: 9 | J25: 14 | K25: 5 | L25: 5 | M25: 0 | N25: 0 | O25: 0 | P25: 3 | Q25: 0 | T25: =SUM(L25:S25) -> 8 | U25: =IFERROR(__xludf.DUMMYFUNCTION("IFERROR( SUM( FILTER( Reporte!$E:$E, REGEXMATCH(Reporte!$A:$A, ""(?i)(TE PAGÓ|PAGASTE)""), Reporte!$H:$H & """" = AG25 & """" ) ), 0 )"),0) -> 0 | V25: =IFERROR(__xludf.DUMMYFUNCTION("IFERROR( SUM( FILTER( Efectivo!$C:$C, Efectivo!$D:$D & """" = AG25 & """" ) ), 0 )"),0) -> 0 | AB25: =IF(AND(L25>0, M25>=8, NOT(OR(W25="C", W25="c"))), "CORTE", "") | AC25: =IF( OR( AND(Q25>0, OR(W25="C", W25="c"), S25<0), AND(Q25>0, W25="") ), "CORTE", "" ) | AD25: =IF(AND(LEN(W25)>0,LEN(Y25)=0),T25,0) -> 0 | AE25: =IF(AND(LEN(W25)>0,TRIM(Y25)="Y"),T25,0) -> 0 | AF25: =TRIM(UPPER(C25)) -> B | AG25: =TRIM(UPPER(C25)) & "-" & TRIM(UPPER(D25)) -> B-12
A26: 25 | B26: ROSMERI SANCHEZ ESPADA | C26: B | D26: 12A | H26: 1 | I26: 365 | J26: 371 | K26: 6 | L26: 6 | M26: 9 | N26: 20 | O26: 0 | P26: 3 | Q26: 0 | T26: =SUM(L26:S26) -> 38 | U26: =IFERROR(__xludf.DUMMYFUNCTION("IFERROR( SUM( FILTER( Reporte!$E:$E, REGEXMATCH(Reporte!$A:$A, ""(?i)(TE PAGÓ|PAGASTE)""), Reporte!$H:$H & """" = AG26 & """" ) ), 0 )"),38) -> 38 | V26: =IFERROR(__xludf.DUMMYFUNCTION("IFERROR( SUM( FILTER( Efectivo!$C:$C, Efectivo!$D:$D & """" = AG26 & """" ) ), 0 )"),0) -> 0 | W26: c | Y26: y | Z26: Debe 20. Corte y reconexion | AB26: =IF(AND(L26>0, M26>=8, NOT(OR(W26="C", W26="c"))), "CORTE", "") | AC26: =IF( OR( AND(Q26>0, OR(W26="C", W26="c"), S26<0), AND(Q26>0, W26="") ), "CORTE", "" ) | AD26: =IF(AND(LEN(W26)>0,LEN(Y26)=0),T26,0) -> 0 | AE26: =IF(AND(LEN(W26)>0,TRIM(Y26)="Y"),T26,0) -> 38 | AF26: =TRIM(UPPER(C26)) -> B | AG26: =TRIM(UPPER(C26)) & "-" & TRIM(UPPER(D26)) -> B-12A
A27: 26 | B27: SALOME AGUSTINA DIAZ VARGAS | C27: B | D27: 13 | H27: 1 | I27: 300 | J27: 306 | K27: 6 | L27: 6 | M27: 0 | N27: 0 | O27: 0 | P27: 3 | Q27: 0 | T27: =SUM(L27:S27) -> 9 | U27: =IFERROR(__xludf.DUMMYFUNCTION("IFERROR( SUM( FILTER( Reporte!$E:$E, REGEXMATCH(Reporte!$A:$A, ""(?i)(TE PAGÓ|PAGASTE)""), Reporte!$H:$H & """" = AG27 & """" ) ), 0 )"),9) -> 9 | V27: =IFERROR(__xludf.DUMMYFUNCTION("IFERROR( SUM( FILTER( Efectivo!$C:$C, Efectivo!$D:$D & """" = AG27 & """" ) ), 0 )"),0) -> 0 | W27: c | Y27: y | AB27: =IF(AND(L27>0, M27>=8, NOT(OR(W27="C", W27="c"))), "CORTE", "") | AC27: =IF( OR( AND(Q27>0, OR(W27="C", W27="c"), S27<0), AND(Q27>0, W27="") ), "CORTE", "" ) | AD27: =IF(AND(LEN(W27)>0,LEN(Y27)=0),T27,0) -> 0 | AE27: =IF(AND(LEN(W27)>0,TRIM(Y27)="Y"),T27,0) -> 9 | AF27: =TRIM(UPPER(C27)) -> B | AG27: =TRIM(UPPER(C27)) & "-" & TRIM(UPPER(D27)) -> B-13
A28: 27 | B28: MELISSA ISABEL PILLACA GARCIA | C28: B | D28: 15 | H28: 1 | I28: 1295 | J28: 1311 | K28: 16 | L28: 16 | M28: 0 | N28: 0 | O28: 0 | P28: 3 | Q28: 0 | T28: =SUM(L28:S28) -> 19 | U28: =IFERROR(__xludf.DUMMYFUNCTION("IFERROR( SUM( FILTER( Reporte!$E:$E, REGEXMATCH(Reporte!$A:$A, ""(?i)(TE PAGÓ|PAGASTE)""), Reporte!$H:$H & """" = AG28 & """" ) ), 0 )"),19) -> 19 | V28: =IFERROR(__xludf.DUMMYFUNCTION("IFERROR( SUM( FILTER( Efectivo!$C:$C, Efectivo!$D:$D & """" = AG28 & """" ) ), 0 )"),0) -> 0 | W28: c | Y28: y | AB28: =IF(AND(L28>0, M28>=8, NOT(OR(W28="C", W28="c"))), "CORTE", "") | AC28: =IF( OR( AND(Q28>0, OR(W28="C", W28="c"), S28<0), AND(Q28>0, W28="") ), "CORTE", "" ) | AD28: =IF(AND(LEN(W28)>0,LEN(Y28)=0),T28,0) -> 0 | AE28: =IF(AND(LEN(W28)>0,TRIM(Y28)="Y"),T28,0) -> 19 | AF28: =TRIM(UPPER(C28)) -> B | AG28: =TRIM(UPPER(C28)) & "-" & TRIM(UPPER(D28)) -> B-15
A29: 28 | B29: ELEUTERIA DOMITILA PARIAMACHI DE PAZ | C29: B | D29: 16 | H29: 1 | I29: 34 | J29: 35 | K29: 5 | L29: 5 | M29: 8 | N29: 40 | O29: 0 | P29: 3 | Q29: 0 | T29: =SUM(L29:S29) -> 56 | U29: =IFERROR(__xludf.DUMMYFUNCTION("IFERROR( SUM( FILTER( Reporte!$E:$E, REGEXMATCH(Reporte!$A:$A, ""(?i)(TE PAGÓ|PAGASTE)""), Reporte!$H:$H & """" = AG29 & """" ) ), 0 )"),0) -> 0 | V29: =IFERROR(__xludf.DUMMYFUNCTION("IFERROR( SUM( FILTER( Efectivo!$C:$C, Efectivo!$D:$D & """" = AG29 & """" ) ), 0 )"),0) -> 0 | AB29: =IF(AND(L29>0, M29>=8, NOT(OR(W29="C", W29="c"))), "CORTE", "") -> CORTE | AC29: =IF( OR( AND(Q29>0, OR(W29="C", W29="c"), S29<0), AND(Q29>0, W29="") ), "CORTE", "" ) | AD29: =IF(AND(LEN(W29)>0,LEN(Y29)=0),T29,0) -> 0 | AE29: =IF(AND(LEN(W29)>0,TRIM(Y29)="Y"),T29,0) -> 0 | AF29: =TRIM(UPPER(C29)) -> B | AG29: =TRIM(UPPER(C29)) & "-" & TRIM(UPPER(D29)) -> B-16
A30: 29 | B30: LUZ DINA MIRAVAL HUERTA | C30: B | D30: 17 | H30: 1 | I30: 1093 | J30: 1122 | K30: 29 | L30: 29 | M30: 31 | O30: 0 | P30: 3 | Q30: 0 | T30: =SUM(L30:S30) -> 63 | U30: =IFERROR(__xludf.DUMMYFUNCTION("IFERROR( SUM( FILTER( Reporte!$E:$E, REGEXMATCH(Reporte!$A:$A, ""(?i)(TE PAGÓ|PAGASTE)""), Reporte!$H:$H & """" = AG30 & """" ) ), 0 )"),63) -> 63 | V30: =IFERROR(__xludf.DUMMYFUNCTION("IFERROR( SUM( FILTER( Efectivo!$C:$C, Efectivo!$D:$D & """" = AG30 & """" ) ), 0 )"),0) -> 0 | W30: c | Y30: y | Z30: Debe 40. Corte y reconexion | AB30: =IF(AND(L30>0, M30>=8, NOT(OR(W30="C", W30="c"))), "CORTE", "") | AC30: =IF( OR( AND(Q30>0, OR(W30="C", W30="c"), S30<0), AND(Q30>0, W30="") ), "CORTE", "" ) | AD30: =IF(AND(LEN(W30)>0,LEN(Y30)=0),T30,0) -> 0 | AE30: =IF(AND(LEN(W30)>0,TRIM(Y30)="Y"),T30,0) -> 63 | AF30: =TRIM(UPPER(C30)) -> B | AG30: =TRIM(UPPER(C30)) & "-" & TRIM(UPPER(D30)) -> B-17
A31: 30 | B31: CLETO TENORIO MORI | C31: B | D31: 18 | H31: 1 | I31: 577 | J31: 584 | K31: 7 | L31: 7 | M31: 8 | N31: 0 | O31: 0 | P31: 3 | Q31: 0 | T31: =SUM(L31:S31) -> 18 | U31: =IFERROR(__xludf.DUMMYFUNCTION("IFERROR( SUM( FILTER( Reporte!$E:$E, REGEXMATCH(Reporte!$A:$A, ""(?i)(TE PAGÓ|PAGASTE)""), Reporte!$H:$H & """" = AG31 & """" ) ), 0 )"),0) -> 0 | V31: =IFERROR(__xludf.DUMMYFUNCTION("IFERROR( SUM( FILTER( Efectivo!$C:$C, Efectivo!$D:$D & """" = AG31 & """" ) ), 0 )"),18) -> 18 | W31: c | AB31: =IF(AND(L31>0, M31>=8, NOT(OR(W31="C", W31="c"))), "CORTE", "") | AC31: =IF( OR( AND(Q31>0, OR(W31="C", W31="c"), S31<0), AND(Q31>0, W31="") ), "CORTE", "" ) | AD31: =IF(AND(LEN(W31)>0,LEN(Y31)=0),T31,0) -> 18 | AE31: =IF(AND(LEN(W31)>0,TRIM(Y31)="Y"),T31,0) -> 0 | AF31: =TRIM(UPPER(C31)) -> B | AG31: =TRIM(UPPER(C31)) & "-" & TRIM(UPPER(D31)) -> B-18
A32: 31 | B32: CAMILA HIDALGO | C32: B | D32: 21 | H32: 1 | I32: 199 | J32: 206 | K32: 7 | L32: 7 | M32: 15 | N32: 20 | O32: 0 | P32: 3 | T32: =SUM(L32:S32) -> 45 | U32: =IFERROR(__xludf.DUMMYFUNCTION("IFERROR( SUM( FILTER( Reporte!$E:$E, REGEXMATCH(Reporte!$A:$A, ""(?i)(TE PAGÓ|PAGASTE)""), Reporte!$H:$H & """" = AG32 & """" ) ), 0 )"),45) -> 45 | V32: =IFERROR(__xludf.DUMMYFUNCTION("IFERROR( SUM( FILTER( Efectivo!$C:$C, Efectivo!$D:$D & """" = AG32 & """" ) ), 0 )"),0) -> 0 | W32: c | Y32: y | Z32: Debe 20. Corte y reconexion. | AB32: =IF(AND(L32>0, M32>=8, NOT(OR(W32="C", W32="c"))), "CORTE", "") | AC32: =IF( OR( AND(Q32>0, OR(W32="C", W32="c"), S32<0), AND(Q32>0, W32="") ), "CORTE", "" ) | AD32: =IF(AND(LEN(W32)>0,LEN(Y32)=0),T32,0) -> 0 | AE32: =IF(AND(LEN(W32)>0,TRIM(Y32)="Y"),T32,0) -> 45 | AF32: =TRIM(UPPER(C32)) -> B | AG32: =TRIM(UPPER(C32)) & "-" & TRIM(UPPER(D32)) -> B-21
T33: =SUM(L33:S33) -> 0 | U33: =IFERROR(__xludf.DUMMYFUNCTION("IFERROR( SUM( FILTER( Reporte!$E:$E, REGEXMATCH(Reporte!$A:$A, ""(?i)(TE PAGÓ|PAGASTE)""), Reporte!$H:$H & """" = AG33 & """" ) ), 0 )"),-8203.9) -> -8203.9 | V33: =IFERROR(__xludf.DUMMYFUNCTION("IFERROR( SUM( FILTER( Efectivo!$C:$C, Efectivo!$D:$D & """" = AG33 & """" ) ), 0 )"),0) -> 0 | AB33: =IF(AND(L33>0, M33>=8, NOT(OR(W33="C", W33="c"))), "CORTE", "") | AC33: =IF( OR( AND(Q33>0, OR(W33="C", W33="c"), S33<0), AND(Q33>0, W33="") ), "CORTE", "" ) | AD33: =IF(AND(LEN(W33)>0,LEN(Y33)=0),T33,0) -> 0 | AE33: =IF(AND(LEN(W33)>0,TRIM(Y33)="Y"),T33,0) -> 0 | AF33: =TRIM(UPPER(C33)) | AG33: =TRIM(UPPER(C33)) & "-" & TRIM(UPPER(D33)) -> -
A34: 32 | B34: JANET FERNANDEZ MINAYA | C34: B | D34: 29 | E34: N | H34: 1 | I34: 187 | J34: 195 | K34: 8 | L34: 8 | M34: 0 | N34: 0 | O34: 283 | P34: 3 | Q34: 0 | T34: =SUM(L34:S34) -> 294 | U34: =IFERROR(__xludf.DUMMYFUNCTION("IFERROR( SUM( FILTER( Reporte!$E:$E, REGEXMATCH(Reporte!$A:$A, ""(?i)(TE PAGÓ|PAGASTE)""), Reporte!$H:$H & """" = AG34 & """" ) ), 0 )"),0) -> 0 | V34: =IFERROR(__xludf.DUMMYFUNCTION("IFERROR( SUM( FILTER( Efectivo!$C:$C, Efectivo!$D:$D & """" = AG34 & """" ) ), 0 )"),0) -> 0 | AB34: =IF(AND(L34>0, M34>=8, NOT(OR(W34="C", W34="c"))), "CORTE", "") | AC34: =IF( OR( AND(Q34>0, OR(W34="C", W34="c"), S34<0), AND(Q34>0, W34="") ), "CORTE", "" ) | AD34: =IF(AND(LEN(W34)>0,LEN(Y34)=0),T34,0) -> 0 | AE34: =IF(AND(LEN(W34)>0,TRIM(Y34)="Y"),T34,0) -> 0 | AF34: =TRIM(UPPER(C34)) -> B | AG34: =TRIM(UPPER(C34)) & "-" & TRIM(UPPER(D34)) -> B-29
A35: 33 | B35: ODILON CERNA ROMERO | C35: C | D35: 1 | H35: 1 | I35: 21 | J35: 37 | K35: 16 | L35: 16 | M35: 18 | N35: 0 | O35: 25 | P35: 3 | Q35: 0 | T35: =SUM(L35:S35) -> 62 | U35: =IFERROR(__xludf.DUMMYFUNCTION("IFERROR( SUM( FILTER( Reporte!$E:$E, REGEXMATCH(Reporte!$A:$A, ""(?i)(TE PAGÓ|PAGASTE)""), Reporte!$H:$H & """" = AG35 & """" ) ), 0 )"),62) -> 62 | V35: =IFERROR(__xludf.DUMMYFUNCTION("IFERROR( SUM( FILTER( Efectivo!$C:$C, Efectivo!$D:$D & """" = AG35 & """" ) ), 0 )"),0) -> 0 | W35: c | Y35: y | AB35: =IF(AND(L35>0, M35>=8, NOT(OR(W35="C", W35="c"))), "CORTE", "") | AC35: =IF( OR( AND(Q35>0, OR(W35="C", W35="c"), S35<0), AND(Q35>0, W35="") ), "CORTE", "" ) | AD35: =IF(AND(LEN(W35)>0,LEN(Y35)=0),T35,0) -> 0 | AE35: =IF(AND(LEN(W35)>0,TRIM(Y35)="Y"),T35,0) -> 62 | AF35: =TRIM(UPPER(C35)) -> C | AG35: =TRIM(UPPER(C35)) & "-" & TRIM(UPPER(D35)) -> C-1
A36: 34 | B36: OLGA FLORENTINA HUERTA AGAMA | C36: C | D36: 2 | H36: 1 | I36: 6 | J36: 11 | K36: 5 | L36: 5 | M36: 0 | N36: 0 | O36: 25 | P36: 3 | Q36: 0 | T36: =SUM(L36:S36) -> 33 | U36: =IFERROR(__xludf.DUMMYFUNCTION("IFERROR( SUM( FILTER( Reporte!$E:$E, REGEXMATCH(Reporte!$A:$A, ""(?i)(TE PAGÓ|PAGASTE)""), Reporte!$H:$H & """" = AG36 & """" ) ), 0 )"),0) -> 0 | V36: =IFERROR(__xludf.DUMMYFUNCTION("IFERROR( SUM( FILTER( Efectivo!$C:$C, Efectivo!$D:$D & """" = AG36 & """" ) ), 0 )"),33) -> 33 | W36: c | AB36: =IF(AND(L36>0, M36>=8, NOT(OR(W36="C", W36="c"))), "CORTE", "") | AC36: =IF( OR( AND(Q36>0, OR(W36="C", W36="c"), S36<0), AND(Q36>0, W36="") ), "CORTE", "" ) | AD36: =IF(AND(LEN(W36)>0,LEN(Y36)=0),T36,0) -> 33 | AE36: =IF(AND(LEN(W36)>0,TRIM(Y36)="Y"),T36,0) -> 0 | AF36: =TRIM(UPPER(C36)) -> C | AG36: =TRIM(UPPER(C36)) & "-" & TRIM(UPPER(D36)) -> C-2
A37: 35 | B37: TIMOTEO ROMERO JULCA | C37: C | D37: 4 | H37: 1 | I37: 21 | J37: 31 | K37: 10 | L37: 10 | M37: 0 | N37: 0 | O37: 25 | P37: 3 | Q37: 0 | T37: =SUM(L37:S37) -> 38 | U37: =IFERROR(__xludf.DUMMYFUNCTION("IFERROR( SUM( FILTER( Reporte!$E:$E, REGEXMATCH(Reporte!$A:$A, ""(?i)(TE PAGÓ|PAGASTE)""), Reporte!$H:$H & """" = AG37 & """" ) ), 0 )"),0) -> 0 | V37: =IFERROR(__xludf.DUMMYFUNCTION("IFERROR( SUM( FILTER( Efectivo!$C:$C, Efectivo!$D:$D & """" = AG37 & """" ) ), 0 )"),38) -> 38 | W37: c | AB37: =IF(AND(L37>0, M37>=8, NOT(OR(W37="C", W37="c"))), "CORTE", "") | AC37: =IF( OR( AND(Q37>0, OR(W37="C", W37="c"), S37<0), AND(Q37>0, W37="") ), "CORTE", "" ) | AD37: =IF(AND(LEN(W37)>0,LEN(Y37)=0),T37,0) -> 38 | AE37: =IF(AND(LEN(W37)>0,TRIM(Y37)="Y"),T37,0) -> 0 | AF37: =TRIM(UPPER(C37)) -> C | AG37: =TRIM(UPPER(C37)) & "-" & TRIM(UPPER(D37)) -> C-4
A38: 36 | B38: AGAPITO PRINCIPE SALINAS | C38: C | D38: 5 | H38: 1 | I38: 26 | J38: 49 | K38: 23 | L38: 23 | M38: 0 | N38: 0 | O38: 25 | P38: 3 | Q38: 0 | T38: =SUM(L38:S38) -> 51 | U38: =IFERROR(__xludf.DUMMYFUNCTION("IFERROR( SUM( FILTER( Reporte!$E:$E, REGEXMATCH(Reporte!$A:$A, ""(?i)(TE PAGÓ|PAGASTE)""), Reporte!$H:$H & """" = AG38 & """" ) ), 0 )"),51) -> 51 | V38: =IFERROR(__xludf.DUMMYFUNCTION("IFERROR( SUM( FILTER( Efectivo!$C:$C, Efectivo!$D:$D & """" = AG38 & """" ) ), 0 )"),0) -> 0 | W38: c | Y38: y | AB38: =IF(AND(L38>0, M38>=8, NOT(OR(W38="C", W38="c"))), "CORTE", "") | AC38: =IF( OR( AND(Q38>0, OR(W38="C", W38="c"), S38<0), AND(Q38>0, W38="") ), "CORTE", "" ) | AD38: =IF(AND(LEN(W38)>0,LEN(Y38)=0),T38,0) -> 0 | AE38: =IF(AND(LEN(W38)>0,TRIM(Y38)="Y"),T38,0) -> 51 | AF38: =TRIM(UPPER(C38)) -> C | AG38: =TRIM(UPPER(C38)) & "-" & TRIM(UPPER(D38)) -> C-5
A39: 37 | B39: DIANA JARA TRUJILLO | C39: C | D39: 6 | H39: 1 | I39: 598 | J39: 605 | K39: 7 | L39: 7 | M39: 0 | N39: 0 | O39: 0 | P39: 3 | Q39: 0 | T39: =SUM(L39:S39) -> 10 | U39: =IFERROR(__xludf.DUMMYFUNCTION("IFERROR( SUM( FILTER( Reporte!$E:$E, REGEXMATCH(Reporte!$A:$A, ""(?i)(TE PAGÓ|PAGASTE)""), Reporte!$H:$H & """" = AG39 & """" ) ), 0 )"),10) -> 10 | V39: =IFERROR(__xludf.DUMMYFUNCTION("IFERROR( SUM( FILTER( Efectivo!$C:$C, Efectivo!$D:$D & """" = AG39 & """" ) ), 0 )"),0) -> 0 | W39: c | Y39: y | AB39: =IF(AND(L39>0, M39>=8, NOT(OR(W39="C", W39="c"))), "CORTE", "") | AC39: =IF( OR( AND(Q39>0, OR(W39="C", W39="c"), S39<0), AND(Q39>0, W39="") ), "CORTE", "" ) | AD39: =IF(AND(LEN(W39)>0,LEN(Y39)=0),T39,0) -> 0 | AE39: =IF(AND(LEN(W39)>0,TRIM(Y39)="Y"),T39,0) -> 10 | AF39: =TRIM(UPPER(C39)) -> C | AG39: =TRIM(UPPER(C39)) & "-" & TRIM(UPPER(D39)) -> C-6
A40: 38 | B40: VICTOR LOPEZ TRUJILLO | C40: C | D40: 7 | H40: 1 | I40: 53 | J40: 79 | K40: 26 | L40: 26 | M40: 0 | N40: 0 | O40: 25 | P40: 3 | Q40: 0 | T40: =SUM(L40:S40) -> 54 | U40: =IFERROR(__xludf.DUMMYFUNCTION("IFERROR( SUM( FILTER( Reporte!$E:$E, REGEXMATCH(Reporte!$A:$A, ""(?i)(TE PAGÓ|PAGASTE)""), Reporte!$H:$H & """" = AG40 & """" ) ), 0 )"),0) -> 0 | V40: =IFERROR(__xludf.DUMMYFUNCTION("IFERROR( SUM( FILTER( Efectivo!$C:$C, Efectivo!$D:$D & """" = AG40 & """" ) ), 0 )"),0) -> 0 | AB40: =IF(AND(L40>0, M40>=8, NOT(OR(W40="C", W40="c"))), "CORTE", "") | AC40: =IF( OR( AND(Q40>0, OR(W40="C", W40="c"), S40<0), AND(Q40>0, W40="") ), "CORTE", "" ) | AD40: =IF(AND(LEN(W40)>0,LEN(Y40)=0),T40,0) -> 0 | AE40: =IF(AND(LEN(W40)>0,TRIM(Y40)="Y"),T40,0) -> 0 | AF40: =TRIM(UPPER(C40)) -> C | AG40: =TRIM(UPPER(C40)) & "-" & TRIM(UPPER(D40)) -> C-7
A41: 39 | B41: JULISSA BARRETO QUITO | C41: C | D41: 8 | H41: 1 | I41: 287 | J41: 295 | K41: 8 | L41: 8 | M41: 0 | N41: 0 | O41: 0 | P41: 3 | Q41: 0 | T41: =SUM(L41:S41) -> 11 | U41: =IFERROR(__xludf.DUMMYFUNCTION("IFERROR( SUM( FILTER( Reporte!$E:$E, REGEXMATCH(Reporte!$A:$A, ""(?i)(TE PAGÓ|PAGASTE)""), Reporte!$H:$H & """" = AG41 & """" ) ), 0 )"),0) -> 0 | V41: =IFERROR(__xludf.DUMMYFUNCTION("IFERROR( SUM( FILTER( Efectivo!$C:$C, Efectivo!$D:$D & """" = AG41 & """" ) ), 0 )"),0) -> 0 | AB41: =IF(AND(L41>0, M41>=8, NOT(OR(W41="C", W41="c"))), "CORTE", "") | AC41: =IF( OR( AND(Q41>0, OR(W41="C", W41="c"), S41<0), AND(Q41>0, W41="") ), "CORTE", "" ) | AD41: =IF(AND(LEN(W41)>0,LEN(Y41)=0),T41,0) -> 0 | AE41: =IF(AND(LEN(W41)>0,TRIM(Y41)="Y"),T41,0) -> 0 | AF41: =TRIM(UPPER(C41)) -> C | AG41: =TRIM(UPPER(C41)) & "-" & TRIM(UPPER(D41)) -> C-8
A42: 40 | B42: JAZMIN QUITO SANCHEZ | C42: C | D42: 8B | H42: 1 | I42: 1017 | J42: 1031 | K42: 14 | L42: 14 | M42: 0 | N42: 0 | O42: 0 | P42: 3 | Q42: 0 | T42: =SUM(L42:S42) -> 17 | U42: =IFERROR(__xludf.DUMMYFUNCTION("IFERROR( SUM( FILTER( Reporte!$E:$E, REGEXMATCH(Reporte!$A:$A, ""(?i)(TE PAGÓ|PAGASTE)""), Reporte!$H:$H & """" = AG42 & """" ) ), 0 )"),0) -> 0 | V42: =IFERROR(__xludf.DUMMYFUNCTION("IFERROR( SUM( FILTER( Efectivo!$C:$C, Efectivo!$D:$D & """" = AG42 & """" ) ), 0 )"),0) -> 0 | AB42: =IF(AND(L42>0, M42>=8, NOT(OR(W42="C", W42="c"))), "CORTE", "") | AC42: =IF( OR( AND(Q42>0, OR(W42="C", W42="c"), S42<0), AND(Q42>0, W42="") ), "CORTE", "" ) | AD42: =IF(AND(LEN(W42)>0,LEN(Y42)=0),T42,0) -> 0 | AE42: =IF(AND(LEN(W42)>0,TRIM(Y42)="Y"),T42,0) -> 0 | AF42: =TRIM(UPPER(C42)) -> C | AG42: =TRIM(UPPER(C42)) & "-" & TRIM(UPPER(D42)) -> C-8B
A43: 41 | B43: JUAN UCULMANA SANCHEZ | C43: C | D43: 9 | H43: 1 | I43: 2151 | J43: 2159 | K43: 8 | L43: 8 | M43: 0 | N43: 0 | O43: 0 | P43: 3 | Q43: 0 | T43: =SUM(L43:S43) -> 11 | U43: =IFERROR(__xludf.DUMMYFUNCTION("IFERROR( SUM( FILTER( Reporte!$E:$E, REGEXMATCH(Reporte!$A:$A, ""(?i)(TE PAGÓ|PAGASTE)""), Reporte!$H:$H & """" = AG43 & """" ) ), 0 )"),0) -> 0 | V43: =IFERROR(__xludf.DUMMYFUNCTION("IFERROR( SUM( FILTER( Efectivo!$C:$C, Efectivo!$D:$D & """" = AG43 & """" ) ), 0 )"),0) -> 0 | AB43: =IF(AND(L43>0, M43>=8, NOT(OR(W43="C", W43="c"))), "CORTE", "") | AC43: =IF( OR( AND(Q43>0, OR(W43="C", W43="c"), S43<0), AND(Q43>0, W43="") ), "CORTE", "" ) | AD43: =IF(AND(LEN(W43)>0,LEN(Y43)=0),T43,0) -> 0 | AE43: =IF(AND(LEN(W43)>0,TRIM(Y43)="Y"),T43,0) -> 0 | AF43: =TRIM(UPPER(C43)) -> C | AG43: =TRIM(UPPER(C43)) & "-" & TRIM(UPPER(D43)) -> C-9
A44: 42 | B44: SONIA GLORIA MORENO CASTILLEJO | C44: C | D44: 9C | H44: 1 | I44: 522 | J44: 530 | K44: 8 | L44: 8 | M44: 0 | N44: 0 | O44: 0 | P44: 3 | Q44: 0 | T44: =SUM(L44:S44) -> 11 | U44: =IFERROR(__xludf.DUMMYFUNCTION("IFERROR( SUM( FILTER( Reporte!$E:$E, REGEXMATCH(Reporte!$A:$A, ""(?i)(TE PAGÓ|PAGASTE)""), Reporte!$H:$H & """" = AG44 & """" ) ), 0 )"),11) -> 11 | V44: =IFERROR(__xludf.DUMMYFUNCTION("IFERROR( SUM( FILTER( Efectivo!$C:$C, Efectivo!$D:$D & """" = AG44 & """" ) ), 0 )"),0) -> 0 | W44: c | Y44: y | AB44: =IF(AND(L44>0, M44>=8, NOT(OR(W44="C", W44="c"))), "CORTE", "") | AC44: =IF( OR( AND(Q44>0, OR(W44="C", W44="c"), S44<0), AND(Q44>0, W44="") ), "CORTE", "" ) | AD44: =IF(AND(LEN(W44)>0,LEN(Y44)=0),T44,0) -> 0 | AE44: =IF(AND(LEN(W44)>0,TRIM(Y44)="Y"),T44,0) -> 11 | AF44: =TRIM(UPPER(C44)) -> C | AG44: =TRIM(UPPER(C44)) & "-" & TRIM(UPPER(D44)) -> C-9C
A45: 43 | B45: CEVERIANO CHAUCA MORALES | C45: C | D45: 11 | H45: 1 | I45: 851 | J45: 867 | K45: 16 | L45: 16 | M45: 0 | N45: 0 | O45: 0 | P45: 3 | Q45: 0 | T45: =SUM(L45:S45) -> 19 | U45: =IFERROR(__xludf.DUMMYFUNCTION("IFERROR( SUM( FILTER( Reporte!$E:$E, REGEXMATCH(Reporte!$A:$A, ""(?i)(TE PAGÓ|PAGASTE)""), Reporte!$H:$H & """" = AG45 & """" ) ), 0 )"),19) -> 19 | V45: =IFERROR(__xludf.DUMMYFUNCTION("IFERROR( SUM( FILTER( Efectivo!$C:$C, Efectivo!$D:$D & """" = AG45 & """" ) ), 0 )"),0) -> 0 | W45: c | Y45: y | AB45: =IF(AND(L45>0, M45>=8, NOT(OR(W45="C", W45="c"))), "CORTE", "") | AC45: =IF( OR( AND(Q45>0, OR(W45="C", W45="c"), S45<0), AND(Q45>0, W45="") ), "CORTE", "" ) | AD45: =IF(AND(LEN(W45)>0,LEN(Y45)=0),T45,0) -> 0 | AE45: =IF(AND(LEN(W45)>0,TRIM(Y45)="Y"),T45,0) -> 19 | AF45: =TRIM(UPPER(C45)) -> C | AG45: =TRIM(UPPER(C45)) & "-" & TRIM(UPPER(D45)) -> C-11
A46: 44 | B46: MACEDONIO MORALES BENTURO | C46: C | D46: 12 | H46: 1 | I46: 1684 | J46: 1698 | K46: 14 | L46: 14 | M46: 0 | N46: 0 | O46: 0 | P46: 3 | Q46: 0 | T46: =SUM(L46:S46) -> 17 | U46: =IFERROR(__xludf.DUMMYFUNCTION("IFERROR( SUM( FILTER( Reporte!$E:$E, REGEXMATCH(Reporte!$A:$A, ""(?i)(TE PAGÓ|PAGASTE)""), Reporte!$H:$H & """" = AG46 & """" ) ), 0 )"),0) -> 0 | V46: =IFERROR(__xludf.DUMMYFUNCTION("IFERROR( SUM( FILTER( Efectivo!$C:$C, Efectivo!$D:$D & """" = AG46 & """" ) ), 0 )"),17) -> 17 | W46: c | AB46: =IF(AND(L46>0, M46>=8, NOT(OR(W46="C", W46="c"))), "CORTE", "") | AC46: =IF( OR( AND(Q46>0, OR(W46="C", W46="c"), S46<0), AND(Q46>0, W46="") ), "CORTE", "" ) | AD46: =IF(AND(LEN(W46)>0,LEN(Y46)=0),T46,0) -> 17 | AE46: =IF(AND(LEN(W46)>0,TRIM(Y46)="Y"),T46,0) -> 0 | AF46: =TRIM(UPPER(C46)) -> C | AG46: =TRIM(UPPER(C46)) & "-" & TRIM(UPPER(D46)) -> C-12
A47: 45 | B47: IRMA HUAÑAHUI LOPEZ | C47: C | D47: 13 | H47: 1 | I47: 12 | J47: 18 | K47: 6 | L47: 6 | M47: 0 | N47: 0 | O47: 25 | P47: 3 | Q47: 0 | T47: =SUM(L47:S47) -> 34 | U47: =IFERROR(__xludf.DUMMYFUNCTION("IFERROR( SUM( FILTER( Reporte!$E:$E, REGEXMATCH(Reporte!$A:$A, ""(?i)(TE PAGÓ|PAGASTE)""), Reporte!$H:$H & """" = AG47 & """" ) ), 0 )"),34) -> 34 | V47: =IFERROR(__xludf.DUMMYFUNCTION("IFERROR( SUM( FILTER( Efectivo!$C:$C, Efectivo!$D:$D & """" = AG47 & """" ) ), 0 )"),0) -> 0 | W47: c | Y47: y | AB47: =IF(AND(L47>0, M47>=8, NOT(OR(W47="C", W47="c"))), "CORTE", "") | AC47: =IF( OR( AND(Q47>0, OR(W47="C", W47="c"), S47<0), AND(Q47>0, W47="") ), "CORTE", "" ) | AD47: =IF(AND(LEN(W47)>0,LEN(Y47)=0),T47,0) -> 0 | AE47: =IF(AND(LEN(W47)>0,TRIM(Y47)="Y"),T47,0) -> 34 | AF47: =TRIM(UPPER(C47)) -> C | AG47: =TRIM(UPPER(C47)) & "-" & TRIM(UPPER(D47)) -> C-13
A48: 46 | B48: JUAN RIOS BLAS | C48: C | D48: 14 | H48: 1 | I48: 9 | J48: 15 | K48: 6 | L48: 6 | M48: 0 | N48: 0 | O48: 33 | P48: 3 | Q48: 0 | T48: =SUM(L48:S48) -> 42 | U48: =IFERROR(__xludf.DUMMYFUNCTION("IFERROR( SUM( FILTER( Reporte!$E:$E, REGEXMATCH(Reporte!$A:$A, ""(?i)(TE PAGÓ|PAGASTE)""), Reporte!$H:$H & """" = AG48 & """" ) ), 0 )"),42) -> 42 | V48: =IFERROR(__xludf.DUMMYFUNCTION("IFERROR( SUM( FILTER( Efectivo!$C:$C, Efectivo!$D:$D & """" = AG48 & """" ) ), 0 )"),0) -> 0 | W48: c | Y48: y | Z48: Debe15. mes anterior | AB48: =IF(AND(L48>0, M48>=8, NOT(OR(W48="C", W48="c"))), "CORTE", "") | AC48: =IF( OR( AND(Q48>0, OR(W48="C", W48="c"), S48<0), AND(Q48>0, W48="") ), "CORTE", "" ) | AD48: =IF(AND(LEN(W48)>0,LEN(Y48)=0),T48,0) -> 0 | AE48: =IF(AND(LEN(W48)>0,TRIM(Y48)="Y"),T48,0) -> 42 | AF48: =TRIM(UPPER(C48)) -> C | AG48: =TRIM(UPPER(C48)) & "-" & TRIM(UPPER(D48)) -> C-14
A49: 47 | B49: JULIO RIOS BLAS | C49: C | D49: 15 | H49: 1 | I49: 136 | J49: 147 | K49: 11 | L49: 11 | M49: 0 | N49: 0 | O49: 0 | P49: 3 | Q49: 0 | T49: =SUM(L49:S49) -> 14 | U49: =IFERROR(__xludf.DUMMYFUNCTION("IFERROR( SUM( FILTER( Reporte!$E:$E, REGEXMATCH(Reporte!$A:$A, ""(?i)(TE PAGÓ|PAGASTE)""), Reporte!$H:$H & """" = AG49 & """" ) ), 0 )"),14) -> 14 | V49: =IFERROR(__xludf.DUMMYFUNCTION("IFERROR( SUM( FILTER( Efectivo!$C:$C, Efectivo!$D:$D & """" = AG49 & """" ) ), 0 )"),0) -> 0 | W49: c | Y49: y | AB49: =IF(AND(L49>0, M49>=8, NOT(OR(W49="C", W49="c"))), "CORTE", "") | AC49: =IF( OR( AND(Q49>0, OR(W49="C", W49="c"), S49<0), AND(Q49>0, W49="") ), "CORTE", "" ) | AD49: =IF(AND(LEN(W49)>0,LEN(Y49)=0),T49,0) -> 0 | AE49: =IF(AND(LEN(W49)>0,TRIM(Y49)="Y"),T49,0) -> 14 | AF49: =TRIM(UPPER(C49)) -> C | AG49: =TRIM(UPPER(C49)) & "-" & TRIM(UPPER(D49)) -> C-15
A50: 48 | B50: MARTHA MASIAS CASIHUAMAN DE TERAN | C50: C | D50: 16 | H50: 1 | I50: 26 | J50: 56 | K50: 30 | L50: 30 | M50: 21 | N50: 0 | O50: 25 | P50: 3 | Q50: 0 | T50: =SUM(L50:S50) -> 79 | U50: =IFERROR(__xludf.DUMMYFUNCTION("IFERROR( SUM( FILTER( Reporte!$E:$E, REGEXMATCH(Reporte!$A:$A, ""(?i)(TE PAGÓ|PAGASTE)""), Reporte!$H:$H & """" = AG50 & """" ) ), 0 )"),79) -> 79 | V50: =IFERROR(__xludf.DUMMYFUNCTION("IFERROR( SUM( FILTER( Efectivo!$C:$C, Efectivo!$D:$D & """" = AG50 & """" ) ), 0 )"),0) -> 0 | W50: c | Y50: y | Z50: Estamos viendo | AB50: =IF(AND(L50>0, M50>=8, NOT(OR(W50="C", W50="c"))), "CORTE", "") | AC50: =IF( OR( AND(Q50>0, OR(W50="C", W50="c"), S50<0), AND(Q50>0, W50="") ), "CORTE", "" ) | AD50: =IF(AND(LEN(W50)>0,LEN(Y50)=0),T50,0) -> 0 | AE50: =IF(AND(LEN(W50)>0,TRIM(Y50)="Y"),T50,0) -> 79 | AF50: =TRIM(UPPER(C50)) -> C | AG50: =TRIM(UPPER(C50)) & "-" & TRIM(UPPER(D50)) -> C-16
A51: 49 | B51: MARCELINO VALLADARES TRUJILLO | C51: C | D51: 18 | H51: 1 | I51: 12 | J51: 21 | K51: 9 | L51: 9 | M51: 0 | N51: 0 | O51: 25 | P51: 3 | Q51: 0 | T51: =SUM(L51:S51) -> 37 | U51: =IFERROR(__xludf.DUMMYFUNCTION("IFERROR( SUM( FILTER( Reporte!$E:$E, REGEXMATCH(Reporte!$A:$A, ""(?i)(TE PAGÓ|PAGASTE)""), Reporte!$H:$H & """" = AG51 & """" ) ), 0 )"),0) -> 0 | V51: =IFERROR(__xludf.DUMMYFUNCTION("IFERROR( SUM( FILTER( Efectivo!$C:$C, Efectivo!$D:$D & """" = AG51 & """" ) ), 0 )"),37) -> 37 | W51: c | AB51: =IF(AND(L51>0, M51>=8, NOT(OR(W51="C", W51="c"))), "CORTE", "") | AC51: =IF( OR( AND(Q51>0, OR(W51="C", W51="c"), S51<0), AND(Q51>0, W51="") ), "CORTE", "" ) | AD51: =IF(AND(LEN(W51)>0,LEN(Y51)=0),T51,0) -> 37 | AE51: =IF(AND(LEN(W51)>0,TRIM(Y51)="Y"),T51,0) -> 0 | AF51: =TRIM(UPPER(C51)) -> C | AG51: =TRIM(UPPER(C51)) & "-" & TRIM(UPPER(D51)) -> C-18
A52: 50 | B52: ANTONIO VALLADARES DOMINGUEZ | C52: C | D52: 19 | H52: 1 | I52: 37 | J52: 65 | K52: 28 | L52: 28 | M52: 0 | N52: 0 | O52: 3 | Q52: 0 | T52: =SUM(L52:S52) -> 31 | U52: =IFERROR(__xludf.DUMMYFUNCTION("IFERROR( SUM( FILTER( Reporte!$E:$E, REGEXMATCH(Reporte!$A:$A, ""(?i)(TE PAGÓ|PAGASTE)""), Reporte!$H:$H & """" = AG52 & """" ) ), 0 )"),0) -> 0 | V52: =IFERROR(__xludf.DUMMYFUNCTION("IFERROR( SUM( FILTER( Efectivo!$C:$C, Efectivo!$D:$D & """" = AG52 & """" ) ), 0 )"),31) -> 31 | W52: c | Z52: Debe 3. Mantenimiento | AB52: =IF(AND(L52>0, M52>=8, NOT(OR(W52="C", W52="c"))), "CORTE", "") | AC52: =IF( OR( AND(Q52>0, OR(W52="C", W52="c"), S52<0), AND(Q52>0, W52="") ), "CORTE", "" ) | AD52: =IF(AND(LEN(W52)>0,LEN(Y52)=0),T52,0) -> 31 | AE52: =IF(AND(LEN(W52)>0,TRIM(Y52)="Y"),T52,0) -> 0 | AF52: =TRIM(UPPER(C52)) -> C | AG52: =TRIM(UPPER(C52)) & "-" & TRIM(UPPER(D52)) -> C-19
A53: 51 | B53: EUSEBIO REYES VILLAFANA | C53: C | D53: 20 | H53: 1 | I53: 25 | J53: 42 | K53: 17 | L53: 17 | M53: 0 | N53: 0 | O53: 25 | P53: 3 | Q53: 0 | T53: =SUM(L53:S53) -> 45 | U53: =IFERROR(__xludf.DUMMYFUNCTION("IFERROR( SUM( FILTER( Reporte!$E:$E, REGEXMATCH(Reporte!$A:$A, ""(?i)(TE PAGÓ|PAGASTE)""), Reporte!$H:$H & """" = AG53 & """" ) ), 0 )"),45) -> 45 | V53: =IFERROR(__xludf.DUMMYFUNCTION("IFERROR( SUM( FILTER( Efectivo!$C:$C, Efectivo!$D:$D & """" = AG53 & """" ) ), 0 )"),0) -> 0 | W53: c | Y53: y | AB53: =IF(AND(L53>0, M53>=8, NOT(OR(W53="C", W53="c"))), "CORTE", "") | AC53: =IF( OR( AND(Q53>0, OR(W53="C", W53="c"), S53<0), AND(Q53>0, W53="") ), "CORTE", "" ) | AD53: =IF(AND(LEN(W53)>0,LEN(Y53)=0),T53,0) -> 0 | AE53: =IF(AND(LEN(W53)>0,TRIM(Y53)="Y"),T53,0) -> 45 | AF53: =TRIM(UPPER(C53)) -> C | AG53: =TRIM(UPPER(C53)) & "-" & TRIM(UPPER(D53)) -> C-20
A54: 52 | B54: PUESTO DE SALUD TUPAC AMARU | C54: C | D54: 21 | H54: 1 | I54: 1700 | J54: 1719 | K54: 19 | L54: 19 | M54: 27 | N54: 0 | O54: 0 | P54: 3 | Q54: 0 | T54: =SUM(L54:S54) -> 49 | U54: =IFERROR(__xludf.DUMMYFUNCTION("IFERROR( SUM( FILTER( Reporte!$E:$E, REGEXMATCH(Reporte!$A:$A, ""(?i)(TE PAGÓ|PAGASTE)""), Reporte!$H:$H & """" = AG54 & """" ) ), 0 )"),0) -> 0 | V54: =IFERROR(__xludf.DUMMYFUNCTION("IFERROR( SUM( FILTER( Efectivo!$C:$C, Efectivo!$D:$D & """" = AG54 & """" ) ), 0 )"),0) -> 0 | AA54: Exonerado | AB54: =IF(AND(L54>0, M54>=8, NOT(OR(W54="C", W54="c"))), "CORTE", "") -> CORTE | AC54: =IF( OR( AND(Q54>0, OR(W54="C", W54="c"), S54<0), AND(Q54>0, W54="") ), "CORTE", "" ) | AD54: =IF(AND(LEN(W54)>0,LEN(Y54)=0),T54,0) -> 0 | AE54: =IF(AND(LEN(W54)>0,TRIM(Y54)="Y"),T54,0) -> 0 | AF54: =TRIM(UPPER(C54)) -> C | AG54: =TRIM(UPPER(C54)) & "-" & TRIM(UPPER(D54)) -> C-21
A55: 53 | B55: ABRAHAM BARRERA VEGA | C55: C | D55: 22 | H55: 1 | I55: 134 | J55: 144 | K55: 10 | L55: 10 | M55: 0 | N55: 0 | O55: 0 | P55: 3 | Q55: 0 | T55: =SUM(L55:S55) -> 13 | U55: =IFERROR(__xludf.DUMMYFUNCTION("IFERROR( SUM( FILTER( Reporte!$E:$E, REGEXMATCH(Reporte!$A:$A, ""(?i)(TE PAGÓ|PAGASTE)""), Reporte!$H:$H & """" = AG55 & """" ) ), 0 )"),13) -> 13 | V55: =IFERROR(__xludf.DUMMYFUNCTION("IFERROR( SUM( FILTER( Efectivo!$C:$C, Efectivo!$D:$D & """" = AG55 & """" ) ), 0 )"),0) -> 0 | W55: c | Y55: y | AB55: =IF(AND(L55>0, M55>=8, NOT(OR(W55="C", W55="c"))), "CORTE", "") | AC55: =IF( OR( AND(Q55>0, OR(W55="C", W55="c"), S55<0), AND(Q55>0, W55="") ), "CORTE", "" ) | AD55: =IF(AND(LEN(W55)>0,LEN(Y55)=0),T55,0) -> 0 | AE55: =IF(AND(LEN(W55)>0,TRIM(Y55)="Y"),T55,0) -> 13 | AF55: =TRIM(UPPER(C55)) -> C | AG55: =TRIM(UPPER(C55)) & "-" & TRIM(UPPER(D55)) -> C-22
A56: 54 | B56: ANTONIA MAYO TRUJILLO | C56: C | D56: 23 | H56: 1 | I56: 280 | J56: 304 | K56: 24 | L56: 24 | M56: 0 | N56: 0 | O56: 0 | P56: 3 | Q56: 0 | T56: =SUM(L56:S56) -> 27 | U56: =IFERROR(__xludf.DUMMYFUNCTION("IFERROR( SUM( FILTER( Reporte!$E:$E, REGEXMATCH(Reporte!$A:$A, ""(?i)(TE PAGÓ|PAGASTE)""), Reporte!$H:$H & """" = AG56 & """" ) ), 0 )"),0) -> 0 | V56: =IFERROR(__xludf.DUMMYFUNCTION("IFERROR( SUM( FILTER( Efectivo!$C:$C, Efectivo!$D:$D & """" = AG56 & """" ) ), 0 )"),27) -> 27 | W56: c | AB56: =IF(AND(L56>0, M56>=8, NOT(OR(W56="C", W56="c"))), "CORTE", "") | AC56: =IF( OR( AND(Q56>0, OR(W56="C", W56="c"), S56<0), AND(Q56>0, W56="") ), "CORTE", "" ) | AD56: =IF(AND(LEN(W56)>0,LEN(Y56)=0),T56,0) -> 27 | AE56: =IF(AND(LEN(W56)>0,TRIM(Y56)="Y"),T56,0) -> 0 | AF56: =TRIM(UPPER(C56)) -> C | AG56: =TRIM(UPPER(C56)) & "-" & TRIM(UPPER(D56)) -> C-23
A57: 55 | B57: ALFREDO CARLOS VENTURO CAPCHA | C57: C | D57: 24 | H57: 1 | I57: 546 | J57: 548 | K57: 5 | L57: 5 | M57: 0 | N57: 0 | O57: 0 | P57: 3 | Q57: 0 | T57: =SUM(L57:S57) -> 8 | U57: =IFERROR(__xludf.DUMMYFUNCTION("IFERROR( SUM( FILTER( Reporte!$E:$E, REGEXMATCH(Reporte!$A:$A, ""(?i)(TE PAGÓ|PAGASTE)""), Reporte!$H:$H & """" = AG57 & """" ) ), 0 )"),0) -> 0 | V57: =IFERROR(__xludf.DUMMYFUNCTION("IFERROR( SUM( FILTER( Efectivo!$C:$C, Efectivo!$D:$D & """" = AG57 & """" ) ), 0 )"),8) -> 8 | W57: c | AB57: =IF(AND(L57>0, M57>=8, NOT(OR(W57="C", W57="c"))), "CORTE", "") | AC57: =IF( OR( AND(Q57>0, OR(W57="C", W57="c"), S57<0), AND(Q57>0, W57="") ), "CORTE", "" ) | AD57: =IF(AND(LEN(W57)>0,LEN(Y57)=0),T57,0) -> 8 | AE57: =IF(AND(LEN(W57)>0,TRIM(Y57)="Y"),T57,0) -> 0 | AF57: =TRIM(UPPER(C57)) -> C | AG57: =TRIM(UPPER(C57)) & "-" & TRIM(UPPER(D57)) -> C-24
A58: 56 | B58: JULIO HUERTA MILLA | C58: C | D58: 25 | H58: 1 | I58: 22 | J58: 38 | K58: 16 | L58: 16 | M58: 0 | N58: 0 | O58: 25 | P58: 3 | Q58: 0 | T58: =SUM(L58:S58) -> 44 | U58: =IFERROR(__xludf.DUMMYFUNCTION("IFERROR( SUM( FILTER( Reporte!$E:$E, REGEXMATCH(Reporte!$A:$A, ""(?i)(TE PAGÓ|PAGASTE)""), Reporte!$H:$H & """" = AG58 & """" ) ), 0 )"),0) -> 0 | V58: =IFERROR(__xludf.DUMMYFUNCTION("IFERROR( SUM( FILTER( Efectivo!$C:$C, Efectivo!$D:$D & """" = AG58 & """" ) ), 0 )"),44) -> 44 | W58: c | AB58: =IF(AND(L58>0, M58>=8, NOT(OR(W58="C", W58="c"))), "CORTE", "") | AC58: =IF( OR( AND(Q58>0, OR(W58="C", W58="c"), S58<0), AND(Q58>0, W58="") ), "CORTE", "" ) | AD58: =IF(AND(LEN(W58)>0,LEN(Y58)=0),T58,0) -> 44 | AE58: =IF(AND(LEN(W58)>0,TRIM(Y58)="Y"),T58,0) -> 0 | AF58: =TRIM(UPPER(C58)) -> C | AG58: =TRIM(UPPER(C58)) & "-" & TRIM(UPPER(D58)) -> C-25
A59: 57 | B59: CORCINO RODRIGUEZ RIVERA | C59: C | D59: 26 | H59: 1 | I59: 1510 | J59: 1511 | K59: 5 | L59: 5 | N59: 0 | O59: 0 | P59: 3 | Q59: 0 | T59: =SUM(L59:S59) -> 8 | U59: =IFERROR(__xludf.DUMMYFUNCTION("IFERROR( SUM( FILTER( Reporte!$E:$E, REGEXMATCH(Reporte!$A:$A, ""(?i)(TE PAGÓ|PAGASTE)""), Reporte!$H:$H & """" = AG59 & """" ) ), 0 )"),8) -> 8 | V59: =IFERROR(__xludf.DUMMYFUNCTION("IFERROR( SUM( FILTER( Efectivo!$C:$C, Efectivo!$D:$D & """" = AG59 & """" ) ), 0 )"),0) -> 0 | W59: c | Y59: y | Z59: Debe 8. Mes anterior | AB59: =IF(AND(L59>0, M59>=8, NOT(OR(W59="C", W59="c"))), "CORTE", "") | AC59: =IF( OR( AND(Q59>0, OR(W59="C", W59="c"), S59<0), AND(Q59>0, W59="") ), "CORTE", "" ) | AD59: =IF(AND(LEN(W59)>0,LEN(Y59)=0),T59,0) -> 0 | AE59: =IF(AND(LEN(W59)>0,TRIM(Y59)="Y"),T59,0) -> 8 | AF59: =TRIM(UPPER(C59)) -> C | AG59: =TRIM(UPPER(C59)) & "-" & TRIM(UPPER(D59)) -> C-26
A60: 58 | B60: NANCY VALERIANA FLORES LEON | C60: C | D60: 27 | H60: 1 | I60: 256 | J60: 275 | K60: 19 | L60: 19 | M60: 0 | N60: 0 | O60: 0 | P60: 3 | Q60: 0 | T60: =SUM(L60:S60) -> 22 | U60: =IFERROR(__xludf.DUMMYFUNCTION("IFERROR( SUM( FILTER( Reporte!$E:$E, REGEXMATCH(Reporte!$A:$A, ""(?i)(TE PAGÓ|PAGASTE)""), Reporte!$H:$H & """" = AG60 & """" ) ), 0 )"),22) -> 22 | V60: =IFERROR(__xludf.DUMMYFUNCTION("IFERROR( SUM( FILTER( Efectivo!$C:$C, Efectivo!$D:$D & """" = AG60 & """" ) ), 0 )"),0) -> 0 | W60: c | Y60: y | AB60: =IF(AND(L60>0, M60>=8, NOT(OR(W60="C", W60="c"))), "CORTE", "") | AC60: =IF( OR( AND(Q60>0, OR(W60="C", W60="c"), S60<0), AND(Q60>0, W60="") ), "CORTE", "" ) | AD60: =IF(AND(LEN(W60)>0,LEN(Y60)=0),T60,0) -> 0 | AE60: =IF(AND(LEN(W60)>0,TRIM(Y60)="Y"),T60,0) -> 22 | AF60: =TRIM(UPPER(C60)) -> C | AG60: =TRIM(UPPER(C60)) & "-" & TRIM(UPPER(D60)) -> C-27
A61: 59 | B61: OSTIN AGÜERO TRUJILLO | C61: C | D61: 28 | H61: 1 | I61: 10 | J61: 116 | K61: 106 | L61: 106 | M61: 0 | N61: 0 | O61: 0 | P61: 3 | Q61: 0 | T61: =SUM(L61:S61) -> 109 | U61: =IFERROR(__xludf.DUMMYFUNCTION("IFERROR( SUM( FILTER( Reporte!$E:$E, REGEXMATCH(Reporte!$A:$A, ""(?i)(TE PAGÓ|PAGASTE)""), Reporte!$H:$H & """" = AG61 & """" ) ), 0 )"),109) -> 109 | V61: =IFERROR(__xludf.DUMMYFUNCTION("IFERROR( SUM( FILTER( Efectivo!$C:$C, Efectivo!$D:$D & """" = AG61 & """" ) ), 0 )"),0) -> 0 | W61: c | Y61: y | AB61: =IF(AND(L61>0, M61>=8, NOT(OR(W61="C", W61="c"))), "CORTE", "") | AC61: =IF( OR( AND(Q61>0, OR(W61="C", W61="c"), S61<0), AND(Q61>0, W61="") ), "CORTE", "" ) | AD61: =IF(AND(LEN(W61)>0,LEN(Y61)=0),T61,0) -> 0 | AE61: =IF(AND(LEN(W61)>0,TRIM(Y61)="Y"),T61,0) -> 109 | AF61: =TRIM(UPPER(C61)) -> C | AG61: =TRIM(UPPER(C61)) & "-" & TRIM(UPPER(D61)) -> C-28
A62: 60 | B62: SONIA CERNA MELGAREJO | C62: C | D62: 30 | H62: 1 | I62: 3591 | J62: 3613 | K62: 22 | L62: 22 | M62: 22 | N62: 0 | O62: 0 | P62: 3 | Q62: 0 | T62: =SUM(L62:S62) -> 47 | U62: =IFERROR(__xludf.DUMMYFUNCTION("IFERROR( SUM( FILTER( Reporte!$E:$E, REGEXMATCH(Reporte!$A:$A, ""(?i)(TE PAGÓ|PAGASTE)""), Reporte!$H:$H & """" = AG62 & """" ) ), 0 )"),47) -> 47 | V62: =IFERROR(__xludf.DUMMYFUNCTION("IFERROR( SUM( FILTER( Efectivo!$C:$C, Efectivo!$D:$D & """" = AG62 & """" ) ), 0 )"),0) -> 0 | W62: c | Y62: y | AB62: =IF(AND(L62>0, M62>=8, NOT(OR(W62="C", W62="c"))), "CORTE", "") | AC62: =IF( OR( AND(Q62>0, OR(W62="C", W62="c"), S62<0), AND(Q62>0, W62="") ), "CORTE", "" ) | AD62: =IF(AND(LEN(W62)>0,LEN(Y62)=0),T62,0) -> 0 | AE62: =IF(AND(LEN(W62)>0,TRIM(Y62)="Y"),T62,0) -> 47 | AF62: =TRIM(UPPER(C62)) -> C | AG62: =TRIM(UPPER(C62)) & "-" & TRIM(UPPER(D62)) -> C-30
A63: 61 | B63: IGLESIA ADVENTISTA DEL SEPTIMO DIA | C63: C | D63: 31 | H63: 1 | I63: 701 | J63: 710 | K63: 9 | L63: 9 | M63: 12 | N63: 0 | O63: 0 | P63: 3 | Q63: 0 | T63: =SUM(L63:S63) -> 24 | U63: =IFERROR(__xludf.DUMMYFUNCTION("IFERROR( SUM( FILTER( Reporte!$E:$E, REGEXMATCH(Reporte!$A:$A, ""(?i)(TE PAGÓ|PAGASTE)""), Reporte!$H:$H & """" = AG63 & """" ) ), 0 )"),24) -> 24 | V63: =IFERROR(__xludf.DUMMYFUNCTION("IFERROR( SUM( FILTER( Efectivo!$C:$C, Efectivo!$D:$D & """" = AG63 & """" ) ), 0 )"),0) -> 0 | W63: c | Y63: y | AB63: =IF(AND(L63>0, M63>=8, NOT(OR(W63="C", W63="c"))), "CORTE", "") | AC63: =IF( OR( AND(Q63>0, OR(W63="C", W63="c"), S63<0), AND(Q63>0, W63="") ), "CORTE", "" ) | AD63: =IF(AND(LEN(W63)>0,LEN(Y63)=0),T63,0) -> 0 | AE63: =IF(AND(LEN(W63)>0,TRIM(Y63)="Y"),T63,0) -> 24 | AF63: =TRIM(UPPER(C63)) -> C | AG63: =TRIM(UPPER(C63)) & "-" & TRIM(UPPER(D63)) -> C-31
A64: 62 | B64: FAUSTA HUERTA AGAMA | C64: C | D64: 32 | H64: 1 | I64: 5 | J64: 8 | K64: 5 | L64: 5 | M64: 0 | N64: 0 | O64: 25 | P64: 3 | Q64: 0 | T64: =SUM(L64:S64) -> 33 | U64: =IFERROR(__xludf.DUMMYFUNCTION("IFERROR( SUM( FILTER( Reporte!$E:$E, REGEXMATCH(Reporte!$A:$A, ""(?i)(TE PAGÓ|PAGASTE)""), Reporte!$H:$H & """" = AG64 & """" ) ), 0 )"),0) -> 0 | V64: =IFERROR(__xludf.DUMMYFUNCTION("IFERROR( SUM( FILTER( Efectivo!$C:$C, Efectivo!$D:$D & """" = AG64 & """" ) ), 0 )"),33) -> 33 | W64: c | AB64: =IF(AND(L64>0, M64>=8, NOT(OR(W64="C", W64="c"))), "CORTE", "") | AC64: =IF( OR( AND(Q64>0, OR(W64="C", W64="c"), S64<0), AND(Q64>0, W64="") ), "CORTE", "" ) | AD64: =IF(AND(LEN(W64)>0,LEN(Y64)=0),T64,0) -> 33 | AE64: =IF(AND(LEN(W64)>0,TRIM(Y64)="Y"),T64,0) -> 0 | AF64: =TRIM(UPPER(C64)) -> C | AG64: =TRIM(UPPER(C64)) & "-" & TRIM(UPPER(D64)) -> C-32
A65: 63 | B65: EDITA ROMERO MAYO | C65: C | D65: 33 | H65: 1 | I65: 348 | J65: 363 | K65: 15 | L65: 15 | M65: 0 | N65: 0 | O65: 0 | P65: 3 | Q65: 0 | T65: =SUM(L65:S65) -> 18 | U65: =IFERROR(__xludf.DUMMYFUNCTION("IFERROR( SUM( FILTER( Reporte!$E:$E, REGEXMATCH(Reporte!$A:$A, ""(?i)(TE PAGÓ|PAGASTE)""), Reporte!$H:$H & """" = AG65 & """" ) ), 0 )"),18) -> 18 | V65: =IFERROR(__xludf.DUMMYFUNCTION("IFERROR( SUM( FILTER( Efectivo!$C:$C, Efectivo!$D:$D & """" = AG65 & """" ) ), 0 )"),0) -> 0 | W65: c | Y65: y | AB65: =IF(AND(L65>0, M65>=8, NOT(OR(W65="C", W65="c"))), "CORTE", "") | AC65: =IF( OR( AND(Q65>0, OR(W65="C", W65="c"), S65<0), AND(Q65>0, W65="") ), "CORTE", "" ) | AD65: =IF(AND(LEN(W65)>0,LEN(Y65)=0),T65,0) -> 0 | AE65: =IF(AND(LEN(W65)>0,TRIM(Y65)="Y"),T65,0) -> 18 | AF65: =TRIM(UPPER(C65)) -> C | AG65: =TRIM(UPPER(C65)) & "-" & TRIM(UPPER(D65)) -> C-33
A66: 64 | B66: EBER AGÜERO TRUJILLO | C66: C | D66: 34 | E66: C | H66: 1 | I66: 23 | J66: 28 | K66: 5 | L66: 5 | M66: 0 | N66: 0 | O66: 0 | P66: 3 | Q66: 0 | T66: =SUM(L66:S66) -> 8 | U66: =IFERROR(__xludf.DUMMYFUNCTION("IFERROR( SUM( FILTER( Reporte!$E:$E, REGEXMATCH(Reporte!$A:$A, ""(?i)(TE PAGÓ|PAGASTE)""), Reporte!$H:$H & """" = AG66 & """" ) ), 0 )"),8) -> 8 | V66: =IFERROR(__xludf.DUMMYFUNCTION("IFERROR( SUM( FILTER( Efectivo!$C:$C, Efectivo!$D:$D & """" = AG66 & """" ) ), 0 )"),0) -> 0 | W66: c | Y66: y | AB66: =IF(AND(L66>0, M66>=8, NOT(OR(W66="C", W66="c"))), "CORTE", "") | AC66: =IF( OR( AND(Q66>0, OR(W66="C", W66="c"), S66<0), AND(Q66>0, W66="") ), "CORTE", "" ) | AD66: =IF(AND(LEN(W66)>0,LEN(Y66)=0),T66,0) -> 0 | AE66: =IF(AND(LEN(W66)>0,TRIM(Y66)="Y"),T66,0) -> 8 | AF66: =TRIM(UPPER(C66)) -> C | AG66: =TRIM(UPPER(C66)) & "-" & TRIM(UPPER(D66)) -> C-34
A67: 65 | B67: ANALY QUINECHE MORANTE | C67: C | D67: 35 | H67: 1 | I67: 634 | J67: 651 | K67: 17 | L67: 17 | M67: 0 | N67: 0 | O67: 300 | P67: 3 | Q67: 10 | T67: =SUM(L67:S67) -> 330 | U67: =IFERROR(__xludf.DUMMYFUNCTION("IFERROR( SUM( FILTER( Reporte!$E:$E, REGEXMATCH(Reporte!$A:$A, ""(?i)(TE PAGÓ|PAGASTE)""), Reporte!$H:$H & """" = AG67 & """" ) ), 0 )"),0) -> 0 | V67: =IFERROR(__xludf.DUMMYFUNCTION("IFERROR( SUM( FILTER( Efectivo!$C:$C, Efectivo!$D:$D & """" = AG67 & """" ) ), 0 )"),0) -> 0 | AB67: =IF(AND(L67>0, M67>=8, NOT(OR(W67="C", W67="c"))), "CORTE", "") | AC67: =IF( OR( AND(Q67>0, OR(W67="C", W67="c"), S67<0), AND(Q67>0, W67="") ), "CORTE", "" ) -> CORTE | AD67: =IF(AND(LEN(W67)>0,LEN(Y67)=0),T67,0) -> 0 | AE67: =IF(AND(LEN(W67)>0,TRIM(Y67)="Y"),T67,0) -> 0 | AF67: =TRIM(UPPER(C67)) -> C | AG67: =TRIM(UPPER(C67)) & "-" & TRIM(UPPER(D67)) -> C-35
A68: 66 | B68: MARIA NORABUENA ESPADA | C68: C | D68: 36 | H68: 1 | I68: 271 | J68: 275 | K68: 5 | L68: 5 | M68: 0 | N68: 0 | O68: 0 | P68: 3 | Q68: 0 | T68: =SUM(L68:S68) -> 8 | U68: =IFERROR(__xludf.DUMMYFUNCTION("IFERROR( SUM( FILTER( Reporte!$E:$E, REGEXMATCH(Reporte!$A:$A, ""(?i)(TE PAGÓ|PAGASTE)""), Reporte!$H:$H & """" = AG68 & """" ) ), 0 )"),8) -> 8 | V68: =IFERROR(__xludf.DUMMYFUNCTION("IFERROR( SUM( FILTER( Efectivo!$C:$C, Efectivo!$D:$D & """" = AG68 & """" ) ), 0 )"),0) -> 0 | W68: c | Y68: y | AB68: =IF(AND(L68>0, M68>=8, NOT(OR(W68="C", W68="c"))), "CORTE", "") | AC68: =IF( OR( AND(Q68>0, OR(W68="C", W68="c"), S68<0), AND(Q68>0, W68="") ), "CORTE", "" ) | AD68: =IF(AND(LEN(W68)>0,LEN(Y68)=0),T68,0) -> 0 | AE68: =IF(AND(LEN(W68)>0,TRIM(Y68)="Y"),T68,0) -> 8 | AF68: =TRIM(UPPER(C68)) -> C | AG68: =TRIM(UPPER(C68)) & "-" & TRIM(UPPER(D68)) -> C-36
A69: 67 | B69: RAQUEL SORIA BUSTAMANTE | C69: C | D69: 37 | H69: 1 | I69: 296 | J69: 304 | K69: 8 | L69: 8 | M69: 0 | N69: 0 | O69: 0 | P69: 3 | Q69: 0 | T69: =SUM(L69:S69) -> 11 | U69: =IFERROR(__xludf.DUMMYFUNCTION("IFERROR( SUM( FILTER( Reporte!$E:$E, REGEXMATCH(Reporte!$A:$A, ""(?i)(TE PAGÓ|PAGASTE)""), Reporte!$H:$H & """" = AG69 & """" ) ), 0 )"),0) -> 0 | V69: =IFERROR(__xludf.DUMMYFUNCTION("IFERROR( SUM( FILTER( Efectivo!$C:$C, Efectivo!$D:$D & """" = AG69 & """" ) ), 0 )"),11) -> 11 | W69: c | AB69: =IF(AND(L69>0, M69>=8, NOT(OR(W69="C", W69="c"))), "CORTE", "") | AC69: =IF( OR( AND(Q69>0, OR(W69="C", W69="c"), S69<0), AND(Q69>0, W69="") ), "CORTE", "" ) | AD69: =IF(AND(LEN(W69)>0,LEN(Y69)=0),T69,0) -> 11 | AE69: =IF(AND(LEN(W69)>0,TRIM(Y69)="Y"),T69,0) -> 0 | AF69: =TRIM(UPPER(C69)) -> C | AG69: =TRIM(UPPER(C69)) & "-" & TRIM(UPPER(D69)) -> C-37
A70: 68 | B70: JANET ROMERO MAYO | C70: C | D70: 42 | E70: N | H70: 1 | I70: 327 | J70: 341 | K70: 14 | L70: 14 | M70: 18 | N70: 0 | O70: 0 | P70: 3 | Q70: 0 | T70: =SUM(L70:S70) -> 35 | U70: =IFERROR(__xludf.DUMMYFUNCTION("IFERROR( SUM( FILTER( Reporte!$E:$E, REGEXMATCH(Reporte!$A:$A, ""(?i)(TE PAGÓ|PAGASTE)""), Reporte!$H:$H & """" = AG70 & """" ) ), 0 )"),0) -> 0 | V70: =IFERROR(__xludf.DUMMYFUNCTION("IFERROR( SUM( FILTER( Efectivo!$C:$C, Efectivo!$D:$D & """" = AG70 & """" ) ), 0 )"),35) -> 35 | W70: c | AB70: =IF(AND(L70>0, M70>=8, NOT(OR(W70="C", W70="c"))), "CORTE", "") | AC70: =IF( OR( AND(Q70>0, OR(W70="C", W70="c"), S70<0), AND(Q70>0, W70="") ), "CORTE", "" ) | AD70: =IF(AND(LEN(W70)>0,LEN(Y70)=0),T70,0) -> 35 | AE70: =IF(AND(LEN(W70)>0,TRIM(Y70)="Y"),T70,0) -> 0 | AF70: =TRIM(UPPER(C70)) -> C | AG70: =TRIM(UPPER(C70)) & "-" & TRIM(UPPER(D70)) -> C-42
A71: 69 | B71: JANET EVARISTO COCHACHIN | C71: C | D71: 45 | H71: 1 | I71: 0 | J71: 0 | K71: 5 | L71: 5 | M71: 0 | N71: 0 | O71: 346 | P71: 3 | Q71: 0 | T71: =SUM(L71:S71) -> 354 | U71: =IFERROR(__xludf.DUMMYFUNCTION("IFERROR( SUM( FILTER( Reporte!$E:$E, REGEXMATCH(Reporte!$A:$A, ""(?i)(TE PAGÓ|PAGASTE)""), Reporte!$H:$H & """" = AG71 & """" ) ), 0 )"),0) -> 0 | V71: =IFERROR(__xludf.DUMMYFUNCTION("IFERROR( SUM( FILTER( Efectivo!$C:$C, Efectivo!$D:$D & """" = AG71 & """" ) ), 0 )"),0) -> 0 | AB71: =IF(AND(L71>0, M71>=8, NOT(OR(W71="C", W71="c"))), "CORTE", "") | AC71: =IF( OR( AND(Q71>0, OR(W71="C", W71="c"), S71<0), AND(Q71>0, W71="") ), "CORTE", "" ) | AD71: =IF(AND(LEN(W71)>0,LEN(Y71)=0),T71,0) -> 0 | AE71: =IF(AND(LEN(W71)>0,TRIM(Y71)="Y"),T71,0) -> 0 | AF71: =TRIM(UPPER(C71)) -> C | AG71: =TRIM(UPPER(C71)) & "-" & TRIM(UPPER(D71)) -> C-45
A72: 70 | B72: JUAN VENTURO CAPCHA | C72: D | D72: 1 | H72: 1 | I72: 13 | J72: 23 | K72: 10 | L72: 10 | M72: 0 | N72: 0 | O72: 25 | P72: 3 | Q72: 0 | T72: =SUM(L72:S72) -> 38 | U72: =IFERROR(__xludf.DUMMYFUNCTION("IFERROR( SUM( FILTER( Reporte!$E:$E, REGEXMATCH(Reporte!$A:$A, ""(?i)(TE PAGÓ|PAGASTE)""), Reporte!$H:$H & """" = AG72 & """" ) ), 0 )"),38) -> 38 | V72: =IFERROR(__xludf.DUMMYFUNCTION("IFERROR( SUM( FILTER( Efectivo!$C:$C, Efectivo!$D:$D & """" = AG72 & """" ) ), 0 )"),0) -> 0 | W72: c | Y72: y | AB72: =IF(AND(L72>0, M72>=8, NOT(OR(W72="C", W72="c"))), "CORTE", "") | AC72: =IF( OR( AND(Q72>0, OR(W72="C", W72="c"), S72<0), AND(Q72>0, W72="") ), "CORTE", "" ) | AD72: =IF(AND(LEN(W72)>0,LEN(Y72)=0),T72,0) -> 0 | AE72: =IF(AND(LEN(W72)>0,TRIM(Y72)="Y"),T72,0) -> 38 | AF72: =TRIM(UPPER(C72)) -> D | AG72: =TRIM(UPPER(C72)) & "-" & TRIM(UPPER(D72)) -> D-1
A73: 71 | B73: VICTOR TRUJILLO POLICARPIO | C73: D | D73: 2 | H73: 1 | I73: 2303 | J73: 2315 | K73: 12 | L73: 12 | M73: 0 | N73: 0 | O73: 0 | P73: 3 | Q73: 0 | T73: =SUM(L73:S73) -> 15 | U73: =IFERROR(__xludf.DUMMYFUNCTION("IFERROR( SUM( FILTER( Reporte!$E:$E, REGEXMATCH(Reporte!$A:$A, ""(?i)(TE PAGÓ|PAGASTE)""), Reporte!$H:$H & """" = AG73 & """" ) ), 0 )"),15) -> 15 | V73: =IFERROR(__xludf.DUMMYFUNCTION("IFERROR( SUM( FILTER( Efectivo!$C:$C, Efectivo!$D:$D & """" = AG73 & """" ) ), 0 )"),0) -> 0 | W73: c | Y73: y | AB73: =IF(AND(L73>0, M73>=8, NOT(OR(W73="C", W73="c"))), "CORTE", "") | AC73: =IF( OR( AND(Q73>0, OR(W73="C", W73="c"), S73<0), AND(Q73>0, W73="") ), "CORTE", "" ) | AD73: =IF(AND(LEN(W73)>0,LEN(Y73)=0),T73,0) -> 0 | AE73: =IF(AND(LEN(W73)>0,TRIM(Y73)="Y"),T73,0) -> 15 | AF73: =TRIM(UPPER(C73)) -> D | AG73: =TRIM(UPPER(C73)) & "-" & TRIM(UPPER(D73)) -> D-2
A74: 72 | B74: ANTONIO CASTILLEJO CUEVA | C74: D | D74: 3 | H74: 1 | I74: 16 | J74: 28 | K74: 12 | L74: 12 | M74: 0 | N74: 0 | O74: 25 | P74: 3 | Q74: 0 | T74: =SUM(L74:S74) -> 40 | U74: =IFERROR(__xludf.DUMMYFUNCTION("IFERROR( SUM( FILTER( Reporte!$E:$E, REGEXMATCH(Reporte!$A:$A, ""(?i)(TE PAGÓ|PAGASTE)""), Reporte!$H:$H & """" = AG74 & """" ) ), 0 )"),40) -> 40 | V74: =IFERROR(__xludf.DUMMYFUNCTION("IFERROR( SUM( FILTER( Efectivo!$C:$C, Efectivo!$D:$D & """" = AG74 & """" ) ), 0 )"),0) -> 0 | W74: c | Y74: y | AB74: =IF(AND(L74>0, M74>=8, NOT(OR(W74="C", W74="c"))), "CORTE", "") | AC74: =IF( OR( AND(Q74>0, OR(W74="C", W74="c"), S74<0), AND(Q74>0, W74="") ), "CORTE", "" ) | AD74: =IF(AND(LEN(W74)>0,LEN(Y74)=0),T74,0) -> 0 | AE74: =IF(AND(LEN(W74)>0,TRIM(Y74)="Y"),T74,0) -> 40 | AF74: =TRIM(UPPER(C74)) -> D | AG74: =TRIM(UPPER(C74)) & "-" & TRIM(UPPER(D74)) -> D-3
A75: 73 | B75: JULIO CESAR PRINCIPE LUNA | C75: D | D75: 4 | H75: 1 | I75: 368 | J75: 387 | K75: 19 | L75: 19 | M75: 0 | N75: 0 | O75: 0 | P75: 3 | Q75: 0 | T75: =SUM(L75:S75) -> 22 | U75: =IFERROR(__xludf.DUMMYFUNCTION("IFERROR( SUM( FILTER( Reporte!$E:$E, REGEXMATCH(Reporte!$A:$A, ""(?i)(TE PAGÓ|PAGASTE)""), Reporte!$H:$H & """" = AG75 & """" ) ), 0 )"),22) -> 22 | V75: =IFERROR(__xludf.DUMMYFUNCTION("IFERROR( SUM( FILTER( Efectivo!$C:$C, Efectivo!$D:$D & """" = AG75 & """" ) ), 0 )"),0) -> 0 | W75: c | Y75: y | AB75: =IF(AND(L75>0, M75>=8, NOT(OR(W75="C", W75="c"))), "CORTE", "") | AC75: =IF( OR( AND(Q75>0, OR(W75="C", W75="c"), S75<0), AND(Q75>0, W75="") ), "CORTE", "" ) | AD75: =IF(AND(LEN(W75)>0,LEN(Y75)=0),T75,0) -> 0 | AE75: =IF(AND(LEN(W75)>0,TRIM(Y75)="Y"),T75,0) -> 22 | AF75: =TRIM(UPPER(C75)) -> D | AG75: =TRIM(UPPER(C75)) & "-" & TRIM(UPPER(D75)) -> D-4
A76: 74 | B76: TERESA PAULA JARA DE FERNANDEZ | C76: D | D76: 5 | H76: 1 | I76: 609 | J76: 637 | K76: 28 | L76: 28 | M76: 0 | N76: 0 | O76: 0 | P76: 3 | Q76: 0 | T76: =SUM(L76:S76) -> 31 | U76: =IFERROR(__xludf.DUMMYFUNCTION("IFERROR( SUM( FILTER( Reporte!$E:$E, REGEXMATCH(Reporte!$A:$A, ""(?i)(TE PAGÓ|PAGASTE)""), Reporte!$H:$H & """" = AG76 & """" ) ), 0 )"),0) -> 0 | V76: =IFERROR(__xludf.DUMMYFUNCTION("IFERROR( SUM( FILTER( Efectivo!$C:$C, Efectivo!$D:$D & """" = AG76 & """" ) ), 0 )"),31) -> 31 | W76: c | AB76: =IF(AND(L76>0, M76>=8, NOT(OR(W76="C", W76="c"))), "CORTE", "") | AC76: =IF( OR( AND(Q76>0, OR(W76="C", W76="c"), S76<0), AND(Q76>0, W76="") ), "CORTE", "" ) | AD76: =IF(AND(LEN(W76)>0,LEN(Y76)=0),T76,0) -> 31 | AE76: =IF(AND(LEN(W76)>0,TRIM(Y76)="Y"),T76,0) -> 0 | AF76: =TRIM(UPPER(C76)) -> D | AG76: =TRIM(UPPER(C76)) & "-" & TRIM(UPPER(D76)) -> D-5
A77: 75 | B77: HERMELINDA JARA TRUJILLO | C77: D | D77: 6 | F77: 1 | H77: 1 | I77: 99 | J77: 179 | K77: 80 | L77: 80 | M77: 0 | N77: 0 | O77: 25 | P77: 3 | Q77: 0 | T77: =SUM(L77:S77) -> 108 | U77: =IFERROR(__xludf.DUMMYFUNCTION("IFERROR( SUM( FILTER( Reporte!$E:$E, REGEXMATCH(Reporte!$A:$A, ""(?i)(TE PAGÓ|PAGASTE)""), Reporte!$H:$H & """" = AG77 & """" ) ), 0 )"),108) -> 108 | V77: =IFERROR(__xludf.DUMMYFUNCTION("IFERROR( SUM( FILTER( Efectivo!$C:$C, Efectivo!$D:$D & """" = AG77 & """" ) ), 0 )"),0) -> 0 | W77: c | Y77: y | AB77: =IF(AND(L77>0, M77>=8, NOT(OR(W77="C", W77="c"))), "CORTE", "") | AC77: =IF( OR( AND(Q77>0, OR(W77="C", W77="c"), S77<0), AND(Q77>0, W77="") ), "CORTE", "" ) | AD77: =IF(AND(LEN(W77)>0,LEN(Y77)=0),T77,0) -> 0 | AE77: =IF(AND(LEN(W77)>0,TRIM(Y77)="Y"),T77,0) -> 108 | AF77: =TRIM(UPPER(C77)) -> D | AG77: =TRIM(UPPER(C77)) & "-" & TRIM(UPPER(D77)) -> D-6
A78: 76 | B78: MAXIMILIANO JARA NIETO | C78: D | D78: 7 | H78: 1 | I78: 5733 | J78: 5844 | K78: 111 | L78: 111 | M78: 95 | N78: 0 | O78: 0 | P78: 3 | Q78: 0 | T78: =SUM(L78:S78) -> 209 | U78: =IFERROR(__xludf.DUMMYFUNCTION("IFERROR( SUM( FILTER( Reporte!$E:$E, REGEXMATCH(Reporte!$A:$A, ""(?i)(TE PAGÓ|PAGASTE)""), Reporte!$H:$H & """" = AG78 & """" ) ), 0 )"),209) -> 209 | V78: =IFERROR(__xludf.DUMMYFUNCTION("IFERROR( SUM( FILTER( Efectivo!$C:$C, Efectivo!$D:$D & """" = AG78 & """" ) ), 0 )"),0) -> 0 | W78: c | Y78: y | AB78: =IF(AND(L78>0, M78>=8, NOT(OR(W78="C", W78="c"))), "CORTE", "") | AC78: =IF( OR( AND(Q78>0, OR(W78="C", W78="c"), S78<0), AND(Q78>0, W78="") ), "CORTE", "" ) | AD78: =IF(AND(LEN(W78)>0,LEN(Y78)=0),T78,0) -> 0 | AE78: =IF(AND(LEN(W78)>0,TRIM(Y78)="Y"),T78,0) -> 209 | AF78: =TRIM(UPPER(C78)) -> D | AG78: =TRIM(UPPER(C78)) & "-" & TRIM(UPPER(D78)) -> D-7
A79: 77 | B79: SANTA ANTONIA SAENZ TICLIO | C79: D | D79: 8 | F79: 1 | H79: 1 | I79: 17 | J79: 29 | K79: 12 | L79: 12 | M79: 0 | N79: 0 | O79: 25 | P79: 3 | Q79: 20 | T79: =SUM(L79:S79) -> 60 | U79: =IFERROR(__xludf.DUMMYFUNCTION("IFERROR( SUM( FILTER( Reporte!$E:$E, REGEXMATCH(Reporte!$A:$A, ""(?i)(TE PAGÓ|PAGASTE)""), Reporte!$H:$H & """" = AG79 & """" ) ), 0 )"),0) -> 0 | V79: =IFERROR(__xludf.DUMMYFUNCTION("IFERROR( SUM( FILTER( Efectivo!$C:$C, Efectivo!$D:$D & """" = AG79 & """" ) ), 0 )"),0) -> 0 | AB79: =IF(AND(L79>0, M79>=8, NOT(OR(W79="C", W79="c"))), "CORTE", "") | AC79: =IF( OR( AND(Q79>0, OR(W79="C", W79="c"), S79<0), AND(Q79>0, W79="") ), "CORTE", "" ) -> CORTE | AD79: =IF(AND(LEN(W79)>0,LEN(Y79)=0),T79,0) -> 0 | AE79: =IF(AND(LEN(W79)>0,TRIM(Y79)="Y"),T79,0) -> 0 | AF79: =TRIM(UPPER(C79)) -> D | AG79: =TRIM(UPPER(C79)) & "-" & TRIM(UPPER(D79)) -> D-8
A80: 78 | B80: RUFINA CABELLO TICLIO | C80: D | D80: 9 | H80: 1 | I80: 4120 | J80: 4131 | K80: 11 | L80: 11 | M80: 0 | N80: 21 | O80: 0 | P80: 3 | Q80: 0 | T80: =SUM(L80:S80) -> 35 | U80: =IFERROR(__xludf.DUMMYFUNCTION("IFERROR( SUM( FILTER( Reporte!$E:$E, REGEXMATCH(Reporte!$A:$A, ""(?i)(TE PAGÓ|PAGASTE)""), Reporte!$H:$H & """" = AG80 & """" ) ), 0 )"),35) -> 35 | V80: =IFERROR(__xludf.DUMMYFUNCTION("IFERROR( SUM( FILTER( Efectivo!$C:$C, Efectivo!$D:$D & """" = AG80 & """" ) ), 0 )"),0) -> 0 | W80: c | Y80: y | Z80: Debe 19. Corte y reconexion | AB80: =IF(AND(L80>0, M80>=8, NOT(OR(W80="C", W80="c"))), "CORTE", "") | AC80: =IF( OR( AND(Q80>0, OR(W80="C", W80="c"), S80<0), AND(Q80>0, W80="") ), "CORTE", "" ) | AD80: =IF(AND(LEN(W80)>0,LEN(Y80)=0),T80,0) -> 0 | AE80: =IF(AND(LEN(W80)>0,TRIM(Y80)="Y"),T80,0) -> 35 | AF80: =TRIM(UPPER(C80)) -> D | AG80: =TRIM(UPPER(C80)) & "-" & TRIM(UPPER(D80)) -> D-9
A81: 79 | B81: LIDIA ASTERIA SALES BLAS | C81: D | D81: 10 | H81: 1 | I81: 2895 | J81: 2912 | K81: 17 | L81: 17 | M81: 16 | N81: 0 | O81: 0 | P81: 3 | Q81: 0 | T81: =SUM(L81:S81) -> 36 | U81: =IFERROR(__xludf.DUMMYFUNCTION("IFERROR( SUM( FILTER( Reporte!$E:$E, REGEXMATCH(Reporte!$A:$A, ""(?i)(TE PAGÓ|PAGASTE)""), Reporte!$H:$H & """" = AG81 & """" ) ), 0 )"),36) -> 36 | V81: =IFERROR(__xludf.DUMMYFUNCTION("IFERROR( SUM( FILTER( Efectivo!$C:$C, Efectivo!$D:$D & """" = AG81 & """" ) ), 0 )"),0) -> 0 | W81: c | Y81: y | AB81: =IF(AND(L81>0, M81>=8, NOT(OR(W81="C", W81="c"))), "CORTE", "") | AC81: =IF( OR( AND(Q81>0, OR(W81="C", W81="c"), S81<0), AND(Q81>0, W81="") ), "CORTE", "" ) | AD81: =IF(AND(LEN(W81)>0,LEN(Y81)=0),T81,0) -> 0 | AE81: =IF(AND(LEN(W81)>0,TRIM(Y81)="Y"),T81,0) -> 36 | AF81: =TRIM(UPPER(C81)) -> D | AG81: =TRIM(UPPER(C81)) & "-" & TRIM(UPPER(D81)) -> D-10
A82: 80 | B82: SALOMON RODRIGUEZ GARCIA | C82: D | D82: 11 | H82: 1 | I82: 1103 | J82: 1119 | K82: 16 | L82: 16 | M82: 19 | N82: 0 | O82: 0 | P82: 3 | Q82: 0 | T82: =SUM(L82:S82) -> 38 | U82: =IFERROR(__xludf.DUMMYFUNCTION("IFERROR( SUM( FILTER( Reporte!$E:$E, REGEXMATCH(Reporte!$A:$A, ""(?i)(TE PAGÓ|PAGASTE)""), Reporte!$H:$H & """" = AG82 & """" ) ), 0 )"),0) -> 0 | V82: =IFERROR(__xludf.DUMMYFUNCTION("IFERROR( SUM( FILTER( Efectivo!$C:$C, Efectivo!$D:$D & """" = AG82 & """" ) ), 0 )"),38) -> 38 | W82: c | AB82: =IF(AND(L82>0, M82>=8, NOT(OR(W82="C", W82="c"))), "CORTE", "") | AC82: =IF( OR( AND(Q82>0, OR(W82="C", W82="c"), S82<0), AND(Q82>0, W82="") ), "CORTE", "" ) | AD82: =IF(AND(LEN(W82)>0,LEN(Y82)=0),T82,0) -> 38 | AE82: =IF(AND(LEN(W82)>0,TRIM(Y82)="Y"),T82,0) -> 0 | AF82: =TRIM(UPPER(C82)) -> D | AG82: =TRIM(UPPER(C82)) & "-" & TRIM(UPPER(D82)) -> D-11
A83: 81 | B83: MARTINA MENDOZA ROMERO | C83: D | D83: 12 | H83: 1 | I83: 274 | J83: 283 | K83: 9 | L83: 9 | M83: 9 | N83: 0 | O83: 0 | P83: 3 | Q83: 0 | T83: =SUM(L83:S83) -> 21 | U83: =IFERROR(__xludf.DUMMYFUNCTION("IFERROR( SUM( FILTER( Reporte!$E:$E, REGEXMATCH(Reporte!$A:$A, ""(?i)(TE PAGÓ|PAGASTE)""), Reporte!$H:$H & """" = AG83 & """" ) ), 0 )"),21) -> 21 | V83: =IFERROR(__xludf.DUMMYFUNCTION("IFERROR( SUM( FILTER( Efectivo!$C:$C, Efectivo!$D:$D & """" = AG83 & """" ) ), 0 )"),0) -> 0 | W83: c | Y83: y | AB83: =IF(AND(L83>0, M83>=8, NOT(OR(W83="C", W83="c"))), "CORTE", "") | AC83: =IF( OR( AND(Q83>0, OR(W83="C", W83="c"), S83<0), AND(Q83>0, W83="") ), "CORTE", "" ) | AD83: =IF(AND(LEN(W83)>0,LEN(Y83)=0),T83,0) -> 0 | AE83: =IF(AND(LEN(W83)>0,TRIM(Y83)="Y"),T83,0) -> 21 | AF83: =TRIM(UPPER(C83)) -> D | AG83: =TRIM(UPPER(C83)) & "-" & TRIM(UPPER(D83)) -> D-12
A84: 82 | B84: ROSELA ELVIRA MUÑOZ HERMITAÑO | C84: D | D84: 13 | H84: 1 | I84: 534 | J84: 559 | K84: 25 | L84: 25 | M84: 0 | N84: 0 | O84: 0 | P84: 3 | Q84: 0 | T84: =SUM(L84:S84) -> 28 | U84: =IFERROR(__xludf.DUMMYFUNCTION("IFERROR( SUM( FILTER( Reporte!$E:$E, REGEXMATCH(Reporte!$A:$A, ""(?i)(TE PAGÓ|PAGASTE)""), Reporte!$H:$H & """" = AG84 & """" ) ), 0 )"),0) -> 0 | V84: =IFERROR(__xludf.DUMMYFUNCTION("IFERROR( SUM( FILTER( Efectivo!$C:$C, Efectivo!$D:$D & """" = AG84 & """" ) ), 0 )"),28) -> 28 | W84: c | AB84: =IF(AND(L84>0, M84>=8, NOT(OR(W84="C", W84="c"))), "CORTE", "") | AC84: =IF( OR( AND(Q84>0, OR(W84="C", W84="c"), S84<0), AND(Q84>0, W84="") ), "CORTE", "" ) | AD84: =IF(AND(LEN(W84)>0,LEN(Y84)=0),T84,0) -> 28 | AE84: =IF(AND(LEN(W84)>0,TRIM(Y84)="Y"),T84,0) -> 0 | AF84: =TRIM(UPPER(C84)) -> D | AG84: =TRIM(UPPER(C84)) & "-" & TRIM(UPPER(D84)) -> D-13
A85: 83 | B85: ESTEBAN GUERRERO CHINGEL | C85: D | D85: 16 | H85: 1 | I85: 10 | J85: 18 | K85: 8 | L85: 8 | M85: 13 | N85: 0 | O85: 25 | P85: 3 | Q85: 0 | T85: =SUM(L85:S85) -> 49 | U85: =IFERROR(__xludf.DUMMYFUNCTION("IFERROR( SUM( FILTER( Reporte!$E:$E, REGEXMATCH(Reporte!$A:$A, ""(?i)(TE PAGÓ|PAGASTE)""), Reporte!$H:$H & """" = AG85 & """" ) ), 0 )"),49) -> 49 | V85: =IFERROR(__xludf.DUMMYFUNCTION("IFERROR( SUM( FILTER( Efectivo!$C:$C, Efectivo!$D:$D & """" = AG85 & """" ) ), 0 )"),0) -> 0 | W85: c | Y85: y | AB85: =IF(AND(L85>0, M85>=8, NOT(OR(W85="C", W85="c"))), "CORTE", "") | AC85: =IF( OR( AND(Q85>0, OR(W85="C", W85="c"), S85<0), AND(Q85>0, W85="") ), "CORTE", "" ) | AD85: =IF(AND(LEN(W85)>0,LEN(Y85)=0),T85,0) -> 0 | AE85: =IF(AND(LEN(W85)>0,TRIM(Y85)="Y"),T85,0) -> 49 | AF85: =TRIM(UPPER(C85)) -> D | AG85: =TRIM(UPPER(C85)) & "-" & TRIM(UPPER(D85)) -> D-16
A86: 84 | B86: MACARIO REQUEZ ROMERO | C86: D | D86: 17 | H86: 1 | I86: 3153 | J86: 3183 | K86: 30 | L86: 30 | M86: 31 | N86: 0 | O86: 0 | P86: 3 | Q86: 0 | T86: =SUM(L86:S86) -> 64 | U86: =IFERROR(__xludf.DUMMYFUNCTION("IFERROR( SUM( FILTER( Reporte!$E:$E, REGEXMATCH(Reporte!$A:$A, ""(?i)(TE PAGÓ|PAGASTE)""), Reporte!$H:$H & """" = AG86 & """" ) ), 0 )"),64) -> 64 | V86: =IFERROR(__xludf.DUMMYFUNCTION("IFERROR( SUM( FILTER( Efectivo!$C:$C, Efectivo!$D:$D & """" = AG86 & """" ) ), 0 )"),0) -> 0 | W86: c | Y86: y | AB86: =IF(AND(L86>0, M86>=8, NOT(OR(W86="C", W86="c"))), "CORTE", "") | AC86: =IF( OR( AND(Q86>0, OR(W86="C", W86="c"), S86<0), AND(Q86>0, W86="") ), "CORTE", "" ) | AD86: =IF(AND(LEN(W86)>0,LEN(Y86)=0),T86,0) -> 0 | AE86: =IF(AND(LEN(W86)>0,TRIM(Y86)="Y"),T86,0) -> 64 | AF86: =TRIM(UPPER(C86)) -> D | AG86: =TRIM(UPPER(C86)) & "-" & TRIM(UPPER(D86)) -> D-17
A87: 85 | B87: LUIS GERARDO SAAVEDRA SAAVEDRA | C87: D | D87: 18 | H87: 1 | I87: 1013 | J87: 1052 | K87: 39 | L87: 39 | M87: 0 | N87: 0 | O87: 0 | P87: 3 | Q87: 0 | T87: =SUM(L87:S87) -> 42 | U87: =IFERROR(__xludf.DUMMYFUNCTION("IFERROR( SUM( FILTER( Reporte!$E:$E, REGEXMATCH(Reporte!$A:$A, ""(?i)(TE PAGÓ|PAGASTE)""), Reporte!$H:$H & """" = AG87 & """" ) ), 0 )"),42) -> 42 | V87: =IFERROR(__xludf.DUMMYFUNCTION("IFERROR( SUM( FILTER( Efectivo!$C:$C, Efectivo!$D:$D & """" = AG87 & """" ) ), 0 )"),0) -> 0 | W87: c | Y87: y | AB87: =IF(AND(L87>0, M87>=8, NOT(OR(W87="C", W87="c"))), "CORTE", "") | AC87: =IF( OR( AND(Q87>0, OR(W87="C", W87="c"), S87<0), AND(Q87>0, W87="") ), "CORTE", "" ) | AD87: =IF(AND(LEN(W87)>0,LEN(Y87)=0),T87,0) -> 0 | AE87: =IF(AND(LEN(W87)>0,TRIM(Y87)="Y"),T87,0) -> 42 | AF87: =TRIM(UPPER(C87)) -> D | AG87: =TRIM(UPPER(C87)) & "-" & TRIM(UPPER(D87)) -> D-18
A88: 86 | B88: FELIPE DOMINGO VENTURO CAPCHA | C88: D | D88: 19 | H88: 1 | I88: 28 | J88: 47 | K88: 19 | L88: 19 | M88: 0 | N88: 0 | O88: 25 | P88: 3 | Q88: 0 | T88: =SUM(L88:S88) -> 47 | U88: =IFERROR(__xludf.DUMMYFUNCTION("IFERROR( SUM( FILTER( Reporte!$E:$E, REGEXMATCH(Reporte!$A:$A, ""(?i)(TE PAGÓ|PAGASTE)""), Reporte!$H:$H & """" = AG88 & """" ) ), 0 )"),47) -> 47 | V88: =IFERROR(__xludf.DUMMYFUNCTION("IFERROR( SUM( FILTER( Efectivo!$C:$C, Efectivo!$D:$D & """" = AG88 & """" ) ), 0 )"),0) -> 0 | W88: c | Y88: y | AB88: =IF(AND(L88>0, M88>=8, NOT(OR(W88="C", W88="c"))), "CORTE", "") | AC88: =IF( OR( AND(Q88>0, OR(W88="C", W88="c"), S88<0), AND(Q88>0, W88="") ), "CORTE", "" ) | AD88: =IF(AND(LEN(W88)>0,LEN(Y88)=0),T88,0) -> 0 | AE88: =IF(AND(LEN(W88)>0,TRIM(Y88)="Y"),T88,0) -> 47 | AF88: =TRIM(UPPER(C88)) -> D | AG88: =TRIM(UPPER(C88)) & "-" & TRIM(UPPER(D88)) -> D-19
A89: 87 | B89: YOLANDA MATILDE MONTALVO COSME | C89: E | D89: 1 | H89: 1 | I89: 303 | J89: 306 | K89: 5 | L89: 5 | M89: 0 | N89: 0 | O89: 0 | P89: 3 | Q89: 0 | T89: =SUM(L89:S89) -> 8 | U89: =IFERROR(__xludf.DUMMYFUNCTION("IFERROR( SUM( FILTER( Reporte!$E:$E, REGEXMATCH(Reporte!$A:$A, ""(?i)(TE PAGÓ|PAGASTE)""), Reporte!$H:$H & """" = AG89 & """" ) ), 0 )"),0) -> 0 | V89: =IFERROR(__xludf.DUMMYFUNCTION("IFERROR( SUM( FILTER( Efectivo!$C:$C, Efectivo!$D:$D & """" = AG89 & """" ) ), 0 )"),8) -> 8 | W89: c | AB89: =IF(AND(L89>0, M89>=8, NOT(OR(W89="C", W89="c"))), "CORTE", "") | AC89: =IF( OR( AND(Q89>0, OR(W89="C", W89="c"), S89<0), AND(Q89>0, W89="") ), "CORTE", "" ) | AD89: =IF(AND(LEN(W89)>0,LEN(Y89)=0),T89,0) -> 8 | AE89: =IF(AND(LEN(W89)>0,TRIM(Y89)="Y"),T89,0) -> 0 | AF89: =TRIM(UPPER(C89)) -> E | AG89: =TRIM(UPPER(C89)) & "-" & TRIM(UPPER(D89)) -> E-1
A90: 88 | B90: DARIO ROSALES TICLIO | C90: E | D90: 2 | H90: 1 | I90: 29 | J90: 53 | K90: 24 | L90: 24 | M90: 0 | N90: 0 | O90: 25 | P90: 3 | Q90: 0 | T90: =SUM(L90:S90) -> 52 | U90: =IFERROR(__xludf.DUMMYFUNCTION("IFERROR( SUM( FILTER( Reporte!$E:$E, REGEXMATCH(Reporte!$A:$A, ""(?i)(TE PAGÓ|PAGASTE)""), Reporte!$H:$H & """" = AG90 & """" ) ), 0 )"),52) -> 52 | V90: =IFERROR(__xludf.DUMMYFUNCTION("IFERROR( SUM( FILTER( Efectivo!$C:$C, Efectivo!$D:$D & """" = AG90 & """" ) ), 0 )"),0) -> 0 | W90: c | Y90: y | AB90: =IF(AND(L90>0, M90>=8, NOT(OR(W90="C", W90="c"))), "CORTE", "") | AC90: =IF( OR( AND(Q90>0, OR(W90="C", W90="c"), S90<0), AND(Q90>0, W90="") ), "CORTE", "" ) | AD90: =IF(AND(LEN(W90)>0,LEN(Y90)=0),T90,0) -> 0 | AE90: =IF(AND(LEN(W90)>0,TRIM(Y90)="Y"),T90,0) -> 52 | AF90: =TRIM(UPPER(C90)) -> E | AG90: =TRIM(UPPER(C90)) & "-" & TRIM(UPPER(D90)) -> E-2
A91: 89 | B91: FELIX ENRIQUE VALENCIA FERNANDEZ | C91: E | D91: 3 | H91: 1 | I91: 2973 | J91: 3000 | K91: 27 | L91: 27 | M91: 0 | N91: 0 | O91: 0 | P91: 3 | Q91: 0 | T91: =SUM(L91:S91) -> 30 | U91: =IFERROR(__xludf.DUMMYFUNCTION("IFERROR( SUM( FILTER( Reporte!$E:$E, REGEXMATCH(Reporte!$A:$A, ""(?i)(TE PAGÓ|PAGASTE)""), Reporte!$H:$H & """" = AG91 & """" ) ), 0 )"),30) -> 30 | V91: =IFERROR(__xludf.DUMMYFUNCTION("IFERROR( SUM( FILTER( Efectivo!$C:$C, Efectivo!$D:$D & """" = AG91 & """" ) ), 0 )"),0) -> 0 | W91: c | Y91: y | AB91: =IF(AND(L91>0, M91>=8, NOT(OR(W91="C", W91="c"))), "CORTE", "") | AC91: =IF( OR( AND(Q91>0, OR(W91="C", W91="c"), S91<0), AND(Q91>0, W91="") ), "CORTE", "" ) | AD91: =IF(AND(LEN(W91)>0,LEN(Y91)=0),T91,0) -> 0 | AE91: =IF(AND(LEN(W91)>0,TRIM(Y91)="Y"),T91,0) -> 30 | AF91: =TRIM(UPPER(C91)) -> E | AG91: =TRIM(UPPER(C91)) & "-" & TRIM(UPPER(D91)) -> E-3
A92: 90 | B92: FELIX VELASQUEZ LOPEZ | C92: E | D92: 4 | H92: 1 | I92: 201 | J92: 218 | K92: 17 | L92: 17 | M92: 19 | N92: 0 | O92: 0 | P92: 3 | Q92: 0 | T92: =SUM(L92:S92) -> 39 | U92: =IFERROR(__xludf.DUMMYFUNCTION("IFERROR( SUM( FILTER( Reporte!$E:$E, REGEXMATCH(Reporte!$A:$A, ""(?i)(TE PAGÓ|PAGASTE)""), Reporte!$H:$H & """" = AG92 & """" ) ), 0 )"),39) -> 39 | V92: =IFERROR(__xludf.DUMMYFUNCTION("IFERROR( SUM( FILTER( Efectivo!$C:$C, Efectivo!$D:$D & """" = AG92 & """" ) ), 0 )"),0) -> 0 | W92: c | Y92: y | AB92: =IF(AND(L92>0, M92>=8, NOT(OR(W92="C", W92="c"))), "CORTE", "") | AC92: =IF( OR( AND(Q92>0, OR(W92="C", W92="c"), S92<0), AND(Q92>0, W92="") ), "CORTE", "" ) | AD92: =IF(AND(LEN(W92)>0,LEN(Y92)=0),T92,0) -> 0 | AE92: =IF(AND(LEN(W92)>0,TRIM(Y92)="Y"),T92,0) -> 39 | AF92: =TRIM(UPPER(C92)) -> E | AG92: =TRIM(UPPER(C92)) & "-" & TRIM(UPPER(D92)) -> E-4
A93: 91 | B93: LUIS ALBERTO GOMEZ LAHUANA | C93: E | D93: 6 | H93: 1 | I93: 953 | J93: 969 | K93: 16 | L93: 16 | M93: 0 | N93: 0 | O93: 0 | P93: 3 | Q93: 0 | T93: =SUM(L93:S93) -> 19 | U93: =IFERROR(__xludf.DUMMYFUNCTION("IFERROR( SUM( FILTER( Reporte!$E:$E, REGEXMATCH(Reporte!$A:$A, ""(?i)(TE PAGÓ|PAGASTE)""), Reporte!$H:$H & """" = AG93 & """" ) ), 0 )"),19) -> 19 | V93: =IFERROR(__xludf.DUMMYFUNCTION("IFERROR( SUM( FILTER( Efectivo!$C:$C, Efectivo!$D:$D & """" = AG93 & """" ) ), 0 )"),0) -> 0 | W93: c | Y93: y | AB93: =IF(AND(L93>0, M93>=8, NOT(OR(W93="C", W93="c"))), "CORTE", "") | AC93: =IF( OR( AND(Q93>0, OR(W93="C", W93="c"), S93<0), AND(Q93>0, W93="") ), "CORTE", "" ) | AD93: =IF(AND(LEN(W93)>0,LEN(Y93)=0),T93,0) -> 0 | AE93: =IF(AND(LEN(W93)>0,TRIM(Y93)="Y"),T93,0) -> 19 | AF93: =TRIM(UPPER(C93)) -> E | AG93: =TRIM(UPPER(C93)) & "-" & TRIM(UPPER(D93)) -> E-6
A94: 92 | B94: GREGORIO TRUJILLO LEON | C94: E | D94: 7 | F94: 1 | H94: 1 | I94: 5 | J94: 19 | K94: 14 | L94: 14 | M94: 0 | N94: 0 | O94: 0 | P94: 3 | Q94: 0 | T94: =SUM(L94:S94) -> 17 | U94: =IFERROR(__xludf.DUMMYFUNCTION("IFERROR( SUM( FILTER( Reporte!$E:$E, REGEXMATCH(Reporte!$A:$A, ""(?i)(TE PAGÓ|PAGASTE)""), Reporte!$H:$H & """" = AG94 & """" ) ), 0 )"),17) -> 17 | V94: =IFERROR(__xludf.DUMMYFUNCTION("IFERROR( SUM( FILTER( Efectivo!$C:$C, Efectivo!$D:$D & """" = AG94 & """" ) ), 0 )"),0) -> 0 | W94: c | Y94: y | AB94: =IF(AND(L94>0, M94>=8, NOT(OR(W94="C", W94="c"))), "CORTE", "") | AC94: =IF( OR( AND(Q94>0, OR(W94="C", W94="c"), S94<0), AND(Q94>0, W94="") ), "CORTE", "" ) | AD94: =IF(AND(LEN(W94)>0,LEN(Y94)=0),T94,0) -> 0 | AE94: =IF(AND(LEN(W94)>0,TRIM(Y94)="Y"),T94,0) -> 17 | AF94: =TRIM(UPPER(C94)) -> E | AG94: =TRIM(UPPER(C94)) & "-" & TRIM(UPPER(D94)) -> E-7
A95: 93 | B95: GERTRUDES VIDAL GONZALES | C95: E | D95: 8 | H95: 1 | I95: 1003 | J95: 1010 | K95: 7 | L95: 7 | M95: 0 | N95: 0 | O95: 0 | P95: 3 | Q95: 0 | T95: =SUM(L95:S95) -> 10 | U95: =IFERROR(__xludf.DUMMYFUNCTION("IFERROR( SUM( FILTER( Reporte!$E:$E, REGEXMATCH(Reporte!$A:$A, ""(?i)(TE PAGÓ|PAGASTE)""), Reporte!$H:$H & """" = AG95 & """" ) ), 0 )"),0) -> 0 | V95: =IFERROR(__xludf.DUMMYFUNCTION("IFERROR( SUM( FILTER( Efectivo!$C:$C, Efectivo!$D:$D & """" = AG95 & """" ) ), 0 )"),10) -> 10 | W95: c | AB95: =IF(AND(L95>0, M95>=8, NOT(OR(W95="C", W95="c"))), "CORTE", "") | AC95: =IF( OR( AND(Q95>0, OR(W95="C", W95="c"), S95<0), AND(Q95>0, W95="") ), "CORTE", "" ) | AD95: =IF(AND(LEN(W95)>0,LEN(Y95)=0),T95,0) -> 10 | AE95: =IF(AND(LEN(W95)>0,TRIM(Y95)="Y"),T95,0) -> 0 | AF95: =TRIM(UPPER(C95)) -> E | AG95: =TRIM(UPPER(C95)) & "-" & TRIM(UPPER(D95)) -> E-8
A96: 94 | B96: MARIA NANCY SIGUEÑAS UGARTE | C96: E | D96: 9 | H96: 1 | I96: 0 | J96: 16 | K96: 16 | L96: 16 | M96: 0 | N96: 0 | O96: 0 | P96: 3 | Q96: 0 | T96: =SUM(L96:S96) -> 19 | U96: =IFERROR(__xludf.DUMMYFUNCTION("IFERROR( SUM( FILTER( Reporte!$E:$E, REGEXMATCH(Reporte!$A:$A, ""(?i)(TE PAGÓ|PAGASTE)""), Reporte!$H:$H & """" = AG96 & """" ) ), 0 )"),0) -> 0 | V96: =IFERROR(__xludf.DUMMYFUNCTION("IFERROR( SUM( FILTER( Efectivo!$C:$C, Efectivo!$D:$D & """" = AG96 & """" ) ), 0 )"),19) -> 19 | W96: c | AB96: =IF(AND(L96>0, M96>=8, NOT(OR(W96="C", W96="c"))), "CORTE", "") | AC96: =IF( OR( AND(Q96>0, OR(W96="C", W96="c"), S96<0), AND(Q96>0, W96="") ), "CORTE", "" ) | AD96: =IF(AND(LEN(W96)>0,LEN(Y96)=0),T96,0) -> 19 | AE96: =IF(AND(LEN(W96)>0,TRIM(Y96)="Y"),T96,0) -> 0 | AF96: =TRIM(UPPER(C96)) -> E | AG96: =TRIM(UPPER(C96)) & "-" & TRIM(UPPER(D96)) -> E-9
A97: 95 | B97: GREGORIA SIGUEÑAS UGARTE | C97: E | D97: 10 | H97: 1 | I97: 1025 | J97: 1060 | K97: 35 | L97: 35 | M97: 42 | N97: 0 | O97: 0 | P97: 3 | Q97: 0 | T97: =SUM(L97:S97) -> 80 | U97: =IFERROR(__xludf.DUMMYFUNCTION("IFERROR( SUM( FILTER( Reporte!$E:$E, REGEXMATCH(Reporte!$A:$A, ""(?i)(TE PAGÓ|PAGASTE)""), Reporte!$H:$H & """" = AG97 & """" ) ), 0 )"),0) -> 0 | V97: =IFERROR(__xludf.DUMMYFUNCTION("IFERROR( SUM( FILTER( Efectivo!$C:$C, Efectivo!$D:$D & """" = AG97 & """" ) ), 0 )"),80) -> 80 | W97: c | AB97: =IF(AND(L97>0, M97>=8, NOT(OR(W97="C", W97="c"))), "CORTE", "") | AC97: =IF( OR( AND(Q97>0, OR(W97="C", W97="c"), S97<0), AND(Q97>0, W97="") ), "CORTE", "" ) | AD97: =IF(AND(LEN(W97)>0,LEN(Y97)=0),T97,0) -> 80 | AE97: =IF(AND(LEN(W97)>0,TRIM(Y97)="Y"),T97,0) -> 0 | AF97: =TRIM(UPPER(C97)) -> E | AG97: =TRIM(UPPER(C97)) & "-" & TRIM(UPPER(D97)) -> E-10
A98: 96 | B98: VILMA SIGUEÑAS UGARTE | C98: E | D98: 11 | H98: 1 | I98: 4213 | J98: 4264 | K98: 51 | L98: 51 | M98: 0 | N98: 0 | O98: 0 | Q98: 0 | T98: =SUM(L98:S98) -> 51 | U98: =IFERROR(__xludf.DUMMYFUNCTION("IFERROR( SUM( FILTER( Reporte!$E:$E, REGEXMATCH(Reporte!$A:$A, ""(?i)(TE PAGÓ|PAGASTE)""), Reporte!$H:$H & """" = AG98 & """" ) ), 0 )"),0) -> 0 | V98: =IFERROR(__xludf.DUMMYFUNCTION("IFERROR( SUM( FILTER( Efectivo!$C:$C, Efectivo!$D:$D & """" = AG98 & """" ) ), 0 )"),51) -> 51 | W98: c | Z98: Debe 3. Mantenimiento | AB98: =IF(AND(L98>0, M98>=8, NOT(OR(W98="C", W98="c"))), "CORTE", "") | AC98: =IF( OR( AND(Q98>0, OR(W98="C", W98="c"), S98<0), AND(Q98>0, W98="") ), "CORTE", "" ) | AD98: =IF(AND(LEN(W98)>0,LEN(Y98)=0),T98,0) -> 51 | AE98: =IF(AND(LEN(W98)>0,TRIM(Y98)="Y"),T98,0) -> 0 | AF98: =TRIM(UPPER(C98)) -> E | AG98: =TRIM(UPPER(C98)) & "-" & TRIM(UPPER(D98)) -> E-11
A99: 97 | B99: TEOFILA FERNANDEZ REYES | C99: E | D99: 12 | H99: 1 | I99: 19 | J99: 37 | K99: 18 | L99: 18 | M99: 0 | N99: 0 | O99: 25 | P99: 3 | Q99: 0 | T99: =SUM(L99:S99) -> 46 | U99: =IFERROR(__xludf.DUMMYFUNCTION("IFERROR( SUM( FILTER( Reporte!$E:$E, REGEXMATCH(Reporte!$A:$A, ""(?i)(TE PAGÓ|PAGASTE)""), Reporte!$H:$H & """" = AG99 & """" ) ), 0 )"),46) -> 46 | V99: =IFERROR(__xludf.DUMMYFUNCTION("IFERROR( SUM( FILTER( Efectivo!$C:$C, Efectivo!$D:$D & """" = AG99 & """" ) ), 0 )"),0) -> 0 | W99: c | Y99: y | AB99: =IF(AND(L99>0, M99>=8, NOT(OR(W99="C", W99="c"))), "CORTE", "") | AC99: =IF( OR( AND(Q99>0, OR(W99="C", W99="c"), S99<0), AND(Q99>0, W99="") ), "CORTE", "" ) | AD99: =IF(AND(LEN(W99)>0,LEN(Y99)=0),T99,0) -> 0 | AE99: =IF(AND(LEN(W99)>0,TRIM(Y99)="Y"),T99,0) -> 46 | AF99: =TRIM(UPPER(C99)) -> E | AG99: =TRIM(UPPER(C99)) & "-" & TRIM(UPPER(D99)) -> E-12
A100: 98 | B100: LINDOLINA MUÑOZ HERMITAÑO | C100: E | D100: 13 | H100: 1 | I100: 3107 | J100: 3118 | K100: 11 | L100: 11 | M100: 0 | N100: 0 | O100: 0 | P100: 3 | Q100: 0 | T100: =SUM(L100:S100) -> 14 | U100: =IFERROR(__xludf.DUMMYFUNCTION("IFERROR( SUM( FILTER( Reporte!$E:$E, REGEXMATCH(Reporte!$A:$A, ""(?i)(TE PAGÓ|PAGASTE)""), Reporte!$H:$H & """" = AG100 & """" ) ), 0 )"),14) -> 14 | V100: =IFERROR(__xludf.DUMMYFUNCTION("IFERROR( SUM( FILTER( Efectivo!$C:$C, Efectivo!$D:$D & """" = AG100 & """" ) ), 0 )"),0) -> 0 | W100: c | Y100: y | AB100: =IF(AND(L100>0, M100>=8, NOT(OR(W100="C", W100="c"))), "CORTE", "") | AC100: =IF( OR( AND(Q100>0, OR(W100="C", W100="c"), S100<0), AND(Q100>0, W100="") ), "CORTE", "" ) | AD100: =IF(AND(LEN(W100)>0,LEN(Y100)=0),T100,0) -> 0 | AE100: =IF(AND(LEN(W100)>0,TRIM(Y100)="Y"),T100,0) -> 14 | AF100: =TRIM(UPPER(C100)) -> E | AG100: =TRIM(UPPER(C100)) & "-" & TRIM(UPPER(D100)) -> E-13
...

Sheet INGRESOS Y EGRESOS
B1: MONEDEROS | F1: EFECTIVO
B2: AGUA | F2: AGUA
A3: FECHA | B3: CONCEPTO | C3: MONTO | F3: CONCEPTO | G3: MONTO
B4: JANET | C4: =Cobranza!AE503 -> 8654.5 | F4: RECAUDADO PLANILLA | G4: =Cobranza!AD503 -> 3105
B5: Yape blanco | C5: 30
B6: Dinero que es del efectivo de planilla | C6: -83 | F6: Dinero que esta en el Yape Planilla | G6: 83
B7: Entrada de Yape | C7: 150
B8: Salida Yape | C8: -8775.9
B20: SALDO | C20: =SUM(C4:C16) -> -24.4 | F20: SALDO | G20: =SUM(G4:G19) -> 3188
B21: Yanet tiene yape Este mes | C21: -24.4 | F21: Yanet tiene efectivo | G21: 3176
B22: Sobra o falta | C22: =C21-C20 -> -3.623768e-13 | F22: Sobra o falta | G22: =G21-G20 -> -12
F24: NOTA
F25: G21 sobra dinero. Se espera su dueño | G25: 18
Z26: 2064

Sheet Techado
A1: Nª | B1: NOMBRE | C1: MZ | D1: LT | E1: MONTO
A2: 54 | B2: ALFREDO CARLOS VENTURO CAPCHA | C2: C | D2: 24 | E2: 25

Sheet Yape por MZ
A1: Yape por Manzana
A3: Mnz | B3: Llave1 | C3: Reporte Yape-M | D3: Planilla-A | E3: Saldos | F3: Comentario
A4: A | B4: =TRIM(UPPER(A4)) -> A | C4: =SUMIF(Reporte!$F$2:$F$632, 'Yape por MZ'!A4, Reporte!$E$2:$E$632) -> 228 | D4: =SUMPRODUCT((UPPER(Cobranza!$C$2:$C$500)=UPPER(A4))*(UPPER(Cobranza!$W$2:$W$500)="C")*(UPPER(Cobranza!$Y$2:$Y$500)="Y")*(Cobranza!$T$2:$T$500)) -> 303 | E4: =C4-D4 -> -75 | G4: =IF(OR(D4=C4), 0, 1) -> 1
A5: B | B5: =TRIM(UPPER(A5)) -> B | C5: =SUMIF(Reporte!$F$2:$F$632, 'Yape por MZ'!A5, Reporte!$E$2:$E$632) -> 338 | D5: =SUMPRODUCT((UPPER(Cobranza!$C$2:$C$500)=UPPER(A5))*(UPPER(Cobranza!$W$2:$W$500)="C")*(UPPER(Cobranza!$Y$2:$Y$500)="Y")*(Cobranza!$T$2:$T$500)) -> 338 | E5: =C5-D5 -> 0 | G5: =IF(OR(D5=C5), 0, 1) -> 0
A6: C | B6: =TRIM(UPPER(A6)) -> C | C6: =SUMIF(Reporte!$F$2:$F$632, 'Yape por MZ'!A6, Reporte!$E$2:$E$632) -> 624 | D6: =SUMPRODUCT((UPPER(Cobranza!$C$2:$C$500)=UPPER(A6))*(UPPER(Cobranza!$W$2:$W$500)="C")*(UPPER(Cobranza!$Y$2:$Y$500)="Y")*(Cobranza!$T$2:$T$500)) -> 624 | E6: =C6-D6 -> 0 | G6: =IF(OR(D6=C6), 0, 1) -> 0
A7: D | B7: =TRIM(UPPER(A7)) -> D | C7: =SUMIF(Reporte!$F$2:$F$632, 'Yape por MZ'!A7, Reporte!$E$2:$E$632) -> 726 | D7: =SUMPRODUCT((UPPER(Cobranza!$C$2:$C$500)=UPPER(A7))*(UPPER(Cobranza!$W$2:$W$500)="C")*(UPPER(Cobranza!$Y$2:$Y$500)="Y")*(Cobranza!$T$2:$T$500)) -> 726 | E7: =C7-D7 -> 0 | G7: =IF(OR(D7=C7), 0, 1) -> 0
A8: E | B8: =TRIM(UPPER(A8)) -> E | C8: =SUMIF(Reporte!$F$2:$F$632, 'Yape por MZ'!A8, Reporte!$E$2:$E$632) -> 244 | D8: =SUMPRODUCT((UPPER(Cobranza!$C$2:$C$500)=UPPER(A8))*(UPPER(Cobranza!$W$2:$W$500)="C")*(UPPER(Cobranza!$Y$2:$Y$500)="Y")*(Cobranza!$T$2:$T$500)) -> 244 | E8: =C8-D8 -> 0 | G8: =IF(OR(D8=C8), 0, 1) -> 0
A9: F | B9: =TRIM(UPPER(A9)) -> F | C9: =SUMIF(Reporte!$F$2:$F$632, 'Yape por MZ'!A9, Reporte!$E$2:$E$632) -> 466 | D9: =SUMPRODUCT((UPPER(Cobranza!$C$2:$C$500)=UPPER(A9))*(UPPER(Cobranza!$W$2:$W$500)="C")*(UPPER(Cobranza!$Y$2:$Y$500)="Y")*(Cobranza!$T$2:$T$500)) -> 466 | E9: =C9-D9 -> 0 | G9: =IF(OR(D9=C9), 0, 1) -> 0
A10: G | B10: =TRIM(UPPER(A10)) -> G | C10: =SUMIF(Reporte!$F$2:$F$632, 'Yape por MZ'!A10, Reporte!$E$2:$E$632) -> 470 | D10: =SUMPRODUCT((UPPER(Cobranza!$C$2:$C$500)=UPPER(A10))*(UPPER(Cobranza!$W$2:$W$500)="C")*(UPPER(Cobranza!$Y$2:$Y$500)="Y")*(Cobranza!$T$2:$T$500)) -> 470 | E10: =C10-D10 -> 0 | G10: =IF(OR(D10=C10), 0, 1) -> 0
A11: H | B11: =TRIM(UPPER(A11)) -> H | C11: =SUMIF(Reporte!$F$2:$F$632, 'Yape por MZ'!A11, Reporte!$E$2:$E$632) -> 438 | D11: =SUMPRODUCT((UPPER(Cobranza!$C$2:$C$500)=UPPER(A11))*(UPPER(Cobranza!$W$2:$W$500)="C")*(UPPER(Cobranza!$Y$2:$Y$500)="Y")*(Cobranza!$T$2:$T$500)) -> 438 | E11: =C11-D11 -> 0 | G11: =IF(OR(D11=C11), 0, 1) -> 0
A12: I | B12: =TRIM(UPPER(A12)) -> I | C12: =SUMIF(Reporte!$F$2:$F$632, 'Yape por MZ'!A12, Reporte!$E$2:$E$632) -> 491 | D12: =SUMPRODUCT((UPPER(Cobranza!$C$2:$C$500)=UPPER(A12))*(UPPER(Cobranza!$W$2:$W$500)="C")*(UPPER(Cobranza!$Y$2:$Y$500)="Y")*(Cobranza!$T$2:$T$500)) -> 491 | E12: =C12-D12 -> 0 | G12: =IF(OR(D12=C12), 0, 1) -> 0
A13: J | B13: =TRIM(UPPER(A13)) -> J | C13: =SUMIF(Reporte!$F$2:$F$632, 'Yape por MZ'!A13, Reporte!$E$2:$E$632) -> 206 | D13: =SUMPRODUCT((UPPER(Cobranza!$C$2:$C$500)=UPPER(A13))*(UPPER(Cobranza!$W$2:$W$500)="C")*(UPPER(Cobranza!$Y$2:$Y$500)="Y")*(Cobranza!$T$2:$T$500)) -> 206 | E13: =C13-D13 -> 0 | G13: =IF(OR(D13=C13), 0, 1) -> 0
A14: K | B14: =TRIM(UPPER(A14)) -> K | C14: =SUMIF(Reporte!$F$2:$F$632, 'Yape por MZ'!A14, Reporte!$E$2:$E$632) -> 372 | D14: =SUMPRODUCT((UPPER(Cobranza!$C$2:$C$500)=UPPER(A14))*(UPPER(Cobranza!$W$2:$W$500)="C")*(UPPER(Cobranza!$Y$2:$Y$500)="Y")*(Cobranza!$T$2:$T$500)) -> 372 | E14: =C14-D14 -> 0 | G14: =IF(OR(D14=C14), 0, 1) -> 0
A15: L | B15: =TRIM(UPPER(A15)) -> L | C15: =SUMIF(Reporte!$F$2:$F$632, 'Yape por MZ'!A15, Reporte!$E$2:$E$632) -> 350 | D15: =SUMPRODUCT((UPPER(Cobranza!$C$2:$C$500)=UPPER(A15))*(UPPER(Cobranza!$W$2:$W$500)="C")*(UPPER(Cobranza!$Y$2:$Y$500)="Y")*(Cobranza!$T$2:$T$500)) -> 350 | E15: =C15-D15 -> 0 | G15: =IF(OR(D15=C15), 0, 1) -> 0
... A20: Q | B20: =TRIM(UPPER(A20)) -> Q | C20: =SUMIF(Reporte!$F$2:$F$632, 'Yape por MZ'!A20, Reporte!$E$2:$E$632) -> 306 | D20: =SUMPRODUCT((UPPER(Cobranza!$C$2:$C$500)=UPPER(A20))*(UPPER(Cobranza!$W$2:$W$500)="C")*(UPPER(Cobranza!$Y$2:$Y$500)="Y")*(Cobranza!$T$2:$T$500)) -> 306 | E20: =C20-D20 -> 0 | G20: =IF(OR(D20=C20), 0, 1) -> 0
A21: R | B21: =TRIM(UPPER(A21)) -> R | C21: =SUMIF(Reporte!$F$2:$F$632, 'Yape por MZ'!A21, Reporte!$E$2:$E$632) -> 93 | D21: =SUMPRODUCT((UPPER(Cobranza!$C$2:$C$500)=UPPER(A21))*(UPPER(Cobranza!$W$2:$W$500)="C")*(UPPER(Cobranza!$Y$2:$Y$500)="Y")*(Cobranza!$T$2:$T$500)) -> 93 | E21: =C21-D21 -> 0 | G21: =IF(OR(D21=C21), 0, 1) -> 0 | J21: NOTA
A22: S | B22: =TRIM(UPPER(A22)) -> S | C22: =SUMIF(Reporte!$F$2:$F$632, 'Yape por MZ'!A22, Reporte!$E$2:$E$632) -> 122 | D22: =SUMPRODUCT((UPPER(Cobranza!$C$2:$C$500)=UPPER(A22))*(UPPER(Cobranza!$W$2:$W$500)="C")*(UPPER(Cobranza!$Y$2:$Y$500)="Y")*(Cobranza!$T$2:$T$500)) -> 122 | E22: =C22-D22 -> 0 | G22: =IF(OR(D22=C22), 0, 1) -> 0 | J22: La diferencia entre:
A23: T | B23: =TRIM(UPPER(A23)) -> T | C23: =SUMIF(Reporte!$F$2:$F$632, 'Yape por MZ'!A23, Reporte!$E$2:$E$632) -> 340.5 | D23: =SUMPRODUCT((UPPER(Cobranza!$C$2:$C$500)=UPPER(A23))*(UPPER(Cobranza!$W$2:$W$500)="C")*(UPPER(Cobranza!$Y$2:$Y$500)="Y")*(Cobranza!$T$2:$T$500)) -> 340.5 | E23: =C23-D23 -> 0 | G23: =IF(OR(D23=C23), 0, 1) -> 0
A24: U | B24: =TRIM(UPPER(A24)) -> U | C24: =SUMIF(Reporte!$F$2:$F$632, 'Yape por MZ'!A24, Reporte!$E$2:$E$632) -> 50 | D24: =SUMPRODUCT((UPPER(Cobranza!$C$2:$C$500)=UPPER(A24))*(UPPER(Cobranza!$W$2:$W$500)="C")*(UPPER(Cobranza!$Y$2:$Y$500)="Y")*(Cobranza!$T$2:$T$500)) -> 50 | E24: =C24-D24 -> 0 | G24: =IF(OR(D24=C24), 0, 1) -> 0 | J24: Yape | K24: -82
A25: V | B25: =TRIM(UPPER(A25)) -> V | C25: =SUMIF(Reporte!$F$2:$F$632, 'Yape por MZ'!A25, Reporte!$E$2:$E$632) -> 171 | D25: =SUMPRODUCT((UPPER(Cobranza!$C$2:$C$500)=UPPER(A25))*(UPPER(Cobranza!$W$2:$W$500)="C")*(UPPER(Cobranza!$Y$2:$Y$500)="Y")*(Cobranza!$T$2:$T$500)) -> 171 | E25: =C25-D25 -> 0 | G25: =IF(OR(D25=C25), 0, 1) -> 0 | J25: Efectivo | K25: 40
A26: W | B26: =TRIM(UPPER(A26)) -> W | C26: =SUMIF(Reporte!$F$2:$F$632, 'Yape por MZ'!A26, Reporte!$E$2:$E$632) -> 262 | D26: =SUMPRODUCT((UPPER(Cobranza!$C$2:$C$500)=UPPER(A26))*(UPPER(Cobranza!$W$2:$W$500)="C")*(UPPER(Cobranza!$Y$2:$Y$500)="Y")*(Cobranza!$T$2:$T$500)) -> 262 | E26: =C26-D26 -> 0 | G26: =IF(OR(D26=C26), 0, 1) -> 0
A27: X | B27: =TRIM(UPPER(A27)) -> X | C27: =SUMIF(Reporte!$F$2:$F$632, 'Yape por MZ'!A27, Reporte!$E$2:$E$632) -> 157 | D27: =SUMPRODUCT((UPPER(Cobranza!$C$2:$C$500)=UPPER(A27))*(UPPER(Cobranza!$W$2:$W$500)="C")*(UPPER(Cobranza!$Y$2:$Y$500)="Y")*(Cobranza!$T$2:$T$500)) -> 157 | E27: =C27-D27 -> 0 | G27: =IF(OR(D27=C27), 0, 1) -> 0 | K27: =SUM(K24:K25) -> -42
A28: Y | B28: =TRIM(UPPER(A28)) -> Y | C28: =SUMIF(Reporte!$F$2:$F$632, 'Yape por MZ'!A28, Reporte!$E$2:$E$632) -> 87 | D28: =SUMPRODUCT((UPPER(Cobranza!$C$2:$C$500)=UPPER(A28))*(UPPER(Cobranza!$W$2:$W$500)="C")*(UPPER(Cobranza!$Y$2:$Y$500)="Y")*(Cobranza!$T$2:$T$500)) -> 87 | E28: =C28-D28 -> 0 | G28: =IF(OR(D28=C28), 0, 1) -> 0
A29: Z | B29: =TRIM(UPPER(A29)) -> Z | C29: =SUMIF(Reporte!$F$2:$F$632, 'Yape por MZ'!A29, Reporte!$E$2:$E$632) -> 125 | D29: =SUMPRODUCT((UPPER(Cobranza!$C$2:$C$500)=UPPER(A29))*(UPPER(Cobranza!$W$2:$W$500)="C")*(UPPER(Cobranza!$Y$2:$Y$500)="Y")*(Cobranza!$T$2:$T$500)) -> 133 | E29: =C29-D29 -> -8 | G29: =IF(OR(D29=C29), 0, 1) -> 1 | J29: Conclusion
A30: A1 | B30: =TRIM(UPPER(A30)) -> A1 | C30: =SUMIF(Reporte!$F$2:$F$632, 'Yape por MZ'!A30, Reporte!$E$2:$E$632) -> 50 | D30: =SUMPRODUCT((UPPER(Cobranza!$C$2:$C$500)=UPPER(A30))*(UPPER(Cobranza!$W$2:$W$500)="C")*(UPPER(Cobranza!$Y$2:$Y$500)="Y")*(Cobranza!$T$2:$T$500)) -> 50 | E30: =C30-D30 -> 0 | G30: =IF(OR(D30=C30), 0, 1) -> 0 | J30: Es producto al dinero que sobro el mes anterior | M30: 42
A31: B1 | B31: =TRIM(UPPER(A31)) -> B1 | C31: =SUMIF(Reporte!$F$2:$F$632, 'Yape por MZ'!A31, Reporte!$E$2:$E$632) -> 166 | D31: =SUMPRODUCT((UPPER(Cobranza!$C$2:$C$500)=UPPER(A31))*(UPPER(Cobranza!$W$2:$W$500)="C")*(UPPER(Cobranza!$Y$2:$Y$500)="Y")*(Cobranza!$T$2:$T$500)) -> 166 | E31: =C31-D31 -> 0 | G31: =IF(OR(D31=C31), 0, 1) -> 0 | J31: Y qu este mes se le devolvio al usuario | M31: -42
A32: C1 | B32: =TRIM(UPPER(A32)) -> C1 | C32: =SUMIF(Reporte!$F$2:$F$632, 'Yape por MZ'!A32, Reporte!$E$2:$E$632) -> 162 | D32: =SUMPRODUCT((UPPER(Cobranza!$C$2:$C$500)=UPPER(A32))*(UPPER(Cobranza!$W$2:$W$500)="C")*(UPPER(Cobranza!$Y$2:$Y$500)="Y")*(Cobranza!$T$2:$T$500)) -> 162 | E32: =C32-D32 -> 0 | G32: =IF(OR(D32=C32), 0, 1) -> 0
A33: D1 | B33: =TRIM(UPPER(A33)) -> D1 | C33: =SUMIF(Reporte!$F$2:$F$632, 'Yape por MZ'!A33, Reporte!$E$2:$E$632) -> 38 | D33: =SUMPRODUCT((UPPER(Cobranza!$C$2:$C$500)=UPPER(A33))*(UPPER(Cobranza!$W$2:$W$500)="C")*(UPPER(Cobranza!$Y$2:$Y$500)="Y")*(Cobranza!$T$2:$T$500)) -> 38 | E33: =C33-D33 -> 0 | G33: =IF(OR(D33=C33), 0, 1) -> 0
A34: E1 | B34: =TRIM(UPPER(A34)) -> E1 | C34: =SUMIF(Reporte!$F$2:$F$632, 'Yape por MZ'!A34, Reporte!$E$2:$E$632) -> 58 | D34: =SUMPRODUCT((UPPER(Cobranza!$C$2:$C$500)=UPPER(A34))*(UPPER(Cobranza!$W$2:$W$500)="C")*(UPPER(Cobranza!$Y$2:$Y$500)="Y")*(Cobranza!$T$2:$T$500)) -> 58 | E34: =C34-D34 -> 0 | G34: =IF(OR(D34=C34), 0, 1) -> 0
A35: F1 | B35: =TRIM(UPPER(A35)) -> F1 | C35: =SUMIF(Reporte!$F$2:$F$632, 'Yape por MZ'!A35, Reporte!$E$2:$E$632) -> 105 | D35: =SUMPRODUCT((UPPER(Cobranza!$C$2:$C$500)=UPPER(A35))*(UPPER(Cobranza!$W$2:$W$500)="C")*(UPPER(Cobranza!$Y$2:$Y$500)="Y")*(Cobranza!$T$2:$T$500)) -> 105 | E35: =C35-D35 -> 0 | G35: =IF(OR(D35=C35), 0, 1) -> 0
A36: G1 | B36: =TRIM(UPPER(A36)) -> G1 | C36: =SUMIF(Reporte!$F$2:$F$632, 'Yape por MZ'!A36, Reporte!$E$2:$E$632) -> 68 | D36: =SUMPRODUCT((UPPER(Cobranza!$C$2:$C$500)=UPPER(A36))*(UPPER(Cobranza!$W$2:$W$500)="C")*(UPPER(Cobranza!$Y$2:$Y$500)="Y")*(Cobranza!$T$2:$T$500)) -> 68 | E36: =C36-D36 -> 0 | G36: =IF(OR(D36=C36), 0, 1) -> 0
A37: H1 | B37: =TRIM(UPPER(A37)) -> H1 | C37: =SUMIF(Reporte!$F$2:$F$632, 'Yape por MZ'!A37, Reporte!$E$2:$E$632) -> 218 | D37: =SUMPRODUCT((UPPER(Cobranza!$C$2:$C$501)=UPPER(A37))*(UPPER(Cobranza!$W$2:$W$501)="C")*(UPPER(Cobranza!$Y$2:$Y$501)="Y")*(Cobranza!$T$2:$T$501)) -> 218 | E37: =C37-D37 -> 0 | G37: =IF(OR(D37=C37), 0, 1) -> 0
C39: =SUM(C4:C37) -> 8571.5 | D39: =SUM(D4:D37) -> 8654.5 | E39: =SUM(E4:E37) -> -83
E40: =C39-D39 -> -83
A43: Efectivo por Manzana
A45: Mnz | B45: Llave1 | C45: Efectivo-M | D45: Planilla-A | E45: Saldos | F45: Comentario
A46: A | B46: =TRIM(UPPER(A46)) -> A | C46: =SUMIF(Efectivo!$A$2:$A$333, 'Yape por MZ'!A46, Efectivo!$C$2:$C$333) -> 119 | D46: =SUMPRODUCT((UPPER(Cobranza!$C$2:$C$500)=UPPER(B46))*(UPPER(Cobranza!$W$2:$W$500)="C")*(UPPER(Cobranza!$Y$2:$Y$500)<>"Y")*(Cobranza!$V$2:$V$500)) -> 44 | E46: =C46-D46 -> 75 | F46: A1. Esta en el yape. Dice que ya pago 25 anteriormente y no debe convenio. | G46: =IF(OR(D46=C46), 0, 1) -> 1
A47: B | B47: =TRIM(UPPER(A47)) -> B | C47: =SUMIF(Efectivo!$A$2:$A$333, 'Yape por MZ'!A47, Efectivo!$C$2:$C$333) -> 304 | D47: =SUMPRODUCT((UPPER(Cobranza!$C$2:$C$500)=UPPER(B47))*(UPPER(Cobranza!$W$2:$W$500)="C")*(UPPER(Cobranza!$Y$2:$Y$500)<>"Y")*(Cobranza!$V$2:$V$500)) -> 304 | E47: =C47-D47 -> 0 | G47: =IF(OR(D47=C47), 0, 1) -> 0
A48: C | B48: =TRIM(UPPER(A48)) -> C | C48: =SUMIF(Efectivo!$A$2:$A$333, 'Yape por MZ'!A48, Efectivo!$C$2:$C$333) -> 314 | D48: =SUMPRODUCT((UPPER(Cobranza!$C$2:$C$500)=UPPER(B48))*(UPPER(Cobranza!$W$2:$W$500)="C")*(UPPER(Cobranza!$Y$2:$Y$500)<>"Y")*(Cobranza!$V$2:$V$500)) -> 314 | E48: =C48-D48 -> 0 | G48: =IF(OR(D48=C48), 0, 1) -> 0
A49: D | B49: =TRIM(UPPER(A49)) -> D | C49: =SUMIF(Efectivo!$A$2:$A$333, 'Yape por MZ'!A49, Efectivo!$C$2:$C$333) -> 97 | D49: =SUMPRODUCT((UPPER(Cobranza!$C$2:$C$500)=UPPER(B49))*(UPPER(Cobranza!$W$2:$W$500)="C")*(UPPER(Cobranza!$Y$2:$Y$500)<>"Y")*(Cobranza!$V$2:$V$500)) -> 97 | E49: =C49-D49 -> 0 | G49: =IF(OR(D49=C49), 0, 1) -> 0
A50: E | B50: =TRIM(UPPER(A50)) -> E | C50: =SUMIF(Efectivo!$A$2:$A$333, 'Yape por MZ'!A50, Efectivo!$C$2:$C$333) -> 201 | D50: =SUMPRODUCT((UPPER(Cobranza!$C$2:$C$500)=UPPER(B50))*(UPPER(Cobranza!$W$2:$W$500)="C")*(UPPER(Cobranza!$Y$2:$Y$500)<>"Y")*(Cobranza!$V$2:$V$500)) -> 201 | E50: =C50-D50 -> 0 | G50: =IF(OR(D50=C50), 0, 1) -> 0
A51: F | B51: =TRIM(UPPER(A51)) -> F | C51: =SUMIF(Efectivo!$A$2:$A$333, 'Yape por MZ'!A51, Efectivo!$C$2:$C$333) -> 65 | D51: =SUMPRODUCT((UPPER(Cobranza!$C$2:$C$500)=UPPER(B51))*(UPPER(Cobranza!$W$2:$W$500)="C")*(UPPER(Cobranza!$Y$2:$Y$500)<>"Y")*(Cobranza!$V$2:$V$500)) -> 65 | E51: =C51-D51 -> 0 | G51: =IF(OR(D51=C51), 0, 1) -> 0
A52: G | B52: =TRIM(UPPER(A52)) -> G | C52: =SUMIF(Efectivo!$A$2:$A$333, 'Yape por MZ'!A52, Efectivo!$C$2:$C$333) -> 345 | D52: =SUMPRODUCT((UPPER(Cobranza!$C$2:$C$500)=UPPER(B52))*(UPPER(Cobranza!$W$2:$W$500)="C")*(UPPER(Cobranza!$Y$2:$Y$500)<>"Y")*(Cobranza!$V$2:$V$500)) -> 345 | E52: =C52-D52 -> 0 | G52: =IF(OR(D52=C52), 0, 1) -> 0
A53: H | B53: =TRIM(UPPER(A53)) -> H | C53: =SUMIF(Efectivo!$A$2:$A$333, 'Yape por MZ'!A53, Efectivo!$C$2:$C$333) -> 235 | D53: =SUMPRODUCT((UPPER(Cobranza!$C$2:$C$500)=UPPER(B53))*(UPPER(Cobranza!$W$2:$W$500)="C")*(UPPER(Cobranza!$Y$2:$Y$500)<>"Y")*(Cobranza!$V$2:$V$500)) -> 235 | E53: =C53-D53 -> 0 | G53: =IF(OR(D53=C53), 0, 1) -> 0
A54: I | B54: =TRIM(UPPER(A54)) -> I | C54: =SUMIF(Efectivo!$A$2:$A$333, 'Yape por MZ'!A54, Efectivo!$C$2:$C$333) -> 120 | D54: =SUMPRODUCT((UPPER(Cobranza!$C$2:$C$500)=UPPER(B54))*(UPPER(Cobranza!$W$2:$W$500)="C")*(UPPER(Cobranza!$Y$2:$Y$500)<>"Y")*(Cobranza!$V$2:$V$500)) -> 120 | E54: =C54-D54 -> 0 | G54: =IF(OR(D54=C54), 0, 1) -> 0
A55: J | B55: =TRIM(UPPER(A55)) -> J | C55: =SUMIF(Efectivo!$A$2:$A$333, 'Yape por MZ'!A55, Efectivo!$C$2:$C$333) -> 109 | D55: =SUMPRODUCT((UPPER(Cobranza!$C$2:$C$500)=UPPER(B55))*(UPPER(Cobranza!$W$2:$W$500)="C")*(UPPER(Cobranza!$Y$2:$Y$500)<>"Y")*(Cobranza!$V$2:$V$500)) -> 109 | E55: =C55-D55 -> 0 | G55: =IF(OR(D55=C55), 0, 1) -> 0
A56: K | B56: =TRIM(UPPER(A56)) -> K | C56: =SUMIF(Efectivo!$A$2:$A$333, 'Yape por MZ'!A56, Efectivo!$C$2:$C$333) -> 161 | D56: =SUMPRODUCT((UPPER(Cobranza!$C$2:$C$500)=UPPER(B56))*(UPPER(Cobranza!$W$2:$W$500)="C")*(UPPER(Cobranza!$Y$2:$Y$500)<>"Y")*(Cobranza!$V$2:$V$500)) -> 161 | E56: =C56-D56 -> 0 | G56: =IF(OR(D56=C56), 0, 1) -> 0
A57: L | B57: =TRIM(UPPER(A57)) -> L | C57: =SUMIF(Efectivo!$A$2:$A$333, 'Yape por MZ'!A57, Efectivo!$C$2:$C$333) -> 68 | D57: =SUMPRODUCT((UPPER(Cobranza!$C$2:$C$500)=UPPER(B57))*(UPPER(Cobranza!$W$2:$W$500)="C")*(UPPER(Cobranza!$Y$2:$Y$500)<>"Y")*(Cobranza!$V$2:$V$500)) -> 68 | E57: =C57-D57 -> 0 | G57: =IF(OR(D57=C57), 0, 1) -> 0
A58: M | B58: =TRIM(UPPER(A58)) -> M | C58: =SUMIF(Efectivo!$A$2:$A$333, 'Yape por MZ'!A58, Efectivo!$C$2:$C$333) -> 123 | D58: =SUMPRODUCT((UPPER(Cobranza!$C$2:$C$500)=UPPER(B58))*(UPPER(Cobranza!$W$2:$W$500)="C")*(UPPER(Cobranza!$Y$2:$Y$500)<>"Y")*(Cobranza!$V$2:$V$500)) -> 123 | E58: =C58-D58 -> 0 | G58: =IF(OR(D58=C58), 0, 1) -> 0
... A70: Y | B70: =TRIM(UPPER(A70)) -> Y | C70: =SUMIF(Efectivo!$A$2:$A$333, 'Yape por MZ'!A70, Efectivo!$C$2:$C$333) -> 45 | D70: =SUMPRODUCT((UPPER(Cobranza!$C$2:$C$500)=UPPER(B70))*(UPPER(Cobranza!$W$2:$W$500)="C")*(UPPER(Cobranza!$Y$2:$Y$500)<>"Y")*(Cobranza!$V$2:$V$500)) -> 45 | E70: =C70-D70 -> 0 | G70: =IF(OR(D70=C70), 0, 1) -> 0
A71: Z | B71: =TRIM(UPPER(A71)) -> Z | C71: =SUMIF(Efectivo!$A$2:$A$333, 'Yape por MZ'!A71, Efectivo!$C$2:$C$333) -> 8 | D71: =SUMPRODUCT((UPPER(Cobranza!$C$2:$C$500)=UPPER(B71))*(UPPER(Cobranza!$W$2:$W$500)="C")*(UPPER(Cobranza!$Y$2:$Y$500)<>"Y")*(Cobranza!$V$2:$V$500)) -> 0 | E71: =C71-D71 -> 8 | F71: Z16. Esta en el yape | G71: =IF(OR(D71=C71), 0, 1) -> 1
A72: A1 | B72: =TRIM(UPPER(A72)) -> A1 | C72: =SUMIF(Efectivo!$A$2:$A$333, 'Yape por MZ'!A72, Efectivo!$C$2:$C$333) -> 129 | D72: =SUMPRODUCT((UPPER(Cobranza!$C$2:$C$500)=UPPER(B72))*(UPPER(Cobranza!$W$2:$W$500)="C")*(UPPER(Cobranza!$Y$2:$Y$500)<>"Y")*(Cobranza!$V$2:$V$500)) -> 129 | E72: =C72-D72 -> 0 | G72: =IF(OR(D72=C72), 0, 1) -> 0
A73: B1 | B73: =TRIM(UPPER(A73)) -> B1 | C73: =SUMIF(Efectivo!$A$2:$A$333, 'Yape por MZ'!A73, Efectivo!$C$2:$C$333) -> 23 | D73: =SUMPRODUCT((UPPER(Cobranza!$C$2:$C$500)=UPPER(B73))*(UPPER(Cobranza!$W$2:$W$500)="C")*(UPPER(Cobranza!$Y$2:$Y$500)<>"Y")*(Cobranza!$V$2:$V$500)) -> 23 | E73: =C73-D73 -> 0 | G73: =IF(OR(D73=C73), 0, 1) -> 0
A74: C1 | B74: =TRIM(UPPER(A74)) -> C1 | C74: =SUMIF(Efectivo!$A$2:$A$333, 'Yape por MZ'!A74, Efectivo!$C$2:$C$333) -> 24 | D74: =SUMPRODUCT((UPPER(Cobranza!$C$2:$C$500)=UPPER(B74))*(UPPER(Cobranza!$W$2:$W$500)="C")*(UPPER(Cobranza!$Y$2:$Y$500)<>"Y")*(Cobranza!$V$2:$V$500)) -> 24 | E74: =C74-D74 -> 0 | G74: =IF(OR(D74=C74), 0, 1) -> 0
A75: D1 | B75: =TRIM(UPPER(A75)) -> D1 | C75: =SUMIF(Efectivo!$A$2:$A$333, 'Yape por MZ'!A75, Efectivo!$C$2:$C$333) -> 11 | D75: =SUMPRODUCT((UPPER(Cobranza!$C$2:$C$500)=UPPER(B75))*(UPPER(Cobranza!$W$2:$W$500)="C")*(UPPER(Cobranza!$Y$2:$Y$500)<>"Y")*(Cobranza!$V$2:$V$500)) -> 11 | E75: =C75-D75 -> 0 | G75: =IF(OR(D75=C75), 0, 1) -> 0
A76: E1 | B76: =TRIM(UPPER(A76)) -> E1 | C76: =SUMIF(Efectivo!$A$2:$A$333, 'Yape por MZ'!A76, Efectivo!$C$2:$C$333) -> 27 | D76: =SUMPRODUCT((UPPER(Cobranza!$C$2:$C$500)=UPPER(B76))*(UPPER(Cobranza!$W$2:$W$500)="C")*(UPPER(Cobranza!$Y$2:$Y$500)<>"Y")*(Cobranza!$V$2:$V$500)) -> 27 | E76: =C76-D76 -> 0 | G76: =IF(OR(D76=C76), 0, 1) -> 0
A77: F1 | B77: =TRIM(UPPER(A77)) -> F1 | C77: =SUMIF(Efectivo!$A$2:$A$333, 'Yape por MZ'!A77, Efectivo!$C$2:$C$333) -> 16 | D77: =SUMPRODUCT((UPPER(Cobranza!$C$2:$C$500)=UPPER(B77))*(UPPER(Cobranza!$W$2:$W$500)="C")*(UPPER(Cobranza!$Y$2:$Y$500)<>"Y")*(Cobranza!$V$2:$V$500)) -> 16 | E77: =C77-D77 -> 0 | G77: =IF(OR(D77=C77), 0, 1) -> 0
A78: G1 | B78: =TRIM(UPPER(A78)) -> G1 | C78: =SUMIF(Efectivo!$A$2:$A$333, 'Yape por MZ'!A78, Efectivo!$C$2:$C$333) -> 0 | D78: =SUMPRODUCT((UPPER(Cobranza!$C$2:$C$500)=UPPER(B78))*(UPPER(Cobranza!$W$2:$W$500)="C")*(UPPER(Cobranza!$Y$2:$Y$500)<>"Y")*(Cobranza!$V$2:$V$500)) -> 0 | E78: =C78-D78 -> 0 | G78: =IF(OR(D78=C78), 0, 1) -> 0
A79: H1 | B79: =TRIM(UPPER(A79)) -> H1 | C79: =SUMIF(Efectivo!$A$2:$A$333, 'Yape por MZ'!A79, Efectivo!$C$2:$C$333) -> 0 | D79: =SUMPRODUCT((UPPER(Cobranza!$C$2:$C$500)=UPPER(B79))*(UPPER(Cobranza!$W$2:$W$500)="C")*(UPPER(Cobranza!$Y$2:$Y$500)<>"Y")*(Cobranza!$V$2:$V$500)) -> 0 | E79: =C79-D79 -> 0 | G79: =IF(OR(D79=C79), 0, 1) -> 0
C81: =SUM(C46:C79) -> 3188 | D81: =SUM(D46:D79) -> 3105 | E81: =SUM(E46:E79) -> 83
A85: Medidor por Manzana
A87: Mnz | B87: Llave1 | C87: Cobro medidor | D87: Planilla | E87: Saldos | F87: Comentario
A88: A | B88: =TRIM(UPPER(A88)) -> A | C88: =IFERROR( SUMIF( 'Cobro medidores'!$Q:$Q, B88, 'Cobro medidores'!$K:$K ), 0 ) -> 125 | D88: =IFERROR( SUMIFS( Cobranza!$O:$O, Cobranza!$AF:$AF, B88, Cobranza!$W:$W, "c" ), 0 ) -> 125 | E88: =D88-C88 -> 0 | G88: =IF(OR(D88=C88), 0, 1) -> 0
A89: B | B89: =TRIM(UPPER(A89)) -> B | C89: =IFERROR( SUMIF( 'Cobro medidores'!$Q:$Q, B89, 'Cobro medidores'!$K:$K ), 0 ) -> 125 | D89: =IFERROR( SUMIFS( Cobranza!$O:$O, Cobranza!$AF:$AF, B89, Cobranza!$W:$W, "c" ), 0 ) -> 125 | E89: =D89-C89 -> 0 | G89: =IF(OR(D89=C89), 0, 1) -> 0
A90: C | B90: =TRIM(UPPER(A90)) -> C | C90: =IFERROR( SUMIF( 'Cobro medidores'!$Q:$Q, B90, 'Cobro medidores'!$K:$K ), 0 ) -> 286 | D90: =IFERROR( SUMIFS( Cobranza!$O:$O, Cobranza!$AF:$AF, B90, Cobranza!$W:$W, "c" ), 0 ) -> 286 | E90: =D90-C90 -> 0 | G90: =IF(OR(D90=C90), 0, 1) -> 0
A91: D | B91: =TRIM(UPPER(A91)) -> D | C91: =IFERROR( SUMIF( 'Cobro medidores'!$Q:$Q, B91, 'Cobro medidores'!$K:$K ), 0 ) -> 125 | D91: =IFERROR( SUMIFS( Cobranza!$O:$O, Cobranza!$AF:$AF, B91, Cobranza!$W:$W, "c" ), 0 ) -> 125 | E91: =D91-C91 -> 0 | G91: =IF(OR(D91=C91), 0, 1) -> 0
A92: E | B92: =TRIM(UPPER(A92)) -> E | C92: =IFERROR( SUMIF( 'Cobro medidores'!$Q:$Q, B92, 'Cobro medidores'!$K:$K ), 0 ) -> 50 | D92: =IFERROR( SUMIFS( Cobranza!$O:$O, Cobranza!$AF:$AF, B92, Cobranza!$W:$W, "c" ), 0 ) -> 50 | E92: =D92-C92 -> 0 | G92: =IF(OR(D92=C92), 0, 1) -> 0
A93: F | B93: =TRIM(UPPER(A93)) -> F | C93: =IFERROR( SUMIF( 'Cobro medidores'!$Q:$Q, B93, 'Cobro medidores'!$K:$K ), 0 ) -> 150 | D93: =IFERROR( SUMIFS( Cobranza!$O:$O, Cobranza!$AF:$AF, B93, Cobranza!$W:$W, "c" ), 0 ) -> 150 | E93: =D93-C93 -> 0 | G93: =IF(OR(D93=C93), 0, 1) -> 0
A94: G | B94: =TRIM(UPPER(A94)) -> G | C94: =IFERROR( SUMIF( 'Cobro medidores'!$Q:$Q, B94, 'Cobro medidores'!$K:$K ), 0 ) -> 325 | D94: =IFERROR( SUMIFS( Cobranza!$O:$O, Cobranza!$AF:$AF, B94, Cobranza!$W:$W, "c" ), 0 ) -> 325 | E94: =D94-C94 -> 0 | G94: =IF(OR(D94=C94), 0, 1) -> 0
A95: H | B95: =TRIM(UPPER(A95)) -> H | C95: =IFERROR( SUMIF( 'Cobro medidores'!$Q:$Q, B95, 'Cobro medidores'!$K:$K ), 0 ) -> 275 | D95: =IFERROR( SUMIFS( Cobranza!$O:$O, Cobranza!$AF:$AF, B95, Cobranza!$W:$W, "c" ), 0 ) -> 275 | E95: =D95-C95 -> 0 | G95: =IF(OR(D95=C95), 0, 1) -> 0
A96: I | B96: =TRIM(UPPER(A96)) -> I | C96: =IFERROR( SUMIF( 'Cobro medidores'!$Q:$Q, B96, 'Cobro medidores'!$K:$K ), 0 ) -> 225 | D96: =IFERROR( SUMIFS( Cobranza!$O:$O, Cobranza!$AF:$AF, B96, Cobranza!$W:$W, "c" ), 0 ) -> 225 | E96: =D96-C96 -> 0 | G96: =IF(OR(D96=C96), 0, 1) -> 0
A97: J | B97: =TRIM(UPPER(A97)) -> J | C97: =IFERROR( SUMIF( 'Cobro medidores'!$Q:$Q, B97, 'Cobro medidores'!$K:$K ), 0 ) -> 125 | D97: =IFERROR( SUMIFS( Cobranza!$O:$O, Cobranza!$AF:$AF, B97, Cobranza!$W:$W, "c" ), 0 ) -> 125 | E97: =D97-C97 -> 0 | G97: =IF(OR(D97=C97), 0, 1) -> 0
A98: K | B98: =TRIM(UPPER(A98)) -> K | C98: =IFERROR( SUMIF( 'Cobro medidores'!$Q:$Q, B98, 'Cobro medidores'!$K:$K ), 0 ) -> 125 | D98: =IFERROR( SUMIFS( Cobranza!$O:$O, Cobranza!$AF:$AF, B98, Cobranza!$W:$W, "c" ), 0 ) -> 125 | E98: =D98-C98 -> 0 | G98: =IF(OR(D98=C98), 0, 1) -> 0
A99: L | B99: =TRIM(UPPER(A99)) -> L | C99: =IFERROR( SUMIF( 'Cobro medidores'!$Q:$Q, B99, 'Cobro medidores'!$K:$K ), 0 ) -> 225 | D99: =IFERROR( SUMIFS( Cobranza!$O:$O, Cobranza!$AF:$AF, B99, Cobranza!$W:$W, "c" ), 0 ) -> 225 | E99: =D99-C99 -> 0 | G99: =IF(OR(D99=C99), 0, 1) -> 0
... A118: E1 | B118: =TRIM(UPPER(A118)) -> E1 | C118: =IFERROR( SUMIF( 'Cobro medidores'!$Q:$Q, B118, 'Cobro medidores'!$K:$K ), 0 ) -> 0 | D118: =IFERROR( SUMIFS( Cobranza!$O:$O, Cobranza!$AF:$AF, B118, Cobranza!$W:$W, "c" ), 0 ) -> 0 | E118: =D118-C118 -> 0 | G118: =IF(OR(D118=C118), 0, 1) -> 0
A119: F1 | B119: =TRIM(UPPER(A119)) -> F1 | C119: =IFERROR( SUMIF( 'Cobro medidores'!$Q:$Q, B119, 'Cobro medidores'!$K:$K ), 0 ) -> 25 | D119: =IFERROR( SUMIFS( Cobranza!$O:$O, Cobranza!$AF:$AF, B119, Cobranza!$W:$W, "c" ), 0 ) -> 25 | E119: =D119-C119 -> 0 | F119: F1-11(50). Convenio | G119: =IF(OR(D119=C119), 0, 1) -> 0
A120: G1 | B120: =TRIM(UPPER(A120)) -> G1 | C120: =IFERROR( SUMIF( 'Cobro medidores'!$Q:$Q, B120, 'Cobro medidores'!$K:$K ), 0 ) -> 25 | D120: =IFERROR( SUMIFS( Cobranza!$O:$O, Cobranza!$AF:$AF, B120, Cobranza!$W:$W, "c" ), 0 ) -> 25 | E120: =D120-C120 -> 0 | G120: =IF(OR(D120=C120), 0, 1) -> 0
A121: H1 | B121: =TRIM(UPPER(A121)) -> H1 | C121: =IFERROR( SUMIF( 'Cobro medidores'!$Q:$Q, B121, 'Cobro medidores'!$K:$K ), 0 ) -> 0 | D121: =IFERROR( SUMIFS( Cobranza!$O:$O, Cobranza!$AF:$AF, B121, Cobranza!$W:$W, "c" ), 0 ) -> 0 | E121: =D121-C121 -> 0 | G121: =IF(OR(D121=C121), 0, 1) -> 0
C123: =SUM(C88:C121) -> 2865 | D123: =SUM(D88:D121) -> 2865 | E123: =D123-C123 -> 0
D124: =D123-E123 -> 2865

Sheet Reporte
A1: Tipo de Transacción | B1: Origen | C1: Destino | D1: Monto | E1: Valor | F1: mz | G1: lt | H1: Llave | I1: Mensaje | J1: Fecha de operación | K1: Año | L1: Mes | M1: Dia | N1: Hora
A2: PAGASTE | B2: Janet Vil* | C2: Janet Vil* | D2: 171.00 | E2: =-VALUE(SUBSTITUTE(D2, ".", ",")) -> -171 | I2: compra de cloro | J2: 09/05/2026 12:35:32 | K2: =MID(J2,7,4) -> 2026 | L2: =MID(J2,4,2) -> 05 | M2: =LEFT(J2,2) -> 09 | N2: =RIGHT(J2,8) -> 12:35:32
A3: PAGASTE | B3: Janet Vil* | C3: Wilder Tru* | D3: 300.00 | E3: =-VALUE(SUBSTITUTE(D3, ".", ",")) -> -300 | I3: apoyo de la jass | J3: 09/05/2026 11:39:20 | K3: =MID(J3,7,4) -> 2026 | L3: =MID(J3,4,2) -> 05 | M3: =LEFT(J3,2) -> 09 | N3: =RIGHT(J3,8) -> 11:39:20
A4: TE PAGÓ | B4: Nelly Mor* | C4: Janet Vil* | D4: 8.00 | E4: =VALUE(SUBSTITUTE(D4, ".", ",")) -> 8 | F4: blanco | H4: =TRIM(UPPER(F4)) & "-" & TRIM(UPPER(G4)) -> BLANCO- | J4: 08/05/2026 10:35:55 | K4: =MID(J4,7,4) -> 2026 | L4: =MID(J4,4,2) -> 05 | M4: =LEFT(J4,2) -> 08 | N4: =RIGHT(J4,8) -> 10:35:55
A5: TE PAGÓ | B5: Nelly Mor* | C5: Janet Vil* | D5: 22.00 | E5: =VALUE(SUBSTITUTE(D5, ".", ",")) -> 22 | F5: blanco | H5: =TRIM(UPPER(F5)) & "-" & TRIM(UPPER(G5)) -> BLANCO- | J5: 08/05/2026 10:35:18 | K5: =MID(J5,7,4) -> 2026 | L5: =MID(J5,4,2) -> 05 | M5: =LEFT(J5,2) -> 08 | N5: =RIGHT(J5,8) -> 10:35:18
A6: TE PAGÓ | B6: Violeta Cau* | C6: Janet Vil* | D6: 35.00 | E6: =VALUE(SUBSTITUTE(D6, ".", ",")) -> 35 | F6: D | G6: 9 | H6: =TRIM(UPPER(F6)) & "-" & TRIM(UPPER(G6)) -> D-9 | I6: Mz D lote 9 | J6: 08/05/2026 10:06:11 | K6: =MID(J6,7,4) -> 2026 | L6: =MID(J6,4,2) -> 05 | M6: =LEFT(J6,2) -> 08 | N6: =RIGHT(J6,8) -> 10:06:11
A7: TE PAGÓ | B7: Adolfo Ros* | C7: Janet Vil* | D7: 19.00 | E7: =VALUE(SUBSTITUTE(D7, ".", ",")) -> 19 | F7: I | G7: 16 | H7: =TRIM(UPPER(F7)) & "-" & TRIM(UPPER(G7)) -> I-16 | I7: Adolfo Rosario Rojas, MZ.1, Lt. 16 de los dos meses | J7: 08/05/2026 08:20:08 | K7: =MID(J7,7,4) -> 2026 | L7: =MID(J7,4,2) -> 05 | M7: =LEFT(J7,2) -> 08 | N7: =RIGHT(J7,8) -> 08:20:08
A8: TE PAGÓ | B8: Camile Hid* | C8: Janet Vil* | D8: 45.00 | E8: =VALUE(SUBSTITUTE(D8, ".", ",")) -> 45 | F8: B | G8: 21 | H8: =TRIM(UPPER(F8)) & "-" & TRIM(UPPER(G8)) -> B-21 | J8: 07/05/2026 18:05:28 | K8: =MID(J8,7,4) -> 2026 | L8: =MID(J8,4,2) -> 05 | M8: =LEFT(J8,2) -> 07 | N8: =RIGHT(J8,8) -> 18:05:28
A9: TE PAGÓ | B9: PLIN - Vilma Norma Celestino Villafana | C9: JANET VILLANUEVA ALEGRIA | D9: 41.00 | E9: =VALUE(SUBSTITUTE(D9, ".", ",")) -> 41 | F9: J | G9: 3 | H9: =TRIM(UPPER(F9)) & "-" & TRIM(UPPER(G9)) -> J-3 | J9: 07/05/2026 13:17:23 | K9: =MID(J9,7,4) -> 2026 | L9: =MID(J9,4,2) -> 05 | M9: =LEFT(J9,2) -> 07 | N9: =RIGHT(J9,8) -> 13:17:23
A10: TE PAGÓ | B10: Julio Hue* | C10: Janet Vil* | D10: 63.00 | E10: =VALUE(SUBSTITUTE(D10, ".", ",")) -> 63 | F10: B | G10: 17 | H10: =TRIM(UPPER(F10)) & "-" & TRIM(UPPER(G10)) -> B-17 | J10: 06/05/2026 21:37:25 | K10: =MID(J10,7,4) -> 2026 | L10: =MID(J10,4,2) -> 05 | M10: =LEFT(J10,2) -> 06 | N10: =RIGHT(J10,8) -> 21:37:25
A11: TE PAGÓ | B11: Victor Sol* | C11: Janet Vil* | D11: 65.00 | E11: =VALUE(SUBSTITUTE(D11, ".", ",")) -> 65 | F11: P | G11: 11 | H11: =TRIM(UPPER(F11)) & "-" & TRIM(UPPER(G11)) -> P-11 | J11: 06/05/2026 21:20:42 | K11: =MID(J11,7,4) -> 2026 | L11: =MID(J11,4,2) -> 05 | M11: =LEFT(J11,2) -> 06 | N11: =RIGHT(J11,8) -> 21:20:42
A12: TE PAGÓ | B12: Jessica Mor* | C12: Janet Vil* | D12: 20.00 | E12: =VALUE(SUBSTITUTE(D12, ".", ",")) -> 20 | F12: Q | G12: 12 | H12: =TRIM(UPPER(F12)) & "-" & TRIM(UPPER(G12)) -> Q-12 | I12: MZ.Q LT 12 | J12: 06/05/2026 15:55:48 | K12: =MID(J12,7,4) -> 2026 | L12: =MID(J12,4,2) -> 05 | M12: =LEFT(J12,2) -> 06 | N12: =RIGHT(J12,8) -> 15:55:48
A13: TE PAGÓ | B13: Rosmery San* | C13: Janet Vil* | D13: 38.00 | E13: =VALUE(SUBSTITUTE(D13, ".", ",")) -> 38 | F13: B | G13: 12A | H13: =TRIM(UPPER(F13)) & "-" & TRIM(UPPER(G13)) -> B-12A | I13: mz.b lt.12 rosmery sanchez | J13: 06/05/2026 14:50:50 | K13: =MID(J13,7,4) -> 2026 | L13: =MID(J13,4,2) -> 05 | M13: =LEFT(J13,2) -> 06 | N13: =RIGHT(J13,8) -> 14:50:50
A14: TE PAGÓ | B14: Leslye Bur* | C14: Janet Vil* | D14: 20.00 | E14: =VALUE(SUBSTITUTE(D14, ".", ",")) -> 20 | F14: H1 | G14: 10 | H14: =TRIM(UPPER(F14)) & "-" & TRIM(UPPER(G14)) -> H1-10 | I14: felicia zapata Mz h1 Lt 10 | J14: 06/05/2026 11:34:56 | K14: =MID(J14,7,4) -> 2026 | L14: =MID(J14,4,2) -> 05 | M14: =LEFT(J14,2) -> 06 | N14: =RIGHT(J14,8) -> 11:34:56
A15: PAGASTE | B15: Janet Vil* | C15: Juana Coc* | D15: 95.00 | E15: =-VALUE(SUBSTITUTE(D15, ".", ",")) -> -95 | I15: compartir en la posta (supervisión) | J15: 06/05/2026 07:24:35 | K15: =MID(J15,7,4) -> 2026 | L15: =MID(J15,4,2) -> 05 | M15: =LEFT(J15,2) -> 06 | N15: =RIGHT(J15,8) -> 07:24:35
A16: TE PAGÓ | B16: Carmen Lop* | C16: Janet Vil* | D16: 11.00 | E16: =VALUE(SUBSTITUTE(D16, ".", ",")) -> 11 | F16: L | G16: 13 | H16: =TRIM(UPPER(F16)) & "-" & TRIM(UPPER(G16)) -> L-13 | I16: MARIA ROSITA HUACANCA HUAROMA ( Mz L Lt 13 ) | J16: 05/05/2026 17:59:10 | K16: =MID(J16,7,4) -> 2026 | L16: =MID(J16,4,2) -> 05 | M16: =LEFT(J16,2) -> 05 | N16: =RIGHT(J16,8) -> 17:59:10
A17: TE PAGÓ | B17: Leslye Bur* | C17: Janet Vil* | D17: 16.00 | E17: =VALUE(SUBSTITUTE(D17, ".", ",")) -> 16 | F17: H1 | G17: 10 | H17: =TRIM(UPPER(F17)) & "-" & TRIM(UPPER(G17)) -> H1-10 | I17: felicia zapata Mz h1 Lt 10 | J17: 05/05/2026 17:37:37 | K17: =MID(J17,7,4) -> 2026 | L17: =MID(J17,4,2) -> 05 | M17: =LEFT(J17,2) -> 05 | N17: =RIGHT(J17,8) -> 17:37:37
A18: TE PAGÓ | B18: Juana Bau* | C18: Janet Vil* | D18: 17.00 | E18: =VALUE(SUBSTITUTE(D18, ".", ",")) -> 17 | F18: T | G18: 19 | H18: =TRIM(UPPER(F18)) & "-" & TRIM(UPPER(G18)) -> T-19 | I18: Miguel Ángel romero valladares MZ T lote 19 | J18: 05/05/2026 16:42:49 | K18: =MID(J18,7,4) -> 2026 | L18: =MID(J18,4,2) -> 05 | M18: =LEFT(J18,2) -> 05 | N18: =RIGHT(J18,8) -> 16:42:49
A19: TE PAGÓ | B19: Elizabeth Hue* | C19: Janet Vil* | D19: 41.00 | E19: =VALUE(SUBSTITUTE(D19, ".", ",")) -> 41 | F19: A | G19: 4 | H19: =TRIM(UPPER(F19)) & "-" & TRIM(UPPER(G19)) -> A-4 | I19: yolanda Espinoza JAIMES | J19: 05/05/2026 16:35:28 | K19: =MID(J19,7,4) -> 2026 | L19: =MID(J19,4,2) -> 05 | M19: =LEFT(J19,2) -> 05 | N19: =RIGHT(J19,8) -> 16:35:28
A20: TE PAGÓ | B20: Jose Mel* | C20: Janet Vil* | D20: 51.00 | E20: =VALUE(SUBSTITUTE(D20, ".", ",")) -> 51 | F20: A | G20: 9 | H20: =TRIM(UPPER(F20)) & "-" & TRIM(UPPER(G20)) -> A-9 | I20: pago de agua, usuario Alejandro Melgarejo. Mz A Lt | J20: 05/05/2026 15:40:40 | K20: =MID(J20,7,4) -> 2026 | L20: =MID(J20,4,2) -> 05 | M20: =LEFT(J20,2) -> 05 | N20: =RIGHT(J20,8) -> 15:40:40
A21: TE PAGÓ | B21: Erika Amb* | C21: Janet Vil* | D21: 10.00 | E21: =VALUE(SUBSTITUTE(D21, ".", ",")) -> 10 | F21: A1 | G21: 8 | H21: =TRIM(UPPER(F21)) & "-" & TRIM(UPPER(G21)) -> A1-8 | I21: Mz.A1 lt .8 | J21: 05/05/2026 07:51:48 | K21: =MID(J21,7,4) -> 2026 | L21: =MID(J21,4,2) -> 05 | M21: =LEFT(J21,2) -> 05 | N21: =RIGHT(J21,8) -> 07:51:48
A22: TE PAGÓ | B22: Milagros Sig* | C22: Janet Vil* | D22: 16.00 | E22: =VALUE(SUBSTITUTE(D22, ".", ",")) -> 16 | F22: Z | G22: 13 | H22: =TRIM(UPPER(F22)) & "-" & TRIM(UPPER(G22)) -> Z-13 | J22: 04/05/2026 16:32:03 | K22: =MID(J22,7,4) -> 2026 | L22: =MID(J22,4,2) -> 05 | M22: =LEFT(J22,2) -> 04 | N22: =RIGHT(J22,8) -> 16:32:03
A23: TE PAGÓ | B23: Luis Rio* | C23: Janet Vil* | D23: 42.00 | E23: =VALUE(SUBSTITUTE(D23, ".", ",")) -> 42 | F23: C | G23: 14 | H23: =TRIM(UPPER(F23)) & "-" & TRIM(UPPER(G23)) -> C-14 | I23: mz C lote 14 | J23: 04/05/2026 09:59:15 | K23: =MID(J23,7,4) -> 2026 | L23: =MID(J23,4,2) -> 05 | M23: =LEFT(J23,2) -> 04 | N23: =RIGHT(J23,8) -> 09:59:15
A24: TE PAGÓ | B24: Junior Tru* | C24: Janet Vil* | D24: 20.00 | E24: =VALUE(SUBSTITUTE(D24, ".", ",")) -> 20 | F24: V | G24: 9 | H24: =TRIM(UPPER(F24)) & "-" & TRIM(UPPER(G24)) -> V-9 | I24: Mz. V lt. 9 Norma vega | J24: 04/05/2026 09:46:00 | K24: =MID(J24,7,4) -> 2026 | L24: =MID(J24,4,2) -> 05 | M24: =LEFT(J24,2) -> 04 | N24: =RIGHT(J24,8) -> 09:46:00
A25: TE PAGÓ | B25: Jessica Mor* | C25: Janet Vil* | D25: 43.00 | E25: =VALUE(SUBSTITUTE(D25, ".", ",")) -> 43 | F25: Q | G25: 12 | H25: =TRIM(UPPER(F25)) & "-" & TRIM(UPPER(G25)) -> Q-12 | J25: 04/05/2026 08:33:12 | K25: =MID(J25,7,4) -> 2026 | L25: =MID(J25,4,2) -> 05 | M25: =LEFT(J25,2) -> 04 | N25: =RIGHT(J25,8) -> 08:33:12
A26: TE PAGÓ | B26: BCP - MONTALVO JULCA FABIAN FELIPE | C26: JANET VILLANUEVA ALEGRIA | D26: 110.00 | E26: =VALUE(SUBSTITUTE(D26, ".", ",")) -> 110 | F26: K | G26: 15 | H26: =TRIM(UPPER(F26)) & "-" & TRIM(UPPER(G26)) -> K-15 | I26: Calle Bolognesi Mz. K LT.15 | J26: 04/05/2026 06:56:43 | K26: =MID(J26,7,4) -> 2026 | L26: =MID(J26,4,2) -> 05 | M26: =LEFT(J26,2) -> 04 | N26: =RIGHT(J26,8) -> 06:56:43
A27: TE PAGÓ | B27: Eloy Sig* | C27: Janet Vil* | D27: 50.00 | E27: =VALUE(SUBSTITUTE(D27, ".", ",")) -> 50 | F27: L | G27: 10 | H27: =TRIM(UPPER(F27)) & "-" & TRIM(UPPER(G27)) -> L-10 | I27: eloy sigueñas ugarte mz: L lote:10 | J27: 03/05/2026 21:24:26 | K27: =MID(J27,7,4) -> 2026 | L27: =MID(J27,4,2) -> 05 | M27: =LEFT(J27,2) -> 03 | N27: =RIGHT(J27,8) -> 21:24:26
A28: TE PAGÓ | B28: Alberto Rod* | C28: Janet Vil* | D28: 41.00 | E28: =VALUE(SUBSTITUTE(D28, ".", ",")) -> 41 | F28: H | G28: 9 | H28: =TRIM(UPPER(F28)) & "-" & TRIM(UPPER(G28)) -> H-9 | I28: Mz H lote9 Clemente Rodriguez Rojas | J28: 03/05/2026 20:44:22 | K28: =MID(J28,7,4) -> 2026 | L28: =MID(J28,4,2) -> 05 | M28: =LEFT(J28,2) -> 03 | N28: =RIGHT(J28,8) -> 20:44:22
A29: TE PAGÓ | B29: Melissa Pil* | C29: Janet Vil* | D29: 19.00 | E29: =VALUE(SUBSTITUTE(D29, ".", ",")) -> 19 | F29: B | G29: 15 | H29: =TRIM(UPPER(F29)) & "-" & TRIM(UPPER(G29)) -> B-15 | I29: MZB LT15 Melissa Pillaca | J29: 03/05/2026 20:03:26 | K29: =MID(J29,7,4) -> 2026 | L29: =MID(J29,4,2) -> 05 | M29: =LEFT(J29,2) -> 03 | N29: =RIGHT(J29,8) -> 20:03:26
A30: TE PAGÓ | B30: Ditmar Dia* | C30: Janet Vil* | D30: 25.00 | E30: =VALUE(SUBSTITUTE(D30, ".", ",")) -> 25 | F30: S | G30: 2 | H30: =TRIM(UPPER(F30)) & "-" & TRIM(UPPER(G30)) -> S-2 | I30: MZ. S lote 02 Miriam Diaz | J30: 03/05/2026 19:40:34 | K30: =MID(J30,7,4) -> 2026 | L30: =MID(J30,4,2) -> 05 | M30: =LEFT(J30,2) -> 03 | N30: =RIGHT(J30,8) -> 19:40:34
A31: TE PAGÓ | B31: Ani Cru* | C31: Janet Vil* | D31: 8.00 | E31: =VALUE(SUBSTITUTE(D31, ".", ",")) -> 8 | F31: F1 | G31: 2 | H31: =TRIM(UPPER(F31)) & "-" & TRIM(UPPER(G31)) -> F1-2 | I31: mz F1_lote 2 | J31: 03/05/2026 18:56:56 | K31: =MID(J31,7,4) -> 2026 | L31: =MID(J31,4,2) -> 05 | M31: =LEFT(J31,2) -> 03 | N31: =RIGHT(J31,8) -> 18:56:56
A32: TE PAGÓ | B32: Pool Cal* | C32: Janet Vil* | D32: 8.00 | E32: =VALUE(SUBSTITUTE(D32, ".", ",")) -> 8 | F32: D1 | G32: 2 | H32: =TRIM(UPPER(F32)) & "-" & TRIM(UPPER(G32)) -> D1-2 | I32: Elami Azucena Ulloa olivo MZ: D1 LT:2 | J32: 03/05/2026 18:44:29 | K32: =MID(J32,7,4) -> 2026 | L32: =MID(J32,4,2) -> 05 | M32: =LEFT(J32,2) -> 03 | N32: =RIGHT(J32,8) -> 18:44:29
A33: TE PAGÓ | B33: Magda Bla* | C33: Janet Vil* | D33: 34.00 | E33: =VALUE(SUBSTITUTE(D33, ".", ",")) -> 34 | F33: M | G33: 14 | H33: =TRIM(UPPER(F33)) & "-" & TRIM(UPPER(G33)) -> M-14 | I33: Mz M lote 14 | J33: 03/05/2026 16:15:51 | K33: =MID(J33,7,4) -> 2026 | L33: =MID(J33,4,2) -> 05 | M33: =LEFT(J33,2) -> 03 | N33: =RIGHT(J33,8) -> 16:15:51
A34: TE PAGÓ | B34: Walter Sol* | C34: Janet Vil* | D34: 8.00 | E34: =VALUE(SUBSTITUTE(D34, ".", ",")) -> 8 | F34: S | G34: 8 | H34: =TRIM(UPPER(F34)) & "-" & TRIM(UPPER(G34)) -> S-8 | I34: s 8 Solorzano Melgarejo Walter | J34: 03/05/2026 16:09:12 | K34: =MID(J34,7,4) -> 2026 | L34: =MID(J34,4,2) -> 05 | M34: =LEFT(J34,2) -> 03 | N34: =RIGHT(J34,8) -> 16:09:12
A35: TE PAGÓ | B35: Walter Sol* | C35: Janet Vil* | D35: 22.00 | E35: =VALUE(SUBSTITUTE(D35, ".", ",")) -> 22 | F35: I | G35: 13 | H35: =TRIM(UPPER(F35)) & "-" & TRIM(UPPER(G35)) -> I-13 | I35: i 13 solorzano estrada julio | J35: 03/05/2026 16:07:30 | K35: =MID(J35,7,4) -> 2026 | L35: =MID(J35,4,2) -> 05 | M35: =LEFT(J35,2) -> 03 | N35: =RIGHT(J35,8) -> 16:07:30
A36: TE PAGÓ | B36: Janet Vil* | C36: Janet Vil* | D36: 8.00 | E36: =VALUE(SUBSTITUTE(D36, ".", ",")) -> 8 | F36: V | G36: 2 | H36: =TRIM(UPPER(F36)) & "-" & TRIM(UPPER(G36)) -> V-2 | I36: mz V lt 2 | J36: 03/05/2026 15:26:55 | K36: =MID(J36,7,4) -> 2026 | L36: =MID(J36,4,2) -> 05 | M36: =LEFT(J36,2) -> 03 | N36: =RIGHT(J36,8) -> 15:26:55
A37: TE PAGÓ | B37: Janet Vil* | C37: Janet Vil* | D37: 8.00 | E37: =VALUE(SUBSTITUTE(D37, ".", ",")) -> 8 | F37: C1 | G37: 15 | H37: =TRIM(UPPER(F37)) & "-" & TRIM(UPPER(G37)) -> C1-15 | I37: mz C1 lt 15 | J37: 03/05/2026 15:26:18 | K37: =MID(J37,7,4) -> 2026 | L37: =MID(J37,4,2) -> 05 | M37: =LEFT(J37,2) -> 03 | N37: =RIGHT(J37,8) -> 15:26:18
... A44: TE PAGÓ | B44: Giulianna Alb* | C44: Janet Vil* | D44: 59.00 | E44: =VALUE(SUBSTITUTE(D44, ".", ",")) -> 59 | F44: G | G44: 17 | H44: =TRIM(UPPER(F44)) & "-" & TRIM(UPPER(G44)) -> G-17 | I44: de consumo y medidor mz.G lote 17 Carlos sigueñas | J44: 03/05/2026 06:31:26 | K44: =MID(J44,7,4) -> 2026 | L44: =MID(J44,4,2) -> 05 | M44: =LEFT(J44,2) -> 03 | N44: =RIGHT(J44,8) -> 06:31:26
A45: TE PAGÓ | B45: PLIN - GRICEL DE LA CRUZ | C45: JANET VILLANUEVA ALEGRIA | D45: 18.00 | E45: =VALUE(SUBSTITUTE(D45, ".", ",")) -> 18 | F45: A | G45: 10 | H45: =TRIM(UPPER(F45)) & "-" & TRIM(UPPER(G45)) -> A-10 | J45: 03/05/2026 05:45:29 | K45: =MID(J45,7,4) -> 2026 | L45: =MID(J45,4,2) -> 05 | M45: =LEFT(J45,2) -> 03 | N45: =RIGHT(J45,8) -> 05:45:29
A46: TE PAGÓ | B46: Giovanna San* | C46: Janet Vil* | D46: 43.00 | E46: =VALUE(SUBSTITUTE(D46, ".", ",")) -> 43 | F46: K | G46: 17 | H46: =TRIM(UPPER(F46)) & "-" & TRIM(UPPER(G46)) -> K-17 | J46: 03/05/2026 00:07:56 | K46: =MID(J46,7,4) -> 2026 | L46: =MID(J46,4,2) -> 05 | M46: =LEFT(J46,2) -> 03 | N46: =RIGHT(J46,8) -> 00:07:56
A47: TE PAGÓ | B47: PLIN - Deysi Stefany Venturo Rosales | C47: JANET VILLANUEVA ALEGRIA | D47: 15.00 | E47: =VALUE(SUBSTITUTE(D47, ".", ",")) -> 15 | F47: D | G47: 2 | H47: =TRIM(UPPER(F47)) & "-" & TRIM(UPPER(G47)) -> D-2 | J47: 02/05/2026 23:08:41 | K47: =MID(J47,7,4) -> 2026 | L47: =MID(J47,4,2) -> 05 | M47: =LEFT(J47,2) -> 02 | N47: =RIGHT(J47,8) -> 23:08:41
A48: TE PAGÓ | B48: PLIN - Deysi Stefany Venturo Rosales | C48: JANET VILLANUEVA ALEGRIA | D48: 38.00 | E48: =VALUE(SUBSTITUTE(D48, ".", ",")) -> 38 | F48: D | G48: 1 | H48: =TRIM(UPPER(F48)) & "-" & TRIM(UPPER(G48)) -> D-1 | J48: 02/05/2026 23:02:47 | K48: =MID(J48,7,4) -> 2026 | L48: =MID(J48,4,2) -> 05 | M48: =LEFT(J48,2) -> 02 | N48: =RIGHT(J48,8) -> 23:02:47
A49: TE PAGÓ | B49: Luz Oso* | C49: Janet Vil* | D49: 16.00 | E49: =VALUE(SUBSTITUTE(D49, ".", ",")) -> 16 | F49: X | G49: 32 | H49: =TRIM(UPPER(F49)) & "-" & TRIM(UPPER(G49)) -> X-32 | I49: mz x lote 32 | J49: 02/05/2026 22:59:05 | K49: =MID(J49,7,4) -> 2026 | L49: =MID(J49,4,2) -> 05 | M49: =LEFT(J49,2) -> 02 | N49: =RIGHT(J49,8) -> 22:59:05
A50: TE PAGÓ | B50: David Lui* | C50: Janet Vil* | D50: 10.00 | E50: =VALUE(SUBSTITUTE(D50, ".", ",")) -> 10 | F50: H1 | G50: 11 | H50: =TRIM(UPPER(F50)) & "-" & TRIM(UPPER(G50)) -> H1-11 | I50: mz H1 lote 11 | J50: 02/05/2026 22:07:36 | K50: =MID(J50,7,4) -> 2026 | L50: =MID(J50,4,2) -> 05 | M50: =LEFT(J50,2) -> 02 | N50: =RIGHT(J50,8) -> 22:07:36
A51: TE PAGÓ | B51: Wendy Bau* | C51: Janet Vil* | D51: 58.00 | E51: =VALUE(SUBSTITUTE(D51, ".", ",")) -> 58 | F51: G | G51: 2 | H51: =TRIM(UPPER(F51)) & "-" & TRIM(UPPER(G51)) -> G-2 | I51: Av. los Angeles Mz. G lote 2 | J51: 02/05/2026 22:04:28 | K51: =MID(J51,7,4) -> 2026 | L51: =MID(J51,4,2) -> 05 | M51: =LEFT(J51,2) -> 02 | N51: =RIGHT(J51,8) -> 22:04:28
A52: TE PAGÓ | B52: Josie San* | C52: Janet Vil* | D52: 59.00 | E52: =VALUE(SUBSTITUTE(D52, ".", ",")) -> 59 | F52: P | G52: 8 | H52: =TRIM(UPPER(F52)) & "-" & TRIM(UPPER(G52)) -> P-8 | I52: mz p lt 8 | J52: 02/05/2026 21:43:58 | K52: =MID(J52,7,4) -> 2026 | L52: =MID(J52,4,2) -> 05 | M52: =LEFT(J52,2) -> 02 | N52: =RIGHT(J52,8) -> 21:43:58
A53: TE PAGÓ | B53: Gilberto Lui* | C53: Janet Vil* | D53: 16.00 | E53: =VALUE(SUBSTITUTE(D53, ".", ",")) -> 16 | F53: G1 | G53: 1 | H53: =TRIM(UPPER(F53)) & "-" & TRIM(UPPER(G53)) -> G1-1 | I53: Mz G1 lt 1 Gilberto Luis meza | J53: 02/05/2026 20:59:54 | K53: =MID(J53,7,4) -> 2026 | L53: =MID(J53,4,2) -> 05 | M53: =LEFT(J53,2) -> 02 | N53: =RIGHT(J53,8) -> 20:59:54
A54: TE PAGÓ | B54: Erika Aya* | C54: Janet Vil* | D54: 44.00 | E54: =VALUE(SUBSTITUTE(D54, ".", ",")) -> 44 | F54: F | G54: 5 | H54: =TRIM(UPPER(F54)) & "-" & TRIM(UPPER(G54)) -> F-5 | I54: Teófilo Ayala Mz"F" Lt05 | J54: 02/05/2026 20:45:32 | K54: =MID(J54,7,4) -> 2026 | L54: =MID(J54,4,2) -> 05 | M54: =LEFT(J54,2) -> 02 | N54: =RIGHT(J54,8) -> 20:45:32
A55: TE PAGÓ | B55: Maria Jim* | C55: Janet Vil* | D55: 8.00 | E55: =VALUE(SUBSTITUTE(D55, ".", ",")) -> 8 | F55: X | G55: 11 | H55: =TRIM(UPPER(F55)) & "-" & TRIM(UPPER(G55)) -> X-11 | I55: Manzana X Lote 11 | J55: 02/05/2026 20:35:19 | K55: =MID(J55,7,4) -> 2026 | L55: =MID(J55,4,2) -> 05 | M55: =LEFT(J55,2) -> 02 | N55: =RIGHT(J55,8) -> 20:35:19
A56: TE PAGÓ | B56: Judith Pas* | C56: Janet Vil* | D56: 44.00 | E56: =VALUE(SUBSTITUTE(D56, ".", ",")) -> 44 | F56: W | G56: 20 | H56: =TRIM(UPPER(F56)) & "-" & TRIM(UPPER(G56)) -> W-20 | J56: 02/05/2026 20:28:28 | K56: =MID(J56,7,4) -> 2026 | L56: =MID(J56,4,2) -> 05 | M56: =LEFT(J56,2) -> 02 | N56: =RIGHT(J56,8) -> 20:28:28
A57: TE PAGÓ | B57: Marleny Sam* | C57: Janet Vil* | D57: 8.00 | E57: =VALUE(SUBSTITUTE(D57, ".", ",")) -> 8 | F57: Z | G57: 7 | H57: =TRIM(UPPER(F57)) & "-" & TRIM(UPPER(G57)) -> Z-7 | I57: Diego mayo samaritano mz Z lt 7 | J57: 02/05/2026 20:20:24 | K57: =MID(J57,7,4) -> 2026 | L57: =MID(J57,4,2) -> 05 | M57: =LEFT(J57,2) -> 02 | N57: =RIGHT(J57,8) -> 20:20:24
A58: TE PAGÓ | B58: Marleny Sam* | C58: Janet Vil* | D58: 8.00 | E58: =VALUE(SUBSTITUTE(D58, ".", ",")) -> 8 | F58: H1 | G58: 16 | H58: =TRIM(UPPER(F58)) & "-" & TRIM(UPPER(G58)) -> H1-16 | I58: marleny samaritano h.mz h1lt 16 | J58: 02/05/2026 20:18:59 | K58: =MID(J58,7,4) -> 2026 | L58: =MID(J58,4,2) -> 05 | M58: =LEFT(J58,2) -> 02 | N58: =RIGHT(J58,8) -> 20:18:59
A59: TE PAGÓ | B59: Luis Mel* | C59: Janet Vil* | D59: 10.00 | E59: =VALUE(SUBSTITUTE(D59, ".", ",")) -> 10 | F59: C | G59: 6 | H59: =TRIM(UPPER(F59)) & "-" & TRIM(UPPER(G59)) -> C-6 | I59: Diana Jara Trujillo. Mz.C Lt.6 | J59: 02/05/2026 20:15:55 | K59: =MID(J59,7,4) -> 2026 | L59: =MID(J59,4,2) -> 05 | M59: =LEFT(J59,2) -> 02 | N59: =RIGHT(J59,8) -> 20:15:55
A60: TE PAGÓ | B60: Cecilia Mel* | C60: Janet Vil* | D60: 27.00 | E60: =VALUE(SUBSTITUTE(D60, ".", ",")) -> 27 | F60: W | G60: 17 | H60: =TRIM(UPPER(F60)) & "-" & TRIM(UPPER(G60)) -> W-17 | I60: ortencia Flavia cabracancha Carrera mz:w. lt:17 | J60: 02/05/2026 20:07:18 | K60: =MID(J60,7,4) -> 2026 | L60: =MID(J60,4,2) -> 05 | M60: =LEFT(J60,2) -> 02 | N60: =RIGHT(J60,8) -> 20:07:18
A61: TE PAGÓ | B61: Levid Car* | C61: Janet Vil* | D61: 26.00 | E61: =VALUE(SUBSTITUTE(D61, ".", ",")) -> 26 | F61: G | G61: 15 | H61: =TRIM(UPPER(F61)) & "-" & TRIM(UPPER(G61)) -> G-15 | I61: MzG Lt 15 Bernardo Aguilar Huaman | J61: 02/05/2026 19:55:36 | K61: =MID(J61,7,4) -> 2026 | L61: =MID(J61,4,2) -> 05 | M61: =LEFT(J61,2) -> 02 | N61: =RIGHT(J61,8) -> 19:55:36
A62: TE PAGÓ | B62: PLIN - ELIAS AGAPITO SALES BLAS | C62: JANET VILLANUEVA ALEGRIA | D62: 22.00 | E62: =VALUE(SUBSTITUTE(D62, ".", ",")) -> 22 | F62: F | G62: 1 | H62: =TRIM(UPPER(F62)) & "-" & TRIM(UPPER(G62)) -> F-1 | J62: 02/05/2026 19:54:37 | K62: =MID(J62,7,4) -> 2026 | L62: =MID(J62,4,2) -> 05 | M62: =LEFT(J62,2) -> 02 | N62: =RIGHT(J62,8) -> 19:54:37
A63: TE PAGÓ | B63: Juan Bau* | C63: Janet Vil* | D63: 42.00 | E63: =VALUE(SUBSTITUTE(D63, ".", ",")) -> 42 | F63: F1 | G63: 8 | H63: =TRIM(UPPER(F63)) & "-" & TRIM(UPPER(G63)) -> F1-8 | J63: 02/05/2026 19:54:19 | K63: =MID(J63,7,4) -> 2026 | L63: =MID(J63,4,2) -> 05 | M63: =LEFT(J63,2) -> 02 | N63: =RIGHT(J63,8) -> 19:54:19
A64: TE PAGÓ | B64: Nidia Est* | C64: Janet Vil* | D64: 17.00 | E64: =VALUE(SUBSTITUTE(D64, ".", ",")) -> 17 | F64: V | G64: 11 | H64: =TRIM(UPPER(F64)) & "-" & TRIM(UPPER(G64)) -> V-11 | I64: MZ V - LT 11 / MARISOL BLAS BARRERA | J64: 02/05/2026 19:49:19 | K64: =MID(J64,7,4) -> 2026 | L64: =MID(J64,4,2) -> 05 | M64: =LEFT(J64,2) -> 02 | N64: =RIGHT(J64,8) -> 19:49:19
A65: TE PAGÓ | B65: Fiorela Gas* | C65: Janet Vil* | D65: 40.00 | E65: =VALUE(SUBSTITUTE(D65, ".", ",")) -> 40 | F65: L | G65: 7 | H65: =TRIM(UPPER(F65)) & "-" & TRIM(UPPER(G65)) -> L-7 | I65: PAGO DE AGUA. Usuario: MARGARITA SAAVEDRA | J65: 02/05/2026 19:45:25 | K65: =MID(J65,7,4) -> 2026 | L65: =MID(J65,4,2) -> 05 | M65: =LEFT(J65,2) -> 02 | N65: =RIGHT(J65,8) -> 19:45:25
A66: TE PAGÓ | B66: Carlos Can* | C66: Janet Vil* | D66: 41.00 | E66: =VALUE(SUBSTITUTE(D66, ".", ",")) -> 41 | F66: L | G66: 4 | H66: =TRIM(UPPER(F66)) & "-" & TRIM(UPPER(G66)) -> L-4 | I66: Mz L Lte 4 Delia Huamansupa Perez | J66: 02/05/2026 19:45:06 | K66: =MID(J66,7,4) -> 2026 | L66: =MID(J66,4,2) -> 05 | M66: =LEFT(J66,2) -> 02 | N66: =RIGHT(J66,8) -> 19:45:06
A67: TE PAGÓ | B67: Yony Sol* | C67: Janet Vil* | D67: 16.00 | E67: =VALUE(SUBSTITUTE(D67, ".", ",")) -> 16 | F67: V | G67: 1 | H67: =TRIM(UPPER(F67)) & "-" & TRIM(UPPER(G67)) -> V-1 | I67: Mzna V Lote 01 | J67: 02/05/2026 19:44:28 | K67: =MID(J67,7,4) -> 2026 | L67: =MID(J67,4,2) -> 05 | M67: =LEFT(J67,2) -> 02 | N67: =RIGHT(J67,8) -> 19:44:28
A68: TE PAGÓ | B68: Anguie Qui* | C68: Janet Vil* | D68: 46.00 | E68: =VALUE(SUBSTITUTE(D68, ".", ",")) -> 46 | F68: M | G68: 19 | H68: =TRIM(UPPER(F68)) & "-" & TRIM(UPPER(G68)) -> M-19 | I68: Mz. M Lt. 19 | J68: 02/05/2026 19:43:23 | K68: =MID(J68,7,4) -> 2026 | L68: =MID(J68,4,2) -> 05 | M68: =LEFT(J68,2) -> 02 | N68: =RIGHT(J68,8) -> 19:43:23
A69: TE PAGÓ | B69: Oscar Pal* | C69: Janet Vil* | D69: 21.00 | E69: =VALUE(SUBSTITUTE(D69, ".", ",")) -> 21 | F69: T | G69: 4 | H69: =TRIM(UPPER(F69)) & "-" & TRIM(UPPER(G69)) -> T-4 | I69: MZ. T lote 4. José palmadera | J69: 02/05/2026 19:39:42 | K69: =MID(J69,7,4) -> 2026 | L69: =MID(J69,4,2) -> 05 | M69: =LEFT(J69,2) -> 02 | N69: =RIGHT(J69,8) -> 19:39:42
A70: TE PAGÓ | B70: Mariza Vid* | C70: Janet Vil* | D70: 44.00 | E70: =VALUE(SUBSTITUTE(D70, ".", ",")) -> 44 | F70: P | G70: 3 | H70: =TRIM(UPPER(F70)) & "-" & TRIM(UPPER(G70)) -> P-3 | I70: Av Jorge Chaves mz-p lote 3 | J70: 02/05/2026 19:38:45 | K70: =MID(J70,7,4) -> 2026 | L70: =MID(J70,4,2) -> 05 | M70: =LEFT(J70,2) -> 02 | N70: =RIGHT(J70,8) -> 19:38:45
A71: TE PAGÓ | B71: Ana Vel* | C71: Janet Vil* | D71: 39.00 | E71: =VALUE(SUBSTITUTE(D71, ".", ",")) -> 39 | F71: E | G71: 4 | H71: =TRIM(UPPER(F71)) & "-" & TRIM(UPPER(G71)) -> E-4 | I71: FELIX VELASQUEZ LOPEZ MZ E LOTE 4 | J71: 02/05/2026 19:33:40 | K71: =MID(J71,7,4) -> 2026 | L71: =MID(J71,4,2) -> 05 | M71: =LEFT(J71,2) -> 02 | N71: =RIGHT(J71,8) -> 19:33:40
A72: TE PAGÓ | B72: Nelly De-* | C72: Janet Vil* | D72: 22.00 | E72: =VALUE(SUBSTITUTE(D72, ".", ",")) -> 22 | F72: O | G72: 15 | H72: =TRIM(UPPER(F72)) & "-" & TRIM(UPPER(G72)) -> O-15 | I72: Juan Pinedo Bedon Mz .O Lt .15 | J72: 02/05/2026 19:28:34 | K72: =MID(J72,7,4) -> 2026 | L72: =MID(J72,4,2) -> 05 | M72: =LEFT(J72,2) -> 02 | N72: =RIGHT(J72,8) -> 19:28:34
A73: TE PAGÓ | B73: Katerin Pat* | C73: Janet Vil* | D73: 22.00 | E73: =VALUE(SUBSTITUTE(D73, ".", ",")) -> 22 | F73: V | G73: 12 | H73: =TRIM(UPPER(F73)) & "-" & TRIM(UPPER(G73)) -> V-12 | I73: Francisca Clara Huayta MZ : V Lt:12 | J73: 02/05/2026 19:19:18 | K73: =MID(J73,7,4) -> 2026 | L73: =MID(J73,4,2) -> 05 | M73: =LEFT(J73,2) -> 02 | N73: =RIGHT(J73,8) -> 19:19:18
A74: TE PAGÓ | B74: Bernardino Gam* | C74: Janet Vil* | D74: 9.00 | E74: =VALUE(SUBSTITUTE(D74, ".", ",")) -> 9 | F74: S | G74: 10 | H74: =TRIM(UPPER(F74)) & "-" & TRIM(UPPER(G74)) -> S-10 | I74: Mz S Lt 10 | J74: 02/05/2026 19:17:42 | K74: =MID(J74,7,4) -> 2026 | L74: =MID(J74,4,2) -> 05 | M74: =LEFT(J74,2) -> 02 | N74: =RIGHT(J74,8) -> 19:17:42
A75: TE PAGÓ | B75: Janet Mac* | C75: Janet Vil* | D75: 26.00 | E75: =VALUE(SUBSTITUTE(D75, ".", ",")) -> 26 | F75: T | G75: 10 | H75: =TRIM(UPPER(F75)) & "-" & TRIM(UPPER(G75)) -> T-10 | I75: mz t lt 10 | J75: 02/05/2026 19:14:36 | K75: =MID(J75,7,4) -> 2026 | L75: =MID(J75,4,2) -> 05 | M75: =LEFT(J75,2) -> 02 | N75: =RIGHT(J75,8) -> 19:14:36
A76: TE PAGÓ | B76: Estela Cap* | C76: Janet Vil* | D76: 18.00 | E76: =VALUE(SUBSTITUTE(D76, ".", ",")) -> 18 | F76: P | G76: 7 | H76: =TRIM(UPPER(F76)) & "-" & TRIM(UPPER(G76)) -> P-7 | J76: 02/05/2026 19:12:56 | K76: =MID(J76,7,4) -> 2026 | L76: =MID(J76,4,2) -> 05 | M76: =LEFT(J76,2) -> 02 | N76: =RIGHT(J76,8) -> 19:12:56
A77: TE PAGÓ | B77: Salome Dia* | C77: Janet Vil* | D77: 9.00 | E77: =VALUE(SUBSTITUTE(D77, ".", ",")) -> 9 | F77: B | G77: 13 | H77: =TRIM(UPPER(F77)) & "-" & TRIM(UPPER(G77)) -> B-13 | I77: Salome agustina Mz. B lt 13 | J77: 02/05/2026 19:12:51 | K77: =MID(J77,7,4) -> 2026 | L77: =MID(J77,4,2) -> 05 | M77: =LEFT(J77,2) -> 02 | N77: =RIGHT(J77,8) -> 19:12:51
A78: TE PAGÓ | B78: Marisol Rom* | C78: Janet Vil* | D78: 24.00 | E78: =VALUE(SUBSTITUTE(D78, ".", ",")) -> 24 | F78: W | G78: 5 | H78: =TRIM(UPPER(F78)) & "-" & TRIM(UPPER(G78)) -> W-5 | I78: Renato Albornoz Sigueñas Mzn.W Lt.5 | J78: 02/05/2026 19:11:00 | K78: =MID(J78,7,4) -> 2026 | L78: =MID(J78,4,2) -> 05 | M78: =LEFT(J78,2) -> 02 | N78: =RIGHT(J78,8) -> 19:11:00
A79: TE PAGÓ | B79: Carmen Mel* | C79: Janet Vil* | D79: 16.00 | E79: =VALUE(SUBSTITUTE(D79, ".", ",")) -> 16 | F79: V | G79: 8 | H79: =TRIM(UPPER(F79)) & "-" & TRIM(UPPER(G79)) -> V-8 | I79: Carmen Mercedes Melchor Albornoz MZ:V LT:8 | J79: 02/05/2026 19:06:54 | K79: =MID(J79,7,4) -> 2026 | L79: =MID(J79,4,2) -> 05 | M79: =LEFT(J79,2) -> 02 | N79: =RIGHT(J79,8) -> 19:06:54
A80: TE PAGÓ | B80: Dedicacion Gar* | C80: Janet Vil* | D80: 80.00 | E80: =VALUE(SUBSTITUTE(D80, ".", ",")) -> 80 | F80: Q | G80: 6 | H80: =TRIM(UPPER(F80)) & "-" & TRIM(UPPER(G80)) -> Q-6 | I80: MZQ LT 6 | J80: 02/05/2026 19:05:43 | K80: =MID(J80,7,4) -> 2026 | L80: =MID(J80,4,2) -> 05 | M80: =LEFT(J80,2) -> 02 | N80: =RIGHT(J80,8) -> 19:05:43
A81: TE PAGÓ | B81: PLIN - YESSICA PAOLA SOCOLA | C81: JANET VILLANUEVA ALEGRIA | D81: 48.00 | E81: =VALUE(SUBSTITUTE(D81, ".", ",")) -> 48 | F81: L | G81: 14 | H81: =TRIM(UPPER(F81)) & "-" & TRIM(UPPER(G81)) -> L-14 | J81: 02/05/2026 19:05:17 | K81: =MID(J81,7,4) -> 2026 | L81: =MID(J81,4,2) -> 05 | M81: =LEFT(J81,2) -> 02 | N81: =RIGHT(J81,8) -> 19:05:17
A82: TE PAGÓ | B82: Elmer Qui* | C82: Janet Vil* | D82: 17.00 | E82: =VALUE(SUBSTITUTE(D82, ".", ",")) -> 17 | F82: C1 | G82: 1 | H82: =TRIM(UPPER(F82)) & "-" & TRIM(UPPER(G82)) -> C1-1 | I82: Mz.C1 Lt.1 | J82: 02/05/2026 19:05:01 | K82: =MID(J82,7,4) -> 2026 | L82: =MID(J82,4,2) -> 05 | M82: =LEFT(J82,2) -> 02 | N82: =RIGHT(J82,8) -> 19:05:01
A83: TE PAGÓ | B83: Nelson Cos* | C83: Janet Vil* | D83: 26.00 | E83: =VALUE(SUBSTITUTE(D83, ".", ",")) -> 26 | F83: G | G83: 21 | H83: =TRIM(UPPER(F83)) & "-" & TRIM(UPPER(G83)) -> G-21 | J83: 02/05/2026 19:02:55 | K83: =MID(J83,7,4) -> 2026 | L83: =MID(J83,4,2) -> 05 | M83: =LEFT(J83,2) -> 02 | N83: =RIGHT(J83,8) -> 19:02:55
A84: TE PAGÓ | B84: Diego Lop* | C84: Janet Vil* | D84: 8.00 | E84: =VALUE(SUBSTITUTE(D84, ".", ",")) -> 8 | F84: A1 | G84: 12 | H84: =TRIM(UPPER(F84)) & "-" & TRIM(UPPER(G84)) -> A1-12 | I84: Mz. A1 Lt.12(Diego Lopez Muñoz) | J84: 02/05/2026 19:01:25 | K84: =MID(J84,7,4) -> 2026 | L84: =MID(J84,4,2) -> 05 | M84: =LEFT(J84,2) -> 02 | N84: =RIGHT(J84,8) -> 19:01:25
A85: TE PAGÓ | B85: Maria Ram* | C85: Janet Vil* | D85: 20.00 | E85: =VALUE(SUBSTITUTE(D85, ".", ",")) -> 20 | F85: O | G85: 7 | H85: =TRIM(UPPER(F85)) & "-" & TRIM(UPPER(G85)) -> O-7 | I85: mz o lt 7 | J85: 02/05/2026 19:00:36 | K85: =MID(J85,7,4) -> 2026 | L85: =MID(J85,4,2) -> 05 | M85: =LEFT(J85,2) -> 02 | N85: =RIGHT(J85,8) -> 19:00:36
A86: TE PAGÓ | B86: Maria Ram* | C86: Janet Vil* | D86: 18.00 | E86: =VALUE(SUBSTITUTE(D86, ".", ",")) -> 18 | F86: O | G86: 27 | H86: =TRIM(UPPER(F86)) & "-" & TRIM(UPPER(G86)) -> O-27 | I86: mz o lt 27 | J86: 02/05/2026 18:59:50 | K86: =MID(J86,7,4) -> 2026 | L86: =MID(J86,4,2) -> 05 | M86: =LEFT(J86,2) -> 02 | N86: =RIGHT(J86,8) -> 18:59:50
A87: TE PAGÓ | B87: Maria Ram* | C87: Janet Vil* | D87: 37.00 | E87: =VALUE(SUBSTITUTE(D87, ".", ",")) -> 37 | F87: O | G87: 6 | H87: =TRIM(UPPER(F87)) & "-" & TRIM(UPPER(G87)) -> O-6 | I87: mz o lt6 | J87: 02/05/2026 18:59:23 | K87: =MID(J87,7,4) -> 2026 | L87: =MID(J87,4,2) -> 05 | M87: =LEFT(J87,2) -> 02 | N87: =RIGHT(J87,8) -> 18:59:23
A88: TE PAGÓ | B88: Norma Jar* | C88: Janet Vil* | D88: 23.00 | E88: =VALUE(SUBSTITUTE(D88, ".", ",")) -> 23 | F88: T | G88: 16 | H88: =TRIM(UPPER(F88)) & "-" & TRIM(UPPER(G88)) -> T-16 | J88: 02/05/2026 18:53:24 | K88: =MID(J88,7,4) -> 2026 | L88: =MID(J88,4,2) -> 05 | M88: =LEFT(J88,2) -> 02 | N88: =RIGHT(J88,8) -> 18:53:24
A89: TE PAGÓ | B89: Bertha Gas* | C89: Janet Vil* | D89: 17.00 | E89: =VALUE(SUBSTITUTE(D89, ".", ",")) -> 17 | F89: X | G89: 3 | H89: =TRIM(UPPER(F89)) & "-" & TRIM(UPPER(G89)) -> X-3 | I89: Mz.x lote 3 bertha gastar peña | J89: 02/05/2026 18:52:31 | K89: =MID(J89,7,4) -> 2026 | L89: =MID(J89,4,2) -> 05 | M89: =LEFT(J89,2) -> 02 | N89: =RIGHT(J89,8) -> 18:52:31
A90: TE PAGÓ | B90: Ruddy Bla* | C90: Janet Vil* | D90: 9.00 | E90: =VALUE(SUBSTITUTE(D90, ".", ",")) -> 9 | F90: X | G90: 21 | H90: =TRIM(UPPER(F90)) & "-" & TRIM(UPPER(G90)) -> X-21 | I90: Mz "X" lt.21 (ruddy Blas) | J90: 02/05/2026 18:42:38 | K90: =MID(J90,7,4) -> 2026 | L90: =MID(J90,4,2) -> 05 | M90: =LEFT(J90,2) -> 02 | N90: =RIGHT(J90,8) -> 18:42:38
A91: TE PAGÓ | B91: Giannella Mun* | C91: Janet Vil* | D91: 64.00 | E91: =VALUE(SUBSTITUTE(D91, ".", ",")) -> 64 | F91: H | G91: 21 | H91: =TRIM(UPPER(F91)) & "-" & TRIM(UPPER(G91)) -> H-21 | I91: ROMAN LOZANO MINAYA MZ "H" LOTE 21 | J91: 02/05/2026 18:41:39 | K91: =MID(J91,7,4) -> 2026 | L91: =MID(J91,4,2) -> 05 | M91: =LEFT(J91,2) -> 02 | N91: =RIGHT(J91,8) -> 18:41:39
A92: TE PAGÓ | B92: Ruddy Bla* | C92: Janet Vil* | D92: 20.00 | E92: =VALUE(SUBSTITUTE(D92, ".", ",")) -> 20 | F92: P | G92: 19 | H92: =TRIM(UPPER(F92)) & "-" & TRIM(UPPER(G92)) -> P-19 | I92: Mz. "P" Lt.19 (Leoncio Blas ) | J92: 02/05/2026 18:41:21 | K92: =MID(J92,7,4) -> 2026 | L92: =MID(J92,4,2) -> 05 | M92: =LEFT(J92,2) -> 02 | N92: =RIGHT(J92,8) -> 18:41:21
A93: TE PAGÓ | B93: Rimenita Mun* | C93: Janet Vil* | D93: 14.00 | E93: =VALUE(SUBSTITUTE(D93, ".", ",")) -> 14 | F93: E | G93: 13 | H93: =TRIM(UPPER(F93)) & "-" & TRIM(UPPER(G93)) -> E-13 | I93: MZ. E. LT. 13. | J93: 02/05/2026 18:40:46 | K93: =MID(J93,7,4) -> 2026 | L93: =MID(J93,4,2) -> 05 | M93: =LEFT(J93,2) -> 02 | N93: =RIGHT(J93,8) -> 18:40:46
A94: TE PAGÓ | B94: Rimenita Mun* | C94: Janet Vil* | D94: 8.00 | E94: =VALUE(SUBSTITUTE(D94, ".", ",")) -> 8 | F94: E | G94: 19 | H94: =TRIM(UPPER(F94)) & "-" & TRIM(UPPER(G94)) -> E-19 | I94: MZ 19. LT 19. MERCADO | J94: 02/05/2026 18:39:22 | K94: =MID(J94,7,4) -> 2026 | L94: =MID(J94,4,2) -> 05 | M94: =LEFT(J94,2) -> 02 | N94: =RIGHT(J94,8) -> 18:39:22
A95: TE PAGÓ | B95: Ruth Per* | C95: Janet Vil* | D95: 90.00 | E95: =VALUE(SUBSTITUTE(D95, ".", ",")) -> 90 | F95: M | G95: 21 | H95: =TRIM(UPPER(F95)) & "-" & TRIM(UPPER(G95)) -> M-21 | J95: 02/05/2026 18:37:28 | K95: =MID(J95,7,4) -> 2026 | L95: =MID(J95,4,2) -> 05 | M95: =LEFT(J95,2) -> 02 | N95: =RIGHT(J95,8) -> 18:37:28
A96: TE PAGÓ | B96: Alan Car* | C96: Janet Vil* | D96: 36.00 | E96: =VALUE(SUBSTITUTE(D96, ".", ",")) -> 36 | F96: L | G96: 1 | H96: =TRIM(UPPER(F96)) & "-" & TRIM(UPPER(G96)) -> L-1 | I96: Mz L lote 1 micaela bastidas ELENA CASPA DÍAS | J96: 02/05/2026 18:33:17 | K96: =MID(J96,7,4) -> 2026 | L96: =MID(J96,4,2) -> 05 | M96: =LEFT(J96,2) -> 02 | N96: =RIGHT(J96,8) -> 18:33:17
A97: TE PAGÓ | B97: Cristopher Gon* | C97: Janet Vil* | D97: 108.00 | E97: =VALUE(SUBSTITUTE(D97, ".", ",")) -> 108 | F97: D | G97: 6 | H97: =TRIM(UPPER(F97)) & "-" & TRIM(UPPER(G97)) -> D-6 | J97: 02/05/2026 18:27:59 | K97: =MID(J97,7,4) -> 2026 | L97: =MID(J97,4,2) -> 05 | M97: =LEFT(J97,2) -> 02 | N97: =RIGHT(J97,8) -> 18:27:59
A98: TE PAGÓ | B98: Samuel Lun* | C98: Janet Vil* | D98: 29.00 | E98: =VALUE(SUBSTITUTE(D98, ".", ",")) -> 29 | F98: Y | G98: 9 | H98: =TRIM(UPPER(F98)) & "-" & TRIM(UPPER(G98)) -> Y-9 | I98: Mz:Y. Lote 9 | J98: 02/05/2026 18:20:42 | K98: =MID(J98,7,4) -> 2026 | L98: =MID(J98,4,2) -> 05 | M98: =LEFT(J98,2) -> 02 | N98: =RIGHT(J98,8) -> 18:20:42
A99: TE PAGÓ | B99: Eugenia Esc* | C99: Janet Vil* | D99: 24.00 | E99: =VALUE(SUBSTITUTE(D99, ".", ",")) -> 24 | F99: C1 | G99: 5 | H99: =TRIM(UPPER(F99)) & "-" & TRIM(UPPER(G99)) -> C1-5 | I99: Eugenia escudero solano c1 | J99: 02/05/2026 18:18:22 | K99: =MID(J99,7,4) -> 2026 | L99: =MID(J99,4,2) -> 05 | M99: =LEFT(J99,2) -> 02 | N99: =RIGHT(J99,8) -> 18:18:22
A100: TE PAGÓ | B100: Raul Bla* | C100: Janet Vil* | D100: 8.00 | E100: =VALUE(SUBSTITUTE(D100, ".", ",")) -> 8 | F100: M | G100: 17 | H100: =TRIM(UPPER(F100)) & "-" & TRIM(UPPER(G100)) -> M-17 | I100: Mz .M. Lt .17 | J100: 02/05/2026 18:16:29 | K100: =MID(J100,7,4) -> 2026 | L100: =MID(J100,4,2) -> 05 | M100: =LEFT(J100,2) -> 02 | N100: =RIGHT(J100,8) -> 18:16:29
A101: TE PAGÓ | B101: Thalia Lau* | C101: Janet Vil* | D101: 132.00 | E101: =VALUE(SUBSTITUTE(D101, ".", ",")) -> 132 | F101: F | G101: 7 | H101: =TRIM(UPPER(F101)) & "-" & TRIM(UPPER(G101)) -> F-7 | I101: manzana F lote 7 | J101: 02/05/2026 18:16:10 | K101: =MID(J101,7,4) -> 2026 | L101: =MID(J101,4,2) -> 05 | M101: =LEFT(J101,2) -> 02 | N101: =RIGHT(J101,8) -> 18:16:10
A102: TE PAGÓ | B102: Fatima Pim* | C102: Janet Vil* | D102: 12.00 | E102: =VALUE(SUBSTITUTE(D102, ".", ",")) -> 12 | F102: P | G102: 17 | H102: =TRIM(UPPER(F102)) & "-" & TRIM(UPPER(G102)) -> P-17 | I102: manzana p lote 17 Mauricia duran Valladares | J102: 02/05/2026 18:15:27 | K102: =MID(J102,7,4) -> 2026 | L102: =MID(J102,4,2) -> 05 | M102: =LEFT(J102,2) -> 02 | N102: =RIGHT(J102,8) -> 18:15:27
A103: TE PAGÓ | B103: Raul Bla* | C103: Janet Vil* | D103: 52.00 | E103: =VALUE(SUBSTITUTE(D103, ".", ",")) -> 52 | F103: O | G103: 9 | H103: =TRIM(UPPER(F103)) & "-" & TRIM(UPPER(G103)) -> O-9 | I103: MZ .O Lt 9 | J103: 02/05/2026 18:15:19 | K103: =MID(J103,7,4) -> 2026 | L103: =MID(J103,4,2) -> 05 | M103: =LEFT(J103,2) -> 02 | N103: =RIGHT(J103,8) -> 18:15:19
A104: TE PAGÓ | B104: Rosa Cor* | C104: Janet Vil* | D104: 50.00 | E104: =VALUE(SUBSTITUTE(D104, ".", ",")) -> 50 | F104: F | G104: 9 | H104: =TRIM(UPPER(F104)) & "-" & TRIM(UPPER(G104)) -> F-9 | I104: Mz F lote 9 | J104: 02/05/2026 18:12:55 | K104: =MID(J104,7,4) -> 2026 | L104: =MID(J104,4,2) -> 05 | M104: =LEFT(J104,2) -> 02 | N104: =RIGHT(J104,8) -> 18:12:55
A105: TE PAGÓ | B105: Maryori Rey* | C105: Janet Vil* | D105: 8.00 | E105: =VALUE(SUBSTITUTE(D105, ".", ",")) -> 8 | F105: C | G105: 26 | H105: =TRIM(UPPER(F105)) & "-" & TRIM(UPPER(G105)) -> C-26 | I105: Mz.c lote 26 | J105: 02/05/2026 18:10:51 | K105: =MID(J105,7,4) -> 2026 | L105: =MID(J105,4,2) -> 05 | M105: =LEFT(J105,2) -> 02 | N105: =RIGHT(J105,8) -> 18:10:51
A106: TE PAGÓ | B106: Brigida Cer* | C106: Janet Vil* | D106: 37.00 | E106: =VALUE(SUBSTITUTE(D106, ".", ",")) -> 37 | F106: H | G106: 5 | H106: =TRIM(UPPER(F106)) & "-" & TRIM(UPPER(G106)) -> H-5 | J106: 02/05/2026 18:07:03 | K106: =MID(J106,7,4) -> 2026 | L106: =MID(J106,4,2) -> 05 | M106: =LEFT(J106,2) -> 02 | N106: =RIGHT(J106,8) -> 18:07:03
...

Sheet Efectivo
A1: Mz | B1: Lt | C1: Monto | D1: Llave | E1: Comparar | F1: Comentario | G1: Fecha | I1: Mz | J1: Lt | K1: Monto | L1: Comparar2 | M1: Comentario
A2: N | B2: 2 | C2: 58 | D2: =TRIM(UPPER(A2)) & "-" & TRIM(UPPER(B2)) -> N-2 | E2: =TRIM(UPPER(A2)) & "-" & TRIM(UPPER(B2) & "-" & TEXT(C2, "0")) -> N-2-58 | F2: Yo puse L2 pero es N2 monto exacto | G2: 46144 | I2: N | J2: 2 | K2: 58 | L2: =TRIM(UPPER(I2)) & "-" & TRIM(UPPER(J2) & "-" & TEXT(K2, "0")) -> N-2-58
A3: N | B3: 4 | C3: 8 | D3: =TRIM(UPPER(A3)) & "-" & TRIM(UPPER(B3)) -> N-4 | E3: =TRIM(UPPER(A3)) & "-" & TRIM(UPPER(B3) & "-" & TEXT(C3, "0")) -> N-4-8 | G3: 46144 | I3: N | J3: 4 | K3: 8 | L3: =TRIM(UPPER(I3)) & "-" & TRIM(UPPER(J3) & "-" & TEXT(K3, "0")) -> N-4-8
A4: O | B4: 26 | C4: 33 | D4: =TRIM(UPPER(A4)) & "-" & TRIM(UPPER(B4)) -> O-26 | E4: =TRIM(UPPER(A4)) & "-" & TRIM(UPPER(B4) & "-" & TEXT(C4, "0")) -> O-26-33 | G4: 46144 | I4: O | J4: 26 | K4: 33 | L4: =TRIM(UPPER(I4)) & "-" & TRIM(UPPER(J4) & "-" & TEXT(K4, "0")) -> O-26-33
A5: Y | B5: 3 | C5: 20 | D5: =TRIM(UPPER(A5)) & "-" & TRIM(UPPER(B5)) -> Y-3 | E5: =TRIM(UPPER(A5)) & "-" & TRIM(UPPER(B5) & "-" & TEXT(C5, "0")) -> Y-3-20 | G5: 46144 | I5: Y | J5: 3 | K5: 20 | L5: =TRIM(UPPER(I5)) & "-" & TRIM(UPPER(J5) & "-" & TEXT(K5, "0")) -> Y-3-20 | O5: =SUM(K2:K5) -> 119 | P5: Efectivo antes del cobro
A6: B1 | B6: 1 | C6: 12 | D6: =TRIM(UPPER(A6)) & "-" & TRIM(UPPER(B6)) -> B1-1 | E6: =TRIM(UPPER(A6)) & "-" & TRIM(UPPER(B6) & "-" & TEXT(C6, "0")) -> B1-1-12 | F6: 75 medidor | G6: 46144 | I6: B1 | J6: 1 | K6: 12 | L6: =TRIM(UPPER(I6)) & "-" & TRIM(UPPER(J6) & "-" & TEXT(K6, "0")) -> B1-1-12 | M6: 75 Medidor
A7: G | B7: 11 | C7: 44 | D7: =TRIM(UPPER(A7)) & "-" & TRIM(UPPER(B7)) -> G-11 | E7: =TRIM(UPPER(A7)) & "-" & TRIM(UPPER(B7) & "-" & TEXT(C7, "0")) -> G-11-44 | G7: 46144 | I7: G | J7: 11 | K7: 44 | L7: =TRIM(UPPER(I7)) & "-" & TRIM(UPPER(J7) & "-" & TEXT(K7, "0")) -> G-11-44
A8: O | B8: 28 | C8: 8 | D8: =TRIM(UPPER(A8)) & "-" & TRIM(UPPER(B8)) -> O-28 | E8: =TRIM(UPPER(A8)) & "-" & TRIM(UPPER(B8) & "-" & TEXT(C8, "0")) -> O-28-8 | F8: Verificar mes anterior (5) | G8: 46144 | I8: O | J8: 28 | K8: 8 | L8: =TRIM(UPPER(I8)) & "-" & TRIM(UPPER(J8) & "-" & TEXT(K8, "0")) -> O-28-8 | M8: 20 Medidor
A9: O | B9: 5 | C9: 8 | D9: =TRIM(UPPER(A9)) & "-" & TRIM(UPPER(B9)) -> O-5 | E9: =TRIM(UPPER(A9)) & "-" & TRIM(UPPER(B9) & "-" & TEXT(C9, "0")) -> O-5-8 | G9: 46144 | I9: O | J9: 5 | K9: 8 | L9: =TRIM(UPPER(I9)) & "-" & TRIM(UPPER(J9) & "-" & TEXT(K9, "0")) -> O-5-8
A10: B | B10: 2 | C10: 38 | D10: =TRIM(UPPER(A10)) & "-" & TRIM(UPPER(B10)) -> B-2 | E10: =TRIM(UPPER(A10)) & "-" & TRIM(UPPER(B10) & "-" & TEXT(C10, "0")) -> B-2-38 | G10: 46144 | I10: B | J10: 2 | K10: 38 | L10: =TRIM(UPPER(I10)) & "-" & TRIM(UPPER(J10) & "-" & TEXT(K10, "0")) -> B-2-38
A11: B | B11: 3 | C11: 12 | D11: =TRIM(UPPER(A11)) & "-" & TRIM(UPPER(B11)) -> B-3 | E11: =TRIM(UPPER(A11)) & "-" & TRIM(UPPER(B11) & "-" & TEXT(C11, "0")) -> B-3-12 | G11: 46144 | I11: B | J11: 3 | K11: 12 | L11: =TRIM(UPPER(I11)) & "-" & TRIM(UPPER(J11) & "-" & TEXT(K11, "0")) -> B-3-12
A12: C | B12: 4 | C12: 38 | D12: =TRIM(UPPER(A12)) & "-" & TRIM(UPPER(B12)) -> C-4 | E12: =TRIM(UPPER(A12)) & "-" & TRIM(UPPER(B12) & "-" & TEXT(C12, "0")) -> C-4-38 | G12: 46144 | I12: C | J12: 4 | K12: 38 | L12: =TRIM(UPPER(I12)) & "-" & TRIM(UPPER(J12) & "-" & TEXT(K12, "0")) -> C-4-38
A13: N | B13: 3 | C13: 20 | D13: =TRIM(UPPER(A13)) & "-" & TRIM(UPPER(B13)) -> N-3 | E13: =TRIM(UPPER(A13)) & "-" & TRIM(UPPER(B13) & "-" & TEXT(C13, "0")) -> N-3-20 | G13: 46144 | I13: N | J13: 3 | K13: 20 | L13: =TRIM(UPPER(I13)) & "-" & TRIM(UPPER(J13) & "-" & TEXT(K13, "0")) -> N-3-20
A14: G | B14: 20 | C14: 50 | D14: =TRIM(UPPER(A14)) & "-" & TRIM(UPPER(B14)) -> G-20 | E14: =TRIM(UPPER(A14)) & "-" & TRIM(UPPER(B14) & "-" & TEXT(C14, "0")) -> G-20-50 | G14: 46144 | I14: G | J14: 20 | K14: 50 | L14: =TRIM(UPPER(I14)) & "-" & TRIM(UPPER(J14) & "-" & TEXT(K14, "0")) -> G-20-50
A15: Q | B15: 1 | C15: 12 | D15: =TRIM(UPPER(A15)) & "-" & TRIM(UPPER(B15)) -> Q-1 | E15: =TRIM(UPPER(A15)) & "-" & TRIM(UPPER(B15) & "-" & TEXT(C15, "0")) -> Q-1-12 | G15: 46144 | I15: Q | J15: 1 | K15: 12 | L15: =TRIM(UPPER(I15)) & "-" & TRIM(UPPER(J15) & "-" & TEXT(K15, "0")) -> Q-1-12
A16: U | B16: 2 | C16: 9 | D16: =TRIM(UPPER(A16)) & "-" & TRIM(UPPER(B16)) -> U-2 | E16: =TRIM(UPPER(A16)) & "-" & TRIM(UPPER(B16) & "-" & TEXT(C16, "0")) -> U-2-9 | F16: consumo + medidor | G16: 46144 | I16: U | J16: 2 | K16: 9 | L16: =TRIM(UPPER(I16)) & "-" & TRIM(UPPER(J16) & "-" & TEXT(K16, "0")) -> U-2-9 | M16: 100 Medidor
A17: J | B17: 8 | C17: 42 | D17: =TRIM(UPPER(A17)) & "-" & TRIM(UPPER(B17)) -> J-8 | E17: =TRIM(UPPER(A17)) & "-" & TRIM(UPPER(B17) & "-" & TEXT(C17, "0")) -> J-8-42 | G17: 46144 | I17: J | J17: 8 | K17: 42 | L17: =TRIM(UPPER(I17)) & "-" & TRIM(UPPER(J17) & "-" & TEXT(K17, "0")) -> J-8-42
A18: P | B18: 13 | C18: 10 | D18: =TRIM(UPPER(A18)) & "-" & TRIM(UPPER(B18)) -> P-13 | E18: =TRIM(UPPER(A18)) & "-" & TRIM(UPPER(B18) & "-" & TEXT(C18, "0")) -> P-13-10 | G18: 46144 | I18: P | J18: 13 | K18: 10 | L18: =TRIM(UPPER(I18)) & "-" & TRIM(UPPER(J18) & "-" & TEXT(K18, "0")) -> P-13-10
A19: J | B19: 9 | C19: 41 | D19: =TRIM(UPPER(A19)) & "-" & TRIM(UPPER(B19)) -> J-9 | E19: =TRIM(UPPER(A19)) & "-" & TRIM(UPPER(B19) & "-" & TEXT(C19, "0")) -> J-9-41 | G19: 46144 | I19: J | J19: 9 | K19: 41 | L19: =TRIM(UPPER(I19)) & "-" & TRIM(UPPER(J19) & "-" & TEXT(K19, "0")) -> J-9-41
A20: C | B20: 37 | C20: 11 | D20: =TRIM(UPPER(A20)) & "-" & TRIM(UPPER(B20)) -> C-37 | E20: =TRIM(UPPER(A20)) & "-" & TRIM(UPPER(B20) & "-" & TEXT(C20, "0")) -> C-37-11 | G20: 46144 | I20: C | J20: 37 | K20: 11 | L20: =TRIM(UPPER(I20)) & "-" & TRIM(UPPER(J20) & "-" & TEXT(K20, "0")) -> C-37-11
A21: M | B21: 4 | C21: 12 | D21: =TRIM(UPPER(A21)) & "-" & TRIM(UPPER(B21)) -> M-4 | E21: =TRIM(UPPER(A21)) & "-" & TRIM(UPPER(B21) & "-" & TEXT(C21, "0")) -> M-4-12 | F21: Ya canceló medidor | G21: 46144 | I21: M | J21: 4 | K21: 12 | L21: =TRIM(UPPER(I21)) & "-" & TRIM(UPPER(J21) & "-" & TEXT(K21, "0")) -> M-4-12 | M21: Consumo Wag anterior S/9
A22: H | B22: 11 | C22: 33 | D22: =TRIM(UPPER(A22)) & "-" & TRIM(UPPER(B22)) -> H-11 | E22: =TRIM(UPPER(A22)) & "-" & TRIM(UPPER(B22) & "-" & TEXT(C22, "0")) -> H-11-33 | F22: Ya canceló medidor | G22: 46144 | I22: H | J22: 11 | K22: 33 | L22: =TRIM(UPPER(I22)) & "-" & TRIM(UPPER(J22) & "-" & TEXT(K22, "0")) -> H-11-33 | M22: Consumo Wag anterior S/8
A23: Q | B23: 8 | C23: 70 | D23: =TRIM(UPPER(A23)) & "-" & TRIM(UPPER(B23)) -> Q-8 | E23: =TRIM(UPPER(A23)) & "-" & TRIM(UPPER(B23) & "-" & TEXT(C23, "0")) -> Q-8-70 | G23: 46144 | I23: Q | J23: 8 | K23: 70 | L23: =TRIM(UPPER(I23)) & "-" & TRIM(UPPER(J23) & "-" & TEXT(K23, "0")) -> Q-8-70 | M23: Coñvenio 50 + Consumo 20
A24: G | B24: 19 | C24: 50 | D24: =TRIM(UPPER(A24)) & "-" & TRIM(UPPER(B24)) -> G-19 | E24: =TRIM(UPPER(A24)) & "-" & TRIM(UPPER(B24) & "-" & TEXT(C24, "0")) -> G-19-50 | G24: 46144 | I24: G | J24: 19 | K24: 50 | L24: =TRIM(UPPER(I24)) & "-" & TRIM(UPPER(J24) & "-" & TEXT(K24, "0")) -> G-19-50
A25: X | B25: 13 | C25: 11 | D25: =TRIM(UPPER(A25)) & "-" & TRIM(UPPER(B25)) -> X-13 | E25: =TRIM(UPPER(A25)) & "-" & TRIM(UPPER(B25) & "-" & TEXT(C25, "0")) -> X-13-11 | F25: Ya pagó 20 soles efectivo. Dice que JAIME pagó medidor. Pago consumo medidor debe consumo 20. Dice que el operario leyó mal. | G25: 46144 | I25: X | J25: 13 | K25: 11 | L25: =TRIM(UPPER(I25)) & "-" & TRIM(UPPER(J25) & "-" & TEXT(K25, "0")) -> X-13-11 | M25: Anterior Wag 20, Medidor
A26: L | B26: 12 | C26: 31 | D26: =TRIM(UPPER(A26)) & "-" & TRIM(UPPER(B26)) -> L-12 | E26: =TRIM(UPPER(A26)) & "-" & TRIM(UPPER(B26) & "-" & TEXT(C26, "0")) -> L-12-31 | G26: 46144 | I26: L | J26: 12 | K26: 31 | L26: =TRIM(UPPER(I26)) & "-" & TRIM(UPPER(J26) & "-" & TEXT(K26, "0")) -> L-12-31 | M26: Verificar lectura
A27: O | B27: 17 | C27: 33 | D27: =TRIM(UPPER(A27)) & "-" & TRIM(UPPER(B27)) -> O-17 | E27: =TRIM(UPPER(A27)) & "-" & TRIM(UPPER(B27) & "-" & TEXT(C27, "0")) -> O-17-33 | G27: 46144 | I27: O | J27: 17 | K27: 33 | L27: =TRIM(UPPER(I27)) & "-" & TRIM(UPPER(J27) & "-" & TEXT(K27, "0")) -> O-17-33
A28: H | B28: 2 | C28: 24 | D28: =TRIM(UPPER(A28)) & "-" & TRIM(UPPER(B28)) -> H-2 | E28: =TRIM(UPPER(A28)) & "-" & TRIM(UPPER(B28) & "-" & TEXT(C28, "0")) -> H-2-24 | F28: 26 + 50 | G28: 46144 | I28: H | J28: 2 | K28: 24 | L28: =TRIM(UPPER(I28)) & "-" & TRIM(UPPER(J28) & "-" & TEXT(K28, "0")) -> H-2-24
A29: H | B29: 3 | C29: 28 | D29: =TRIM(UPPER(A29)) & "-" & TRIM(UPPER(B29)) -> H-3 | E29: =TRIM(UPPER(A29)) & "-" & TRIM(UPPER(B29) & "-" & TEXT(C29, "0")) -> H-3-28 | G29: 46144 | I29: H | J29: 3 | K29: 28 | L29: =TRIM(UPPER(I29)) & "-" & TRIM(UPPER(J29) & "-" & TEXT(K29, "0")) -> H-3-28
A30: C | B30: 23 | C30: 27 | D30: =TRIM(UPPER(A30)) & "-" & TRIM(UPPER(B30)) -> C-23 | E30: =TRIM(UPPER(A30)) & "-" & TRIM(UPPER(B30) & "-" & TEXT(C30, "0")) -> C-23-27 | G30: 46144 | I30: C | J30: 23 | K30: 27 | L30: =TRIM(UPPER(I30)) & "-" & TRIM(UPPER(J30) & "-" & TEXT(K30, "0")) -> C-23-27 | P30: Se cambio 27 por 23
A31: S | B31: 13 | C31: 25 | D31: =TRIM(UPPER(A31)) & "-" & TRIM(UPPER(B31)) -> S-13 | E31: =TRIM(UPPER(A31)) & "-" & TRIM(UPPER(B31) & "-" & TEXT(C31, "0")) -> S-13-25 | G31: 46144 | I31: S | J31: 13 | K31: 25 | L31: =TRIM(UPPER(I31)) & "-" & TRIM(UPPER(J31) & "-" & TEXT(K31, "0")) -> S-13-25
A32: W | B32: 9 | C32: 8 | D32: =TRIM(UPPER(A32)) & "-" & TRIM(UPPER(B32)) -> W-9 | E32: =TRIM(UPPER(A32)) & "-" & TRIM(UPPER(B32) & "-" & TEXT(C32, "0")) -> W-9-8 | G32: 46144 | I32: W | J32: 9 | K32: 8 | L32: =TRIM(UPPER(I32)) & "-" & TRIM(UPPER(J32) & "-" & TEXT(K32, "0")) -> W-9-8
A33: S | B33: 7 | C33: 8 | D33: =TRIM(UPPER(A33)) & "-" & TRIM(UPPER(B33)) -> S-7 | E33: =TRIM(UPPER(A33)) & "-" & TRIM(UPPER(B33) & "-" & TEXT(C33, "0")) -> S-7-8 | G33: 46144 | I33: S | J33: 7 | K33: 8 | L33: =TRIM(UPPER(I33)) & "-" & TRIM(UPPER(J33) & "-" & TEXT(K33, "0")) -> S-7-8
A34: I | B34: 18 | C34: 20 | D34: =TRIM(UPPER(A34)) & "-" & TRIM(UPPER(B34)) -> I-18 | E34: =TRIM(UPPER(A34)) & "-" & TRIM(UPPER(B34) & "-" & TEXT(C34, "0")) -> I-18-20 | G34: 46144 | I34: I | J34: 18 | K34: 20 | L34: =TRIM(UPPER(I34)) & "-" & TRIM(UPPER(J34) & "-" & TEXT(K34, "0")) -> I-18-20
A35: C | B35: 32 | C35: 33 | D35: =TRIM(UPPER(A35)) & "-" & TRIM(UPPER(B35)) -> C-32 | E35: =TRIM(UPPER(A35)) & "-" & TRIM(UPPER(B35) & "-" & TEXT(C35, "0")) -> C-32-33 | G35: 46144 | I35: C | J35: 32 | K35: 33 | L35: =TRIM(UPPER(I35)) & "-" & TRIM(UPPER(J35) & "-" & TEXT(K35, "0")) -> C-32-33
A36: C | B36: 2 | C36: 33 | D36: =TRIM(UPPER(A36)) & "-" & TRIM(UPPER(B36)) -> C-2 | E36: =TRIM(UPPER(A36)) & "-" & TRIM(UPPER(B36) & "-" & TEXT(C36, "0")) -> C-2-33 | F36: Va a yapear consumo | G36: 46144 | I36: C | J36: 2 | K36: 33 | L36: =TRIM(UPPER(I36)) & "-" & TRIM(UPPER(J36) & "-" & TEXT(K36, "0")) -> C-2-33 | M36: 26 + 50 Medidor
A37: A | B37: 1 | C37: 75 | D37: =TRIM(UPPER(A37)) & "-" & TRIM(UPPER(B37)) -> A-1 | E37: =TRIM(UPPER(A37)) & "-" & TRIM(UPPER(B37) & "-" & TEXT(C37, "0")) -> A-1-75 | F37: paga medidor 75 | G37: Pago antes de cobro | I37: A | J37: 1 | K37: 75 | L37: =TRIM(UPPER(I37)) & "-" & TRIM(UPPER(J37) & "-" & TEXT(K37, "0")) -> A-1-75
A38: A | B38: 5 | C38: 44 | D38: =TRIM(UPPER(A38)) & "-" & TRIM(UPPER(B38)) -> A-5 | E38: =TRIM(UPPER(A38)) & "-" & TRIM(UPPER(B38) & "-" & TEXT(C38, "0")) -> A-5-44 | G38: 46144 | I38: A | J38: 5 | K38: 44 | L38: =TRIM(UPPER(I38)) & "-" & TRIM(UPPER(J38) & "-" & TEXT(K38, "0")) -> A-5-44 | M38: Verificar
A39: E | B39: 10 | C39: 80 | D39: =TRIM(UPPER(A39)) & "-" & TRIM(UPPER(B39)) -> E-10 | E39: =TRIM(UPPER(A39)) & "-" & TRIM(UPPER(B39) & "-" & TEXT(C39, "0")) -> E-10-80 | G39: 46144 | I39: E | J39: 10 | K39: 80 | L39: =TRIM(UPPER(I39)) & "-" & TRIM(UPPER(J39) & "-" & TEXT(K39, "0")) -> E-10-80
A40: E | B40: 9 | C40: 19 | D40: =TRIM(UPPER(A40)) & "-" & TRIM(UPPER(B40)) -> E-9 | E40: =TRIM(UPPER(A40)) & "-" & TRIM(UPPER(B40) & "-" & TEXT(C40, "0")) -> E-9-19 | G40: 46144 | I40: E | J40: 9 | K40: 19 | L40: =TRIM(UPPER(I40)) & "-" & TRIM(UPPER(J40) & "-" & TEXT(K40, "0")) -> E-9-19
A41: G | B41: 1 | C41: 29 | D41: =TRIM(UPPER(A41)) & "-" & TRIM(UPPER(B41)) -> G-1 | E41: =TRIM(UPPER(A41)) & "-" & TRIM(UPPER(B41) & "-" & TEXT(C41, "0")) -> G-1-29 | F41: YAPE | G41: 46144 | I41: G | J41: 1 | K41: 29 | L41: =TRIM(UPPER(I41)) & "-" & TRIM(UPPER(J41) & "-" & TEXT(K41, "0")) -> G-1-29 | M41: medidor
A42: M | B42: 15 | C42: 8 | D42: =TRIM(UPPER(A42)) & "-" & TRIM(UPPER(B42)) -> M-15 | E42: =TRIM(UPPER(A42)) & "-" & TRIM(UPPER(B42) & "-" & TEXT(C42, "0")) -> M-15-8 | G42: 46144 | I42: M | J42: 15 | K42: 8 | L42: =TRIM(UPPER(I42)) & "-" & TRIM(UPPER(J42) & "-" & TEXT(K42, "0")) -> M-15-8
A43: P | B43: 1 | C43: 16 | D43: =TRIM(UPPER(A43)) & "-" & TRIM(UPPER(B43)) -> P-1 | E43: =TRIM(UPPER(A43)) & "-" & TRIM(UPPER(B43) & "-" & TEXT(C43, "0")) -> P-1-16 | G43: 46144 | I43: P | J43: 1 | K43: 16 | L43: =TRIM(UPPER(I43)) & "-" & TRIM(UPPER(J43) & "-" & TEXT(K43, "0")) -> P-1-16
A44: Y | B44: 6 | C44: 25 | D44: =TRIM(UPPER(A44)) & "-" & TRIM(UPPER(B44)) -> Y-6 | E44: =TRIM(UPPER(A44)) & "-" & TRIM(UPPER(B44) & "-" & TEXT(C44, "0")) -> Y-6-25 | G44: 46144 | I44: Y | J44: 6 | K44: 25 | L44: =TRIM(UPPER(I44)) & "-" & TRIM(UPPER(J44) & "-" & TEXT(K44, "0")) -> Y-6-25
A45: H | B45: 18 | C45: 38 | D45: =TRIM(UPPER(A45)) & "-" & TRIM(UPPER(B45)) -> H-18 | E45: =TRIM(UPPER(A45)) & "-" & TRIM(UPPER(B45) & "-" & TEXT(C45, "0")) -> H-18-38 | G45: 46144 | I45: H | J45: 18 | K45: 38 | L45: =TRIM(UPPER(I45)) & "-" & TRIM(UPPER(J45) & "-" & TEXT(K45, "0")) -> H-18-38
A46: S | B46: 12 | C46: 8 | D46: =TRIM(UPPER(A46)) & "-" & TRIM(UPPER(B46)) -> S-12 | E46: =TRIM(UPPER(A46)) & "-" & TRIM(UPPER(B46) & "-" & TEXT(C46, "0")) -> S-12-8 | G46: 46144 | I46: S | J46: 12 | K46: 8 | L46: =TRIM(UPPER(I46)) & "-" & TRIM(UPPER(J46) & "-" & TEXT(K46, "0")) -> S-12-8 | M46: Yo puse S-12-8. Es S-8-8 por sobrante
A47: R | B47: 8 | C47: 27 | D47: =TRIM(UPPER(A47)) & "-" & TRIM(UPPER(B47)) -> R-8 | E47: =TRIM(UPPER(A47)) & "-" & TRIM(UPPER(B47) & "-" & TEXT(C47, "0")) -> R-8-27 | G47: 46144 | I47: R | J47: 8 | K47: 27 | L47: =TRIM(UPPER(I47)) & "-" & TRIM(UPPER(J47) & "-" & TEXT(K47, "0")) -> R-8-27
A48: H | B48: 4 | C48: 15 | D48: =TRIM(UPPER(A48)) & "-" & TRIM(UPPER(B48)) -> H-4 | E48: =TRIM(UPPER(A48)) & "-" & TRIM(UPPER(B48) & "-" & TEXT(C48, "0")) -> H-4-15 | G48: 46144 | I48: H | J48: 4 | K48: 15 | L48: =TRIM(UPPER(I48)) & "-" & TRIM(UPPER(J48) & "-" & TEXT(K48, "0")) -> H-4-15
A49: A1 | B49: 4 | C49: 12 | D49: =TRIM(UPPER(A49)) & "-" & TRIM(UPPER(B49)) -> A1-4 | E49: =TRIM(UPPER(A49)) & "-" & TRIM(UPPER(B49) & "-" & TEXT(C49, "0")) -> A1-4-12 | G49: 46144 | I49: A1 | J49: 4 | K49: 12 | L49: =TRIM(UPPER(I49)) & "-" & TRIM(UPPER(J49) & "-" & TEXT(K49, "0")) -> A1-4-12
A50: A1 | B50: 11 | C50: 14 | D50: =TRIM(UPPER(A50)) & "-" & TRIM(UPPER(B50)) -> A1-11 | E50: =TRIM(UPPER(A50)) & "-" & TRIM(UPPER(B50) & "-" & TEXT(C50, "0")) -> A1-11-14 | G50: 46144 | I50: A1 | J50: 11 | K50: 14 | L50: =TRIM(UPPER(I50)) & "-" & TRIM(UPPER(J50) & "-" & TEXT(K50, "0")) -> A1-11-14
A51: A1 | B51: 3 | C51: 57 | D51: =TRIM(UPPER(A51)) & "-" & TRIM(UPPER(B51)) -> A1-3 | E51: =TRIM(UPPER(A51)) & "-" & TRIM(UPPER(B51) & "-" & TEXT(C51, "0")) -> A1-3-57 | G51: 46144 | I51: A1 | J51: 3 | K51: 57 | L51: =TRIM(UPPER(I51)) & "-" & TRIM(UPPER(J51) & "-" & TEXT(K51, "0")) -> A1-3-57
A52: H | B52: 12 | C52: 40 | D52: =TRIM(UPPER(A52)) & "-" & TRIM(UPPER(B52)) -> H-12 | E52: =TRIM(UPPER(A52)) & "-" & TRIM(UPPER(B52) & "-" & TEXT(C52, "0")) -> H-12-40 | F52: Janet dice que pagó (corte a tico) | G52: 46144 | I52: H | J52: 12 | K52: 40 | L52: =TRIM(UPPER(I52)) & "-" & TRIM(UPPER(J52) & "-" & TEXT(K52, "0")) -> H-12-40
A53: O | B53: 11 | C53: 8 | D53: =TRIM(UPPER(A53)) & "-" & TRIM(UPPER(B53)) -> O-11 | E53: =TRIM(UPPER(A53)) & "-" & TRIM(UPPER(B53) & "-" & TEXT(C53, "0")) -> O-11-8 | G53: 46144 | I53: O | J53: 11 | K53: 8 | L53: =TRIM(UPPER(I53)) & "-" & TRIM(UPPER(J53) & "-" & TEXT(K53, "0")) -> O-11-8
A54: Q | B54: 14 | C54: 12 | D54: =TRIM(UPPER(A54)) & "-" & TRIM(UPPER(B54)) -> Q-14 | E54: =TRIM(UPPER(A54)) & "-" & TRIM(UPPER(B54) & "-" & TEXT(C54, "0")) -> Q-14-12 | G54: 46144 | I54: Q | J54: 14 | K54: 12 | L54: =TRIM(UPPER(I54)) & "-" & TRIM(UPPER(J54) & "-" & TEXT(K54, "0")) -> Q-14-12
A55: [Tachado] | B55: [Tachado] | C55: [Tachado] | D55: =TRIM(UPPER(A55)) & "-" & TRIM(UPPER(B55)) -> [TACHADO]-[TACHADO] | E55: =TRIM(UPPER(A55)) & "-" & TRIM(UPPER(B55) & "-" & TEXT(C55, "0")) -> [TACHADO]-[TACHADO]-[Tachado] | G55: 46144 | I55: I | J55: 4 | K55: 0 | L55: =TRIM(UPPER(I55)) & "-" & TRIM(UPPER(J55) & "-" & TEXT(K55, "0")) -> I-4-0 | M55: yapeara
G56: 46144 | I56: D1 | J56: 4 | K56: 0 | L56: =TRIM(UPPER(I56)) & "-" & TRIM(UPPER(J56) & "-" & TEXT(K56, "0")) -> D1-4-0 | M56: yapeara
A57: H | B57: 19 | C57: 34 | D57: =TRIM(UPPER(A57)) & "-" & TRIM(UPPER(B57)) -> H-19 | E57: =TRIM(UPPER(A57)) & "-" & TRIM(UPPER(B57) & "-" & TEXT(C57, "0")) -> H-19-34 | G57: 46144 | I57: H | J57: 19 | K57: 34 | L57: =TRIM(UPPER(I57)) & "-" & TRIM(UPPER(J57) & "-" & TEXT(K57, "0")) -> H-19-34
A58: J | B58: 12 | C58: 10 | D58: =TRIM(UPPER(A58)) & "-" & TRIM(UPPER(B58)) -> J-12 | E58: =TRIM(UPPER(A58)) & "-" & TRIM(UPPER(B58) & "-" & TEXT(C58, "0")) -> J-12-10 | G58: 46144 | I58: J | J58: 12 | K58: 10 | L58: =TRIM(UPPER(I58)) & "-" & TRIM(UPPER(J58) & "-" & TEXT(K58, "0")) -> J-12-10
A59: J | B59: 11 | C59: 16 | D59: =TRIM(UPPER(A59)) & "-" & TRIM(UPPER(B59)) -> J-11 | E59: =TRIM(UPPER(A59)) & "-" & TRIM(UPPER(B59) & "-" & TEXT(C59, "0")) -> J-11-16 | G59: 46144 | I59: J | J59: 11 | K59: 16 | L59: =TRIM(UPPER(I59)) & "-" & TRIM(UPPER(J59) & "-" & TEXT(K59, "0")) -> J-11-16
A60: F1 | B60: 9 | C60: 8 | D60: =TRIM(UPPER(A60)) & "-" & TRIM(UPPER(B60)) -> F1-9 | E60: =TRIM(UPPER(A60)) & "-" & TRIM(UPPER(B60) & "-" & TEXT(C60, "0")) -> F1-9-8 | G60: 46144 | I60: F1 | J60: 9 | K60: 8 | L60: =TRIM(UPPER(I60)) & "-" & TRIM(UPPER(J60) & "-" & TEXT(K60, "0")) -> F1-9-8
A61: D1 | B61: 4 | C61: 11 | D61: =TRIM(UPPER(A61)) & "-" & TRIM(UPPER(B61)) -> D1-4 | E61: =TRIM(UPPER(A61)) & "-" & TRIM(UPPER(B61) & "-" & TEXT(C61, "0")) -> D1-4-11 | G61: 46144 | I61: D1 | J61: 4 | K61: 11 | L61: =TRIM(UPPER(I61)) & "-" & TRIM(UPPER(J61) & "-" & TEXT(K61, "0")) -> D1-4-11
A62: C | B62: 18 | C62: 37 | D62: =TRIM(UPPER(A62)) & "-" & TRIM(UPPER(B62)) -> C-18 | E62: =TRIM(UPPER(A62)) & "-" & TRIM(UPPER(B62) & "-" & TEXT(C62, "0")) -> C-18-37 | G62: 46144 | I62: C | J62: 18 | K62: 37 | L62: =TRIM(UPPER(I62)) & "-" & TRIM(UPPER(J62) & "-" & TEXT(K62, "0")) -> C-18-37
A63: G | B63: 12 | C63: 36 | D63: =TRIM(UPPER(A63)) & "-" & TRIM(UPPER(B63)) -> G-12 | E63: =TRIM(UPPER(A63)) & "-" & TRIM(UPPER(B63) & "-" & TEXT(C63, "0")) -> G-12-36 | F63: 2 meses consumo + 50 medidor | G63: 46144 | I63: G | J63: 12 | K63: 36 | L63: =TRIM(UPPER(I63)) & "-" & TRIM(UPPER(J63) & "-" & TEXT(K63, "0")) -> G-12-36
A64: C | B64: 42 | C64: 35 | D64: =TRIM(UPPER(A64)) & "-" & TRIM(UPPER(B64)) -> C-42 | E64: =TRIM(UPPER(A64)) & "-" & TRIM(UPPER(B64) & "-" & TEXT(C64, "0")) -> C-42-35 | G64: 46144 | I64: C | J64: 42 | K64: 35 | L64: =TRIM(UPPER(I64)) & "-" & TRIM(UPPER(J64) & "-" & TEXT(K64, "0")) -> C-42-35
A65: O | B65: 13 | C65: 22 | D65: =TRIM(UPPER(A65)) & "-" & TRIM(UPPER(B65)) -> O-13 | E65: =TRIM(UPPER(A65)) & "-" & TRIM(UPPER(B65) & "-" & TEXT(C65, "0")) -> O-13-22 | G65: 46144 | I65: O | J65: 13 | K65: 22 | L65: =TRIM(UPPER(I65)) & "-" & TRIM(UPPER(J65) & "-" & TEXT(K65, "0")) -> O-13-22 | M65: 2 meses consumo + 50 Medidor
A66: E1 | B66: 9 | C66: 27 | D66: =TRIM(UPPER(A66)) & "-" & TRIM(UPPER(B66)) -> E1-9 | E66: =TRIM(UPPER(A66)) & "-" & TRIM(UPPER(B66) & "-" & TEXT(C66, "0")) -> E1-9-27 | G66: 46144 | I66: E1 | J66: 9 | K66: 27 | L66: =TRIM(UPPER(I66)) & "-" & TRIM(UPPER(J66) & "-" & TEXT(K66, "0")) -> E1-9-27
A67: G | B67: 8 | C67: 31 | D67: =TRIM(UPPER(A67)) & "-" & TRIM(UPPER(B67)) -> G-8 | E67: =TRIM(UPPER(A67)) & "-" & TRIM(UPPER(B67) & "-" & TEXT(C67, "0")) -> G-8-31 | G67: 46144 | I67: G | J67: 8 | K67: 31 | L67: =TRIM(UPPER(I67)) & "-" & TRIM(UPPER(J67) & "-" & TEXT(K67, "0")) -> G-8-31
A68: C | B68: 24 | C68: 8 | D68: =TRIM(UPPER(A68)) & "-" & TRIM(UPPER(B68)) -> C-24 | E68: =TRIM(UPPER(A68)) & "-" & TRIM(UPPER(B68) & "-" & TEXT(C68, "0")) -> C-24-8 | G68: 46144 | I68: C | J68: 24 | K68: 8 | L68: =TRIM(UPPER(I68)) & "-" & TRIM(UPPER(J68) & "-" & TEXT(K68, "0")) -> C-24-8
A69: B | B69: 18 | C69: 18 | D69: =TRIM(UPPER(A69)) & "-" & TRIM(UPPER(B69)) -> B-18 | E69: =TRIM(UPPER(A69)) & "-" & TRIM(UPPER(B69) & "-" & TEXT(C69, "0")) -> B-18-18 | G69: 46144 | I69: B | J69: 18 | K69: 18 | L69: =TRIM(UPPER(I69)) & "-" & TRIM(UPPER(J69) & "-" & TEXT(K69, "0")) -> B-18-18
A70: K | B70: 9 | C70: 110 | D70: =TRIM(UPPER(A70)) & "-" & TRIM(UPPER(B70)) -> K-9 | E70: =TRIM(UPPER(A70)) & "-" & TRIM(UPPER(B70) & "-" & TEXT(C70, "0")) -> K-9-110 | G70: 46144 | I70: K | J70: 9 | K70: 110 | L70: =TRIM(UPPER(I70)) & "-" & TRIM(UPPER(J70) & "-" & TEXT(K70, "0")) -> K-9-110
A71: W | B71: 6 | C71: 8 | D71: =TRIM(UPPER(A71)) & "-" & TRIM(UPPER(B71)) -> W-6 | E71: =TRIM(UPPER(A71)) & "-" & TRIM(UPPER(B71) & "-" & TEXT(C71, "0")) -> W-6-8 | G71: 46144 | I71: W | J71: 6 | K71: 8 | L71: =TRIM(UPPER(I71)) & "-" & TRIM(UPPER(J71) & "-" & TEXT(K71, "0")) -> W-6-8
A72: P | B72: 14 | C72: 13 | D72: =TRIM(UPPER(A72)) & "-" & TRIM(UPPER(B72)) -> P-14 | E72: =TRIM(UPPER(A72)) & "-" & TRIM(UPPER(B72) & "-" & TEXT(C72, "0")) -> P-14-13 | G72: 46144 | I72: P | J72: 14 | K72: 13 | L72: =TRIM(UPPER(I72)) & "-" & TRIM(UPPER(J72) & "-" & TEXT(K72, "0")) -> P-14-13
A73: M | B73: 20 | C73: 28 | D73: =TRIM(UPPER(A73)) & "-" & TRIM(UPPER(B73)) -> M-20 | E73: =TRIM(UPPER(A73)) & "-" & TRIM(UPPER(B73) & "-" & TEXT(C73, "0")) -> M-20-28 | G73: 46144 | I73: M | J73: 20 | K73: 28 | L73: =TRIM(UPPER(I73)) & "-" & TRIM(UPPER(J73) & "-" & TEXT(K73, "0")) -> M-20-28
A74: V | B74: 5 | C74: 25 | D74: =TRIM(UPPER(A74)) & "-" & TRIM(UPPER(B74)) -> V-5 | E74: =TRIM(UPPER(A74)) & "-" & TRIM(UPPER(B74) & "-" & TEXT(C74, "0")) -> V-5-25 | G74: 46144 | I74: V | J74: 5 | K74: 25 | L74: =TRIM(UPPER(I74)) & "-" & TRIM(UPPER(J74) & "-" & TEXT(K74, "0")) -> V-5-25
A75: M | B75: 8 | C75: 16 | D75: =TRIM(UPPER(A75)) & "-" & TRIM(UPPER(B75)) -> M-8 | E75: =TRIM(UPPER(A75)) & "-" & TRIM(UPPER(B75) & "-" & TEXT(C75, "0")) -> M-8-16 | G75: 46144 | I75: M | J75: 8 | K75: 16 | L75: =TRIM(UPPER(I75)) & "-" & TRIM(UPPER(J75) & "-" & TEXT(K75, "0")) -> M-8-16
A76: G | B76: 16 | C76: 8 | D76: =TRIM(UPPER(A76)) & "-" & TRIM(UPPER(B76)) -> G-16 | E76: =TRIM(UPPER(A76)) & "-" & TRIM(UPPER(B76) & "-" & TEXT(C76, "0")) -> G-16-8 | G76: 46144 | I76: G | J76: 16 | K76: 8 | L76: =TRIM(UPPER(I76)) & "-" & TRIM(UPPER(J76) & "-" & TEXT(K76, "0")) -> G-16-8
A77: A1 | B77: 2 | C77: 38 | D77: =TRIM(UPPER(A77)) & "-" & TRIM(UPPER(B77)) -> A1-2 | E77: =TRIM(UPPER(A77)) & "-" & TRIM(UPPER(B77) & "-" & TEXT(C77, "0")) -> A1-2-38 | G77: 46144 | I77: A1 | J77: 2 | K77: 38 | L77: =TRIM(UPPER(I77)) & "-" & TRIM(UPPER(J77) & "-" & TEXT(K77, "0")) -> A1-2-38
A78: B | B78: 11 | C78: 69 | D78: =TRIM(UPPER(A78)) & "-" & TRIM(UPPER(B78)) -> B-11 | E78: =TRIM(UPPER(A78)) & "-" & TRIM(UPPER(B78) & "-" & TEXT(C78, "0")) -> B-11-69 | G78: 46144 | I78: B | J78: 11 | K78: 69 | L78: =TRIM(UPPER(I78)) & "-" & TRIM(UPPER(J78) & "-" & TEXT(K78, "0")) -> B-11-69
A79: K | B79: 1 | C79: 40 | D79: =TRIM(UPPER(A79)) & "-" & TRIM(UPPER(B79)) -> K-1 | E79: =TRIM(UPPER(A79)) & "-" & TRIM(UPPER(B79) & "-" & TEXT(C79, "0")) -> K-1-40 | F79: 23 + 75 medidor | G79: 46144 | I79: K | J79: 1 | K79: 40 | L79: =TRIM(UPPER(I79)) & "-" & TRIM(UPPER(J79) & "-" & TEXT(K79, "0")) -> K-1-40
A80: T | B80: 5 | C80: 8 | D80: =TRIM(UPPER(A80)) & "-" & TRIM(UPPER(B80)) -> T-5 | E80: =TRIM(UPPER(A80)) & "-" & TRIM(UPPER(B80) & "-" & TEXT(C80, "0")) -> T-5-8 | F80: Yo puse P5. Es T5 por montos | G80: 46144 | I80: T | J80: 5 | K80: 8 | L80: =TRIM(UPPER(I80)) & "-" & TRIM(UPPER(J80) & "-" & TEXT(K80, "0")) -> T-5-8
A81: T | B81: 14 | C81: 54 | D81: =TRIM(UPPER(A81)) & "-" & TRIM(UPPER(B81)) -> T-14 | E81: =TRIM(UPPER(A81)) & "-" & TRIM(UPPER(B81) & "-" & TEXT(C81, "0")) -> T-14-54 | G81: Antes de cobro | I81: T | J81: 14 | K81: 54 | L81: =TRIM(UPPER(I81)) & "-" & TRIM(UPPER(J81) & "-" & TEXT(K81, "0")) -> T-14-54 | M81: Antes de cobro
A82: F | B82: 6 | C82: 65 | D82: =TRIM(UPPER(A82)) & "-" & TRIM(UPPER(B82)) -> F-6 | E82: =TRIM(UPPER(A82)) & "-" & TRIM(UPPER(B82) & "-" & TEXT(C82, "0")) -> F-6-65 | G82: 46144 | I82: F | J82: 6 | K82: 65 | L82: =TRIM(UPPER(I82)) & "-" & TRIM(UPPER(J82) & "-" & TEXT(K82, "0")) -> F-6-65
A83: O | B83: 27B | C83: 9 | D83: =TRIM(UPPER(A83)) & "-" & TRIM(UPPER(B83)) -> O-27B | E83: =TRIM(UPPER(A83)) & "-" & TRIM(UPPER(B83) & "-" & TEXT(C83, "0")) -> O-27B-9 | G83: 46144 | I83: O | J83: 27B | K83: 9 | L83: =TRIM(UPPER(I83)) & "-" & TRIM(UPPER(J83) & "-" & TEXT(K83, "0")) -> O-27B-9
A84: K | B84: 8 | C84: 11 | D84: =TRIM(UPPER(A84)) & "-" & TRIM(UPPER(B84)) -> K-8 | E84: =TRIM(UPPER(A84)) & "-" & TRIM(UPPER(B84) & "-" & TEXT(C84, "0")) -> K-8-11 | G84: 46144 | I84: K | J84: 8 | K84: 11 | L84: =TRIM(UPPER(I84)) & "-" & TRIM(UPPER(J84) & "-" & TEXT(K84, "0")) -> K-8-11
A85: O | B85: 12 | C85: 10 | D85: =TRIM(UPPER(A85)) & "-" & TRIM(UPPER(B85)) -> O-12 | E85: =TRIM(UPPER(A85)) & "-" & TRIM(UPPER(B85) & "-" & TEXT(C85, "0")) -> O-12-10 | G85: 46144 | I85: O | J85: 12 | K85: 10 | L85: =TRIM(UPPER(I85)) & "-" & TRIM(UPPER(J85) & "-" & TEXT(K85, "0")) -> O-12-10
A86: M | B86: 3 | C86: 16 | D86: =TRIM(UPPER(A86)) & "-" & TRIM(UPPER(B86)) -> M-3 | E86: =TRIM(UPPER(A86)) & "-" & TRIM(UPPER(B86) & "-" & TEXT(C86, "0")) -> M-3-16 | G86: 46144 | I86: M | J86: 3 | K86: 16 | L86: =TRIM(UPPER(I86)) & "-" & TRIM(UPPER(J86) & "-" & TEXT(K86, "0")) -> M-3-16
A87: M | B87: 1 | C87: 27 | D87: =TRIM(UPPER(A87)) & "-" & TRIM(UPPER(B87)) -> M-1 | E87: =TRIM(UPPER(A87)) & "-" & TRIM(UPPER(B87) & "-" & TEXT(C87, "0")) -> M-1-27 | G87: 46144 | I87: M | J87: 1 | K87: 27 | L87: =TRIM(UPPER(I87)) & "-" & TRIM(UPPER(J87) & "-" & TEXT(K87, "0")) -> M-1-27
A88: O | B88: 4 | C88: 33 | D88: =TRIM(UPPER(A88)) & "-" & TRIM(UPPER(B88)) -> O-4 | E88: =TRIM(UPPER(A88)) & "-" & TRIM(UPPER(B88) & "-" & TEXT(C88, "0")) -> O-4-33 | G88: 46144 | I88: O | J88: 4 | K88: 33 | L88: =TRIM(UPPER(I88)) & "-" & TRIM(UPPER(J88) & "-" & TEXT(K88, "0")) -> O-4-33
A89: O | B89: 3 | C89: 13 | D89: =TRIM(UPPER(A89)) & "-" & TRIM(UPPER(B89)) -> O-3 | E89: =TRIM(UPPER(A89)) & "-" & TRIM(UPPER(B89) & "-" & TEXT(C89, "0")) -> O-3-13 | F89: Terminó convenio | G89: 46144 | I89: O | J89: 3 | K89: 13 | L89: =TRIM(UPPER(I89)) & "-" & TRIM(UPPER(J89) & "-" & TEXT(K89, "0")) -> O-3-13
A90: L | B90: 11 | C90: 37 | D90: =TRIM(UPPER(A90)) & "-" & TRIM(UPPER(B90)) -> L-11 | E90: =TRIM(UPPER(A90)) & "-" & TRIM(UPPER(B90) & "-" & TEXT(C90, "0")) -> L-11-37 | G90: 46144 | I90: L | J90: 11 | K90: 37 | L90: =TRIM(UPPER(I90)) & "-" & TRIM(UPPER(J90) & "-" & TEXT(K90, "0")) -> L-11-37 | M90: Termina convenio
A91: C1 | B91: 3 | C91: 16 | D91: =TRIM(UPPER(A91)) & "-" & TRIM(UPPER(B91)) -> C1-3 | E91: =TRIM(UPPER(A91)) & "-" & TRIM(UPPER(B91) & "-" & TEXT(C91, "0")) -> C1-3-16 | G91: 46144 | I91: C1 | J91: 3 | K91: 16 | L91: =TRIM(UPPER(I91)) & "-" & TRIM(UPPER(J91) & "-" & TEXT(K91, "0")) -> C1-3-16
A92: M | B92: 3 | C92: 16 | D92: =TRIM(UPPER(A92)) & "-" & TRIM(UPPER(B92)) -> M-3 | E92: =TRIM(UPPER(A92)) & "-" & TRIM(UPPER(B92) & "-" & TEXT(C92, "0")) -> M-3-16 | F92: Pago consumo 8 soles anterior | G92: 46144 | I92: M | J92: 3 | K92: 16 | L92: =TRIM(UPPER(I92)) & "-" & TRIM(UPPER(J92) & "-" & TEXT(K92, "0")) -> M-3-16
A93: E | B93: 11 | C93: 51 | D93: =TRIM(UPPER(A93)) & "-" & TRIM(UPPER(B93)) -> E-11 | E93: =TRIM(UPPER(A93)) & "-" & TRIM(UPPER(B93) & "-" & TEXT(C93, "0")) -> E-11-51 | F93: Pago consumo efectivo (14) preguntar Jaime | G93: 46144 | I93: E | J93: 11 | K93: 51 | L93: =TRIM(UPPER(I93)) & "-" & TRIM(UPPER(J93) & "-" & TEXT(K93, "0")) -> E-11-51 | M93: Efectivo Wag 8
A94: O | B94: 14 | C94: 13 | D94: =TRIM(UPPER(A94)) & "-" & TRIM(UPPER(B94)) -> O-14 | E94: =TRIM(UPPER(A94)) & "-" & TRIM(UPPER(B94) & "-" & TEXT(C94, "0")) -> O-14-13 | G94: 46144 | I94: O | J94: 14 | K94: 13 | L94: =TRIM(UPPER(I94)) & "-" & TRIM(UPPER(J94) & "-" & TEXT(K94, "0")) -> O-14-13 | M94: Efectivo Wag 14
A95: C | B95: 25 | C95: 44 | D95: =TRIM(UPPER(A95)) & "-" & TRIM(UPPER(B95)) -> C-25 | E95: =TRIM(UPPER(A95)) & "-" & TRIM(UPPER(B95) & "-" & TEXT(C95, "0")) -> C-25-44 | G95: 46144 | I95: C | J95: 25 | K95: 44 | L95: =TRIM(UPPER(I95)) & "-" & TRIM(UPPER(J95) & "-" & TEXT(K95, "0")) -> C-25-44
A96: P | B96: 2 | C96: 17 | D96: =TRIM(UPPER(A96)) & "-" & TRIM(UPPER(B96)) -> P-2 | E96: =TRIM(UPPER(A96)) & "-" & TRIM(UPPER(B96) & "-" & TEXT(C96, "0")) -> P-2-17 | G96: 46144 | I96: P | J96: 2 | K96: 17 | L96: =TRIM(UPPER(I96)) & "-" & TRIM(UPPER(J96) & "-" & TEXT(K96, "0")) -> P-2-17
A97: V | B97: 15 | C97: 11 | D97: =TRIM(UPPER(A97)) & "-" & TRIM(UPPER(B97)) -> V-15 | E97: =TRIM(UPPER(A97)) & "-" & TRIM(UPPER(B97) & "-" & TEXT(C97, "0")) -> V-15-11 | G97: 46144 | I97: V | J97: 15 | K97: 11 | L97: =TRIM(UPPER(I97)) & "-" & TRIM(UPPER(J97) & "-" & TEXT(K97, "0")) -> V-15-11
A98: C | B98: 19 | C98: 31 | D98: =TRIM(UPPER(A98)) & "-" & TRIM(UPPER(B98)) -> C-19 | E98: =TRIM(UPPER(A98)) & "-" & TRIM(UPPER(B98) & "-" & TEXT(C98, "0")) -> C-19-31 | G98: 46144 | I98: C | J98: 19 | K98: 31 | L98: =TRIM(UPPER(I98)) & "-" & TRIM(UPPER(J98) & "-" & TEXT(K98, "0")) -> C-19-31
A99: G | B99: 18 | C99: 70 | D99: =TRIM(UPPER(A99)) & "-" & TRIM(UPPER(B99)) -> G-18 | E99: =TRIM(UPPER(A99)) & "-" & TRIM(UPPER(B99) & "-" & TEXT(C99, "0")) -> G-18-70 | F99: 20+50 | G99: 46144 | I99: G | J99: 18 | K99: 70 | L99: =TRIM(UPPER(I99)) & "-" & TRIM(UPPER(J99) & "-" & TEXT(K99, "0")) -> G-18-70 | M99: Consumo 20 + Convenio 50
A100: E | B100: 8 | C100: 10 | D100: =TRIM(UPPER(A100)) & "-" & TRIM(UPPER(B100)) -> E-8 | E100: =TRIM(UPPER(A100)) & "-" & TRIM(UPPER(B100) & "-" & TEXT(C100, "0")) -> E-8-10 | G100: 46144 | I100: E | J100: 8 | K100: 10 | L100: =TRIM(UPPER(I100)) & "-" & TRIM(UPPER(J100) & "-" & TEXT(K100, "0")) -> E-8-10
...

Sheet Cobro medidores
A1: Usuario | B1: MZ | C1: LT | D1: Marcacion Actual | E1: Deuda | F1: Diciembre-2025 | G1: Enero-2025 | H1: Febrero-2026 | I1: Marzo-2026 | J1: Abril-2026 | K1: Mayo-2026 | N1: Saldo | O1: Contador | P1: Comentario | Q1: Llave1 | R1: Llave2
B2: A | C2: 1 | D2: 2630 | E2: 100 | I2: 0 | J2: 100 | K2: =IFERROR(__xludf.DUMMYFUNCTION("IFERROR( SUM( FILTER( Cobranza!$O:$O, (Cobranza!$AG:$AG & """" = P2 & """") * ((Cobranza!$W:$W = ""C"") + (Cobranza!$W:$W = ""c"")) ) ), 0 )"),75) -> 75 | N2: =E2-(H2+K2+I2+L2) -> 25 | O2: 1 | Q2: =TRIM(UPPER(B2)) -> A | R2: =TRIM(UPPER(B2)) & "-" & TRIM(UPPER(C2)) -> A-1
B3: A | C3: 4 | D3: 1735 | E3: 100 | I3: 25 | K3: =IFERROR(__xludf.DUMMYFUNCTION("IFERROR( SUM( FILTER( Cobranza!$O:$O, (Cobranza!$AG:$AG & """" = P3 & """") * ((Cobranza!$W:$W = ""C"") + (Cobranza!$W:$W = ""c"")) ) ), 0 )"),0) -> 0 | N3: =E3-(H3+K3+I3+L3) -> 75 | O3: 1 | Q3: =TRIM(UPPER(B3)) -> A | R3: =TRIM(UPPER(B3)) & "-" & TRIM(UPPER(C3)) -> A-4
B4: A | C4: 5 | D4: 3441 | E4: 100 | I4: 25 | J4: 25 | K4: =IFERROR(__xludf.DUMMYFUNCTION("IFERROR( SUM( FILTER( Cobranza!$O:$O, (Cobranza!$AG:$AG & """" = P4 & """") * ((Cobranza!$W:$W = ""C"") + (Cobranza!$W:$W = ""c"")) ) ), 0 )"),25) -> 25 | N4: =E4-(H4+K4+I4+L4) -> 50 | O4: 1 | Q4: =TRIM(UPPER(B4)) -> A | R4: =TRIM(UPPER(B4)) & "-" & TRIM(UPPER(C4)) -> A-5
A5: ESTEBAN REYES | B5: A | C5: 6 | E5: 100 | I5: 25 | J5: 25 | K5: =IFERROR(__xludf.DUMMYFUNCTION("IFERROR( SUM( FILTER( Cobranza!$O:$O, (Cobranza!$AG:$AG & """" = P5 & """") * ((Cobranza!$W:$W = ""C"") + (Cobranza!$W:$W = ""c"")) ) ), 0 )"),25) -> 25 | N5: =E5-(H5+K5+I5+L5) -> 50 | O5: 1 | Q5: =TRIM(UPPER(B5)) -> A | R5: =TRIM(UPPER(B5)) & "-" & TRIM(UPPER(C5)) -> A-6
B6: A | C6: 8 | D6: 6395 | E6: 100 | I6: 0 | J6: 25 | K6: =IFERROR(__xludf.DUMMYFUNCTION("IFERROR( SUM( FILTER( Cobranza!$O:$O, (Cobranza!$AG:$AG & """" = P6 & """") * ((Cobranza!$W:$W = ""C"") + (Cobranza!$W:$W = ""c"")) ) ), 0 )"),0) -> 0 | N6: =E6-(H6+K6+I6+L6) -> 100 | O6: 1 | Q6: =TRIM(UPPER(B6)) -> A | R6: =TRIM(UPPER(B6)) & "-" & TRIM(UPPER(C6)) -> A-8
B7: B | C7: 1 | E7: 100 | I7: 100 | K7: =IFERROR(__xludf.DUMMYFUNCTION("IFERROR( SUM( FILTER( Cobranza!$O:$O, (Cobranza!$AG:$AG & """" = P7 & """") * ((Cobranza!$W:$W = ""C"") + (Cobranza!$W:$W = ""c"")) ) ), 0 )"),0) -> 0 | N7: =E7-(H7+K7+I7+L7) -> 0 | Q7: =TRIM(UPPER(B7)) -> B | R7: =TRIM(UPPER(B7)) & "-" & TRIM(UPPER(C7)) -> B-1
B8: B | C8: 2 | D8: 2299 | E8: 100 | I8: 25 | J8: 25 | K8: =IFERROR(__xludf.DUMMYFUNCTION("IFERROR( SUM( FILTER( Cobranza!$O:$O, (Cobranza!$AG:$AG & """" = P8 & """") * ((Cobranza!$W:$W = ""C"") + (Cobranza!$W:$W = ""c"")) ) ), 0 )"),25) -> 25 | N8: =E8-(H8+K8+I8+L8) -> 50 | O8: 1 | Q8: =TRIM(UPPER(B8)) -> B | R8: =TRIM(UPPER(B8)) & "-" & TRIM(UPPER(C8)) -> B-2
B9: B | C9: 5 | E9: 100 | I9: 25 | K9: =IFERROR(__xludf.DUMMYFUNCTION("IFERROR( SUM( FILTER( Cobranza!$O:$O, (Cobranza!$AG:$AG & """" = P9 & """") * ((Cobranza!$W:$W = ""C"") + (Cobranza!$W:$W = ""c"")) ) ), 0 )"),25) -> 25 | N9: =E9-(H9+K9+I9+L9) -> 50 | O9: 1 | Q9: =TRIM(UPPER(B9)) -> B | R9: =TRIM(UPPER(B9)) & "-" & TRIM(UPPER(C9)) -> B-5
B10: B | C10: 6 | E10: 100 | I10: 25 | J10: 25 | K10: =IFERROR(__xludf.DUMMYFUNCTION("IFERROR( SUM( FILTER( Cobranza!$O:$O, (Cobranza!$AG:$AG & """" = P10 & """") * ((Cobranza!$W:$W = ""C"") + (Cobranza!$W:$W = ""c"")) ) ), 0 )"),25) -> 25 | N10: =E10-(H10+K10+I10+L10) -> 50 | O10: 1 | Q10: =TRIM(UPPER(B10)) -> B | R10: =TRIM(UPPER(B10)) & "-" & TRIM(UPPER(C10)) -> B-6
B11: B | C11: 7 | E11: 100 | I11: 25 | K11: =IFERROR(__xludf.DUMMYFUNCTION("IFERROR( SUM( FILTER( Cobranza!$O:$O, (Cobranza!$AG:$AG & """" = P11 & """") * ((Cobranza!$W:$W = ""C"") + (Cobranza!$W:$W = ""c"")) ) ), 0 )"),25) -> 25 | N11: =E11-(H11+K11+I11+L11) -> 50 | O11: 1 | Q11: =TRIM(UPPER(B11)) -> B | R11: =TRIM(UPPER(B11)) & "-" & TRIM(UPPER(C11)) -> B-7
B12: B | C12: 8 | E12: 100 | I12: 0 | J12: 25 | K12: =IFERROR(__xludf.DUMMYFUNCTION("IFERROR( SUM( FILTER( Cobranza!$O:$O, (Cobranza!$AG:$AG & """" = P12 & """") * ((Cobranza!$W:$W = ""C"") + (Cobranza!$W:$W = ""c"")) ) ), 0 )"),0) -> 0 | N12: =E12-(H12+K12+I12+L12) -> 100 | O12: 1 | Q12: =TRIM(UPPER(B12)) -> B | R12: =TRIM(UPPER(B12)) & "-" & TRIM(UPPER(C12)) -> B-8
B13: B | C13: 11 | E13: 100 | I13: 25 | K13: =IFERROR(__xludf.DUMMYFUNCTION("IFERROR( SUM( FILTER( Cobranza!$O:$O, (Cobranza!$AG:$AG & """" = P13 & """") * ((Cobranza!$W:$W = ""C"") + (Cobranza!$W:$W = ""c"")) ) ), 0 )"),25) -> 25 | N13: =E13-(H13+K13+I13+L13) -> 50 | O13: 1 | Q13: =TRIM(UPPER(B13)) -> B | R13: =TRIM(UPPER(B13)) & "-" & TRIM(UPPER(C13)) -> B-11
B14: B | C14: 12 | E14: 100 | H14: 59 | I14: 41 | K14: =IFERROR(__xludf.DUMMYFUNCTION("IFERROR( SUM( FILTER( Cobranza!$O:$O, (Cobranza!$AG:$AG & """" = P14 & """") * ((Cobranza!$W:$W = ""C"") + (Cobranza!$W:$W = ""c"")) ) ), 0 )"),0) -> 0 | N14: =E14-(H14+K14+I14+L14) -> 0 | O14: 1 | P14: ADELAN/EFEC | Q14: =TRIM(UPPER(B14)) -> B | R14: =TRIM(UPPER(B14)) & "-" & TRIM(UPPER(C14)) -> B-12
B15: C | C15: 1 | D15: 2119 | E15: 100 | I15: 25 | K15: =IFERROR(__xludf.DUMMYFUNCTION("IFERROR( SUM( FILTER( Cobranza!$O:$O, (Cobranza!$AG:$AG & """" = P15 & """") * ((Cobranza!$W:$W = ""C"") + (Cobranza!$W:$W = ""c"")) ) ), 0 )"),25) -> 25 | N15: =E15-(H15+K15+I15+L15) -> 50 | O15: 1 | Q15: =TRIM(UPPER(B15)) -> C | R15: =TRIM(UPPER(B15)) & "-" & TRIM(UPPER(C15)) -> C-1
B16: C | C16: 2 | D16: 817 | E16: 100 | I16: 25 | J16: 25 | K16: =IFERROR(__xludf.DUMMYFUNCTION("IFERROR( SUM( FILTER( Cobranza!$O:$O, (Cobranza!$AG:$AG & """" = P16 & """") * ((Cobranza!$W:$W = ""C"") + (Cobranza!$W:$W = ""c"")) ) ), 0 )"),25) -> 25 | N16: =E16-(H16+K16+I16+L16) -> 50 | O16: 1 | Q16: =TRIM(UPPER(B16)) -> C | R16: =TRIM(UPPER(B16)) & "-" & TRIM(UPPER(C16)) -> C-2
B17: C | C17: 4 | D17: 3391 | E17: 100 | I17: 25 | J17: 25 | K17: =IFERROR(__xludf.DUMMYFUNCTION("IFERROR( SUM( FILTER( Cobranza!$O:$O, (Cobranza!$AG:$AG & """" = P17 & """") * ((Cobranza!$W:$W = ""C"") + (Cobranza!$W:$W = ""c"")) ) ), 0 )"),25) -> 25 | N17: =E17-(H17+K17+I17+L17) -> 50 | O17: 1 | Q17: =TRIM(UPPER(B17)) -> C | R17: =TRIM(UPPER(B17)) & "-" & TRIM(UPPER(C17)) -> C-4
B18: C | C18: 5 | D18: 4179 | E18: 100 | I18: 25 | J18: 25 | K18: =IFERROR(__xludf.DUMMYFUNCTION("IFERROR( SUM( FILTER( Cobranza!$O:$O, (Cobranza!$AG:$AG & """" = P18 & """") * ((Cobranza!$W:$W = ""C"") + (Cobranza!$W:$W = ""c"")) ) ), 0 )"),25) -> 25 | N18: =E18-(H18+K18+I18+L18) -> 50 | O18: 1 | Q18: =TRIM(UPPER(B18)) -> C | R18: =TRIM(UPPER(B18)) & "-" & TRIM(UPPER(C18)) -> C-5
B19: C | C19: 7 | D19: 2596 | E19: 100 | I19: 25 | J19: 25 | K19: =IFERROR(__xludf.DUMMYFUNCTION("IFERROR( SUM( FILTER( Cobranza!$O:$O, (Cobranza!$AG:$AG & """" = P19 & """") * ((Cobranza!$W:$W = ""C"") + (Cobranza!$W:$W = ""c"")) ) ), 0 )"),0) -> 0 | N19: =E19-(H19+K19+I19+L19) -> 75 | O19: 1 | Q19: =TRIM(UPPER(B19)) -> C | R19: =TRIM(UPPER(B19)) & "-" & TRIM(UPPER(C19)) -> C-7
B20: C | C20: 13 | E20: 100 | I20: 25 | J20: 25 | K20: =IFERROR(__xludf.DUMMYFUNCTION("IFERROR( SUM( FILTER( Cobranza!$O:$O, (Cobranza!$AG:$AG & """" = P20 & """") * ((Cobranza!$W:$W = ""C"") + (Cobranza!$W:$W = ""c"")) ) ), 0 )"),25) -> 25 | N20: =E20-(H20+K20+I20+L20) -> 50 | O20: 1 | Q20: =TRIM(UPPER(B20)) -> C | R20: =TRIM(UPPER(B20)) & "-" & TRIM(UPPER(C20)) -> C-13
B21: C | C21: 14 | E21: 100 | I21: 25 | K21: =IFERROR(__xludf.DUMMYFUNCTION("IFERROR( SUM( FILTER( Cobranza!$O:$O, (Cobranza!$AG:$AG & """" = P21 & """") * ((Cobranza!$W:$W = ""C"") + (Cobranza!$W:$W = ""c"")) ) ), 0 )"),33) -> 33 | N21: =E21-(H21+K21+I21+L21) -> 42 | O21: 1 | Q21: =TRIM(UPPER(B21)) -> C | R21: =TRIM(UPPER(B21)) & "-" & TRIM(UPPER(C21)) -> C-14
A22: MARTHA MASIA | B22: C | C22: 16 | E22: 100 | I22: 25 | K22: =IFERROR(__xludf.DUMMYFUNCTION("IFERROR( SUM( FILTER( Cobranza!$O:$O, (Cobranza!$AG:$AG & """" = P22 & """") * ((Cobranza!$W:$W = ""C"") + (Cobranza!$W:$W = ""c"")) ) ), 0 )"),25) -> 25 | N22: =E22-(H22+K22+I22+L22) -> 50 | O22: 1 | Q22: =TRIM(UPPER(B22)) -> C | R22: =TRIM(UPPER(B22)) & "-" & TRIM(UPPER(C22)) -> C-16
B23: C | C23: 18 | D23: 426 | E23: 100 | I23: 25 | J23: 25 | K23: =IFERROR(__xludf.DUMMYFUNCTION("IFERROR( SUM( FILTER( Cobranza!$O:$O, (Cobranza!$AG:$AG & """" = P23 & """") * ((Cobranza!$W:$W = ""C"") + (Cobranza!$W:$W = ""c"")) ) ), 0 )"),25) -> 25 | N23: =E23-(H23+K23+I23+L23) -> 50 | O23: 1 | Q23: =TRIM(UPPER(B23)) -> C | R23: =TRIM(UPPER(B23)) & "-" & TRIM(UPPER(C23)) -> C-18
B24: C | C24: 19 | D24: 3737 | E24: 100 | I24: 50 | J24: 47 | K24: =IFERROR(__xludf.DUMMYFUNCTION("IFERROR( SUM( FILTER( Cobranza!$O:$O, (Cobranza!$AG:$AG & """" = P24 & """") * ((Cobranza!$W:$W = ""C"") + (Cobranza!$W:$W = ""c"")) ) ), 0 )"),3) -> 3 | N24: =E24-(H24+K24+I24+L24) -> 47 | O24: 1 | Q24: =TRIM(UPPER(B24)) -> C | R24: =TRIM(UPPER(B24)) & "-" & TRIM(UPPER(C24)) -> C-19
B25: C | C25: 20 | E25: 100 | H25: 25 | I25: 15 | J25: 25 | K25: =IFERROR(__xludf.DUMMYFUNCTION("IFERROR( SUM( FILTER( Cobranza!$O:$O, (Cobranza!$AG:$AG & """" = P25 & """") * ((Cobranza!$W:$W = ""C"") + (Cobranza!$W:$W = ""c"")) ) ), 0 )"),25) -> 25 | N25: =E25-(H25+K25+I25+L25) -> 35 | O25: 1 | P25: ADELAN/EFEC | Q25: =TRIM(UPPER(B25)) -> C | R25: =TRIM(UPPER(B25)) & "-" & TRIM(UPPER(C25)) -> C-20
B26: C | C26: 28 | D26: 5610 | E26: 100 | H26: 100 | I26: 0 | K26: =IFERROR(__xludf.DUMMYFUNCTION("IFERROR( SUM( FILTER( Cobranza!$O:$O, (Cobranza!$AG:$AG & """" = P26 & """") * ((Cobranza!$W:$W = ""C"") + (Cobranza!$W:$W = ""c"")) ) ), 0 )"),0) -> 0 | N26: =E26-(H26+K26+I26+L26) -> 0 | O26: 1 | P26: YAPE | Q26: =TRIM(UPPER(B26)) -> C | R26: =TRIM(UPPER(B26)) & "-" & TRIM(UPPER(C26)) -> C-28
B27: C | C27: 25 | D27: 3966 | E27: 100 | I27: 25 | J27: 15 | K27: =IFERROR(__xludf.DUMMYFUNCTION("IFERROR( SUM( FILTER( Cobranza!$O:$O, (Cobranza!$AG:$AG & """" = P27 & """") * ((Cobranza!$W:$W = ""C"") + (Cobranza!$W:$W = ""c"")) ) ), 0 )"),25) -> 25 | N27: =E27-(H27+K27+I27+L27) -> 50 | O27: 1 | Q27: =TRIM(UPPER(B27)) -> C | R27: =TRIM(UPPER(B27)) & "-" & TRIM(UPPER(C27)) -> C-25
B28: C | C28: 32 | D28: 1678 | E28: 100 | I28: 25 | J28: 25 | K28: =IFERROR(__xludf.DUMMYFUNCTION("IFERROR( SUM( FILTER( Cobranza!$O:$O, (Cobranza!$AG:$AG & """" = P28 & """") * ((Cobranza!$W:$W = ""C"") + (Cobranza!$W:$W = ""c"")) ) ), 0 )"),25) -> 25 | N28: =E28-(H28+K28+I28+L28) -> 50 | O28: 1 | Q28: =TRIM(UPPER(B28)) -> C | R28: =TRIM(UPPER(B28)) & "-" & TRIM(UPPER(C28)) -> C-32
B29: C | C29: 24 | E29: 100 | H29: 100 | I29: 0 | K29: =IFERROR(__xludf.DUMMYFUNCTION("IFERROR( SUM( FILTER( Cobranza!$O:$O, (Cobranza!$AG:$AG & """" = P29 & """") * ((Cobranza!$W:$W = ""C"") + (Cobranza!$W:$W = ""c"")) ) ), 0 )"),0) -> 0 | N29: =E29-(H29+K29+I29+L29) -> 0 | O29: 1 | Q29: =TRIM(UPPER(B29)) -> C | R29: =TRIM(UPPER(B29)) & "-" & TRIM(UPPER(C29)) -> C-24
B30: D | C30: 1 | E30: 100 | I30: 0 | J30: 25 | K30: =IFERROR(__xludf.DUMMYFUNCTION("IFERROR( SUM( FILTER( Cobranza!$O:$O, (Cobranza!$AG:$AG & """" = P30 & """") * ((Cobranza!$W:$W = ""C"") + (Cobranza!$W:$W = ""c"")) ) ), 0 )"),25) -> 25 | N30: =E30-(H30+K30+I30+L30) -> 75 | O30: 1 | Q30: =TRIM(UPPER(B30)) -> D | R30: =TRIM(UPPER(B30)) & "-" & TRIM(UPPER(C30)) -> D-1
B31: D | C31: 3 | D31: 1377 | E31: 100 | I31: 25 | J31: 25 | K31: =IFERROR(__xludf.DUMMYFUNCTION("IFERROR( SUM( FILTER( Cobranza!$O:$O, (Cobranza!$AG:$AG & """" = P31 & """") * ((Cobranza!$W:$W = ""C"") + (Cobranza!$W:$W = ""c"")) ) ), 0 )"),25) -> 25 | N31: =E31-(H31+K31+I31+L31) -> 50 | O31: 1 | Q31: =TRIM(UPPER(B31)) -> D | R31: =TRIM(UPPER(B31)) & "-" & TRIM(UPPER(C31)) -> D-3
B32: D | C32: 6 | E32: 100 | I32: 25 | J32: 25 | K32: =IFERROR(__xludf.DUMMYFUNCTION("IFERROR( SUM( FILTER( Cobranza!$O:$O, (Cobranza!$AG:$AG & """" = P32 & """") * ((Cobranza!$W:$W = ""C"") + (Cobranza!$W:$W = ""c"")) ) ), 0 )"),25) -> 25 | N32: =E32-(H32+K32+I32+L32) -> 50 | O32: 1 | Q32: =TRIM(UPPER(B32)) -> D | R32: =TRIM(UPPER(B32)) & "-" & TRIM(UPPER(C32)) -> D-6
B33: D | C33: 19 | E33: 100 | I33: 25 | J33: 25 | K33: =IFERROR(__xludf.DUMMYFUNCTION("IFERROR( SUM( FILTER( Cobranza!$O:$O, (Cobranza!$AG:$AG & """" = P33 & """") * ((Cobranza!$W:$W = ""C"") + (Cobranza!$W:$W = ""c"")) ) ), 0 )"),25) -> 25 | N33: =E33-(H33+K33+I33+L33) -> 50 | O33: 1 | Q33: =TRIM(UPPER(B33)) -> D | R33: =TRIM(UPPER(B33)) & "-" & TRIM(UPPER(C33)) -> D-19
B34: D | C34: 8 | D34: 1790 | E34: 100 | I34: 0 | J34: 25 | K34: =IFERROR(__xludf.DUMMYFUNCTION("IFERROR( SUM( FILTER( Cobranza!$O:$O, (Cobranza!$AG:$AG & """" = P34 & """") * ((Cobranza!$W:$W = ""C"") + (Cobranza!$W:$W = ""c"")) ) ), 0 )"),0) -> 0 | N34: =E34-(H34+K34+I34+L34) -> 100 | O34: 1 | Q34: =TRIM(UPPER(B34)) -> D | R34: =TRIM(UPPER(B34)) & "-" & TRIM(UPPER(C34)) -> D-8
B35: D | C35: 16 | D35: 1651 | E35: 100 | I35: 25 | K35: =IFERROR(__xludf.DUMMYFUNCTION("IFERROR( SUM( FILTER( Cobranza!$O:$O, (Cobranza!$AG:$AG & """" = P35 & """") * ((Cobranza!$W:$W = ""C"") + (Cobranza!$W:$W = ""c"")) ) ), 0 )"),25) -> 25 | N35: =E35-(H35+K35+I35+L35) -> 50 | O35: 1 | Q35: =TRIM(UPPER(B35)) -> D | R35: =TRIM(UPPER(B35)) & "-" & TRIM(UPPER(C35)) -> D-16
B36: E | C36: 2 | D36: 3282 | E36: 100 | I36: 25 | J36: 25 | K36: =IFERROR(__xludf.DUMMYFUNCTION("IFERROR( SUM( FILTER( Cobranza!$O:$O, (Cobranza!$AG:$AG & """" = P36 & """") * ((Cobranza!$W:$W = ""C"") + (Cobranza!$W:$W = ""c"")) ) ), 0 )"),25) -> 25 | N36: =E36-(H36+K36+I36+L36) -> 50 | O36: 1 | Q36: =TRIM(UPPER(B36)) -> E | R36: =TRIM(UPPER(B36)) & "-" & TRIM(UPPER(C36)) -> E-2
B37: E | C37: 7 | D37: 1902 | E37: 100 | H37: 100 | I37: 0 | K37: =IFERROR(__xludf.DUMMYFUNCTION("IFERROR( SUM( FILTER( Cobranza!$O:$O, (Cobranza!$AG:$AG & """" = P37 & """") * ((Cobranza!$W:$W = ""C"") + (Cobranza!$W:$W = ""c"")) ) ), 0 )"),0) -> 0 | N37: =E37-(H37+K37+I37+L37) -> 0 | O37: 1 | Q37: =TRIM(UPPER(B37)) -> E | R37: =TRIM(UPPER(B37)) & "-" & TRIM(UPPER(C37)) -> E-7
B38: E | C38: 9 | D38: 3667 | E38: 100 | I38: 0 | J38: 100 | K38: =IFERROR(__xludf.DUMMYFUNCTION("IFERROR( SUM( FILTER( Cobranza!$O:$O, (Cobranza!$AG:$AG & """" = P38 & """") * ((Cobranza!$W:$W = ""C"") + (Cobranza!$W:$W = ""c"")) ) ), 0 )"),0) -> 0 | N38: =E38-(H38+K38+I38+L38) -> 100 | O38: 1 | Q38: =TRIM(UPPER(B38)) -> E | R38: =TRIM(UPPER(B38)) & "-" & TRIM(UPPER(C38)) -> E-9
B39: E | C39: 12 | D39: 3705 | E39: 100 | I39: 24 | J39: 25 | K39: =IFERROR(__xludf.DUMMYFUNCTION("IFERROR( SUM( FILTER( Cobranza!$O:$O, (Cobranza!$AG:$AG & """" = P39 & """") * ((Cobranza!$W:$W = ""C"") + (Cobranza!$W:$W = ""c"")) ) ), 0 )"),25) -> 25 | N39: =E39-(H39+K39+I39+L39) -> 51 | O39: 1 | Q39: =TRIM(UPPER(B39)) -> E | R39: =TRIM(UPPER(B39)) & "-" & TRIM(UPPER(C39)) -> E-12
B40: F | C40: 6 | D40: 3222 | E40: 100 | I40: 25 | K40: =IFERROR(__xludf.DUMMYFUNCTION("IFERROR( SUM( FILTER( Cobranza!$O:$O, (Cobranza!$AG:$AG & """" = P40 & """") * ((Cobranza!$W:$W = ""C"") + (Cobranza!$W:$W = ""c"")) ) ), 0 )"),25) -> 25 | N40: =E40-(H40+K40+I40+L40) -> 50 | O40: 1 | Q40: =TRIM(UPPER(B40)) -> F | R40: =TRIM(UPPER(B40)) & "-" & TRIM(UPPER(C40)) -> F-6
B41: F | C41: 7 | D41: 7360 | E41: 100 | I41: 25 | J41: 25 | K41: =IFERROR(__xludf.DUMMYFUNCTION("IFERROR( SUM( FILTER( Cobranza!$O:$O, (Cobranza!$AG:$AG & """" = P41 & """") * ((Cobranza!$W:$W = ""C"") + (Cobranza!$W:$W = ""c"")) ) ), 0 )"),25) -> 25 | N41: =E41-(H41+K41+I41+L41) -> 50 | O41: 1 | Q41: =TRIM(UPPER(B41)) -> F | R41: =TRIM(UPPER(B41)) & "-" & TRIM(UPPER(C41)) -> F-7
B42: F | C42: 8 | E42: 100 | I42: 25 | J42: 25 | K42: =IFERROR(__xludf.DUMMYFUNCTION("IFERROR( SUM( FILTER( Cobranza!$O:$O, (Cobranza!$AG:$AG & """" = P42 & """") * ((Cobranza!$W:$W = ""C"") + (Cobranza!$W:$W = ""c"")) ) ), 0 )"),25) -> 25 | N42: =E42-(H42+K42+I42+L42) -> 50 | O42: 1 | Q42: =TRIM(UPPER(B42)) -> F | R42: =TRIM(UPPER(B42)) & "-" & TRIM(UPPER(C42)) -> F-8
B43: F | C43: 9 | D43: 4150 | E43: 100 | I43: 0 | J43: 25 | K43: =IFERROR(__xludf.DUMMYFUNCTION("IFERROR( SUM( FILTER( Cobranza!$O:$O, (Cobranza!$AG:$AG & """" = P43 & """") * ((Cobranza!$W:$W = ""C"") + (Cobranza!$W:$W = ""c"")) ) ), 0 )"),25) -> 25 | N43: =E43-(H43+K43+I43+L43) -> 75 | O43: 1 | Q43: =TRIM(UPPER(B43)) -> F | R43: =TRIM(UPPER(B43)) & "-" & TRIM(UPPER(C43)) -> F-9
B44: F | C44: 12 | E44: 100 | I44: 25 | J44: 25 | K44: =IFERROR(__xludf.DUMMYFUNCTION("IFERROR( SUM( FILTER( Cobranza!$O:$O, (Cobranza!$AG:$AG & """" = P44 & """") * ((Cobranza!$W:$W = ""C"") + (Cobranza!$W:$W = ""c"")) ) ), 0 )"),0) -> 0 | N44: =E44-(H44+K44+I44+L44) -> 75 | O44: 1 | Q44: =TRIM(UPPER(B44)) -> F | R44: =TRIM(UPPER(B44)) & "-" & TRIM(UPPER(C44)) -> F-12
B45: F | C45: 14 | D45: 1464 | E45: 100 | I45: 0 | J45: 50 | K45: =IFERROR(__xludf.DUMMYFUNCTION("IFERROR( SUM( FILTER( Cobranza!$O:$O, (Cobranza!$AG:$AG & """" = P45 & """") * ((Cobranza!$W:$W = ""C"") + (Cobranza!$W:$W = ""c"")) ) ), 0 )"),25) -> 25 | N45: =E45-(H45+K45+I45+L45) -> 75 | O45: 1 | Q45: =TRIM(UPPER(B45)) -> F | R45: =TRIM(UPPER(B45)) & "-" & TRIM(UPPER(C45)) -> F-14
B46: F | C46: 3B | D46: 2971 | E46: 100 | I46: 25 | J46: 25 | K46: =IFERROR(__xludf.DUMMYFUNCTION("IFERROR( SUM( FILTER( Cobranza!$O:$O, (Cobranza!$AG:$AG & """" = P46 & """") * ((Cobranza!$W:$W = ""C"") + (Cobranza!$W:$W = ""c"")) ) ), 0 )"),25) -> 25 | N46: =E46-(H46+K46+I46+L46) -> 50 | O46: 1 | Q46: =TRIM(UPPER(B46)) -> F | R46: =TRIM(UPPER(B46)) & "-" & TRIM(UPPER(C46)) -> F-3B
B47: F1 | C47: 8 | E47: 100 | I47: 25 | J47: 25 | K47: =IFERROR(__xludf.DUMMYFUNCTION("IFERROR( SUM( FILTER( Cobranza!$O:$O, (Cobranza!$AG:$AG & """" = P47 & """") * ((Cobranza!$W:$W = ""C"") + (Cobranza!$W:$W = ""c"")) ) ), 0 )"),25) -> 25 | N47: =E47-(H47+K47+I47+L47) -> 50 | O47: 1 | Q47: =TRIM(UPPER(B47)) -> F1 | R47: =TRIM(UPPER(B47)) & "-" & TRIM(UPPER(C47)) -> F1-8
B48: G | C48: 2 | D48: 3922 | E48: 100 | I48: 25 | J48: 25 | K48: =IFERROR(__xludf.DUMMYFUNCTION("IFERROR( SUM( FILTER( Cobranza!$O:$O, (Cobranza!$AG:$AG & """" = P48 & """") * ((Cobranza!$W:$W = ""C"") + (Cobranza!$W:$W = ""c"")) ) ), 0 )"),25) -> 25 | N48: =E48-(H48+K48+I48+L48) -> 50 | O48: 1 | Q48: =TRIM(UPPER(B48)) -> G | R48: =TRIM(UPPER(B48)) & "-" & TRIM(UPPER(C48)) -> G-2
B49: G | C49: 3 | D49: 2757 | E49: 100 | I49: 25 | J49: 25 | K49: =IFERROR(__xludf.DUMMYFUNCTION("IFERROR( SUM( FILTER( Cobranza!$O:$O, (Cobranza!$AG:$AG & """" = P49 & """") * ((Cobranza!$W:$W = ""C"") + (Cobranza!$W:$W = ""c"")) ) ), 0 )"),25) -> 25 | N49: =E49-(H49+K49+I49+L49) -> 50 | O49: 1 | Q49: =TRIM(UPPER(B49)) -> G | R49: =TRIM(UPPER(B49)) & "-" & TRIM(UPPER(C49)) -> G-3
B50: G | C50: 4 | E50: 100 | I50: 0 | K50: =IFERROR(__xludf.DUMMYFUNCTION("IFERROR( SUM( FILTER( Cobranza!$O:$O, (Cobranza!$AG:$AG & """" = P50 & """") * ((Cobranza!$W:$W = ""C"") + (Cobranza!$W:$W = ""c"")) ) ), 0 )"),25) -> 25 | N50: =E50-(H50+K50+I50+L50) -> 75 | O50: 1 | Q50: =TRIM(UPPER(B50)) -> G | R50: =TRIM(UPPER(B50)) & "-" & TRIM(UPPER(C50)) -> G-4
B51: G | C51: 6 | D51: 3882 | E51: 100 | I51: 25 | K51: =IFERROR(__xludf.DUMMYFUNCTION("IFERROR( SUM( FILTER( Cobranza!$O:$O, (Cobranza!$AG:$AG & """" = P51 & """") * ((Cobranza!$W:$W = ""C"") + (Cobranza!$W:$W = ""c"")) ) ), 0 )"),25) -> 25 | N51: =E51-(H51+K51+I51+L51) -> 50 | O51: 1 | Q51: =TRIM(UPPER(B51)) -> G | R51: =TRIM(UPPER(B51)) & "-" & TRIM(UPPER(C51)) -> G-6
B52: G | C52: 11 | E52: 100 | I52: 25 | J52: 25 | K52: =IFERROR(__xludf.DUMMYFUNCTION("IFERROR( SUM( FILTER( Cobranza!$O:$O, (Cobranza!$AG:$AG & """" = P52 & """") * ((Cobranza!$W:$W = ""C"") + (Cobranza!$W:$W = ""c"")) ) ), 0 )"),25) -> 25 | N52: =E52-(H52+K52+I52+L52) -> 50 | O52: 1 | Q52: =TRIM(UPPER(B52)) -> G | R52: =TRIM(UPPER(B52)) & "-" & TRIM(UPPER(C52)) -> G-11
B53: G | C53: 12 | D53: 2143 | E53: 100 | I53: 25 | J53: 25 | K53: =IFERROR(__xludf.DUMMYFUNCTION("IFERROR( SUM( FILTER( Cobranza!$O:$O, (Cobranza!$AG:$AG & """" = P53 & """") * ((Cobranza!$W:$W = ""C"") + (Cobranza!$W:$W = ""c"")) ) ), 0 )"),25) -> 25 | N53: =E53-(H53+K53+I53+L53) -> 50 | O53: 1 | Q53: =TRIM(UPPER(B53)) -> G | R53: =TRIM(UPPER(B53)) & "-" & TRIM(UPPER(C53)) -> G-12
B54: G | C54: 13 | E54: 100 | I54: 25 | K54: =IFERROR(__xludf.DUMMYFUNCTION("IFERROR( SUM( FILTER( Cobranza!$O:$O, (Cobranza!$AG:$AG & """" = P54 & """") * ((Cobranza!$W:$W = ""C"") + (Cobranza!$W:$W = ""c"")) ) ), 0 )"),25) -> 25 | N54: =E54-(H54+K54+I54+L54) -> 50 | O54: 1 | Q54: =TRIM(UPPER(B54)) -> G | R54: =TRIM(UPPER(B54)) & "-" & TRIM(UPPER(C54)) -> G-13
B55: G | C55: 14 | D55: 2030 | E55: 100 | I55: 11 | J55: 26 | K55: =IFERROR(__xludf.DUMMYFUNCTION("IFERROR( SUM( FILTER( Cobranza!$O:$O, (Cobranza!$AG:$AG & """" = P55 & """") * ((Cobranza!$W:$W = ""C"") + (Cobranza!$W:$W = ""c"")) ) ), 0 )"),25) -> 25 | N55: =E55-(H55+K55+I55+L55) -> 64 | O55: 1 | Q55: =TRIM(UPPER(B55)) -> G | R55: =TRIM(UPPER(B55)) & "-" & TRIM(UPPER(C55)) -> G-14
B56: G | C56: 17 | E56: 100 | I56: 25 | J56: 25 | K56: =IFERROR(__xludf.DUMMYFUNCTION("IFERROR( SUM( FILTER( Cobranza!$O:$O, (Cobranza!$AG:$AG & """" = P56 & """") * ((Cobranza!$W:$W = ""C"") + (Cobranza!$W:$W = ""c"")) ) ), 0 )"),25) -> 25 | N56: =E56-(H56+K56+I56+L56) -> 50 | O56: 1 | Q56: =TRIM(UPPER(B56)) -> G | R56: =TRIM(UPPER(B56)) & "-" & TRIM(UPPER(C56)) -> G-17
B57: G | C57: 16 | E57: 100 | I57: 100 | K57: =IFERROR(__xludf.DUMMYFUNCTION("IFERROR( SUM( FILTER( Cobranza!$O:$O, (Cobranza!$AG:$AG & """" = P57 & """") * ((Cobranza!$W:$W = ""C"") + (Cobranza!$W:$W = ""c"")) ) ), 0 )"),0) -> 0 | N57: =E57-(H57+K57+I57+L57) -> 0 | O57: 1 | Q57: =TRIM(UPPER(B57)) -> G | R57: =TRIM(UPPER(B57)) & "-" & TRIM(UPPER(C57)) -> G-16
B58: G | C58: 18 | E58: 100 | I58: 0 | K58: =IFERROR(__xludf.DUMMYFUNCTION("IFERROR( SUM( FILTER( Cobranza!$O:$O, (Cobranza!$AG:$AG & """" = P58 & """") * ((Cobranza!$W:$W = ""C"") + (Cobranza!$W:$W = ""c"")) ) ), 0 )"),50) -> 50 | N58: =E58-(H58+K58+I58+L58) -> 50 | Q58: =TRIM(UPPER(B58)) -> G | R58: =TRIM(UPPER(B58)) & "-" & TRIM(UPPER(C58)) -> G-18
B59: G | C59: 19 | D59: 3327 | E59: 100 | I59: 0 | J59: 75 | K59: =IFERROR(__xludf.DUMMYFUNCTION("IFERROR( SUM( FILTER( Cobranza!$O:$O, (Cobranza!$AG:$AG & """" = P59 & """") * ((Cobranza!$W:$W = ""C"") + (Cobranza!$W:$W = ""c"")) ) ), 0 )"),25) -> 25 | N59: =E59-(H59+K59+I59+L59) -> 75 | O59: 1 | Q59: =TRIM(UPPER(B59)) -> G | R59: =TRIM(UPPER(B59)) & "-" & TRIM(UPPER(C59)) -> G-19
B60: G | C60: 20 | D60: 3062 | E60: 100 | I60: 25 | J60: 25 | K60: =IFERROR(__xludf.DUMMYFUNCTION("IFERROR( SUM( FILTER( Cobranza!$O:$O, (Cobranza!$AG:$AG & """" = P60 & """") * ((Cobranza!$W:$W = ""C"") + (Cobranza!$W:$W = ""c"")) ) ), 0 )"),25) -> 25 | N60: =E60-(H60+K60+I60+L60) -> 50 | O60: 1 | Q60: =TRIM(UPPER(B60)) -> G | R60: =TRIM(UPPER(B60)) & "-" & TRIM(UPPER(C60)) -> G-20
B61: H | C61: 1 | D61: 2665 | E61: 100 | I61: 0 | J61: 25 | K61: =IFERROR(__xludf.DUMMYFUNCTION("IFERROR( SUM( FILTER( Cobranza!$O:$O, (Cobranza!$AG:$AG & """" = P61 & """") * ((Cobranza!$W:$W = ""C"") + (Cobranza!$W:$W = ""c"")) ) ), 0 )"),25) -> 25 | N61: =E61-(H61+K61+I61+L61) -> 75 | O61: 1 | Q61: =TRIM(UPPER(B61)) -> H | R61: =TRIM(UPPER(B61)) & "-" & TRIM(UPPER(C61)) -> H-1
B62: G1 | C62: 5 | E62: 100 | I62: 25 | J62: 25 | K62: =IFERROR(__xludf.DUMMYFUNCTION("IFERROR( SUM( FILTER( Cobranza!$O:$O, (Cobranza!$AG:$AG & """" = P62 & """") * ((Cobranza!$W:$W = ""C"") + (Cobranza!$W:$W = ""c"")) ) ), 0 )"),25) -> 25 | N62: =E62-(H62+K62+I62+L62) -> 50 | O62: 1 | Q62: =TRIM(UPPER(B62)) -> G1 | R62: =TRIM(UPPER(B62)) & "-" & TRIM(UPPER(C62)) -> G1-5
